Workbook

Sheet Tong quan
A1: Phân tích hoạt động mô phỏng – Khóa C#: OOP + OOAD
A2: Đã xét: toàn bộ bài đọc (biểu tượng cuốn sách) và một số hoạt động phân tích có quá trình chạy rõ. Bài tập nộp, thảo luận, trắc nghiệm được giữ nguyên nên không liệt kê.
A4: Chương | B4: Nên làm | C4: Làm thêm nếu muốn | D4: Không cần | E4: Tổng số học liệu đã xét | F4: Đã duyệt OK | G4: Done | H4: Chưa done
A5: 1. Giới thiệu Lập trình hướng đối tượng (OOP) | B5: =COUNTIFS('Phan tich'!$B$2:$B$63,$A5,'Phan tich'!$F$2:$F$63,"Nên làm") | C5: =COUNTIFS('Phan tich'!$B$2:$B$63,$A5,'Phan tich'!$F$2:$F$63,"Làm thêm nếu muốn") | D5: =COUNTIFS('Phan tich'!$B$2:$B$63,$A5,'Phan tich'!$F$2:$F$63,"Không cần") | E5: =COUNTIF('Phan tich'!$B$2:$B$63,$A5) | F5: =COUNTIFS('Phan tich'!$B$2:$B$63,$A5,'Phan tich'!$N$2:$N$63,"OK") | G5: =COUNTIFS('Phan tich'!$B$2:$B$63,$A5,'Phan tich'!$G$2:$G$63,"Done") | H5: =COUNTIFS('Phan tich'!$B$2:$B$63,$A5,'Phan tich'!$G$2:$G$63,"Chưa done")
A6: 2. Đối tượng, Lớp và Đóng gói (Encapsulation) | B6: =COUNTIFS('Phan tich'!$B$2:$B$63,$A6,'Phan tich'!$F$2:$F$63,"Nên làm") | C6: =COUNTIFS('Phan tich'!$B$2:$B$63,$A6,'Phan tich'!$F$2:$F$63,"Làm thêm nếu muốn") | D6: =COUNTIFS('Phan tich'!$B$2:$B$63,$A6,'Phan tich'!$F$2:$F$63,"Không cần") | E6: =COUNTIF('Phan tich'!$B$2:$B$63,$A6) | F6: =COUNTIFS('Phan tich'!$B$2:$B$63,$A6,'Phan tich'!$N$2:$N$63,"OK") | G6: =COUNTIFS('Phan tich'!$B$2:$B$63,$A6,'Phan tich'!$G$2:$G$63,"Done") | H6: =COUNTIFS('Phan tich'!$B$2:$B$63,$A6,'Phan tich'!$G$2:$G$63,"Chưa done")
A7: 3. Kế thừa (Inheritance) và Tái sử dụng Mã | B7: =COUNTIFS('Phan tich'!$B$2:$B$63,$A7,'Phan tich'!$F$2:$F$63,"Nên làm") | C7: =COUNTIFS('Phan tich'!$B$2:$B$63,$A7,'Phan tich'!$F$2:$F$63,"Làm thêm nếu muốn") | D7: =COUNTIFS('Phan tich'!$B$2:$B$63,$A7,'Phan tich'!$F$2:$F$63,"Không cần") | E7: =COUNTIF('Phan tich'!$B$2:$B$63,$A7) | F7: =COUNTIFS('Phan tich'!$B$2:$B$63,$A7,'Phan tich'!$N$2:$N$63,"OK") | G7: =COUNTIFS('Phan tich'!$B$2:$B$63,$A7,'Phan tich'!$G$2:$G$63,"Done") | H7: =COUNTIFS('Phan tich'!$B$2:$B$63,$A7,'Phan tich'!$G$2:$G$63,"Chưa done")
A8: 4. Đa hình (Polymorphism) và Thiết kế linh hoạt | B8: =COUNTIFS('Phan tich'!$B$2:$B$63,$A8,'Phan tich'!$F$2:$F$63,"Nên làm") | C8: =COUNTIFS('Phan tich'!$B$2:$B$63,$A8,'Phan tich'!$F$2:$F$63,"Làm thêm nếu muốn") | D8: =COUNTIFS('Phan tich'!$B$2:$B$63,$A8,'Phan tich'!$F$2:$F$63,"Không cần") | E8: =COUNTIF('Phan tich'!$B$2:$B$63,$A8) | F8: =COUNTIFS('Phan tich'!$B$2:$B$63,$A8,'Phan tich'!$N$2:$N$63,"OK") | G8: =COUNTIFS('Phan tich'!$B$2:$B$63,$A8,'Phan tich'!$G$2:$G$63,"Done") | H8: =COUNTIFS('Phan tich'!$B$2:$B$63,$A8,'Phan tich'!$G$2:$G$63,"Chưa done")
A9: 5. Trừu tượng (Abstraction) với Abstract Class và Interface | B9: =COUNTIFS('Phan tich'!$B$2:$B$63,$A9,'Phan tich'!$F$2:$F$63,"Nên làm") | C9: =COUNTIFS('Phan tich'!$B$2:$B$63,$A9,'Phan tich'!$F$2:$F$63,"Làm thêm nếu muốn") | D9: =COUNTIFS('Phan tich'!$B$2:$B$63,$A9,'Phan tich'!$F$2:$F$63,"Không cần") | E9: =COUNTIF('Phan tich'!$B$2:$B$63,$A9) | F9: =COUNTIFS('Phan tich'!$B$2:$B$63,$A9,'Phan tich'!$N$2:$N$63,"OK") | G9: =COUNTIFS('Phan tich'!$B$2:$B$63,$A9,'Phan tich'!$G$2:$G$63,"Done") | H9: =COUNTIFS('Phan tich'!$B$2:$B$63,$A9,'Phan tich'!$G$2:$G$63,"Chưa done")
A10: 6. Giới thiệu Phân tích & Thiết kế hướng đối tượng (OOAD) | B10: =COUNTIFS('Phan tich'!$B$2:$B$63,$A10,'Phan tich'!$F$2:$F$63,"Nên làm") | C10: =COUNTIFS('Phan tich'!$B$2:$B$63,$A10,'Phan tich'!$F$2:$F$63,"Làm thêm nếu muốn") | D10: =COUNTIFS('Phan tich'!$B$2:$B$63,$A10,'Phan tich'!$F$2:$F$63,"Không cần") | E10: =COUNTIF('Phan tich'!$B$2:$B$63,$A10) | F10: =COUNTIFS('Phan tich'!$B$2:$B$63,$A10,'Phan tich'!$N$2:$N$63,"OK") | G10: =COUNTIFS('Phan tich'!$B$2:$B$63,$A10,'Phan tich'!$G$2:$G$63,"Done") | H10: =COUNTIFS('Phan tich'!$B$2:$B$63,$A10,'Phan tich'!$G$2:$G$63,"Chưa done")
A11: 7. Mối quan hệ giữa các lớp và Sơ đồ lớp UML (Class Diagram) | B11: =COUNTIFS('Phan tich'!$B$2:$B$63,$A11,'Phan tich'!$F$2:$F$63,"Nên làm") | C11: =COUNTIFS('Phan tich'!$B$2:$B$63,$A11,'Phan tich'!$F$2:$F$63,"Làm thêm nếu muốn") | D11: =COUNTIFS('Phan tich'!$B$2:$B$63,$A11,'Phan tich'!$F$2:$F$63,"Không cần") | E11: =COUNTIF('Phan tich'!$B$2:$B$63,$A11) | F11: =COUNTIFS('Phan tich'!$B$2:$B$63,$A11,'Phan tich'!$N$2:$N$63,"OK") | G11: =COUNTIFS('Phan tich'!$B$2:$B$63,$A11,'Phan tich'!$G$2:$G$63,"Done") | H11: =COUNTIFS('Phan tich'!$B$2:$B$63,$A11,'Phan tich'!$G$2:$G$63,"Chưa done")
A12: 8. Nguyên tắc thiết kế hướng đối tượng cơ bản và Mã nguồn sạch | B12: =COUNTIFS('Phan tich'!$B$2:$B$63,$A12,'Phan tich'!$F$2:$F$63,"Nên làm") | C12: =COUNTIFS('Phan tich'!$B$2:$B$63,$A12,'Phan tich'!$F$2:$F$63,"Làm thêm nếu muốn") | D12: =COUNTIFS('Phan tich'!$B$2:$B$63,$A12,'Phan tich'!$F$2:$F$63,"Không cần") | E12: =COUNTIF('Phan tich'!$B$2:$B$63,$A12) | F12: =COUNTIFS('Phan tich'!$B$2:$B$63,$A12,'Phan tich'!$N$2:$N$63,"OK") | G12: =COUNTIFS('Phan tich'!$B$2:$B$63,$A12,'Phan tich'!$G$2:$G$63,"Done") | H12: =COUNTIFS('Phan tich'!$B$2:$B$63,$A12,'Phan tich'!$G$2:$G$63,"Chưa done")
A13: 9. Xây dựng dự án thực tế với OOP & OOAD | B13: =COUNTIFS('Phan tich'!$B$2:$B$63,$A13,'Phan tich'!$F$2:$F$63,"Nên làm") | C13: =COUNTIFS('Phan tich'!$B$2:$B$63,$A13,'Phan tich'!$F$2:$F$63,"Làm thêm nếu muốn") | D13: =COUNTIFS('Phan tich'!$B$2:$B$63,$A13,'Phan tich'!$F$2:$F$63,"Không cần") | E13: =COUNTIF('Phan tich'!$B$2:$B$63,$A13) | F13: =COUNTIFS('Phan tich'!$B$2:$B$63,$A13,'Phan tich'!$N$2:$N$63,"OK") | G13: =COUNTIFS('Phan tich'!$B$2:$B$63,$A13,'Phan tich'!$G$2:$G$63,"Done") | H13: =COUNTIFS('Phan tich'!$B$2:$B$63,$A13,'Phan tich'!$G$2:$G$63,"Chưa done")
A14: Tổng | B14: =SUM(B5:B13) | C14: =SUM(C5:C13) | D14: =SUM(D5:D13) | E14: =SUM(E5:E13) | F14: =SUM(F5:F13) | G14: =SUM(G5:G13) | H14: =SUM(H5:H13)
A16: Cách đọc file
A17: Nên làm | B17: Bài đọc có quá trình chạy (luồng gọi hàm, bộ nhớ, đối tượng) mà chữ và ảnh tĩnh khó diễn tả.
A18: Làm thêm nếu muốn | B18: Có ích nhưng ý chính đã được bài khác hoặc bài đọc truyền tải khá tốt.
A19: Không cần | B19: Lý thuyết, tóm tắt, hướng dẫn ra quyết định, hoặc trùng ý: ghi rõ dùng lại mô phỏng nào.
A20: Cột Trạng thái | B20: Done = đã viết mô phỏng và kiểm thử, file nằm ở cột Đường dẫn. Chưa done = chưa làm.
A21: Cột Duyệt | B21: Ô vàng ở sheet 'Phan tich': chọn OK / Sửa / Bỏ và ghi ý kiến; bảng trên tự đếm số đã duyệt.
A23: Quy ước kỹ thuật (giữ theo mẫu khóa Thuật toán)
A24: Khung trang | B24: Mỗi bài 1 file HTML độc lập, giữ CSS và engine snapshot (Bước tiếp / Chạy hết / Làm lại), có chế độ tối, rộng 390px không tràn.
A25: Mở rộng cho OOP | B25: Khung bộ nhớ thêm vùng 'Đối tượng' (heap): hộp có tên lớp và mã #1, #2, liệt kê trường; biến tham chiếu hiện →Car#1. Hộp không còn ai tham chiếu thì mờ đi.
A26: Mở rộng cho UML (chương 6-7) | B26: Thêm thành phần vẽ hộp lớp UML và các mũi tên quan hệ bằng SVG thuần; khung #code dùng được cho văn bản (đề bài, kịch bản Use Case).
A27: Lỗi biên dịch / ngoại lệ | B27: Hiện ở console bằng màu đỏ, kèm mã lỗi C# thật (CS0122, CS0144, CS0534, CS0535, NullReferenceException, InvalidCastException...).
A28: Không quiz, không thử thách | B28: Chỉ quan sát và bấm từng bước; tab dùng để đổi tình huống.
A29: Thư mục | B29: oop_ooad/<chuong>/<bai-hoc>/<hoc-lieu>/index.html, đẩy lên GitHub Pages như khóa Thuật toán.

Sheet Phan tich
A1: STT | B1: Chương (Module) | C1: Bài học (Lesson) | D1: Học liệu (Activity) | E1: Loại học liệu | F1: Mức đề xuất | G1: Trạng thái | H1: Ý chính cần mô phỏng | I1: Cách hoạt động của mô phỏng | J1: Dạng giao diện | K1: Đường dẫn file (đề xuất) | L1: Link GitHub Pages (sau khi đẩy) | M1: Ghi chú | N1: Duyệt (OK / Sửa / Bỏ) | O1: Ý kiến của bạn | P1: Nội dung cũ | Q1: Nội dung mới | R1: Đã cập nhật nội dung
A2: 3 | B2: 1. Giới thiệu Lập trình hướng đối tượng (OOP) | C2: Giới thiệu Lập trình hướng đối tượng (OOP) | D2: Các khái niệm cốt lõi của OOP (Tổng quan) | E2: Bài đọc | F2: Nên làm | G2: Done | H2: Nhìn nhanh 4 trụ cột bằng một ví dụ nhỏ cho mỗi trụ cột. | I2: 4 tab, mỗi tab 3-4 bước. Tab Đóng gói: acc.Deposit(-50) bị chặn, Balance giữ nguyên. Tab Kế thừa: Dog : Animal, dog.Eat() dùng phương thức của lớp cha. Tab Đa hình: Animal a lần lượt trỏ Dog, Cat; cùng lời gọi a.Speak() in Gâu, Meo. Tab Trừu tượng: chỉ gọi car.Start(), các bước bên trong ẩn (mờ). Bộ nhớ hiện hộp đối tượng và giá trị trường. | J2: 1 cột, nhiều tab | K2: oop_ooad/gioi-thieu-lap-trinh-huong-doi-tuong-oop/gioi-thieu-lap-trinh-huong-doi-tuong-oop/cac-khai-niem-cot-loi-cua-oop-tong-quan/index.html | L2: https://codegym-vn.github.io/programming-course-demos/oop_ooad/gioi-thieu-lap-trinh-huong-doi-tuong-oop/gioi-thieu-lap-trinh-huong-doi-tuong-oop/cac-khai-niem-cot-loi-cua-oop-tong-quan/ | M2: Mỗi tab chỉ là bản rút gọn; chi tiết có ở chương 2 đến 5. | P2: Giới thiệu về các khái niệm cốt lõi của OOP Lập trình hướng đối tượng (OOP) không chỉ là một phương pháp lập trình; nó là một triết lý được xây dựng dựa trên một bộ các nguyên tắc cơ bản. Việc nắm vững các nguyên tắc này là chìa khóa để viết mã nguồn mạnh mẽ, dễ bảo trì và mở rộng. Trong trang này, chúng ta sẽ cùng tìm hiểu tổng quan về sáu khái niệm cốt lõi của OOP, tạo nền tảng vững chắc cho hành trình học tập C# và OOP của bạn. Các khái niệm này bao gồm: Đối tượng (Object), Lớp (Class), Đóng gói (Encapsulation), Kế thừa (Inheritance), Đa hình (Polymorphism) và Trừu tượng (Abstraction). Đối tượng (Object) và Lớp (Class) Đối tượng (Object) Như bạn đã tìm hiểu ở trang trước, OOP xoay quanh khái niệm 'đối tượng'. Một đối tượng là một thực thể trong thế giới thực hoặc trong hệ thống phần mềm của chúng ta, có hai đặc điểm chính: Trạng thái (State): Là các thuộc tính, dữ liệu mô tả đối tượng tại một thời điểm nhất định. Ví dụ, một đối tượng Car có thể có trạng thái như Color (màu sắc), Model (kiểu xe), CurrentSpeed (tốc độ hiện tại). Hành vi (Behavior): Là các hành động mà đối tượng có thể thực hiện hoặc các hành động có thể tác động lên đối tượng. Ví dụ, đối tượng Car có thể có các hành vi như Accelerate() (tăng tốc), Brake() (phanh), Turn() (rẽ). Lớp (Class) Nếu đối tượng là một thực thể cụ thể, thì lớp chính là bản thiết kế, khuôn mẫu hay định nghĩa để tạo ra các đối tượng đó. Một lớp không phải là một đối tượng; nó chỉ mô tả cách một đối tượng thuộc loại đó sẽ trông như thế nào và cách nó sẽ hoạt động. Hãy hình dung một bản thiết kế nhà (lớp). Từ bản thiết kế đó, bạn có thể xây dựng nhiều ngôi nhà khác nhau (đối tượng), mỗi ngôi nhà có thể có màu sơn khác nhau, nhưng tất cả đều tuân theo cấu trúc và chức năng được định nghĩa trong bản thiết kế. Trong C#, chúng ta định nghĩa một lớp bằng từ khóa class. // Định nghĩa một lớp tên là 'Car' public class Car { // Trạng thái (Thuộc tính) public string Model { get; set; } public string Color { get; set; } public int CurrentSpeed { get; private set; } = 0; // Tốc độ ban đầu là 0 // Hành vi (Phương thức) public void Accelerate(int increment) { CurrentSpeed += increment; Console.WriteLine($"Xe {Color} {Model} đang tăng tốc lên {CurrentSpeed} km/h."); } public void Brake() { CurrentSpeed = 0; Console.WriteLine($"Xe {Color} {Model} đã dừng lại."); } } // Để tạo một đối tượng (instance) từ lớp Car: // Car myCar = new Car(); // myCar.Model = "Toyota Camry"; // myCar.Color = "Đỏ"; // myCar.Accelerate(60); Đóng gói (Encapsulation) Đóng gói là nguyên tắc che giấu dữ liệu và hành vi bên trong một đối tượng, chỉ cho phép truy cập thông qua một giao diện công khai được kiểm soát. Điều này có nghĩa là các chi tiết triển khai nội bộ của một đối tượng được giữ kín, và các đối tượng khác không thể trực tiếp thay đổi trạng thái nội bộ một cách tùy tiện. Mục đích chính của đóng gói là: Bảo toàn tính toàn vẹn của dữ liệu: Ngăn chặn việc thay đổi dữ liệu một cách không hợp lệ. Giảm sự phụ thuộc: Khi thay đổi cách một đối tượng hoạt động nội bộ, các đối tượng khác sử dụng nó không cần phải thay đổi, miễn là giao diện công khai vẫn giữ nguyên. Tăng tính mô-đun: Mỗi đối tượng trở thành một "hộp đen" tự chứa, dễ dàng quản lý và tái sử dụng. Trong C#, đóng gói thường được thực hiện thông qua: Bộ chỉ định truy cập (Access Modifiers): Như public, private, protected. Ví dụ, một thuộc tính private chỉ có thể được truy cập từ bên trong lớp đó. Thuộc tính (Properties): Cung cấp các phương thức get và set để kiểm soát cách dữ liệu được đọc và ghi. public class BankAccount { private decimal _balance; // Dữ liệu nội bộ được bảo vệ (private) public BankAccount(decimal initialBalance) { if (initialBalance < 0) { throw new ArgumentException("Số dư ban đầu không thể âm."); } _balance = initialBalance; } // Phương thức công khai để thay đổi trạng thái (hành vi) public void Deposit(decimal amount) { if (amount > 0) { _balance += amount; Console.WriteLine($"Đã gửi {amount:C}. Số dư mới: {_balance:C}"); } } // Phương thức công khai để đọc trạng thái (hành vi) public decimal GetBalance() { return _balance; } } Trong ví dụ trên, _balance được đóng gói. Bạn không thể trực tiếp gán giá trị cho _balance từ bên ngoài lớp BankAccount; thay vào đó, bạn phải sử dụng phương thức Deposit() hoặc GetBalance(), đảm bảo rằng mọi thao tác đều được kiểm soát. Kế thừa (Inheritance) Kế thừa là một cơ chế cho phép một lớp (lớp con hoặc lớp dẫn xuất) nhận tất cả các thuộc tính và phương thức từ một lớp khác (lớp cha hoặc lớp cơ sở). Nguyên tắc này giúp thiết lập mối quan hệ "là một loại" (is-a relationship) giữa các lớp, ví dụ: "Một Carlà một loạiVehicle". Lợi ích chính của kế thừa là: Tái sử dụng mã: Tránh viết lại cùng một mã nhiều lần. Các tính năng chung được định nghĩa ở lớp cha và được các lớp con tự động kế thừa. Mở rộng tính năng: Lớp con có thể thêm các thuộc tính và phương thức mới hoặc ghi đè (override) các phương thức của lớp cha để cung cấp hành vi chuyên biệt hơn. Tạo cấu trúc phân cấp: Giúp tổ chức mã nguồn một cách logic, phản ánh các mối quan hệ tự nhiên giữa các thực thể. Trong C#, chúng ta sử dụng dấu hai chấm : để chỉ ra mối quan hệ kế thừa. public class Vehicle // Lớp cha (Base Class) { public string Manufacturer { get; set; } public int Year { get; set; } public void StartEngine() { Console.WriteLine("Động cơ đã khởi động."); } } public class Car : Vehicle // Lớp con (Derived Class) kế thừa từ Vehicle { public int NumberOfDoors { get; set; } public void Honk() { Console.WriteLine("Bíp bíp!"); } } // Đối tượng Car có thể sử dụng các thuộc tính và phương thức của Vehicle // Car myCar = new Car(); // myCar.Manufacturer = "Honda"; // Thuộc tính từ Vehicle // myCar.StartEngine(); // Phương thức từ Vehicle // myCar.Honk(); // Phương thức riêng của Car Đa hình (Polymorphism) Đa hình có nghĩa là "nhiều hình thái". Trong OOP, nó đề cập đến khả năng một đối tượng có thể mang nhiều hình thái khác nhau hoặc khả năng một phương thức có thể được gọi trên các đối tượng thuộc các lớp khác nhau và thực hiện các hành vi khác nhau tùy thuộc vào loại đối tượng cụ thể. Đa hình cho phép chúng ta: Viết mã linh hoạt và mở rộng: Có thể xử lý các đối tượng thuộc các lớp khác nhau thông qua một giao diện chung. Giảm sự phức tạp: Không cần biết chính xác loại đối tượng nào đang được xử lý tại thời điểm biên dịch; hành vi đúng sẽ được gọi tại thời điểm chạy. Trong C#, đa hình thường được triển khai thông qua: Ghi đè phương thức (Method Overriding): Lớp con cung cấp một triển khai cụ thể cho một phương thức đã được định nghĩa trong lớp cha. Để làm điều này, phương thức trong lớp cha phải được đánh dấu bằng từ khóa virtual, và phương thức trong lớp con phải được đánh dấu bằng từ khóa override. Giao diện (Interfaces): Định nghĩa một tập hợp các phương thức mà các lớp phải triển khai. public class Animal { public virtual void MakeSound() // Phương thức virtual có thể được ghi đè { Console.WriteLine("Một con vật tạo ra âm thanh."); } } public class Dog : Animal { public override void MakeSound() // Ghi đè phương thức MakeSound của Animal { Console.WriteLine("Gâu gâu!"); } } public class Cat : Animal { public override void MakeSound() // Ghi đè phương thức MakeSound của Animal { Console.WriteLine("Meo meo!"); } } // Ví dụ về đa hình: // Animal myDog = new Dog(); // Animal myCat = new Cat(); // myDog.MakeSound(); // In ra "Gâu gâu!" // myCat.MakeSound(); // In ra "Meo meo!" Trừu tượng (Abstraction) Trừu tượng là nguyên tắc tập trung vào những gì một đối tượng làm (giao diện công khai) thay vì làm như thế nào (chi tiết triển khai nội bộ). Nó cho phép chúng ta ẩn đi những chi tiết phức tạp không cần thiết từ người dùng hoặc từ các phần khác của hệ thống, chỉ phơi bày những thông tin và chức năng quan trọng. Lợi ích của trừu tượng: Quản lý độ phức tạp: Đơn giản hóa các hệ thống phức tạp bằng cách chia chúng thành các phần nhỏ hơn, dễ hiểu hơn. Tăng tính dễ sử dụng: Người dùng chỉ cần biết cách tương tác với giao diện công khai mà không cần lo lắng về các hoạt động bên trong. Dễ dàng thay đổi và bảo trì: Các chi tiết triển khai có thể thay đổi mà không ảnh hưởng đến các đối tượng sử dụng giao diện trừu tượng. Trong C#, trừu tượng được triển khai thông qua: Lớp trừu tượng (Abstract Classes): Các lớp không thể được khởi tạo trực tiếp và có thể chứa các phương thức trừu tượng (không có phần thân) mà các lớp con phải triển khai. Giao diện (Interfaces): Định nghĩa một hợp đồng về các phương thức mà một lớp phải triển khai, nhưng không cung cấp bất kỳ triển khai nào. public abstract class Shape // Lớp trừu tượng { public abstract double CalculateArea(); // Phương thức trừu tượng, không có phần thân public void Display() { Console.WriteLine($"Đây là một hình có diện tích: {CalculateArea()}"); } } public class Circle : Shape { public double Radius { get; set; } public Circle(double radius) { Radius = radius; } public override double CalculateArea() // Lớp con phải triển khai phương thức trừu tượng { return Math.PI * Radius * Radius; } } public class Rectangle : Shape { public double Width { get; set; } public double Height { get; set; } public Rectangle(double width, double height) { Width = width; Height = height; } public override double CalculateArea() // Lớp con phải triển khai phương thức trừu tượng { return Width * Height; } } // Shape s1 = new Circle(5); // s1.Display(); // In ra "Đây là một hình có diện tích: 78.53981633974483" // Shape s2 = new Rectangle(4, 6); // s2.Display(); // In ra "Đây là một hình có diện tích: 24" Trong ví dụ này, người dùng chỉ cần biết rằng mọi Shape đều có thể CalculateArea() và Display(), mà không cần biết chi tiết cách mỗi hình cụ thể (như Circle hay Rectangle) tính toán diện tích của nó. Đó chính là trừu tượng. | Q2: # Các khái niệm cốt lõi của OOP ## Mục tiêu học tập Sau bài học này, bạn có thể: - Kể tên sáu khái niệm cốt lõi của OOP: đối tượng, lớp, đóng gói, kế thừa, đa hình và trừu tượng. - Phân biệt lớp (bản thiết kế) với đối tượng (thực thể được tạo ra từ lớp). - Giải thích mỗi trụ cột bằng một ví dụ C# ngắn. - Nhận ra từ khóa C# gắn với từng trụ cột: `private`, dấu `:`, `virtual` và `override`, `abstract`. - Quan sát từng bước chạy của bốn trụ cột bằng hoạt động mô phỏng. ## Tổng quan Lập trình hướng đối tượng (OOP) không chỉ là một cách viết mã. Nó dựa trên một bộ nguyên tắc giúp mã nguồn **mạnh mẽ, dễ bảo trì và dễ mở rộng**. Bài này giới thiệu nhanh sáu khái niệm cốt lõi, làm nền cho các chương sau: - **Đối tượng (Object)** và **Lớp (Class)**: hai khái niệm nền tảng. - **Đóng gói (Encapsulation)**, **Kế thừa (Inheritance)**, **Đa hình (Polymorphism)** và **Trừu tượng (Abstraction)**: bốn trụ cột của OOP. ## Đối tượng và lớp ### Đối tượng (Object) Đối tượng là một thực thể trong thế giới thực hoặc trong phần mềm, có hai đặc điểm chính: - **Trạng thái (State):** dữ liệu mô tả đối tượng tại một thời điểm. Ví dụ, một đối tượng `Car` có `Color` (màu), `Model` (kiểu xe), `CurrentSpeed` (tốc độ hiện tại). - **Hành vi (Behavior):** những việc đối tượng có thể làm. Ví dụ, `Car` có thể `Accelerate()` (tăng tốc), `Brake()` (phanh). ### Lớp (Class) Lớp là **bản thiết kế** dùng để tạo ra đối tượng. Lớp mô tả đối tượng sẽ có những gì và làm được gì, nhưng bản thân lớp chưa phải là một đối tượng. Hãy hình dung một bản thiết kế nhà (lớp). Từ đó bạn xây được nhiều ngôi nhà (đối tượng), mỗi nhà một màu sơn khác nhau nhưng cùng cấu trúc. Trong C#, ta định nghĩa lớp bằng từ khóa `class` và tạo đối tượng bằng từ khóa `new`: ```csharp using System; public class Car { // Trạng thái public string Model { get; set; } public string Color { get; set; } public int CurrentSpeed { get; private set; } = 0; // Hành vi public void Accelerate(int increment) { CurrentSpeed += increment; Console.WriteLine($"Xe {Color} {Model} đang tăng tốc lên {CurrentSpeed} km/h."); } public void Brake() { CurrentSpeed = 0; Console.WriteLine($"Xe {Color} {Model} đã dừng lại."); } } public class Program { public static void Main() { Car myCar = new Car(); myCar.Model = "Toyota Camry"; myCar.Color = "Đỏ"; myCar.Accelerate(60); // Xe Đỏ Toyota Camry đang tăng tốc lên 60 km/h. } } ``` ## Bốn trụ cột của OOP ### Đóng gói (Encapsulation) Đóng gói là che giấu dữ liệu bên trong đối tượng và chỉ cho phép thay đổi qua các phương thức công khai có kiểm soát. Nhờ đó: - **Dữ liệu luôn hợp lệ:** không ai gán tùy tiện một giá trị sai. - **Giảm phụ thuộc:** đổi cách làm bên trong thì code bên ngoài không phải sửa, miễn là phương thức công khai giữ nguyên. - **Tăng tính mô-đun:** mỗi đối tượng là một "hộp đen" dễ quản lý và tái sử dụng. Trong C#, đóng gói thường dùng từ khóa kiểm soát truy cập (`public`, `private`, `protected`) và thuộc tính (property): ```csharp using System; public class BankAccount { private decimal _balance; // dữ liệu nội bộ, được bảo vệ public BankAccount(decimal initialBalance) { if (initialBalance < 0) { throw new ArgumentException("Số dư ban đầu không thể âm."); } _balance = initialBalance; } public void Deposit(decimal amount) { if (amount > 0) { _balance += amount; Console.WriteLine($"Đã gửi {amount:C}. Số dư mới: {_balance:C}"); } } public decimal GetBalance() { return _balance; } } ``` Bạn không thể gán trực tiếp `_balance` từ bên ngoài lớp. Muốn đổi số dư, phải gọi `Deposit()`, và `Deposit()` chỉ chấp nhận số tiền lớn hơn 0. ### Kế thừa (Inheritance) Kế thừa cho phép một lớp (lớp con) nhận lại những gì lớp khác (lớp cha) đã có. Hai lớp có quan hệ **"là một loại"** (is-a): `Dog` là một loại `Animal`. Lợi ích: - **Tái sử dụng mã:** viết một lần ở lớp cha, mọi lớp con dùng được. - **Mở rộng:** lớp con thêm thành viên mới hoặc ghi đè hành vi của lớp cha. - **Cấu trúc phân cấp:** mã phản ánh đúng quan hệ giữa các thực thể. Trong C#, ta dùng dấu hai chấm `:` để kế thừa: ```csharp using System; public class Animal // lớp cha { public void Eat() { Console.WriteLine("Đang ăn"); } } public class Dog : Animal // lớp con kế thừa Animal { public void Bark() { Console.WriteLine("Gâu!"); } } public class Program { public static void Main() { Dog dog = new Dog(); dog.Eat(); // phương thức của Animal dog.Bark(); // phương thức riêng của Dog } } ``` ### Đa hình (Polymorphism) Đa hình nghĩa là "nhiều hình thái": cùng một lời gọi phương thức, nhưng hành vi thay đổi theo **đối tượng thật** mà biến đang trỏ tới. Nhờ đó ta viết mã linh hoạt, dễ mở rộng, và không cần biết trước chính xác loại đối tượng nào sẽ được xử lý. Trong C#, đa hình thường dùng **ghi đè phương thức**: lớp cha đánh dấu `virtual`, lớp con đánh dấu `override`. Ngoài ra còn có giao diện (interface). ```csharp using System; public class Animal { public virtual void Speak() { Console.WriteLine("Một con vật kêu."); } } public class Dog : Animal { public override void Speak() { Console.WriteLine("Gâu"); } } public class Cat : Animal { public override void Speak() { Console.WriteLine("Meo"); } } public class Program { public static void Main() { Animal a = new Dog(); a.Speak(); // Gâu a = new Cat(); a.Speak(); // Meo } } ``` ### Trừu tượng (Abstraction) Trừu tượng tập trung vào việc đối tượng **làm gì**, không phải **làm như thế nào**. Giống như lái xe: bạn chỉ cần bấm nút Start, không cần biết động cơ bên trong hoạt động ra sao. Lợi ích: - **Giảm độ phức tạp:** người dùng chỉ thấy phần cần dùng. - **Dễ sử dụng:** chỉ cần biết cách gọi, không cần biết bên trong. - **Dễ thay đổi:** sửa chi tiết bên trong mà không ảnh hưởng nơi gọi. Trong C#, trừu tượng được thể hiện bằng **lớp trừu tượng** (`abstract class`) và **giao diện** (`interface`). ```csharp using System; public abstract class Shape { public abstract double CalculateArea(); // không có thân, lớp con phải tự cài đặt public void Display() { Console.WriteLine($"Diện tích: {CalculateArea()}"); } } public class Rectangle : Shape { public double Width { get; set; } public double Height { get; set; } public Rectangle(double width, double height) { Width = width; Height = height; } public override double CalculateArea() => Width * Height; } public class Program { public static void Main() { Shape s = new Rectangle(4, 6); s.Display(); // Diện tích: 24 } } ``` Người dùng chỉ cần biết mọi `Shape` đều có `Display()`. Cách mỗi hình tính diện tích là chi tiết bên trong. ### So sánh nhanh bốn trụ cột | Trụ cột | Ý chính | Từ khóa C# thường gặp | |---|---|---| | Đóng gói | Giấu dữ liệu, chỉ đổi qua phương thức có kiểm soát | `private`, `public`, property | | Kế thừa | Lớp con dùng lại những gì lớp cha có | `:` | | Đa hình | Cùng lời gọi, hành vi tùy đối tượng thật | `virtual`, `override` | | Trừu tượng | Chỉ lộ phần cần dùng, ẩn chi tiết bên trong | `abstract`, `interface` | ## Hoạt động: Bốn trụ cột qua từng bước chạy Mô phỏng dưới đây có bốn tab, mỗi tab là một ví dụ nhỏ của một trụ cột. Hãy thao tác theo thứ tự sau, bấm **Bước tiếp** để chạy từng dòng: - Mở tab **Đóng gói**. `balance` là `private`. `Deposit(100)` hợp lệ nên `balance` tăng lên 100. `Deposit(-50)` bị chặn vì `x` không lớn hơn 0, nên `balance` vẫn là 100. - Chuyển sang tab **Kế thừa**. Lớp `Dog : Animal` không tự viết gì, nhưng `dog.Eat()` vẫn chạy được vì `Eat()` được thừa hưởng từ `Animal`. - Mở tab **Đa hình**. Dòng `a.Speak()` được gọi hai lần. Lần đầu `a` trỏ tới `Dog` nên in "Gâu". Sau khi gán `a = new Cat()`, lần hai in "Meo". Hãy để ý đối tượng `Dog` cũ mờ đi vì không còn biến nào trỏ tới. - Mở tab **Trừu tượng**. Người dùng chỉ gọi `car.Start()`. Các bước bên trong (`CheckFuel()`, `TurnKey()`, `running = true`) ban đầu bị ẩn mờ, rồi sáng lên khi `Start()` chạy. ``` <iframe src="https://codegym-vn.github.io/programming-course-demos/oop_ooad/gioi-thieu-lap-trinh-huong-doi-tuong-oop/gioi-thieu-lap-trinh-huong-doi-tuong-oop/cac-khai-niem-cot-loi-cua-oop-tong-quan/" title="Bốn trụ cột của OOP" style="border:0;" allowfullscreen></iframe> ``` Điều rút ra: bốn ví dụ khác nhau nhưng có chung một ý. Mỗi trụ cột giải quyết một vấn đề cụ thể. Đóng gói giữ dữ liệu hợp lệ, kế thừa tránh viết lại mã, đa hình cho phép một lời gọi phục vụ nhiều loại đối tượng, trừu tượng che bớt chi tiết không cần thiết. Các chương sau sẽ đi sâu vào từng trụ cột. ## Tóm tắt - **Đối tượng** có trạng thái và hành vi. **Lớp** là bản thiết kế để tạo ra đối tượng bằng `new`. - **Đóng gói** giấu dữ liệu bằng `private` và chỉ cho đổi qua phương thức có kiểm tra. - **Kế thừa** dùng `:` để lớp con tái sử dụng và mở rộng lớp cha (quan hệ "là một loại"). - **Đa hình** dùng `virtual` và `override`: cùng một lời gọi, kết quả tùy đối tượng thật. - **Trừu tượng** dùng `abstract class` hoặc `interface` để chỉ lộ phần cần dùng và ẩn chi tiết bên trong. - Bốn trụ cột bổ trợ cho nhau để mã nguồn dễ bảo trì và mở rộng.
A3: 4 | B3: 2. Đối tượng, Lớp và Đóng gói (Encapsulation) | C3: Giới thiệu về Lớp và Đối tượng trong C# | D3: Lớp là gì? Đối tượng là gì? | E3: Bài đọc | F3: Nên làm | G3: Done | H3: Lớp là khuôn, đối tượng là bản cụ thể được tạo bằng new. | I3: Code: class Car { string Color; int Speed; } rồi Car a = new Car(); a.Color = "Đỏ"; Car b = new Car(); b.Color = "Xanh";. Bộ nhớ chia 2 vùng: Biến (a, b giữ tham chiếu →Car#1, →Car#2) và Đối tượng (2 hộp Car với trường riêng). Mỗi bước tô sáng hộp vừa tạo/vừa đổi. Ghi chú cuối: một lớp, nhiều đối tượng, mỗi đối tượng có dữ liệu riêng. | J3: 1 cột | K3: oop_ooad/doi-tuong-lop-va-dong-goi-encapsulation/gioi-thieu-ve-lop-va-doi-tuong-trong-c-sharp/lop-la-gi-doi-tuong-la-gi/index.html | L3: https://codegym-vn.github.io/programming-course-demos/oop_ooad/doi-tuong-lop-va-dong-goi-encapsulation/gioi-thieu-ve-lop-va-doi-tuong-trong-c-sharp/lop-la-gi-doi-tuong-la-gi/ | M3: Cần mở rộng khung #mem: thêm vùng Đối tượng (heap) dạng hộp có tên lớp, mã #1, #2 và các trường. | P3: Lập trình Hướng đối tượng (OOP): Một Cách Nhìn Mới về Giải Quyết Vấn Đề Trong lập trình thủ tục truyền thống, chúng ta thường tập trung vào trình tự các bước thực hiện để giải quyết một vấn đề. Dữ liệu và các hàm thao tác trên dữ liệu thường được tách rời. Tuy nhiên, khi các hệ thống trở nên phức tạp hơn, cách tiếp cận này có thể dẫn đến khó khăn trong việc quản lý, mở rộng và bảo trì mã nguồn. Lập trình hướng đối tượng (OOP) ra đời để giải quyết những thách thức này bằng cách cung cấp một mô hình mạnh mẽ hơn, gần gũi hơn với cách chúng ta nhận thức thế giới thực. Thay vì chỉ tập trung vào "làm gì", OOP tập trung vào "ai/cái gì" thực hiện hành động đó. Nền tảng của OOP chính là hai khái niệm cơ bản: Lớp (Class) và Đối tượng (Object). Chúng ta sẽ cùng ôn lại và đi sâu vào ý nghĩa của chúng. Lớp là gì? Bản Thiết Kế của Thế Giới Số Hãy tưởng tượng bạn muốn xây dựng một ngôi nhà. Bạn sẽ không xây dựng ngay lập tức, mà trước tiên bạn cần một bản thiết kế chi tiết. Bản thiết kế này mô tả mọi thứ về ngôi nhà: số phòng, kích thước các phòng, vị trí cửa sổ, loại vật liệu, v.v. Nó là một khuôn mẫu, một kế hoạch tổng thể. Trong lập trình hướng đối tượng, Lớp (Class) chính là bản thiết kế đó. Một lớp là một khuôn mẫu (template) hoặc bản thiết kế (blueprint) để tạo ra các đối tượng. Nó định nghĩa cấu trúc và hành vi chung mà tất cả các đối tượng được tạo ra từ lớp đó sẽ có. Một lớp không phải là một thực thể cụ thể; nó là một định nghĩa trừu tượng về một loại đối tượng. Một lớp bao gồm hai thành phần chính: Thuộc tính (Attributes/Fields/Properties): Đây là dữ liệu, trạng thái hoặc đặc điểm của đối tượng. Tương tự như màu sơn, số bánh xe của một chiếc ô tô, hoặc tên, tuổi của một người. Phương thức (Methods): Đây là các hành vi hoặc chức năng mà đối tượng có thể thực hiện. Ví dụ, một chiếc ô tô có thể Lái(), Phanh(); một người có thể Ăn(), Ngủ(). Ví dụ về một Lớp trong C#: Hãy xem xét lớp Oto (Car) dưới đây. Đây là một bản thiết kế định nghĩa những đặc điểm và hành vi mà một chiếc ô tô sẽ có. class Oto { // Thuộc tính (Attributes) - Đặc điểm của chiếc xe public string HangSanXuat; public string MauSac; public int SoBanhXe; // Mặc định là 4 // Phương thức (Methods) - Hành vi của chiếc xe public void KhoiDong() { // Mã để khởi động xe Console.WriteLine("Xe đang khởi động..."); } public void DiChuyen(int tocDo) { // Mã để điều khiển xe di chuyển Console.WriteLine($"Xe đang di chuyển với tốc độ {tocDo} km/h."); } public void DungLai() { // Mã để dừng xe Console.WriteLine("Xe đã dừng lại."); } } Trong ví dụ trên, Oto là một lớp. Nó định nghĩa rằng mọi chiếc ô tô sẽ có HangSanXuat, MauSac, SoBanhXe và có thể thực hiện các hành động KhoiDong(), DiChuyen(), DungLai(). Bản thân lớp Oto không phải là một chiếc xe cụ thể mà bạn có thể lái được; nó chỉ là khuôn mẫu để tạo ra chúng. Đối tượng là gì? Thể Hiện Cụ Thể Từ Bản Thiết Kế Tiếp tục với ví dụ ngôi nhà: Sau khi có bản thiết kế, bạn có thể sử dụng nó để xây dựng một ngôi nhà cụ thể. Ngôi nhà đó là một thực thể vật lý, có địa chỉ cụ thể, có thể ở được, có màu sơn riêng, v.v. Trong OOP, Đối tượng (Object) chính là thực thể cụ thể đó. Một đối tượng là một thể hiện (instance) của một lớp. Nó là một thực thể cụ thể, tồn tại trong bộ nhớ máy tính, được tạo ra dựa trên định nghĩa của một lớp. Mỗi đối tượng có trạng thái (state) riêng (tức là các giá trị cụ thể cho các thuộc tính của nó) và có thể thực hiện các hành vi được định nghĩa trong lớp của nó. Từ bản thiết kế Oto ở trên, bạn có thể tạo ra vô số đối tượng ô tô khác nhau. Mỗi đối tượng sẽ là một chiếc ô tô độc lập với các đặc điểm riêng: Đối tượng 1:myCar HangSanXuat: "Toyota" MauSac: "Đỏ" SoBanhXe: 4 Đối tượng 2:yourCar HangSanXuat: "Honda" MauSac: "Xanh" SoBanhXe: 4 Đối tượng 3:taxiCar HangSanXuat: "Hyundai" MauSac: "Trắng" SoBanhXe: 4 Mỗi đối tượng này là một thực thể riêng biệt, chiếm một vùng nhớ riêng và có thể hoạt động độc lập. Mặc dù tất cả chúng đều được tạo ra từ cùng một lớp Oto, nhưng chúng có thể có các giá trị thuộc tính khác nhau, tạo nên sự đa dạng và độc lập. Phân Biệt Lớp và Đối tượng: Từ Khái Quát đến Cụ Thể Để củng cố sự hiểu biết, chúng ta hãy cùng nhìn lại sự khác biệt cơ bản giữa lớp và đối tượng: Hãy nhớ rằng, lớp là một khái niệm, một sự trừu tượng; đối tượng là hiện thực hóa của khái niệm đó. Vai trò của Lớp và Đối tượng trong Mô hình hóa Thế giới Thực Mục tiêu chính của lập trình hướng đối tượng là giúp chúng ta mô hình hóa các thực thể và mối quan hệ trong thế giới thực một cách tự nhiên và hiệu quả hơn. Lớp và đối tượng đóng vai trò trung tâm trong quá trình này: Trừu tượng hóa (Abstraction): Lớp giúp chúng ta trừu tượng hóa các khái niệm phức tạp thành các đơn vị dễ quản lý. Thay vì nghĩ về hàng trăm dòng mã, chúng ta nghĩ về "một sinh viên" hoặc "một đơn hàng". Đóng gói (Encapsulation): Lớp cho phép chúng ta nhóm dữ liệu (thuộc tính) và hành vi (phương thức) liên quan lại với nhau thành một đơn vị duy nhất (đối tượng). Điều này giúp bảo vệ dữ liệu và làm cho mã dễ hiểu, dễ bảo trì hơn. (Chúng ta sẽ tìm hiểu sâu hơn về Đóng gói trong các bài học sau). Tái sử dụng (Reusability): Khi đã định nghĩa một lớp, bạn có thể tái sử dụng nó để tạo ra nhiều đối tượng khác nhau mà không cần viết lại mã từ đầu. Điều này giúp tiết kiệm thời gian và công sức phát triển. Tổ chức mã nguồn: Lớp giúp cấu trúc chương trình một cách rõ ràng và logic, phản ánh cấu trúc của vấn đề trong thế giới thực. Điều này làm cho các dự án lớn trở nên dễ quản lý hơn. Bằng cách sử dụng lớp để định nghĩa các loại thực thể và tạo ra các đối tượng cụ thể từ chúng, chúng ta có thể xây dựng các ứng dụng phức tạp một cách có hệ thống, phản ánh chân thực các thực thể và tương tác trong thế giới mà chúng ta đang cố gắng mô hình hóa. Đây chính là sức mạnh và vẻ đẹp của lập trình hướng đối tượng. | Q3: # Lớp là gì? Đối tượng là gì? ## Mục tiêu học tập Sau bài học này, bạn có thể: - Giải thích lớp (class) là bản thiết kế và đối tượng (object) là thực thể được tạo ra từ bản thiết kế đó. - Phân biệt hai thành phần chính của lớp: trường (dữ liệu) và phương thức (hành vi). - Viết một lớp đơn giản trong C# và tạo nhiều đối tượng từ nó bằng từ khóa `new`. - Nhận ra rằng mỗi đối tượng giữ dữ liệu riêng, dù cùng một lớp. - Quan sát từng bước chạy của lớp `Car` và hai đối tượng bằng hoạt động mô phỏng. ## Từ "làm gì" sang "ai làm" Trong lập trình thủ tục, ta hay nghĩ theo các bước: làm việc này, rồi làm việc kia. Dữ liệu và các hàm xử lý dữ liệu thường nằm tách rời. Khi chương trình lớn dần, cách này khó quản lý và khó bảo trì. Lập trình hướng đối tượng (OOP) nhìn theo hướng khác, gần với thế giới thật hơn. Ta không chỉ hỏi "làm gì", mà hỏi thêm "**ai** hoặc **cái gì** làm việc đó". Nền tảng của cách nhìn này là hai khái niệm: **lớp** và **đối tượng**. ## Lớp (Class) Hãy tưởng tượng bạn muốn xây một ngôi nhà. Trước hết bạn cần một **bản thiết kế**: số phòng, kích thước, vị trí cửa sổ, vật liệu. Bản thiết kế chưa phải là một ngôi nhà bạn có thể ở. Trong OOP, **lớp** chính là bản thiết kế đó: - Lớp là **khuôn mẫu** (template) để tạo ra các đối tượng. - Lớp mô tả những gì mọi đối tượng thuộc loại đó **có** và **làm được**. - Lớp không phải là một thực thể cụ thể. Nó chỉ là định nghĩa về một loại đối tượng. Một lớp có hai thành phần chính: - **Trường (Field):** dữ liệu mô tả đặc điểm hay trạng thái của đối tượng. Ví dụ: màu sắc và tốc độ của xe, tên và tuổi của một người. - **Phương thức (Method):** hành vi mà đối tượng có thể thực hiện. Ví dụ: xe có thể khởi động, chạy, dừng. Dưới đây là lớp `Car` có hai trường `Color` (màu) và `Speed` (tốc độ), cùng một phương thức `Run()`: ```csharp using System; public class Car { // Trường: đặc điểm của chiếc xe public string Color; public int Speed; // Phương thức: hành vi của chiếc xe public void Run() { Console.WriteLine("Xe " + Color + " đang chạy với tốc độ " + Speed + " km/h."); } } ``` Lớp `Car` nói rằng: mọi chiếc xe đều có `Color` và `Speed`, và đều chạy được. Bản thân lớp `Car` không phải một chiếc xe để lái. Viết xong lớp thì bộ nhớ vẫn chưa có chiếc xe nào. ## Đối tượng (Object) Có bản thiết kế rồi, bạn xây một ngôi nhà cụ thể: có địa chỉ, có màu sơn riêng, ở được. Trong OOP, đó là **đối tượng**: - Đối tượng là một **thể hiện** (instance) của lớp. - Đối tượng là thực thể cụ thể, **tồn tại trong bộ nhớ**, được tạo ra dựa trên định nghĩa của lớp. - Mỗi đối tượng có **trạng thái** (state) riêng, tức là giá trị riêng cho từng trường. Trong C#, ta tạo đối tượng bằng từ khóa `new`: ```csharp using System; public class Program { public static void Main() { Car a = new Car(); a.Color = "Đỏ"; a.Speed = 40; Car b = new Car(); b.Color = "Xanh"; b.Speed = 60; a.Run(); // Xe Đỏ đang chạy với tốc độ 40 km/h. b.Run(); // Xe Xanh đang chạy với tốc độ 60 km/h. } } ``` Hai đối tượng `a` và `b` cùng đến từ lớp `Car`, nhưng mỗi đối tượng có màu và tốc độ riêng. Chúng nằm ở hai vùng nhớ khác nhau và hoạt động độc lập. ## Phân biệt lớp và đối tượng | | Lớp (Class) | Đối tượng (Object) | |---|---|---| | Bản chất | Bản thiết kế, khái niệm trừu tượng | Thực thể cụ thể được tạo ra từ lớp | | Bộ nhớ | Chưa chiếm vùng nhớ cho dữ liệu | Chiếm vùng nhớ riêng | | Số lượng | Viết một lần | Tạo được nhiều đối tượng từ một lớp | | Dữ liệu | Chỉ mô tả có những trường nào | Mỗi đối tượng giữ giá trị cụ thể | | Ví dụ | `Car` | Chiếc xe đỏ `a`, chiếc xe xanh `b` | Hãy nhớ: **lớp là khái niệm, đối tượng là sự hiện thực hóa của khái niệm đó.** ## Hoạt động: Một lớp, hai đối tượng Mô phỏng dưới đây chạy từng dòng một chương trình dùng lớp `Car`. Hãy thao tác theo thứ tự sau, bấm **Bước tiếp** để chạy từng dòng: - Mở tab **Lớp Car và hai đối tượng**. Ở bước đầu, lớp `Car` chỉ mới được viết ra. Nó mô tả mỗi xe có `Color` và `Speed`, còn bộ nhớ vẫn trống vì chưa có chiếc xe nào. - Bước `new Car()` đầu tiên tạo đối tượng `Car#1`. Các trường nhận giá trị mặc định `Color = null` và `Speed = 0`, còn biến `a` giữ đường dẫn tới `Car#1`. Sau đó `a.Color = "Đỏ"` chỉ đổi trường của `Car#1`. - Dòng `new Car()` thứ hai tạo thêm `Car#2`, hoàn toàn tách biệt với `Car#1`, và biến `b` trỏ tới nó. `b.Color = "Xanh"` chỉ đổi `Car#2`, còn `Car#1` vẫn màu Đỏ. - Bước `b.Speed = 60` đặt tốc độ cho `Car#2`. Hãy để ý `Speed` của `Car#1` vẫn là 0. - Hai dòng `Console.WriteLine` in ra `Đỏ` rồi `Xanh`. Bước cuối ghi chú rằng một lớp tạo được nhiều đối tượng, mỗi đối tượng giữ dữ liệu riêng. ``` <iframe src="https://codegym-vn.github.io/programming-course-demos/oop_ooad/doi-tuong-lop-va-dong-goi-encapsulation/gioi-thieu-ve-lop-va-doi-tuong-trong-c-sharp/lop-la-gi-doi-tuong-la-gi/" title="Lớp và Đối tượng" style="border:0;" allowfullscreen></iframe> ``` Điều rút ra: lớp chỉ mô tả "có những gì", còn mỗi đối tượng giữ giá trị cụ thể của riêng nó. Đổi dữ liệu của đối tượng này không làm đổi dữ liệu của đối tượng kia. ## Vì sao lớp và đối tượng quan trọng? - **Trừu tượng hóa:** thay vì nghĩ về hàng trăm dòng mã, ta nghĩ về "một chiếc xe", "một sinh viên", "một đơn hàng". - **Đóng gói:** lớp gom dữ liệu và hành vi liên quan vào một đơn vị. Bài sau sẽ nói sâu hơn về điều này. - **Tái sử dụng:** viết lớp một lần, tạo bao nhiêu đối tượng cũng được. - **Tổ chức mã nguồn:** chương trình được chia theo các loại thực thể của bài toán, nên dự án lớn dễ quản lý hơn. ## Tóm tắt - **Lớp** là bản thiết kế: mô tả có những **trường** và **phương thức** nào. - **Đối tượng** là thể hiện cụ thể của lớp, tồn tại trong bộ nhớ. - Trong C#, ta tạo đối tượng bằng `new`, ví dụ `Car a = new Car();`. - Từ một lớp tạo được nhiều đối tượng, mỗi đối tượng có dữ liệu riêng. - Viết lớp chưa tạo ra đối tượng nào. Đối tượng chỉ xuất hiện khi gọi `new`.
A4: 5 | B4: 2. Đối tượng, Lớp và Đóng gói (Encapsulation) | C4: Giới thiệu về Lớp và Đối tượng trong C# | D4: Tạo và Sử dụng Đối tượng | E4: Bài đọc | F4: Nên làm | G4: Done | H4: new tạo đối tượng; biến lớp chứa tham chiếu, không chứa đối tượng. | I4: 3 tab. Tab Tạo và dùng: new, gán trường, gọi phương thức, in console. Tab Gán tham chiếu: Car b = a; b.Color = "Đen"; in a.Color ra Đen vì a và b cùng trỏ Car#1. Tab null: Car c = null; c.Run(); dừng ở bước báo NullReferenceException (console hiện lỗi màu đỏ). | J4: 1 cột, nhiều tab | K4: oop_ooad/doi-tuong-lop-va-dong-goi-encapsulation/gioi-thieu-ve-lop-va-doi-tuong-trong-c-sharp/tao-va-su-dung-doi-tuong/index.html | L4: https://codegym-vn.github.io/programming-course-demos/oop_ooad/doi-tuong-lop-va-dong-goi-encapsulation/gioi-thieu-ve-lop-va-doi-tuong-trong-c-sharp/tao-va-su-dung-doi-tuong/ | M4: Tab 2 là ý quan trọng nhất, nên để mặc định. | P4: Tạo và Sử dụng Đối tượng Trong bài học trước, bạn đã làm quen với khái niệm Lớp (Class) như một bản thiết kế và Đối tượng (Object) như một thể hiện cụ thể của bản thiết kế đó. Nhưng làm thế nào để chúng ta biến bản thiết kế trừu tượng thành một "thực thể" hoạt động trong chương trình C# của mình? Đó chính là nội dung chúng ta sẽ khám phá trong trang bài đọc này: quy trình tạo (hay còn gọi là khởi tạo) và cách tương tác với các đối tượng. Khởi tạo Đối tượng: Biến Bản thiết kế thành Hiện thực Khi bạn định nghĩa một Lớp, bạn chỉ mới tạo ra một khuôn mẫu hoặc một kiểu dữ liệu tùy chỉnh. Lớp đó tự nó không chiếm bộ nhớ hoặc thực hiện bất kỳ hành động nào. Để sử dụng Lớp, bạn cần tạo ra một hoặc nhiều đối tượng từ Lớp đó. Quá trình này được gọi là khởi tạo đối tượng (object instantiation). Mỗi đối tượng được tạo ra là một thể hiện (instance) độc lập của lớp, có bộ nhớ riêng và có thể chứa các giá trị dữ liệu riêng biệt. Hãy hình dung bạn có bản thiết kế cho một ngôi nhà (lớp House). Để có một ngôi nhà thực tế, bạn cần xây dựng nó. Mỗi ngôi nhà được xây dựng từ bản thiết kế đó là một đối tượng House cụ thể, có thể có màu sơn khác nhau, số phòng khác nhau, dù chúng đều tuân theo cùng một cấu trúc cơ bản từ bản thiết kế. Sử dụng từ khóa new và Hàm tạo (Constructor) Trong C#, việc khởi tạo một đối tượng được thực hiện chủ yếu thông qua từ khóa new. Khi bạn sử dụng new, ba việc chính sẽ xảy ra: Cấp phát bộ nhớ: Hệ thống sẽ cấp phát một vùng nhớ trên Heap (khu vực bộ nhớ động) đủ lớn để chứa tất cả các trường (fields) của đối tượng mới. Khởi tạo mặc định: Các trường của đối tượng sẽ được khởi tạo với giá trị mặc định của kiểu dữ liệu tương ứng (ví dụ: 0 cho số nguyên, 0.0 cho số thực, false cho boolean, null cho các kiểu tham chiếu). Gọi Hàm tạo (Constructor): Một phương thức đặc biệt của lớp, được gọi là hàm tạo, sẽ được thực thi. Hàm tạo có nhiệm vụ thiết lập trạng thái ban đầu cho đối tượng, gán các giá trị khởi tạo cho các trường, hoặc thực hiện bất kỳ logic cần thiết nào để đối tượng sẵn sàng sử dụng. Cú pháp cơ bản để tạo một đối tượng là: TenLop tenDoiTuong = new TenLop(); Trong đó: TenLop: Là tên của lớp mà bạn muốn tạo đối tượng. tenDoiTuong: Là tên của biến tham chiếu sẽ "chứa" địa chỉ của đối tượng mới được tạo ra. new TenLop(): Là biểu thức thực hiện việc cấp phát bộ nhớ và gọi hàm tạo của TenLop. Ví dụ: Giả sử chúng ta có một lớp Student đơn giản: public class Student { public string Name; public int Age; // Đây là một hàm tạo (constructor) mặc định // Nếu bạn không định nghĩa, C# sẽ tự động cung cấp một cái. public Student() { Console.WriteLine("Một đối tượng Student mới đã được tạo!"); } } Để tạo một đối tượng Student từ lớp này, bạn sẽ làm như sau: // Khai báo một biến tham chiếu kiểu Student Student student1; // Sử dụng từ khóa 'new' để tạo một đối tượng Student và gán địa chỉ của nó cho student1 student1 = new Student(); // Hoặc kết hợp cả khai báo và khởi tạo trong một dòng: Student student2 = new Student(); Khi dòng Student student1 = new Student(); được thực thi, C# sẽ cấp phát bộ nhớ cho student1, các trường Name và Age sẽ được khởi tạo mặc định (null và 0), và sau đó hàm tạo Student() sẽ được gọi, in ra thông báo. Biến student1 lúc này không chứa bản thân đối tượng mà chứa tham chiếu (địa chỉ) đến đối tượng Student vừa được tạo trên bộ nhớ Heap. Truy cập các thành phần của Đối tượng với Toán tử Chấm (.) Sau khi một đối tượng đã được tạo, bạn cần cách để tương tác với nó – tức là truy cập và thay đổi dữ liệu của nó (các trường hoặc thuộc tính) hoặc yêu cầu nó thực hiện một hành động (gọi các phương thức). Trong C#, điều này được thực hiện thông qua toán tử chấm (.). Toán tử chấm cho phép bạn "đi vào bên trong" đối tượng để truy cập các thành phần công khai (public members) của nó. 1. Truy cập và thay đổi dữ liệu (Trường/Thuộc tính): Bạn có thể đọc hoặc gán giá trị cho các trường (hoặc thuộc tính, sẽ được học kỹ hơn trong bài về Đóng gói) của đối tượng bằng cách sử dụng toán tử chấm. Cú pháp: tenDoiTuong.tenTruong hoặc tenDoiTuong.TenThuocTinh Ví dụ tiếp nối lớp Student: public class Student { public string Name; public int Age; public Student() { Console.WriteLine("Một đối tượng Student mới đã được tạo!"); } public void DisplayInfo() { Console.WriteLine($"Tên: {Name}, Tuổi: {Age}"); } } // Trong phương thức Main hoặc một nơi nào đó trong chương trình của bạn: Student student1 = new Student(); // Tạo đối tượng // Gán giá trị cho các trường của student1 student1.Name = "Nguyễn Văn A"; student1.Age = 20; // Đọc giá trị từ các trường của student1 Console.WriteLine($"Tên của sinh viên là: {student1.Name}"); // Output: Tên của sinh viên là: Nguyễn Văn A Console.WriteLine($"Tuổi của sinh viên là: {student1.Age}"); // Output: Tuổi của sinh viên là: 20 // Tạo một đối tượng Student khác Student student2 = new Student(); student2.Name = "Trần Thị B"; student2.Age = 22; // student1 và student2 là hai đối tượng độc lập, // có dữ liệu riêng biệt mặc dù cùng được tạo từ lớp Student. Console.WriteLine($"Tên của sinh viên 2 là: {student2.Name}"); // Output: Tên của sinh viên 2 là: Trần Thị B 2. Gọi các phương thức (Methods): Các phương thức định nghĩa hành vi của đối tượng. Bạn gọi một phương thức của đối tượng bằng cách sử dụng toán tử chấm, theo sau là tên phương thức và dấu ngoặc đơn (có thể có hoặc không có đối số). Cú pháp: tenDoiTuong.TenPhuongThuc(doiSo1, doiSo2, ...); Ví dụ tiếp nối: // Tiếp tục từ ví dụ trên: Student student1 = new Student(); student1.Name = "Nguyễn Văn A"; student1.Age = 20; // Gọi phương thức DisplayInfo() của đối tượng student1 student1.DisplayInfo(); // Output: Tên: Nguyễn Văn A, Tuổi: 20 Student student2 = new Student(); student2.Name = "Trần Thị B"; student2.Age = 22; // Gọi phương thức DisplayInfo() của đối tượng student2 student2.DisplayInfo(); // Output: Tên: Trần Thị B, Tuổi: 22 Như bạn thấy, student1.DisplayInfo() và student2.DisplayInfo() đều gọi cùng một phương thức, nhưng vì chúng được gọi trên các đối tượng khác nhau, chúng sẽ hiển thị thông tin riêng của từng đối tượng. Đây là một trong những sức mạnh cốt lõi của lập trình hướng đối tượng: mỗi đối tượng hoạt động độc lập với dữ liệu của chính nó. Việc nắm vững cách tạo và sử dụng đối tượng là bước nền tảng quan trọng nhất để bạn có thể xây dựng các ứng dụng hướng đối tượng mạnh mẽ và linh hoạt trong C#. Trong các bài học tiếp theo, chúng ta sẽ đi sâu vào cách định nghĩa lớp một cách chi tiết hơn, bao gồm các loại thành phần khác nhau và cách kiểm soát quyền truy cập để bảo vệ dữ liệu. | Q4: # Tạo và Sử dụng Đối tượng ## Mục tiêu học tập Sau bài học này, bạn có thể: - Tạo đối tượng từ một lớp bằng từ khóa `new` và giải thích `new` làm những việc gì. - Dùng toán tử chấm (`.`) để gán trường và gọi phương thức của đối tượng. - Giải thích biến kiểu lớp chứa **tham chiếu** (reference) tới đối tượng, không chứa bản thân đối tượng. - Nhận ra khi gán `b = a` thì hai biến cùng trỏ tới một đối tượng. - Nhận ra lỗi `NullReferenceException` khi dùng biến đang là `null`. - Quan sát từng bước chạy qua ba tình huống trong hoạt động mô phỏng. ## Khởi tạo đối tượng Khi viết một lớp, ta mới tạo ra một bản thiết kế. Lớp tự nó không chiếm bộ nhớ cho dữ liệu và không làm gì cả. Muốn dùng, ta phải tạo **đối tượng** từ lớp. Việc này gọi là **khởi tạo đối tượng** (object instantiation). Mỗi đối tượng là một **thể hiện** (instance) độc lập, có vùng nhớ riêng và dữ liệu riêng. Trong bài này ta dùng lớp `Dog` (con chó) có trường `Name` và phương thức `Bark()`: ```csharp using System; public class Dog { public string Name; public void Bark() { string s = Name + ": Gâu!"; Console.WriteLine(s); } } ``` ### Từ khóa `new` Cú pháp tạo đối tượng: ```csharp Dog d = new Dog(); ``` Trong đó: - `Dog` (bên trái): kiểu của biến, tức tên lớp. - `d`: tên **biến tham chiếu**, nơi giữ "đường dẫn" tới đối tượng. - `new Dog()`: biểu thức tạo ra đối tượng mới. Khi chạy `new`, C# làm ba việc: 1. **Cấp phát bộ nhớ** trên vùng nhớ **heap** đủ chỗ cho các trường của đối tượng. 2. **Đặt giá trị mặc định** cho các trường: `0` cho số nguyên, `false` cho `bool`, `null` cho kiểu tham chiếu như `string`. 3. **Gọi hàm tạo** (constructor), một phương thức đặc biệt thiết lập trạng thái ban đầu. Nếu bạn không viết, C# tự cung cấp hàm tạo mặc định không làm gì thêm. Hàm tạo sẽ được học kỹ ở bài sau. Ở bài này, ta chỉ cần nhớ `new Dog()` luôn cho ra một đối tượng mới. ## Biến giữ tham chiếu, không giữ đối tượng Đây là điểm dễ nhầm nhất. Với kiểu lớp, biến `d` **không chứa** đối tượng `Dog`. Đối tượng nằm ở heap, còn `d` chỉ giữ **tham chiếu** (đường dẫn) tới nó. Hãy hình dung biến là một tấm danh thiếp ghi địa chỉ, còn đối tượng là căn nhà ở địa chỉ đó. Hệ quả: - Hai biến có thể cùng trỏ tới một đối tượng. - Một biến có thể không trỏ tới đối tượng nào, khi đó giá trị của nó là `null`. ## Dùng đối tượng với toán tử chấm Sau khi có đối tượng, ta dùng **toán tử chấm** (`.`) để "đi vào" bên trong nó. Dấu chấm đọc là "của đối tượng mà biến này trỏ tới". - Gán hoặc đọc trường: `tenBien.TenTruong` - Gọi phương thức: `tenBien.TenPhuongThuc(...)` ```csharp using System; public class Program { public static void Main() { Dog d = new Dog(); // tạo đối tượng, Name đang là null d.Name = "Lu"; // gán trường Name của đối tượng d trỏ tới d.Bark(); // Lu: Gâu! } } ``` Ba bước dùng đối tượng là: tạo bằng `new`, gán dữ liệu qua dấu chấm, gọi phương thức qua dấu chấm. Trong `Bark()`, `Name` là `Name` của chính đối tượng đang được gọi. ## Gán một biến đối tượng cho biến khác Điều gì xảy ra với `Dog b = a;`? Vì **không có `new`**, nên không có đối tượng mới nào được tạo. Biến `b` chỉ chép tham chiếu của `a`. Từ lúc này `a` và `b` cùng trỏ tới một con chó: ```csharp Dog a = new Dog(); a.Name = "Lu"; Dog b = a; // chép tham chiếu, không tạo chó mới b.Name = "Mực"; Console.WriteLine(a.Name); // Mực ``` Đổi tên qua `b` cũng là đổi tên của đối tượng mà `a` đang trỏ tới, nên `a.Name` in ra `Mực`. Muốn có con chó thứ hai thật sự, bạn phải dùng `new Dog()` một lần nữa. ## Biến `null` và NullReferenceException Biến kiểu lớp có thể mang giá trị `null`, nghĩa là chưa trỏ tới đối tượng nào. Nếu dùng dấu chấm trên biến `null`, chương trình không biết đối tượng nào để làm việc và dừng với lỗi: ```csharp Dog c = null; c.Bark(); // System.NullReferenceException: // Object reference not set to an instance of an object. ``` Cách tránh: luôn tạo đối tượng bằng `new` trước khi dùng dấu chấm, hoặc kiểm tra `c != null` khi chưa chắc biến đã trỏ tới đối tượng. ## Hoạt động: Tạo, gán tham chiếu và null Mô phỏng dưới đây có ba tab, dùng lớp `Dog` ở trên. Hãy thao tác theo thứ tự sau, bấm **Bước tiếp** để chạy từng dòng: - Mở tab **Tạo và dùng**. `new Dog()` tạo đối tượng `Dog#1` với `Name` là `null`, biến `d` trỏ tới nó. Sau `d.Name = "Lu"`, dòng `d.Bark()` nhảy vào thân `Bark()` và in `Lu: Gâu!`. - Chuyển sang tab **Gán tham chiếu**. Sau khi tạo `Dog#1` và đặt tên `Lu`, dòng `Dog b = a;` không tạo đối tượng mới. Ở vùng biến, `a` và `b` cùng trỏ tới `Dog#1`. Bước `b.Name = "Mực"` đổi chính `Dog#1`, nên `Console.WriteLine(a.Name)` in ra `Mực`, không phải `Lu`. - Mở tab **Biến null**. Dòng `Dog c = null;` cho `c` giá trị `null`, trong heap chưa có `Dog` nào. Dòng `c.Bark();` làm console hiện lỗi màu đỏ `System.NullReferenceException` và chương trình dừng. ``` <iframe src="https://codegym-vn.github.io/programming-course-demos/oop_ooad/doi-tuong-lop-va-dong-goi-encapsulation/gioi-thieu-ve-lop-va-doi-tuong-trong-c-sharp/tao-va-su-dung-doi-tuong/" title="Tạo và Sử dụng Đối tượng" style="border:0;" allowfullscreen></iframe> ``` Điều rút ra: biến kiểu lớp chỉ giữ tham chiếu tới đối tượng. Gán biến này cho biến khác chỉ chép tham chiếu, nên sửa qua biến nào cũng thấy ở biến kia. Biến `null` thì chưa có đối tượng để dùng. ## Tóm tắt - Viết lớp chưa tạo đối tượng. Dùng `new TenLop()` để tạo đối tượng mới trên heap. - `new` cấp phát bộ nhớ, đặt giá trị mặc định cho trường, rồi gọi hàm tạo. - Dùng toán tử chấm `.` để gán trường và gọi phương thức của đối tượng. - Biến kiểu lớp giữ **tham chiếu**. `Dog b = a;` chỉ chép tham chiếu, `a` và `b` cùng trỏ một đối tượng. - Biến `null` chưa trỏ tới đối tượng nào. Dùng dấu chấm trên nó gây `NullReferenceException`.
A5: 6 | B5: 2. Đối tượng, Lớp và Đóng gói (Encapsulation) | C5: Các Thành phần của Lớp: Trường và Phương thức | D5: Trường (Fields) trong C# | E5: Bài đọc | F5: Nên làm | G5: Done | H5: Trường là dữ liệu của đối tượng; có giá trị mặc định; mỗi đối tượng giữ bản riêng. | I5: 2 tab. Tab Giá trị mặc định: new Student() chưa gán gì, bộ nhớ hiện Name = null, Age = 0, IsActive = false; sau đó gán từng trường. Tab Mỗi đối tượng một bản: s1.Age = 18; s2.Age = 20; đổi s1 không ảnh hưởng s2 (ô s2 giữ nguyên, ô s1 tô vàng). | J5: 1 cột, nhiều tab | K5: oop_ooad/doi-tuong-lop-va-dong-goi-encapsulation/cac-thanh-phan-cua-lop-truong-va-phuong-thuc/truong-fields-trong-c-sharp/index.html | L5: https://codegym-vn.github.io/programming-course-demos/oop_ooad/doi-tuong-lop-va-dong-goi-encapsulation/cac-thanh-phan-cua-lop-truong-va-phuong-thuc/truong-fields-trong-c-sharp/ | P5: Trường (Fields) là gì? Trong lập trình hướng đối tượng (OOP) nói chung và C# nói riêng, các đối tượng được xây dựng để mô phỏng các thực thể trong thế giới thực. Mỗi thực thể này có những đặc điểm riêng biệt và những hành động mà nó có thể thực hiện. Trường (field) là một thành phần cơ bản của lớp, đóng vai trò lưu trữ dữ liệu, đại diện cho trạng thái hay đặc điểm của một đối tượng. Hãy hình dung một đối tượng XeOto. Chiếc xe này có thể có các đặc điểm như: màu sắc, số bánh, tốc độ hiện tại, hãng sản xuất, v.v. Những đặc điểm này chính là các trường của lớp XeOto. Khi bạn tạo ra một đối tượng XeOto cụ thể (ví dụ: myCar), các trường này sẽ giữ những giá trị riêng biệt cho myCar (ví dụ: màu đỏ, tốc độ 60 km/h). Mỗi đối tượng được tạo ra từ cùng một lớp sẽ có bộ trường riêng của nó, với các giá trị có thể khác nhau, tạo nên sự độc đáo cho từng đối tượng. "Trường là một biến cấp lớp (class-level variable) được sử dụng để lưu trữ dữ liệu cho một đối tượng." Vai trò chính của trường là: Lưu trữ trạng thái: Ghi nhớ các thông tin cần thiết về đối tượng. Phân biệt đối tượng: Giúp phân biệt các đối tượng cùng loại với nhau thông qua các giá trị dữ liệu khác nhau mà chúng nắm giữ. Các Kiểu Dữ liệu của Trường Một trường có thể lưu trữ bất kỳ loại dữ liệu hợp lệ nào trong C#. Điều này có nghĩa là bạn có thể khai báo một trường với hầu hết các kiểu dữ liệu mà bạn đã quen thuộc, cũng như các kiểu dữ liệu phức tạp hơn. Dưới đây là một số kiểu dữ liệu phổ biến thường được sử dụng cho các trường: Kiểu số nguyên:int, long, short, byte (ví dụ: soBanhXe, soCua). Kiểu số thực:float, double, decimal (ví dụ: giaBan, quangDuongDaDi). Kiểu ký tự/chuỗi:char, string (ví dụ: mauSac, tenHangSanXuat). Kiểu Boolean:bool (ví dụ: coKhoaCua, dangBatMayLanh). Kiểu ngày/giờ:DateTime (ví dụ: ngaySanXuat). Các kiểu dữ liệu khác: Bạn cũng có thể sử dụng các kiểu dữ liệu phức tạp hơn như mảng (arrays), danh sách (lists), hoặc thậm chí là các đối tượng của các lớp khác mà bạn tự định nghĩa (ví dụ: một trường kiểu DongCo trong lớp XeOto). Việc lựa chọn kiểu dữ liệu phù hợp cho mỗi trường là rất quan trọng để đảm bảo dữ liệu được lưu trữ chính xác và hiệu quả. Cách Khai báo Trường trong Lớp Để khai báo một trường trong C#, bạn cần đặt nó bên trong định nghĩa của một lớp. Cú pháp cơ bản bao gồm một bộ định danh truy cập (access modifier), kiểu dữ liệu của trường và tên của trường đó. Cú pháp chung: [access_modifier] [data_type] [field_name]; access_modifier: Xác định phạm vi truy cập của trường. Các bộ định danh phổ biến bao gồm public, private, protected. Trong ngữ cảnh của các trường lưu trữ trạng thái nội bộ của đối tượng, private là bộ định danh được sử dụng phổ biến nhất để tuân thủ nguyên tắc đóng gói (Encapsulation) mà chúng ta sẽ tìm hiểu sâu hơn sau này. private có nghĩa là trường đó chỉ có thể được truy cập từ bên trong chính lớp đó. data_type: Kiểu dữ liệu mà trường sẽ lưu trữ (ví dụ: int, string, bool). field_name: Tên của trường. Theo quy ước của C#, tên trường thường bắt đầu bằng ký tự thường và sử dụng camelCase (ví dụ: tenSanPham, maSo). Nếu là trường private, đôi khi người ta dùng quy ước bắt đầu bằng dấu gạch dưới _ (ví dụ: _tenSanPham). Hãy xem ví dụ về lớp SanPham (Sản phẩm) và cách khai báo các trường của nó: public class SanPham { // Trường private để lưu trữ mã sản phẩm private string _maSanPham; // Trường private để lưu trữ tên sản phẩm private string _tenSanPham; // Trường private để lưu trữ giá của sản phẩm private decimal _gia; // Trường private để lưu trữ số lượng tồn kho private int _soLuongTonKho; // Trường private để kiểm tra sản phẩm có còn hàng hay không private bool _conHang; // Constructor (chúng ta sẽ học về nó sau) public SanPham(string ma, string ten, decimal gia, int soLuong) { _maSanPham = ma; _tenSanPham = ten; _gia = gia; _soLuongTonKho = soLuong; _conHang = (soLuong > 0); } } Trong ví dụ trên: _maSanPham, _tenSanPham, _gia, _soLuongTonKho, _conHang là các trường của lớp SanPham. Chúng được khai báo với bộ định danh private, nghĩa là chúng chỉ có thể được truy cập và sửa đổi từ bên trong lớp SanPham. Mỗi trường có một kiểu dữ liệu cụ thể (string, decimal, int, bool) để phù hợp với loại dữ liệu mà nó cần lưu trữ. Giá trị Mặc định của Trường Một điểm quan trọng cần lưu ý khi làm việc với các trường trong C# là chúng sẽ tự động được khởi tạo với một giá trị mặc định nếu bạn không gán giá trị rõ ràng cho chúng khi khai báo hoặc thông qua constructor. Đây là một điểm khác biệt so với các biến cục bộ (local variables) trong phương thức, vốn yêu cầu phải được khởi tạo trước khi sử dụng. Giá trị mặc định phụ thuộc vào kiểu dữ liệu của trường: Kiểu số nguyên (int, long, short, byte, v.v.): 0 Kiểu số thực (float, double, decimal): 0.0 Kiểu Boolean (bool): false Kiểu ký tự (char): '\0' (ký tự null) Kiểu tham chiếu (reference types - ví dụ: string, các đối tượng của lớp khác): null Hãy xem một ví dụ để hiểu rõ hơn: public class HocVien { // Trường string (kiểu tham chiếu) public string tenHocVien; // Trường int (kiểu giá trị) public int tuoi; // Trường bool (kiểu giá trị) public bool daHoanThanhKhoaHoc; // Trường decimal (kiểu giá trị) public decimal diemTrungBinh; } // Trong một phương thức khác (ví dụ: Main) public class ChuongTrinh { public static void Main(string[] args) { HocVien hocVienMoi = new HocVien(); // Nếu không khởi tạo, các trường sẽ có giá trị mặc định: Console.WriteLine($"Tên: {hocVienMoi.tenHocVien ?? "NULL"}"); // Output: Tên: NULL Console.WriteLine($"Tuổi: {hocVienMoi.tuoi}"); // Output: Tuổi: 0 Console.WriteLine($"Đã hoàn thành khóa học: {hocVienMoi.daHoanThanhKhoaHoc}"); // Output: Đã hoàn thành khóa học: False Console.WriteLine($"Điểm trung bình: {hocVienMoi.diemTrungBinh}"); // Output: Điểm trung bình: 0.0 } } Trong ví dụ trên, khi đối tượng hocVienMoi được tạo, các trường của nó tự động nhận giá trị mặc định. tenHocVien là null vì string là kiểu tham chiếu, tuoi là 0, daHoanThanhKhoaHoc là false, và diemTrungBinh là 0.0. Hiểu rõ về giá trị mặc định giúp bạn tránh được các lỗi không mong muốn khi làm việc với dữ liệu của đối tượng và đảm bảo rằng các trường luôn có một trạng thái ban đầu xác định. Với kiến thức về trường, bạn đã nắm được cách một đối tượng lưu trữ dữ liệu. Ở bài đọc tiếp theo, chúng ta sẽ tìm hiểu về phương thức (methods), thành phần giúp đối tượng thực hiện các hành vi dựa trên dữ liệu mà các trường lưu trữ. | Q5: # Trường (Fields) trong C# ## Mục tiêu học tập Sau bài học này, bạn có thể: - Giải thích trường (field) là biến khai báo trong lớp, dùng để lưu dữ liệu của đối tượng. - Khai báo trường với bộ định danh truy cập, kiểu dữ liệu và tên. - Nêu giá trị mặc định của trường: `null`, `0`, `false`. - Phân biệt trường với biến cục bộ (local variable) ở điểm có giá trị mặc định. - Giải thích mỗi đối tượng giữ một bản trường riêng. - Quan sát giá trị mặc định và dữ liệu riêng của từng đối tượng bằng hoạt động mô phỏng. ## Trường là gì? Mỗi đối tượng có những đặc điểm riêng. Một sinh viên có tên, tuổi. Một chiếc xe có màu, tốc độ. Những đặc điểm này được lưu trong **trường** (field). **Trường là một biến khai báo trực tiếp trong lớp, dùng để lưu trạng thái của đối tượng.** Vai trò chính của trường: - **Lưu trạng thái:** ghi nhớ thông tin cần thiết về đối tượng. - **Phân biệt đối tượng:** hai đối tượng cùng lớp khác nhau nhờ giá trị trường khác nhau. ## Khai báo trường Trường được đặt bên trong lớp, nhưng ngoài mọi phương thức. Cú pháp: ```csharp [bộ_định_danh_truy_cập] kiểu_dữ_liệu tên_trường; ``` - **Bộ định danh truy cập** (access modifier): quyết định ai được dùng trường. `public` cho phép truy cập từ bên ngoài lớp, `private` chỉ cho phép trong chính lớp. Để bảo vệ dữ liệu, trường thường để `private`. Bài sau sẽ học kỹ phần này. Trong các ví dụ đầu, ta tạm dùng `public` cho dễ quan sát. - **Kiểu dữ liệu:** trường có thể là `int`, `double`, `decimal`, `bool`, `char`, `string`, `DateTime`, mảng, danh sách, hoặc một lớp khác do bạn định nghĩa. - **Tên trường:** với trường `private`, người ta thường dùng tiền tố gạch dưới và camelCase, ví dụ `_name`. Với trường `public`, nhiều nhóm dùng PascalCase như `Name`. Lớp `Student` trong bài này có ba trường: ```csharp public class Student { public string Name; public int Age; public bool IsActive; } ``` ## Giá trị mặc định của trường Khi tạo đối tượng bằng `new`, mọi trường **tự động** nhận một giá trị mặc định nếu bạn chưa gán gì: | Kiểu của trường | Giá trị mặc định | |---|---| | Số nguyên (`int`, `long`, `byte`...) | `0` | | Số thực (`double`, `float`, `decimal`) | `0` (viết đầy đủ là `0.0`) | | `bool` | `false` | | `char` | ký tự `'\0'` | | Kiểu tham chiếu (`string`, đối tượng của lớp khác) | `null` | Đây là điểm khác với **biến cục bộ** khai báo trong phương thức: biến cục bộ phải được gán giá trị trước khi dùng, nếu không trình biên dịch báo lỗi. Trường thì luôn có giá trị ban đầu xác định. ```csharp using System; public class Student { public string Name; public int Age; public bool IsActive; } public class Program { public static void Main() { Student s = new Student(); Console.WriteLine(s.Name ?? "null"); // null Console.WriteLine(s.Age); // 0 Console.WriteLine(s.IsActive); // False s.Name = "An"; s.Age = 18; s.IsActive = true; } } ``` Lưu ý: `Console.WriteLine` in giá trị `bool` là `True` hoặc `False` (viết hoa chữ cái đầu). Chuỗi `null` in ra là chuỗi rỗng, nên ví dụ trên dùng `??` để hiện chữ `null`. ## Mỗi đối tượng một bản trường Trường thuộc về **từng đối tượng**. Nếu lớp `Student` có trường `Age`, thì mỗi `Student` được tạo ra có một ô `Age` riêng: ```csharp Student s1 = new Student(); Student s2 = new Student(); s1.Age = 18; s2.Age = 20; s1.Age = 19; // chỉ đổi ô Age của s1, s2.Age vẫn là 20 ``` Vì vậy đổi dữ liệu của đối tượng này không ảnh hưởng đến đối tượng khác. ## Hoạt động: Giá trị mặc định và dữ liệu riêng Mô phỏng dưới đây có hai tab. Hãy thao tác theo thứ tự sau, bấm **Bước tiếp** để chạy từng dòng: - Mở tab **Giá trị mặc định**. Lớp `Student` có `Name`, `Age`, `IsActive`. Ngay sau `new Student()` mà chưa gán gì, bộ nhớ đã hiện `Name = null`, `Age = 0`, `IsActive = false`. Sau đó ba dòng gán lần lượt thay bằng `"An"`, `18` và `true`. - Chuyển sang tab **Mỗi đối tượng một bản**. Lớp `Student` chỉ có trường `Age`. Dòng `var s1 = new Student();` tạo `Student#1`, dòng `var s2 = new Student();` tạo `Student#2`, mỗi đối tượng có ô `Age` riêng bằng 0. Sau `s1.Age = 18` và `s2.Age = 20`, hai ô có giá trị khác nhau. Khi đổi `s1.Age = 19`, ô của `s1` được tô vàng còn ô của `s2` giữ nguyên 20. ``` <iframe src="https://codegym-vn.github.io/programming-course-demos/oop_ooad/doi-tuong-lop-va-dong-goi-encapsulation/cac-thanh-phan-cua-lop-truong-va-phuong-thuc/truong-fields-trong-c-sharp/" title="Trường (Fields)" style="border:0;" allowfullscreen></iframe> ``` Điều rút ra: trường chưa gán vẫn có giá trị mặc định xác định (`null`, `0`, `false`), và mỗi đối tượng giữ một bản trường riêng của mình. ## Tóm tắt - **Trường** là biến khai báo trong lớp, lưu trạng thái của đối tượng. - Cú pháp: bộ định danh truy cập, kiểu dữ liệu, tên trường. - Trường chưa gán có giá trị mặc định: `null` cho kiểu tham chiếu, `0` cho số, `false` cho `bool`. - Biến cục bộ phải được gán trước khi dùng, còn trường thì tự có giá trị mặc định. - Mỗi đối tượng có bản trường riêng. Đổi đối tượng này không ảnh hưởng đối tượng kia. - Bài sau sẽ học phương thức, thành phần giúp đối tượng thực hiện hành vi dựa trên các trường.
A6: 7 | B6: 2. Đối tượng, Lớp và Đóng gói (Encapsulation) | C6: Các Thành phần của Lớp: Trường và Phương thức | D6: Phương thức (Methods) và Hành vi của Đối tượng | E6: Bài đọc | F6: Nên làm | G6: Done | H6: Gọi phương thức: truyền tham số, chạy thân hàm, đổi trạng thái đối tượng, trả về giá trị. | I6: Lớp Counter có Count và Add(int step) trả về Count mới. Main gọi c.Add(2) rồi c.Add(3). Dòng tô sáng nhảy từ Main vào thân Add rồi quay lại. Bộ nhớ hiện ngăn gọi hàm: tham số step, đối tượng đang dùng (this →Counter#1), giá trị trả về; ngăn biến mất khi hàm kết thúc. Nhập được giá trị bước (1-9). | J6: 1 cột | K6: oop_ooad/doi-tuong-lop-va-dong-goi-encapsulation/cac-thanh-phan-cua-lop-truong-va-phuong-thuc/phuong-thuc-methods-va-hanh-vi-cua-doi-tuong/index.html | L6: https://codegym-vn.github.io/programming-course-demos/oop_ooad/doi-tuong-lop-va-dong-goi-encapsulation/cac-thanh-phan-cua-lop-truong-va-phuong-thuc/phuong-thuc-methods-va-hanh-vi-cua-doi-tuong/ | M6: Có ô nhập step. | P6: Phương thức (Methods) và Hành vi của Đối tượng Trong bài học trước, chúng ta đã tìm hiểu về trường (fields) – những thành phần dùng để lưu trữ dữ liệu, định nghĩa trạng thái hay đặc điểm của một đối tượng. Tuy nhiên, một đối tượng không chỉ có trạng thái; nó còn có thể thực hiện các hành động hoặc hành vi. Đây chính là lúc phương thức (methods) phát huy vai trò của mình. Phương thức là gì và Vai trò của nó? Nếu bạn hình dung một đối tượng là một thực thể trong thế giới thực (ví dụ: một chiếc xe hơi, một con người, một tài khoản ngân hàng), thì: Các trường sẽ là các thuộc tính của thực thể đó (ví dụ: màu sắc, tốc độ hiện tại của xe; tên, tuổi của người; số dư, chủ tài khoản ngân hàng). Các phương thức chính là các hành động mà thực thể đó có thể thực hiện hoặc những thao tác mà người khác có thể tác động lên nó (ví dụ: xe có thể KhởiĐộng(), TăngTốc(), Phanh(); người có thể GiớiThiệuBảnThân(), ĐiBộ(), Ăn(); tài khoản có thể GửiTiền(), RútTiền()). Trong lập trình hướng đối tượng, phương thức là một khối mã lệnh được đặt tên, thực hiện một nhiệm vụ cụ thể. Nó định nghĩa hành vi của một lớp và các đối tượng được tạo ra từ lớp đó. Phương thức cho phép đối tượng: Thực hiện hành động: Chứa logic để thay đổi trạng thái của đối tượng (thay đổi giá trị của các trường) hoặc thực hiện các tác vụ khác. Tương tác với bên ngoài: Nhận dữ liệu đầu vào (thông qua tham số) và/hoặc trả về kết quả (thông qua kiểu trả về). Đóng gói logic: Giúp tổ chức mã nguồn, làm cho mã dễ đọc, dễ bảo trì và tái sử dụng hơn. Cú pháp khai báo phương thức trong C# Để khai báo một phương thức trong C#, chúng ta cần chỉ rõ các thành phần sau: <bổ_từ_truy_cập> <kiểu_trả_về> TênPhươngThức(<danh_sách_tham_số>) { // Phần thân phương thức: chứa các câu lệnh } Hãy cùng phân tích từng thành phần: <bổ_từ_truy_cập> (Access Modifier): Xác định phạm vi truy cập của phương thức (ví dụ: public, private, protected). Chúng ta sẽ tìm hiểu sâu hơn về chúng trong bài học về đóng gói. Hiện tại, bạn có thể dùng public để phương thức có thể được gọi từ bên ngoài lớp. <kiểu_trả_về> (Return Type): Kiểu dữ liệu của giá trị mà phương thức sẽ trả về sau khi hoàn thành công việc. Nếu phương thức không trả về giá trị nào, bạn sử dụng từ khóa void. Nếu phương thức trả về một giá trị, bạn phải chỉ rõ kiểu dữ liệu của giá trị đó (ví dụ: int, string, bool, double, hoặc một kiểu lớp khác). Phương thức phải chứa câu lệnh return với giá trị có kiểu dữ liệu tương ứng. TênPhươngThức (Method Name): Tên định danh cho phương thức. Theo quy ước chuẩn của C# (PascalCase), tên phương thức nên bắt đầu bằng một chữ cái viết hoa và thường là một động từ hoặc cụm động từ miêu tả hành động mà phương thức thực hiện (ví dụ: CalculateSum, PrintDetails, GetAge). <danh_sách_tham_số> (Parameter List): Một danh sách các biến được khai báo bên trong dấu ngoặc đơn (), phân tách bằng dấu phẩy. Các tham số này là dữ liệu đầu vào mà phương thức cần để thực hiện công việc của nó. Mỗi tham số bao gồm kiểu_dữ_liệu và tên_tham_số. Nếu phương thức không cần dữ liệu đầu vào, danh sách tham số sẽ để trống (). Phần thân phương thức: Là khối mã lệnh nằm trong cặp dấu ngoặc nhọn {}. Đây là nơi chứa logic thực thi của phương thức. Ví dụ về khai báo phương thức: public class ConNguoi { public string Ten; // Trường public int Tuoi; // Trường // Phương thức không có tham số, không trả về giá trị (void) public void GioiThieu() { Console.WriteLine($"Xin chào, tôi là {Ten} và tôi {Tuoi} tuổi."); } // Phương thức có tham số, không trả về giá trị (void) public void ChucMungSinhNhat(int namHienTai) { Tuoi = namHienTai - (DateTime.Now.Year - Tuoi); // Giả sử Tuoi ban đầu là tuổi hiện tại Console.WriteLine($"{Ten} vừa đón sinh nhật! Tuổi mới là {Tuoi}."); } // Phương thức có tham số và trả về giá trị (int) public int TinhNamSinh(int namHienTai) { return namHienTai - Tuoi; } } Cách gọi phương thức và truyền đối số Sau khi đã định nghĩa một lớp với các phương thức, để thực sự sử dụng chúng, chúng ta cần tạo một đối tượng từ lớp đó và sau đó gọi phương thức trên đối tượng đó. Cú pháp để gọi một phương thức là: tên_đối_tượng.TênPhươngThức(đối_số); tên_đối_tượng: Là tên của biến đối tượng mà bạn đã tạo. TênPhươngThức: Tên của phương thức bạn muốn gọi. đối_số: Các giá trị thực tế được truyền vào phương thức. Các đối số này phải tương ứng về số lượng, thứ tự và kiểu dữ liệu với các tham số đã được định nghĩa trong phương thức. Lưu ý quan trọng: Tham số (Parameters): Là các biến được khai báo trong định nghĩa phương thức, dùng để nhận giá trị. Đối số (Arguments): Là các giá trị thực tế được truyền vào phương thức khi nó được gọi. Ví dụ về cách gọi phương thức: Tiếp tục với lớp ConNguoi ở trên: // Tạo một đối tượng từ lớp ConNguoi ConNguoi alice = new ConNguoi(); alice.Ten = "Alice"; alice.Tuoi = 30; // Gọi phương thức không có tham số alice.GioiThieu(); // Output: Xin chào, tôi là Alice và tôi 30 tuổi. // Gọi phương thức có tham số alice.ChucMungSinhNhat(2023); // Output: Alice vừa đón sinh nhật! Tuổi mới là 30. (Giả sử Tuoi ban đầu là 30, năm hiện tại 2023, vậy tuổi vẫn là 30. Cần sửa logic ChucMungSinhNhat cho đúng: Tuoi++; ) // Let's fix the ChucMungSinhNhat logic for the example to make more sense. // Original: Tuoi = namHienTai - (DateTime.Now.Year - Tuoi); This recalculates based on initial age and current year. // Better: Tuoi++; for a birthday. Or pass new age. // For the purpose of demonstration, let's assume the original `Tuoi` is `current age`. // If `Tuoi` is `birth year`, then `Tuoi = namHienTai - Tuoi;` or `Tuoi = namHienTai - namSinh;` // Let's simplify and make `ChucMungSinhNhat` simply increment `Tuoi`. // Corrected ConNguoi class for better example: /* public class ConNguoi { public string Ten; public int Tuoi; public void GioiThieu() { Console.WriteLine($"Xin chào, tôi là {Ten} và tôi {Tuoi} tuổi."); } public void ChucMungSinhNhat() // No parameter, just increments age { Tuoi++; // Tăng tuổi lên 1 Console.WriteLine($"{Ten} vừa đón sinh nhật! Tuổi mới là {Tuoi}."); } public int TinhNamSinh(int namHienTai) { return namHienTai - Tuoi; } } */ // Rerun the invocation example with the simplified ChucMungSinhNhat. // Assuming the class definition is now fixed: // Tạo một đối tượng từ lớp ConNguoi ConNguoi alice = new ConNguoi(); alice.Ten = "Alice"; alice.Tuoi = 30; // Gọi phương thức không có tham số alice.GioiThieu(); // Output: Xin chào, tôi là Alice và tôi 30 tuổi. // Gọi phương thức có tham số (nếu có) // alice.ChucMungSinhNhat(2023); // This method signature changed. // Let's use the original method for `ChucMungSinhNhat` to stick to the outline example. // The original `ChucMungSinhNhat(int namHienTai)` was a bit confusing. // Let's make a new method `DatLaiTuoi(int tuoiMoi)` for argument passing clarity. /* public class ConNguoi { public string Ten; public int Tuoi; public void GioiThieu() { Console.WriteLine($"Xin chào, tôi là {Ten} và tôi {Tuoi} tuổi."); } // Phương thức có tham số, không trả về giá trị (void) public void DatLaiTuoi(int tuoiMoi) { if (tuoiMoi > Tuoi) // Chỉ cập nhật nếu tuổi mới lớn hơn tuổi hiện tại { Tuoi = tuoiMoi; Console.WriteLine($"{Ten} đã cập nhật tuổi mới thành {Tuoi}."); } else { Console.WriteLine($"Tuổi mới {tuoiMoi} không hợp lệ cho {Ten}."); } } // Phương thức có tham số và trả về giá trị (int) public int TinhNamSinh(int namHienTai) { return namHienTai - Tuoi; } } */ // Now, let's write the invocation example based on this revised class. ```csharp // Tạo một đối tượng từ lớp ConNguoi ConNguoi alice = new ConNguoi(); alice.Ten = "Alice"; alice.Tuoi = 30; Console.WriteLine("--- Hành động của Alice ---"); // Gọi phương thức không có tham số alice.GioiThieu(); // Output: Xin chào, tôi là Alice và tôi 30 tuổi. // Gọi phương thức có tham số để thay đổi trạng thái đối tượng alice.DatLaiTuoi(31); // Output: Alice đã cập nhật tuổi mới thành 31. // Gọi lại phương thức để thấy sự thay đổi trạng thái alice.GioiThieu(); // Output: Xin chào, tôi là Alice và tôi 31 tuổi. // Gọi phương thức có tham số và nhận giá trị trả về int namSinhCuaAlice = alice.TinhNamSinh(2023); Console.WriteLine($"Năm sinh của Alice là: {namSinhCuaAlice}"); // Output: Năm sinh của Alice là: 1992 (2023 - 31) // Bạn cũng có thể dùng giá trị trả về trực tiếp Console.WriteLine($"Alice sẽ 32 tuổi vào năm {alice.TinhNamSinh(2023) + 32}."); // Output: Alice sẽ 32 tuổi vào năm 2024. (Năm sinh 1992 + 32 = 2024) Qua ví dụ trên, bạn có thể thấy rằng phương thức không chỉ giúp chúng ta thực hiện các hành động mà còn là cầu nối để đối tượng tương tác với thế giới bên ngoài, nhận thông tin (tham số) và cung cấp kết quả (giá trị trả về). Đây là một trong những viên gạch cơ bản nhất để xây dựng các ứng dụng hướng đối tượng mạnh mẽ và linh hoạt. | Q6: # Phương thức (Methods) và Hành vi của Đối tượng ## Mục tiêu học tập Sau bài học này, bạn có thể: - Giải thích phương thức (method) là khối mã có tên, mô tả hành vi của đối tượng. - Đọc và viết khai báo phương thức: bộ định danh truy cập, kiểu trả về, tên, danh sách tham số. - Phân biệt tham số (parameter) với đối số (argument), `void` với phương thức có giá trị trả về. - Giải thích phương thức có thể đổi trường của đối tượng và trả về một giá trị cho nơi gọi. - Quan sát tham số đi vào, thân hàm chạy và giá trị trả về bằng hoạt động mô phỏng. ## Phương thức là gì? Bài trước ta học **trường**, nơi lưu dữ liệu và trạng thái của đối tượng. Nhưng đối tượng không chỉ có dữ liệu, nó còn **làm được việc**. Những việc đó được viết thành **phương thức** (method). Hãy nghĩ đến một tài khoản ngân hàng. Số dư và chủ tài khoản là trường. Gửi tiền, rút tiền là phương thức. Phương thức là một khối mã có tên, thực hiện một nhiệm vụ cụ thể. Nó cho phép đối tượng: - **Thực hiện hành động:** đổi giá trị các trường hoặc làm việc khác. - **Giao tiếp với bên ngoài:** nhận dữ liệu qua tham số và trả kết quả qua giá trị trả về. - **Gói gọn logic:** mã dễ đọc, dễ bảo trì, dễ tái sử dụng. ## Khai báo phương thức ```csharp bộ_định_danh_truy_cập kiểu_trả_về TênPhươngThức(danh_sách_tham_số) { // thân phương thức } ``` - **Bộ định danh truy cập** (access modifier): ví dụ `public` để gọi được từ bên ngoài lớp. Phần này sẽ học kỹ ở bài về đóng gói. - **Kiểu trả về** (return type): kiểu của giá trị phương thức trả về. Nếu không trả gì thì dùng `void`. Nếu có trả giá trị thì phải có câu lệnh `return` đúng kiểu. - **Tên phương thức:** theo quy ước C#, viết PascalCase và thường là động từ, ví dụ `Add`, `PrintDetails`, `GetAge`. - **Danh sách tham số** (parameter list): các biến đầu vào, mỗi tham số gồm kiểu và tên, cách nhau bằng dấu phẩy. Không cần đầu vào thì để `()`. - **Thân phương thức:** các câu lệnh nằm trong cặp `{ }`. Lớp `Counter` dưới đây có trường `Count` và phương thức `Add(int step)`: ```csharp public class Counter { public int Count; public int Add(int step) { Count += step; return Count; } } ``` `Add` nhận một tham số `step`, cộng vào trường `Count` (đổi trạng thái của đối tượng) rồi trả về `Count` mới. ## Gọi phương thức Muốn gọi phương thức, ta cần một đối tượng, rồi dùng toán tử chấm: ```csharp tên_đối_tượng.TênPhươngThức(đối_số); ``` Hai thuật ngữ hay bị lẫn: - **Tham số** (parameter): biến khai báo trong định nghĩa phương thức, ví dụ `step` trong `Add(int step)`. - **Đối số** (argument): giá trị thực tế truyền vào khi gọi, ví dụ `2` trong `c.Add(2)`. Đối số phải khớp tham số về số lượng, thứ tự và kiểu. ```csharp using System; public class Counter { public int Count; public int Add(int step) { Count += step; return Count; } } public class Program { public static void Main() { Counter c = new Counter(); int r1 = c.Add(2); // Count = 2, r1 = 2 int r2 = c.Add(3); // Count = 5, r2 = 5 Console.WriteLine(r1); // 2 Console.WriteLine(r2); // 5 Console.WriteLine(c.Count); // 5 } } ``` Chú ý: `Count` là trường của đối tượng nên giá trị được giữ lại sau mỗi lần gọi. Còn tham số `step` chỉ tồn tại trong lúc phương thức đang chạy. ## Phương thức `void` và phương thức có giá trị trả về ```csharp public void Reset() // không trả giá trị { Count = 0; } public int Add(int step) // trả về một int { Count += step; return Count; } ``` Phương thức trả về giá trị có thể được dùng như một biểu thức: gán vào biến (`int r1 = c.Add(2);`) hoặc dùng trực tiếp trong câu lệnh khác. ## Từ khóa `this` Bên trong phương thức, `this` chỉ đến **chính đối tượng đang được gọi**. Khi bạn viết `c.Add(2)`, thì trong `Add`, `this` trỏ tới đối tượng mà `c` đang trỏ tới. Nhờ vậy `Count` trong thân hàm là `Count` của đúng đối tượng đó. Thông thường bạn không cần viết `this.Count`, chỉ cần viết `Count`. ## Hoạt động: Theo dõi lời gọi c.Add(step) Mô phỏng dưới đây dùng lớp `Counter` ở trên. Bạn có thể đổi giá trị `step` của lần gọi đầu (từ 1 đến 9, mặc định là 2). Hãy thao tác theo thứ tự sau, bấm **Bước tiếp** để chạy từng dòng: - Mở tab **Counter.Add(step)**. Dòng `var c = new Counter();` tạo `Counter#1` với `Count = 0`. - Dòng `int r1 = c.Add(2);` (với `step` mặc định là 2) làm dòng tô sáng nhảy từ `Main` vào thân `Add`. Bộ nhớ hiện một ngăn gọi hàm có tham số `step = 2` và `this` trỏ tới `Counter#1`. Dòng `Count += step` đổi `Count` từ 0 thành 2. Dòng `return Count` đặt giá trị trả về 2. - Khi quay về `Main`, ngăn gọi hàm biến mất. `r1` nhận giá trị 2 và `Count` vẫn là 2. - Dòng `int r2 = c.Add(3);` lặp lại quá trình với `step = 3`. `Count` đổi từ 2 thành 5, hàm trả về 5, và `r2` nhận 5. Hãy thử đổi `step` rồi chạy lại để thấy các số thay đổi theo. ``` <iframe src="https://codegym-vn.github.io/programming-course-demos/oop_ooad/doi-tuong-lop-va-dong-goi-encapsulation/cac-thanh-phan-cua-lop-truong-va-phuong-thuc/phuong-thuc-methods-va-hanh-vi-cua-doi-tuong/" title="Gọi phương thức" style="border:0;" allowfullscreen></iframe> ``` Điều rút ra: gọi phương thức là truyền tham số vào, chạy thân hàm, có thể đổi trạng thái của đối tượng (trường `Count`) và trả về một giá trị. Ngăn gọi hàm biến mất khi hàm kết thúc, còn trường của đối tượng thì ở lại. ## Tóm tắt - **Phương thức** là khối mã có tên, mô tả hành vi của đối tượng. - Khai báo gồm: bộ định danh truy cập, kiểu trả về, tên (PascalCase), danh sách tham số, thân hàm. - **Tham số** nằm trong định nghĩa, **đối số** là giá trị truyền khi gọi. - `void` nghĩa là không trả giá trị. Kiểu khác thì phải có `return` đúng kiểu. - Phương thức có thể đổi trường của đối tượng. Trường giữ giá trị sau khi hàm kết thúc, còn tham số thì mất. - Bên trong phương thức, `this` là chính đối tượng đang được gọi.
A7: 9 | B7: 2. Đối tượng, Lớp và Đóng gói (Encapsulation) | C7: Nguyên lý Đóng gói (Encapsulation) và Kiểm soát truy cập | D7: Đóng gói là gì? Tại sao lại cần Đóng gói? | E7: Bài đọc | F7: Nên làm | G7: Done | H7: Ẩn dữ liệu, chỉ cho thay đổi qua phương thức có kiểm tra. | I7: 2 cột cùng kịch bản (gửi 100, rút 500). Cột trái: public decimal Balance, code bên ngoài gán acc.Balance -= 500 → số dư âm -400. Cột phải: private balance + Withdraw(amount) kiểm tra đủ tiền → từ chối, số dư giữ 100. Câu kết so sánh hai số dư cuối. | J7: 2 cột song song | K7: oop_ooad/doi-tuong-lop-va-dong-goi-encapsulation/nguyen-ly-dong-goi-encapsulation-va-kiem-soat-truy-cap/dong-goi-la-gi-tai-sao-lai-can-dong-goi/index.html | L7: https://codegym-vn.github.io/programming-course-demos/oop_ooad/doi-tuong-lop-va-dong-goi-encapsulation/nguyen-ly-dong-goi-encapsulation-va-kiem-soat-truy-cap/dong-goi-la-gi-tai-sao-lai-can-dong-goi/ | P7: Đóng gói (Encapsulation) là gì? Đóng gói (Encapsulation) là một trong bốn trụ cột cơ bản của Lập trình Hướng đối tượng (OOP), cùng với Kế thừa, Đa hình và Trừu tượng. Về cơ bản, đóng gói là nguyên lý kết hợp dữ liệu (các trường/thuộc tính) và các phương thức (hành vi) thao tác trên dữ liệu đó thành một đơn vị duy nhất – một lớp (class). Đồng thời, nó cũng là cơ chế ẩn đi chi tiết cài đặt bên trong của một đối tượng khỏi thế giới bên ngoài, chỉ cho phép truy cập thông qua một giao diện được định nghĩa rõ ràng. Hãy hình dung một chiếc điều khiển TV. Bạn biết cách sử dụng các nút (tăng giảm âm lượng, chuyển kênh) để tương tác với TV. Bạn không cần biết bên trong điều khiển có những mạch điện, chip xử lý nào, hay cách các nút đó thực sự gửi tín hiệu đến TV ra sao. Điều khiển TV đã đóng gói toàn bộ logic phức tạp bên trong, chỉ phơi bày ra một giao diện đơn giản (các nút bấm) để bạn sử dụng. Trong OOP, nguyên lý đóng gói cũng hoạt động tương tự. Một lớp sẽ chứa các dữ liệu (trạng thái của đối tượng) và các phương thức (hành vi của đối tượng). Bằng cách sử dụng các từ khóa kiểm soát truy cập (như private, public mà bạn sẽ tìm hiểu chi tiết hơn trong bài đọc "Các Từ khóa Kiểm soát Truy cập"), chúng ta có thể quyết định phần nào của đối tượng có thể được truy cập trực tiếp từ bên ngoài và phần nào nên được giữ kín. Mục tiêu chính là bảo vệ dữ liệu nội bộ và đảm bảo rằng đối tượng luôn ở trong một trạng thái hợp lệ. Tại sao lại cần Đóng gói? Lợi ích cốt lõi Đóng gói không chỉ là một khái niệm lý thuyết mà còn mang lại nhiều lợi ích thiết thực trong quá trình phát triển phần mềm: Bảo vệ dữ liệu (Data Protection và Data Integrity) Đóng gói giúp ngăn chặn việc truy cập và thay đổi trực tiếp các trường dữ liệu nội bộ của một đối tượng từ bên ngoài. Thay vào đó, mọi thao tác với dữ liệu phải thông qua các phương thức hoặc thuộc tính (properties) được kiểm soát. Điều này cho phép chúng ta áp dụng các quy tắc hoặc logic kiểm tra tính hợp lệ trước khi dữ liệu được thay đổi, đảm bảo rằng đối tượng luôn duy trì một trạng thái hợp lệ và nhất quán. Ví dụ: Một đối tượng TaiKhoanNganHang (Tài khoản ngân hàng) có số dư. Nếu số dư được truy cập trực tiếp, bất kỳ ai cũng có thể đặt nó về một giá trị âm. Với đóng gói, chúng ta có thể viết một phương thức RutTien() kiểm tra xem số dư có đủ hay không trước khi thực hiện giao dịch, hoặc một thuộc tính SoDu chỉ cho phép đọc từ bên ngoài và thay đổi qua các phương thức GuiTien() hoặc RutTien(). Tăng tính bảo mật (Increased Security) Mặc dù không phải bảo mật theo nghĩa mã hóa, đóng gói tăng cường "bảo mật" cho cấu trúc nội bộ của chương trình. Nó che giấu các chi tiết cài đặt phức tạp khỏi người dùng (các lập trình viên khác sử dụng lớp đó). Điều này giúp giảm thiểu rủi ro các thành phần bên ngoài vô tình hoặc cố ý làm hỏng trạng thái của đối tượng bằng cách truy cập các thành phần nội bộ không đúng cách. Dễ bảo trì và mở rộng (Easier Maintenance and Scalability) Khi các chi tiết cài đặt của một lớp được đóng gói, bạn có thể thay đổi cách thức hoạt động nội bộ của lớp đó mà không ảnh hưởng đến các phần khác của chương trình, miễn là giao diện công khai (public interface) của lớp không thay đổi. Điều này làm cho việc sửa lỗi, cải tiến hiệu suất hoặc thêm chức năng mới trở nên dễ dàng hơn rất nhiều, vì bạn chỉ cần tập trung vào một phần nhỏ của mã mà không phải lo lắng về việc phá vỡ các phần phụ thuộc khác. Giảm sự phụ thuộc giữa các thành phần (Reduced Coupling) Đóng gói thúc đẩy việc tương tác giữa các đối tượng thông qua các giao diện được định nghĩa rõ ràng, thay vì thông qua việc truy cập trực tiếp vào các chi tiết cài đặt. Điều này làm giảm sự phụ thuộc (coupling) giữa các lớp. Khi các lớp ít phụ thuộc vào nhau, chúng trở nên độc lập hơn, dễ kiểm thử hơn và dễ tái sử dụng hơn trong các dự án khác. Đóng gói trong thực tế: So sánh truy cập trực tiếp và kiểm soát Để hiểu rõ hơn về tầm quan trọng của đóng gói, hãy xem xét một ví dụ thực tế về một lớp TaiKhoanNganHang. Kịch bản 1: Không đóng gói (Truy cập trực tiếp các trường công khai) Trong kịch bản này, chúng ta định nghĩa các trường dữ liệu của tài khoản là public, cho phép mọi thành phần bên ngoài truy cập và thay đổi trực tiếp. public class TaiKhoanNganHangKhongDongGoi { public string SoTaiKhoan; public string TenChuTaiKhoan; public decimal SoDu; // Có thể bị thay đổi trực tiếp public TaiKhoanNganHangKhongDongGoi(string soTK, string tenCTK, decimal soDuBanDau) { SoTaiKhoan = soTK; TenChuTaiKhoan = tenCTK; SoDu = soDuBanDau; } } Khi sử dụng lớp này, bạn có thể thấy vấn đề: TaiKhoanNganHangKhongDongGoi tk = new TaiKhoanNganHangKhongDongGoi("123456", "Nguyen Van A", 1000m); Console.WriteLine($"Số dư ban đầu: {tk.SoDu}"); // Output: 1000 // Vấn đề: Có thể thay đổi trực tiếp số dư mà không có kiểm tra tk.SoDu = -500m; // Gán một giá trị không hợp lệ! Console.WriteLine($"Số dư sau khi thay đổi trực tiếp: {tk.SoDu}"); // Output: -500 // Hoặc tệ hơn, có thể gán giá trị mà không qua logic nghiệp vụ tk.SoDu += 200m; // Ai đó có thể "gửi tiền" bằng cách này mà không qua quy trình Như bạn thấy, việc truy cập trực tiếp trường SoDu cho phép gán bất kỳ giá trị nào, kể cả giá trị âm, làm hỏng tính toàn vẹn dữ liệu của đối tượng và bỏ qua mọi logic nghiệp vụ liên quan đến việc gửi/rút tiền. Kịch bản 2: Áp dụng Đóng gói (Sử dụng thuộc tính và phương thức) Bây giờ, chúng ta sẽ áp dụng đóng gói bằng cách định nghĩa các trường dữ liệu là private và cung cấp các thuộc tính (property) hoặc phương thức (method) công khai để kiểm soát việc truy cập và thay đổi dữ liệu. public class TaiKhoanNganHangDongGoi { // Các trường dữ liệu được đánh dấu là private để ẩn đi chi tiết cài đặt private string _soTaiKhoan; private string _tenChuTaiKhoan; private decimal _soDu; // Thuộc tính công khai để truy cập _soTaiKhoan và _tenChuTaiKhoan (chỉ đọc) public string SoTaiKhoan { get { return _soTaiKhoan; } } public string TenChuTaiKhoan { get { return _tenChuTaiKhoan; } } // Thuộc tính công khai để đọc _soDu, nhưng không cho phép gán trực tiếp public decimal SoDu { get { return _soDu; } // set { _soDu = value; } // Không có setter công khai để kiểm soát việc thay đổi } public TaiKhoanNganHangDongGoi(string soTK, string tenCTK, decimal soDuBanDau) { // Có thể thêm kiểm tra tính hợp lệ tại đây if (string.IsNullOrWhiteSpace(soTK) || string.IsNullOrWhiteSpace(tenCTK) || soDuBanDau < 0) { throw new ArgumentException("Thông tin tài khoản không hợp lệ."); } _soTaiKhoan = soTK; _tenChuTaiKhoan = tenCTK; _soDu = soDuBanDau; } // Phương thức công khai để gửi tiền, có logic kiểm tra public void GuiTien(decimal soTien) { if (soTien <= 0) { throw new ArgumentException("Số tiền gửi phải lớn hơn 0."); } _soDu += soTien; Console.WriteLine($"Đã gửi {soTien:C}. Số dư mới: {_soDu:C}"); } // Phương thức công khai để rút tiền, có logic kiểm tra public bool RutTien(decimal soTien) { if (soTien <= 0) { throw new ArgumentException("Số tiền rút phải lớn hơn 0."); } if (_soDu >= soTien) { _soDu -= soTien; Console.WriteLine($"Đã rút {soTien:C}. Số dư mới: {_soDu:C}"); return true; } else { Console.WriteLine("Không đủ số dư để rút tiền."); return false; } } } Và cách sử dụng: TaiKhoanNganHangDongGoi tkDongGoi = new TaiKhoanNganHangDongGoi("987654", "Tran Thi B", 500m); Console.WriteLine($"Số dư ban đầu: {tkDongGoi.SoDu}"); // Output: 500 // tkDongGoi.SoDu = -100m; // Lỗi biên dịch: Không thể gán giá trị cho 'SoDu' vì nó là thuộc tính chỉ đọc // tkDongGoi._soDu = -100m; // Lỗi biên dịch: '_soDu' không thể truy cập được do mức độ bảo vệ của nó tkDongGoi.GuiTien(200m); // Output: Đã gửi 200.00. Số dư mới: 700.00 tkDongGoi.RutTien(800m); // Output: Không đủ số dư để rút tiền. tkDongGoi.RutTien(300m); // Output: Đã rút 300.00. Số dư mới: 400.00 Trong kịch bản này, bạn thấy rằng: Các trường dữ liệu như _soTaiKhoan, _tenChuTaiKhoan và _soDu được khai báo là private, nghĩa là chúng chỉ có thể được truy cập từ bên trong lớp TaiKhoanNganHangDongGoi này. Chúng ta cung cấp các thuộc tính public như SoTaiKhoan, TenChuTaiKhoan, SoDu chỉ với get accessor, cho phép bên ngoài đọc giá trị nhưng không thể gán trực tiếp. Mọi thay đổi đối với số dư phải thông qua các phương thức GuiTien() và RutTien(). Các phương thức này chứa logic kiểm tra để đảm bảo rằng số tiền gửi/rút hợp lệ và tài khoản không bị rơi vào trạng thái không mong muốn (ví dụ: số dư âm). Đây chính là sức mạnh của đóng gói: nó bảo vệ dữ liệu, kiểm soát hành vi và tạo ra một giao diện rõ ràng, an toàn để tương tác với đối tượng. | Q7: # Đóng gói là gì? Tại sao lại cần Đóng gói? ## Mục tiêu học tập Sau bài học này, bạn có thể: - Giải thích đóng gói (encapsulation) là gom dữ liệu và phương thức vào một lớp, đồng thời ẩn chi tiết bên trong. - Nêu vì sao để trường `public` có thể làm đối tượng rơi vào trạng thái sai. - Viết lớp đóng gói đúng cách: trường `private` và phương thức `public` có kiểm tra. - Kể ra các lợi ích của đóng gói: bảo vệ dữ liệu, dễ bảo trì, giảm phụ thuộc. - Quan sát cùng một kịch bản chạy trên hai lớp, có và không có đóng gói, bằng hoạt động mô phỏng. ## Đóng gói là gì? **Đóng gói** (Encapsulation) là một trong bốn trụ cột của OOP, cùng với kế thừa, đa hình và trừu tượng. Đóng gói có hai ý: - **Gom lại:** đặt dữ liệu (trường) và các phương thức xử lý dữ liệu đó vào cùng một đơn vị, là lớp. - **Giấu đi:** che chi tiết bên trong của đối tượng, chỉ cho bên ngoài tác động qua một "giao diện" công khai được định nghĩa rõ. Hãy nghĩ đến chiếc điều khiển TV. Bạn bấm nút tăng giảm âm lượng, đổi kênh. Bạn không cần biết mạch điện bên trong hay tín hiệu được gửi đi thế nào. Điều khiển đã giấu phần phức tạp, chỉ đưa ra vài nút đơn giản. Trong C#, ta dùng từ khóa kiểm soát truy cập như `private` và `public` để quyết định phần nào của đối tượng được truy cập từ bên ngoài. Mục tiêu là bảo vệ dữ liệu nội bộ, để đối tượng **luôn ở trạng thái hợp lệ**. ## Vấn đề khi không đóng gói Giả sử ta viết lớp `Account` (tài khoản) với số dư là trường `public`: ```csharp public class Account { public decimal Balance; } ``` Bất kỳ đoạn mã nào cũng gán trực tiếp được cho `Balance`, không ai kiểm tra: ```csharp Account acc = new Account(); acc.Balance = 100; // nạp 100 acc.Balance -= 500; // rút 500, số dư thành -400 ``` Tài khoản chỉ có 100 mà vẫn rút được 500, số dư thành **-400**. Đây là trạng thái không được phép xảy ra, và không có cơ chế nào ngăn chặn. ## Giải pháp: đóng gói Ta để trường ở `private` và chỉ cho bên ngoài thay đổi thông qua phương thức `public` có kiểm tra: ```csharp using System; public class Account { private decimal balance; // ẩn khỏi bên ngoài public void Deposit(decimal x) { if (x > 0) balance += x; } public bool Withdraw(decimal x) { if (x > balance) return false; // không đủ tiền, từ chối balance -= x; return true; } public decimal GetBalance() { return balance; } } public class Program { public static void Main() { Account acc = new Account(); acc.Deposit(100); acc.Withdraw(500); // bị từ chối Console.WriteLine(acc.GetBalance()); // 100 // acc.balance = -400; // lỗi biên dịch CS0122: 'balance' không truy cập được } } ``` Giờ muốn đổi số dư, bên ngoài buộc phải gọi `Deposit()` hoặc `Withdraw()`. Hai phương thức này kiểm tra điều kiện trước khi đổi, nên số dư không thể âm. Ngoài phương thức, C# còn có **thuộc tính** (property) giúp đọc và ghi dữ liệu private gọn hơn. Ta sẽ học ở các bài sau. ## Tại sao cần đóng gói? Các lợi ích - **Bảo vệ dữ liệu và giữ tính toàn vẹn:** mọi thay đổi đi qua phương thức có kiểm tra, nên đối tượng luôn hợp lệ và nhất quán. - **Che chi tiết cài đặt:** các lập trình viên khác chỉ cần biết cách dùng lớp, không cần biết bên trong. Điều này cũng giảm nguy cơ vô tình làm hỏng trạng thái đối tượng. - **Dễ bảo trì và mở rộng:** bạn đổi cách làm bên trong lớp mà không ảnh hưởng nơi khác, miễn là các phương thức `public` giữ nguyên. - **Giảm phụ thuộc** (coupling): các lớp tương tác qua giao diện rõ ràng thay vì chạm vào chi tiết nội bộ nhau, nên dễ kiểm thử và tái sử dụng hơn. ## Hoạt động: Rút quá số dư Mô phỏng dưới đây chạy **cùng một kịch bản** (nạp 100 rồi rút 500) trên hai lớp `Account`. Hãy thao tác theo thứ tự sau, bấm **Bước tiếp** để hai cột cùng chạy: - Mở tab **Rút quá số dư**. Cột trái là **Không đóng gói**: `Balance` là `public`. Cột phải là **Có đóng gói**: `balance` là `private`, chỉ đổi qua phương thức. - Bước tạo tài khoản: ở cột trái `Balance` mặc định là 0. Ở cột phải, `balance` là `private` nên code bên ngoài không đọc hay sửa trực tiếp được. - Bước nạp 100: cột trái gán thẳng `acc.Balance = 100`. Cột phải gọi `Deposit(100)`, vì `x = 100 > 0` nên `balance` tăng lên 100. - Bước rút 500: cột trái chạy `acc.Balance -= 500` không ai kiểm tra, số dư thành **-400** (tô đỏ). Cột phải gọi `Withdraw(500)`, vì `500 > 100` nên phương thức trả về `false` và không trừ tiền, số dư giữ **100**. - Dòng cuối in số dư: cột trái in `-400`, cột phải in `100`. Câu kết so sánh hai số dư cuối. ``` <iframe src="https://codegym-vn.github.io/programming-course-demos/oop_ooad/doi-tuong-lop-va-dong-goi-encapsulation/nguyen-ly-dong-goi-encapsulation-va-kiem-soat-truy-cap/dong-goi-la-gi-tai-sao-lai-can-dong-goi/" title="Đóng gói là gì?" style="border:0;" allowfullscreen></iframe> ``` Điều rút ra: số dư cuối bên trái là -400 (sai), bên phải là 100 (đúng). Đóng gói nghĩa là để dữ liệu ở `private` và chỉ cho thay đổi qua phương thức `public` có kiểm tra, nhờ đó đối tượng luôn ở trạng thái hợp lệ. ## Tóm tắt - **Đóng gói** là gom dữ liệu và phương thức vào lớp, đồng thời giấu chi tiết bên trong. - Trường `public` cho phép bên ngoài sửa tùy ý, có thể làm đối tượng rơi vào trạng thái sai, ví dụ số dư âm. - Cách làm đúng: trường `private`, phương thức `public` có kiểm tra điều kiện. - Mã bên ngoài truy cập trường `private` sẽ bị lỗi biên dịch CS0122. - Lợi ích: bảo vệ dữ liệu, dễ bảo trì và mở rộng, giảm phụ thuộc giữa các lớp.
A8: 10 | B8: 2. Đối tượng, Lớp và Đóng gói (Encapsulation) | C8: Nguyên lý Đóng gói (Encapsulation) và Kiểm soát truy cập | D8: Các Từ khóa Kiểm soát Truy cập (Access Modifiers) | E8: Bài đọc | F8: Nên làm | G8: Done | H8: public, private, protected, internal: ai được truy cập thành viên nào. | I8: 4 tab theo vị trí code đứng: Trong chính lớp, Trong lớp con, Lớp khác cùng project, Project khác. Mỗi bước thử truy cập một thành viên (public/private/protected/internal), ô kết quả hiện ✓ được phép (xanh) hoặc ✗ lỗi biên dịch CS0122 (đỏ). Bước cuối hiện bảng tổng hợp 4x4. | J8: 1 cột, nhiều tab | K8: oop_ooad/doi-tuong-lop-va-dong-goi-encapsulation/nguyen-ly-dong-goi-encapsulation-va-kiem-soat-truy-cap/cac-tu-khoa-kiem-soat-truy-cap-access-modifiers/index.html | L8: https://codegym-vn.github.io/programming-course-demos/oop_ooad/doi-tuong-lop-va-dong-goi-encapsulation/nguyen-ly-dong-goi-encapsulation-va-kiem-soat-truy-cap/cac-tu-khoa-kiem-soat-truy-cap-access-modifiers/ | M8: Không chạy code thật, mô phỏng kết quả biên dịch theo luật C#. | P8: Giới thiệu các Từ khóa Kiểm soát Truy cập Trong bài đọc trước, chúng ta đã tìm hiểu về nguyên lý Đóng gói (Encapsulation) và tầm quan trọng của nó trong việc bảo vệ dữ liệu, che giấu chi tiết cài đặt bên trong một đối tượng. Để thực sự hiện thực hóa nguyên lý đóng gói trong C#, chúng ta cần đến các Từ khóa Kiểm soát Truy cập (Access Modifiers). Các từ khóa này cho phép bạn định nghĩa phạm vi hiển thị và khả năng truy cập của các thành viên (trường dữ liệu, thuộc tính, phương thức, sự kiện) bên trong một lớp, hoặc thậm chí là bản thân lớp đó. Bằng cách sử dụng chúng một cách hợp lý, bạn có thể kiểm soát chặt chẽ ai có thể "nhìn thấy" và "tương tác" với các thành phần của đối tượng, từ đó duy trì tính toàn vẹn và dễ bảo trì của mã nguồn. C# cung cấp một số từ khóa kiểm soát truy cập chính: public, private, protected, và internal. Chúng ta sẽ đi sâu vào từng loại để hiểu rõ ý nghĩa và cách sử dụng của chúng. public: Truy cập Mọi Nơi Từ khóa public là từ khóa kiểm soát truy cập ít hạn chế nhất. Khi một thành viên (hoặc bản thân một lớp) được khai báo là public, nó có thể được truy cập từ bất kỳ đâu trong dự án của bạn, không có giới hạn. Điều này có nghĩa là bất kỳ lớp nào, trong bất kỳ assembly nào, đều có thể truy cập thành viên public đó. Sử dụng public khi bạn muốn một thành viên hoặc một lớp cung cấp một giao diện công khai để các phần khác của ứng dụng có thể tương tác. Ví dụ, các phương thức để thực hiện hành động chính của một đối tượng thường là public. Ví dụ: public class SinhVien { public string Ten { get; set; } // Thuộc tính Ten có thể truy cập từ bên ngoài public string MaSoSinhVien { get; private set; } // MaSoSinhVien có thể đọc từ bên ngoài, nhưng chỉ có thể gán giá trị bên trong lớp public SinhVien(string ten, string maSo) { Ten = ten; MaSoSinhVien = maSo; // Có thể gán giá trị bên trong lớp } public void HienThiThongTin() // Phương thức công khai { Console.WriteLine($"Tên: {Ten}, Mã số: {MaSoSinhVien}"); } } // Trong một lớp khác hoặc chương trình chính: public class ChuongTrinh { public static void Main(string[] args) { SinhVien sv = new SinhVien("Nguyen Van A", "SV001"); Console.WriteLine($"Tên sinh viên: {sv.Ten}"); // Truy cập thuộc tính public sv.HienThiThongTin(); // Gọi phương thức public // sv.MaSoSinhVien = "SV002"; // Lỗi: setter là private } } Trong ví dụ trên, Ten và HienThiThongTin() là public, cho phép chúng ta dễ dàng truy cập từ bên ngoài lớp SinhVien. Lưu ý cách setter của MaSoSinhVien là private, chúng ta sẽ tìm hiểu về nó tiếp theo. private: Chỉ Truy cập Trong Cùng Lớp Ngược lại với public, từ khóa private là từ khóa kiểm soát truy cập hạn chế nhất. Khi một thành viên được khai báo là private, nó chỉ có thể được truy cập từ bên trong cùng một lớp mà nó được định nghĩa. Không có lớp nào khác, kể cả các lớp kế thừa, có thể truy cập trực tiếp thành viên private. private là xương sống của nguyên lý đóng gói. Nó cho phép bạn ẩn đi các chi tiết cài đặt nội bộ, các trường dữ liệu hoặc các phương thức hỗ trợ chỉ dùng cho mục đích nội bộ của lớp. Việc này giúp bảo vệ trạng thái của đối tượng khỏi sự thay đổi không mong muốn từ bên ngoài và làm cho mã nguồn dễ quản lý hơn. Ví dụ: public class TaiKhoanNganHang { private decimal _soDu; // Trường _soDu là private, chỉ truy cập trong lớp TaiKhoanNganHang public TaiKhoanNganHang(decimal soDuBanDau) { _soDu = soDuBanDau; } public void NapTien(decimal soTien) { if (soTien > 0) { _soDu += soTien; Console.WriteLine($"Đã nạp {soTien}. Số dư hiện tại: {_soDu}"); } } public void RutTien(decimal soTien) { if (soTien > 0 && _soDu >= soTien) { _soDu -= soTien; Console.WriteLine($"Đã rút {soTien}. Số dư hiện tại: {_soDu}"); } else { Console.WriteLine("Không đủ số dư hoặc số tiền không hợp lệ."); } } public decimal LaySoDu() // Phương thức public để đọc giá trị của _soDu { return _soDu; } } // Trong một lớp khác: public class GiaoDich { public static void Main(string[] args) { TaiKhoanNganHang tk = new TaiKhoanNganHang(1000); // Console.WriteLine(tk._soDu); // Lỗi: _soDu là private tk.NapTien(500); tk.RutTien(200); Console.WriteLine($"Số dư cuối cùng: {tk.LaySoDu()}"); // Truy cập gián tiếp qua phương thức public } } Ở đây, _soDu được giữ private, đảm bảo rằng không ai có thể trực tiếp thay đổi số dư từ bên ngoài. Thay vào đó, bạn phải sử dụng các phương thức public như NapTien() và RutTien(), cho phép lớp kiểm soát logic nghiệp vụ và tính hợp lệ của các giao dịch. protected: Truy cập trong Cùng Lớp và Lớp Kế Thừa Từ khóa protected cung cấp một mức độ truy cập trung gian, hữu ích khi làm việc với kế thừa. Một thành viên được khai báo là protected có thể được truy cập: Từ bên trong cùng lớp mà nó được định nghĩa. Từ bên trong các lớp kế thừa từ lớp đó. Nó không thể được truy cập từ bên ngoài lớp hoặc các lớp không kế thừa. protected cho phép các lớp con truy cập và mở rộng hành vi của lớp cha một cách có kiểm soát, trong khi vẫn giữ các chi tiết triển khai cụ thể ẩn khỏi thế giới bên ngoài. Ví dụ: public class HinhDang { protected double ChieuRong { get; set; } // Có thể truy cập bởi lớp con protected double ChieuCao { get; set; } // Có thể truy cập bởi lớp con public HinhDang(double rong, double cao) { ChieuRong = rong; ChieuCao = cao; } protected void InKichThuoc() // Phương thức protected { Console.WriteLine($"Chiều rộng: {ChieuRong}, Chiều cao: {ChieuCao}"); } } public class HinhChuNhat : HinhDang // HinhChuNhat kế thừa từ HinhDang { public HinhChuNhat(double rong, double cao) : base(rong, cao) { // Có thể truy cập ChieuRong và ChieuCao (protected) từ lớp cha Console.WriteLine("Khởi tạo Hình chữ nhật."); InKichThuoc(); // Gọi phương thức protected từ lớp cha } public double TinhDienTich() { return ChieuRong * ChieuCao; // Truy cập ChieuRong và ChieuCao (protected) } } // Trong một lớp khác: public class VeHinh { public static void Main(string[] args) { HinhChuNhat hcn = new HinhChuNhat(10, 5); Console.WriteLine($"Diện tích Hình chữ nhật: {hcn.TinhDienTich()}"); // HinhDang hinh = new HinhDang(10, 5); // hinh.InKichThuoc(); // Lỗi: InKichThuoc là protected, không thể gọi từ bên ngoài lớp hoặc lớp con } } Trong ví dụ này, ChieuRong, ChieuCao và InKichThuoc() của lớp HinhDang được khai báo là protected. Điều này cho phép lớp HinhChuNhat (là lớp con của HinhDang) truy cập và sử dụng chúng để tính toán diện tích hoặc in thông tin, nhưng các lớp không liên quan hoặc code bên ngoài không thể truy cập trực tiếp. internal: Truy cập trong Cùng Assembly Từ khóa internal cho phép truy cập đến các thành viên hoặc lớp trong cùng một assembly. Một assembly trong C# thường là một file .dll (thư viện) hoặc .exe (ứng dụng) đã được biên dịch. Điều này có nghĩa là nếu bạn định nghĩa một thành viên là internal trong một thư viện, tất cả các lớp trong cùng thư viện đó có thể truy cập nó, nhưng các lớp trong một thư viện hoặc ứng dụng khác (ngay cả khi nó tham chiếu thư viện của bạn) thì không thể. internal rất hữu ích khi bạn đang xây dựng một thư viện và muốn các thành phần cụ thể chỉ được sử dụng nội bộ trong thư viện đó, không phải là một phần của API công khai mà người dùng thư viện có thể truy cập. Ví dụ: Giả sử bạn có một dự án thư viện tên là MyBankingLib và một dự án ứng dụng tên là MyBankApp tham chiếu đến MyBankingLib. // Trong dự án MyBankingLib (assembly MyBankingLib.dll) public class KhachHang { public string TenKhachHang { get; set; } internal string MaSoNoiBo { get; private set; } // Chỉ truy cập trong MyBankingLib public KhachHang(string ten, string maSo) { TenKhachHang = ten; MaSoNoiBo = maSo; } internal void GhiLogHoatDong(string hoatDong) // Phương thức internal { Console.WriteLine($"[{DateTime.Now}] Khách hàng {TenKhachHang} - {hoatDong}"); } } internal class TienIchNoiBo // Một lớp internal, chỉ có thể được sử dụng trong MyBankingLib { public static void XuLyDuLieuMat() { Console.WriteLine("Đang xử lý dữ liệu nội bộ của ngân hàng..."); } } // Trong dự án MyBankApp (assembly MyBankApp.exe), tham chiếu MyBankingLib.dll public class UngDung { public static void Main(string[] args) { KhachHang kh = new KhachHang("Tran Thi B", "NB002"); Console.WriteLine($"Tên khách hàng: {kh.TenKhachHang}"); // Console.WriteLine(kh.MaSoNoiBo); // Lỗi: MaSoNoiBo là internal, không thể truy cập từ MyBankApp // kh.GhiLogHoatDong("Đăng nhập"); // Lỗi: GhiLogHoatDong là internal // TienIchNoiBo.XuLyDuLieuMat(); // Lỗi: TienIchNoiBo là internal class } } // Nhưng trong một lớp khác của MyBankingLib: public class QuanLyKhachHang { public void CapNhatKhachHang(KhachHang khachHang) { khachHang.MaSoNoiBo = "NewInternalCode"; // OK: truy cập trong cùng assembly khachHang.GhiLogHoatDong("Cập nhật thông tin"); // OK: truy cập trong cùng assembly TienIchNoiBo.XuLyDuLieuMat(); // OK: truy cập trong cùng assembly } } Trong ví dụ này, MaSoNoiBo và GhiLogHoatDong() của lớp KhachHang, cùng với lớp TienIchNoiBo hoàn toàn, chỉ có thể được truy cập bởi các lớp khác trong cùng assembly MyBankingLib. Khi MyBankApp cố gắng truy cập chúng, trình biên dịch sẽ báo lỗi, đảm bảo rằng các chi tiết triển khai nội bộ của thư viện được bảo vệ. Kết hợp các Từ khóa và Tầm quan trọng của chúng Việc lựa chọn từ khóa kiểm soát truy cập phù hợp là một phần thiết yếu của thiết kế hướng đối tượng tốt. Nó cho phép bạn: Thực thi Đóng gói: Bằng cách sử dụng private và protected để ẩn đi trạng thái nội bộ và chi tiết triển khai, bạn đảm bảo rằng đối tượng chỉ có thể được thao tác thông qua giao diện public được kiểm soát. Giảm sự phụ thuộc: Khi bạn thay đổi một thành viên private, bạn không cần phải lo lắng về việc phá vỡ mã ở các phần khác của ứng dụng. Tạo API rõ ràng: Các thành viên public định nghĩa rõ ràng cách các đối tượng khác tương tác với lớp của bạn, trong khi internal giúp tạo ra các thư viện có API rõ ràng và được kiểm soát. Hỗ trợ Kế thừa có kiểm soát: protected cho phép các lớp con mở rộng và tùy chỉnh hành vi của lớp cha mà không làm lộ quá nhiều chi tiết ra bên ngoài. Khi thiết kế một lớp, hãy luôn bắt đầu với mức độ truy cập hạn chế nhất có thể (private) và chỉ mở rộng phạm vi truy cập khi thực sự cần thiết. Cách tiếp cận này giúp tạo ra các hệ thống mạnh mẽ, dễ bảo trì và mở rộng. | Q8: # Các Từ khóa Kiểm soát Truy cập (Access Modifiers) ## Mục tiêu học tập Sau bài học này, bạn có thể: - Giải thích từ khóa kiểm soát truy cập (access modifier) quyết định ai được dùng một thành viên của lớp. - Phân biệt bốn mức truy cập: `public`, `private`, `protected` và `internal`. - Xác định một đoạn code ở vị trí nào có được dùng thành viên đó hay không. - Nhận ra lỗi biên dịch CS0122 khi truy cập sai mức. - Quan sát kết quả truy cập ở bốn vị trí code khác nhau bằng hoạt động mô phỏng. ## Từ khóa kiểm soát truy cập là gì? Bài trước ta thấy đóng gói cần giấu dữ liệu. Để làm được việc đó trong C#, ta dùng **từ khóa kiểm soát truy cập** (access modifier). Từ khóa này đặt trước một thành viên (trường, thuộc tính, phương thức) hoặc trước bản thân lớp, để quyết định **ai được "nhìn thấy" và dùng** nó. C# có bốn mức chính: `public`, `private`, `protected`, `internal`. ## `public`: truy cập ở mọi nơi `public` ít hạn chế nhất. Thành viên `public` được truy cập từ bất kỳ đâu, kể cả từ project khác. Dùng `public` cho những gì bạn muốn công khai làm "giao diện" của lớp, ví dụ các phương thức thực hiện hành động chính. ## `private`: chỉ trong chính lớp `private` hạn chế nhất. Thành viên `private` chỉ dùng được bên trong **chính lớp** khai báo nó. Ngay cả lớp con cũng không truy cập được. Đây là nền tảng của đóng gói: giấu trường và các phương thức hỗ trợ nội bộ. ```csharp using System; public class Account { private decimal _balance; // chỉ dùng trong Account public Account(decimal initial) { _balance = initial; } public void Deposit(decimal amount) { if (amount > 0) { _balance += amount; } } public decimal GetBalance() { return _balance; } } public class Program { public static void Main() { Account acc = new Account(1000); acc.Deposit(500); Console.WriteLine(acc.GetBalance()); // 1500 // Console.WriteLine(acc._balance); // lỗi CS0122: '_balance' không truy cập được } } ``` ## `protected`: trong lớp và lớp con `protected` ở mức trung gian, hữu ích khi có kế thừa. Thành viên `protected` dùng được: - bên trong chính lớp khai báo nó, - bên trong các **lớp con** (lớp kế thừa). Code không liên quan kế thừa thì không dùng được, kể cả khi nằm cùng project. ```csharp using System; public class Shape { protected double Width = 10; protected double Height = 5; } public class Rectangle : Shape { public double Area() { return Width * Height; // OK: lớp con dùng được thành viên protected } } public class Program { public static void Main() { Rectangle r = new Rectangle(); Console.WriteLine(r.Area()); // 50 // Console.WriteLine(r.Width); // lỗi CS0122: 'Width' không truy cập được từ ngoài } } ``` ## `internal`: trong cùng project (assembly) `internal` cho phép truy cập từ mọi code trong **cùng assembly**, tức cùng một project khi biên dịch ra một file `.dll` hoặc `.exe`. Code ở project khác, kể cả khi đã tham chiếu tới project này, thì không dùng được. `internal` thường dùng khi viết thư viện: những phần chỉ để thư viện tự dùng, không muốn lộ ra ngoài. ## Bảng tổng hợp Bảng dưới đây giả định lớp con nằm cùng project với lớp chứa thành viên: | Code đứng ở | `public` | `private` | `protected` | `internal` | |---|:---:|:---:|:---:|:---:| | Trong chính lớp | Được | Được | Được | Được | | Trong lớp con | Được | Không | Được | Được | | Lớp khác cùng project | Được | Không | Không | Được | | Project khác | Được | Không | Không | Không | Khi truy cập sai mức, trình biên dịch báo lỗi: ``` error CS0122: 'Account.Priv' is inaccessible due to its protection level ``` Nguyên tắc thiết kế: **bắt đầu với mức hạn chế nhất (`private`)**, chỉ mở rộng khi thật sự cần. Cách này giúp lớp dễ bảo trì, vì đổi thành viên `private` không làm hỏng mã ở nơi khác. ## Hoạt động: Ai được truy cập thành viên nào? Mô phỏng dưới đây dùng lớp `Account` có bốn thành viên: `public int Pub`, `private int Priv`, `protected int Prot`, `internal int Intl`. Đây là mô phỏng kết quả biên dịch theo luật C#, không chạy code thật. Hãy thao tác theo thứ tự sau, bấm **Bước tiếp** để thử truy cập từng thành viên: - Mở tab **Trong chính lớp**. Code nằm ngay trong `Account`, lần lượt gán `Pub`, `Priv`, `Prot`, `Intl`. Cả bốn đều hiện "✓ được phép". - Chuyển sang tab **Trong lớp con**. Code nằm trong `Dog : Account`. `Pub`, `Prot`, `Intl` được phép, riêng `Priv` hiện "✗ CS0122". - Mở tab **Lớp khác cùng project**. Code nằm trong lớp `Shop` không liên quan kế thừa, truy cập qua một đối tượng `a`. Chỉ `Pub` và `Intl` được phép, còn `Priv` và `Prot` báo CS0122. - Mở tab **Project khác**. Code nằm ở project khác, đã tham chiếu tới `Account`. Chỉ `Pub` được phép, còn `Priv`, `Prot` và `Intl` đều báo CS0122. - Ở mỗi tab, bước cuối hiện bảng tổng hợp 4 hàng, trong đó hàng của vị trí đang xem được tô đậm. ``` <iframe src="https://codegym-vn.github.io/programming-course-demos/oop_ooad/doi-tuong-lop-va-dong-goi-encapsulation/nguyen-ly-dong-goi-encapsulation-va-kiem-soat-truy-cap/cac-tu-khoa-kiem-soat-truy-cap-access-modifiers/" title="Từ khóa kiểm soát truy cập" style="border:0;" allowfullscreen></iframe> ``` Điều rút ra: `private` chỉ trong lớp, `protected` thêm lớp con, `internal` trong cùng project, `public` ở mọi nơi. Dòng nào có dấu ✗ thì không biên dịch được. ## Tóm tắt - Từ khóa kiểm soát truy cập quyết định ai được dùng một thành viên, là công cụ hiện thực hóa đóng gói. - `public`: mọi nơi. `private`: chỉ trong chính lớp. - `protected`: trong lớp và các lớp con. `internal`: trong cùng project (assembly). - Truy cập sai mức gây lỗi biên dịch CS0122. - Nên bắt đầu với `private` và chỉ mở rộng phạm vi khi thật cần.
A9: 12 | B9: 2. Đối tượng, Lớp và Đóng gói (Encapsulation) | C9: Thuộc tính (Properties) trong C# | D9: Giới thiệu về Thuộc tính (Properties) | E9: Bài đọc | F9: Nên làm | G9: Done | H9: Property trông như trường nhưng chạy qua get/set. | I9: Lớp Person có private int age và property Age { get; set { if (value >= 0) age = value; } }. Main: p.Age = 20; p.Age = -5; Console.WriteLine(p.Age);. Dòng tô sáng nhảy vào khối set (hiện ô value) và get. Bước -5 chỉ rõ điều kiện sai nên age vẫn 20. Nhập được giá trị gán thứ hai. | J9: 1 cột | K9: oop_ooad/doi-tuong-lop-va-dong-goi-encapsulation/thuoc-tinh-properties-trong-c-sharp/gioi-thieu-ve-thuoc-tinh-properties/index.html | L9: https://codegym-vn.github.io/programming-course-demos/oop_ooad/doi-tuong-lop-va-dong-goi-encapsulation/thuoc-tinh-properties-trong-c-sharp/gioi-thieu-ve-thuoc-tinh-properties/ | M9: Có ô nhập giá trị (cho phép số âm). | P9: Giới thiệu về Thuộc tính (Properties) trong C# Trong lập trình hướng đối tượng (OOP), nguyên lý đóng gói (encapsulation) là một trong những trụ cột quan trọng nhất. Nó khuyến khích chúng ta ẩn giấu dữ liệu bên trong một đối tượng và chỉ cung cấp các giao diện được kiểm soát để tương tác với dữ liệu đó. C# cung cấp một cơ chế mạnh mẽ và thanh lịch để hiện thực hóa nguyên lý này: Thuộc tính (Properties). Thuộc tính là một thành phần đặc biệt của lớp, cho phép bạn truy cập dữ liệu nội bộ của đối tượng một cách an toàn và có kiểm soát, tương tự như truy cập trực tiếp vào một trường (field) công khai, nhưng đồng thời vẫn cho phép bạn nhúng logic xử lý phức tạp. Chúng là "cầu nối" giữa dữ liệu riêng tư của đối tượng và thế giới bên ngoài. So sánh với Trường (Field) và Phương thức (Method) truyền thống Để hiểu rõ hơn về vai trò của thuộc tính, chúng ta hãy so sánh cách nó hoạt động với hai cách tiếp cận truyền thống để quản lý dữ liệu đối tượng: sử dụng trường công khai và sử dụng các phương thức Get/Set. Trường (Field) Trường là các biến được khai báo trực tiếp bên trong một lớp. Khi bạn khai báo một trường là public, bất kỳ mã nào bên ngoài lớp cũng có thể trực tiếp đọc hoặc ghi giá trị vào trường đó. public class SinhVien { public string Ten; // Trường công khai public int Tuoi; // Trường công khai } Ưu điểm: Đơn giản, dễ sử dụng. Nhược điểm: Thiếu kiểm soát: Không có cách nào để xác thực dữ liệu đầu vào. Ví dụ, Tuoi có thể được gán giá trị âm mà không có bất kỳ cảnh báo nào. Vi phạm đóng gói: Phơi bày trực tiếp cấu trúc dữ liệu bên trong, khiến việc thay đổi cấu trúc dữ liệu trở nên khó khăn vì sẽ ảnh hưởng đến tất cả các đoạn mã đang sử dụng trường đó. Khó mở rộng: Không thể thêm logic xử lý khi giá trị thay đổi mà không thay đổi chữ ký trường. Phương thức Get/Set truyền thống Để giải quyết các vấn đề của trường công khai, nguyên lý đóng gói thường khuyến nghị sử dụng các trường private và cung cấp các phương thức public để truy cập và sửa đổi chúng. Đây là cách tiếp cận phổ biến trong nhiều ngôn ngữ OOP khác (ví dụ, Java). public class SinhVien { private string _ten; // Trường riêng tư (backing field) private int _tuoi; // Trường riêng tư public string GetTen() { return _ten; } public void SetTen(string ten) { // Có thể thêm logic kiểm tra tại đây _ten = ten; } public int GetTuoi() { return _tuoi; } public void SetTuoi(int tuoi) { if (tuoi >= 0 && tuoi <= 120) // Logic kiểm tra dữ liệu { _tuoi = tuoi; } else { Console.WriteLine("Tuổi không hợp lệ!"); } } } Ưu điểm: Kiểm soát dữ liệu: Cho phép xác thực, xử lý logic khi đọc hoặc ghi dữ liệu. Tuân thủ đóng gói: Ẩn giấu dữ liệu nội bộ, chỉ cung cấp giao diện công khai. Nhược điểm: Dài dòng (Verbose): Phải viết hai phương thức cho mỗi trường, làm cho mã trở nên cồng kềnh. Ít trực quan: Khi sử dụng, mã gọi sẽ là sinhVien.SetTuoi(20) thay vì sinhVien.Tuoi = 20, kém tự nhiên hơn. Thuộc tính (Properties) trong C# Thuộc tính trong C# cung cấp một giải pháp "tốt nhất của cả hai thế giới". Nó cho phép bạn viết mã truy cập dữ liệu như thể bạn đang làm việc với một trường công khai, nhưng đằng sau hậu trường, nó thực sự gọi các phương thức truy cập (accessor methods) để đọc (get) hoặc ghi (set) giá trị. public class SinhVien { private string _ten; // Trường riêng tư public string Ten // Thuộc tính { get { return _ten; } set { _ten = value; } // 'value' là giá trị được gán } private int _tuoi; // Trường riêng tư public int Tuoi // Thuộc tính với logic kiểm tra { get { return _tuoi; } set { if (value >= 0 && value <= 120) { _tuoi = value; } else { Console.WriteLine("Tuổi không hợp lệ!"); } } } } Cách sử dụng: SinhVien sv = new SinhVien(); sv.Ten = "Nguyen Van A"; // Gọi setter của thuộc tính Ten Console.WriteLine(sv.Ten); // Gọi getter của thuộc tính Ten sv.Tuoi = 25; // Gọi setter của thuộc tính Tuoi (hợp lệ) sv.Tuoi = -5; // Gọi setter của thuộc tính Tuoi (không hợp lệ, sẽ in thông báo) Console.WriteLine(sv.Tuoi); // Gọi getter của thuộc tính Tuoi Ưu điểm: Cú pháp tự nhiên: Trông và hoạt động như một trường, dễ đọc và dễ viết. Kiểm soát đầy đủ: Vẫn cho phép nhúng logic xác thực, biến đổi hoặc các hành động khác bên trong các trình truy cập get và set. Tuân thủ đóng gói: Dữ liệu nội bộ vẫn được bảo vệ. Tương thích: Là tiêu chuẩn trong .NET cho việc phơi bày dữ liệu, đặc biệt quan trọng cho các công nghệ như data binding. Lợi ích của việc sử dụng Thuộc tính Việc sử dụng thuộc tính mang lại nhiều lợi ích đáng kể, giúp mã của bạn an toàn hơn, dễ bảo trì hơn và mạnh mẽ hơn: 1. Kiểm soát dữ liệu đầu vào (Input Data Control) Đây là lợi ích cơ bản và quan trọng nhất. Với thuộc tính, bạn có thể đảm bảo rằng dữ liệu được gán cho một đối tượng luôn hợp lệ và nhất quán. Xác thực: Kiểm tra xem giá trị có nằm trong phạm vi cho phép không (ví dụ: điểm số từ 0-100, tuổi không âm). Biến đổi: Tự động chuyển đổi dữ liệu thành định dạng mong muốn (ví dụ: chuyển đổi tất cả các chuỗi thành chữ hoa hoặc chữ thường). Kiểm tra điều kiện: Thực hiện các kiểm tra phức tạp hơn trước khi cho phép gán giá trị. Ví dụ, một thuộc tính Email có thể kiểm tra định dạng email trước khi lưu trữ, hoặc thuộc tính MaSo có thể đảm bảo rằng mã số có độ dài và định dạng nhất định. 2. Logic xử lý nội bộ (Internal Processing Logic) Thuộc tính không chỉ dùng để gán hoặc lấy giá trị trực tiếp. Bạn có thể nhúng logic phức tạp vào bên trong các trình truy cập get và set. Tính toán giá trị dẫn xuất: Một thuộc tính có thể trả về một giá trị được tính toán dựa trên các trường khác của đối tượng mà không cần lưu trữ trực tiếp. Ví dụ, một thuộc tính DiemTrungBinh có thể tính toán điểm trung bình từ các điểm môn học khác mỗi khi nó được truy cập. Kích hoạt sự kiện: Khi một thuộc tính quan trọng thay đổi, bạn có thể kích hoạt một sự kiện để thông báo cho các phần khác của ứng dụng biết. Ghi nhật ký (Logging): Ghi lại thông tin mỗi khi một thuộc tính được đọc hoặc ghi, hữu ích cho việc gỡ lỗi hoặc kiểm tra. public class SanPham { private decimal _giaBanLe; public decimal GiaBanLe { get { return _giaBanLe; } set { if (value < 0) throw new ArgumentOutOfRangeException("Giá bán lẻ không thể âm."); _giaBanLe = value; // Ví dụ: Cập nhật giá bán sỉ tự động hoặc kích hoạt sự kiện Console.WriteLine($"Giá bán lẻ đã được cập nhật thành: {value}"); } } public decimal GiaBanSi // Thuộc tính chỉ đọc, tính toán giá trị { get { return _giaBanLe * 0.8m; } // Giảm 20% cho giá sỉ } } 3. Tính tương thích với Data Binding Trong phát triển giao diện người dùng (UI) với các framework như WPF, WinForms, hoặc ASP.NET Core MVC, data binding là một kỹ thuật mạnh mẽ cho phép bạn tự động đồng bộ hóa dữ liệu giữa các điều khiển UI và các đối tượng dữ liệu của bạn. Các cơ chế data binding của .NET được thiết kế để hoạt động hiệu quả nhất với các thuộc tính. Khi bạn liên kết một thuộc tính của đối tượng với một điều khiển UI (ví dụ: một TextBox được liên kết với thuộc tính Ten của SinhVien), framework sẽ sử dụng các trình truy cập get và set của thuộc tính đó để đọc và ghi dữ liệu. Nếu bạn chỉ sử dụng các trường công khai hoặc các phương thức Get/Set truyền thống, việc thiết lập data binding sẽ phức tạp hơn hoặc thậm chí không thể thực hiện được một cách tự động, làm giảm đáng kể hiệu quả phát triển UI. Tóm lại, thuộc tính là một tính năng cốt lõi của C# giúp bạn xây dựng các lớp tuân thủ nguyên tắc đóng gói, cung cấp giao diện truy cập dữ liệu trực quan nhưng vẫn mạnh mẽ và linh hoạt. | Q9: # Giới thiệu về Thuộc tính (Properties) ## Mục tiêu học tập Sau bài học này, bạn có thể: - Giải thích thuộc tính (property) trông như trường nhưng thực chất chạy qua khối `get` và `set`. - So sánh ba cách quản lý dữ liệu: trường `public`, cặp phương thức Get/Set và thuộc tính. - Viết thuộc tính có kiểm tra dữ liệu trong `set`, dùng từ khóa `value`. - Nêu lợi ích của thuộc tính: kiểm soát dữ liệu, thêm logic xử lý, tương thích data binding. - Quan sát khối `set` và `get` chạy từng dòng bằng hoạt động mô phỏng. ## Vì sao cần thuộc tính? Đóng gói khuyên ta giấu dữ liệu bên trong đối tượng và chỉ mở ra giao diện được kiểm soát. C# có một cơ chế gọn gàng cho việc này: **thuộc tính** (property). Thuộc tính là thành phần của lớp cho phép đọc và ghi dữ liệu nội bộ **như thể** đang dùng một trường `public`, nhưng phía sau vẫn chạy mã của bạn để kiểm tra hoặc xử lý. Nó là "cầu nối" giữa dữ liệu riêng tư và bên ngoài. Để thấy thuộc tính giải quyết điều gì, hãy so sánh ba cách. ### Cách 1: trường `public` ```csharp public class Person { public int Age; } ``` - Ưu điểm: đơn giản. - Nhược điểm: không kiểm soát được. Ai cũng gán `Age = -5` được. Ngoài ra, lộ trực tiếp cấu trúc dữ liệu nên sau này khó đổi. ### Cách 2: trường `private` kèm phương thức Get/Set ```csharp public class Person { private int age; public int GetAge() { return age; } public void SetAge(int value) { if (value >= 0) age = value; } } ``` - Ưu điểm: kiểm soát được dữ liệu, giữ được đóng gói. - Nhược điểm: dài dòng, phải viết hai phương thức cho mỗi trường. Khi dùng, `p.SetAge(20)` kém tự nhiên hơn `p.Age = 20`. ### Cách 3: thuộc tính Thuộc tính lấy điểm tốt của cả hai cách: ```csharp using System; public class Person { private int age; // trường riêng tư (backing field) public int Age // thuộc tính { get { return age; } set { if (value >= 0) age = value; // 'value' là giá trị đang được gán } } } public class Program { public static void Main() { Person p = new Person(); p.Age = 20; // chạy khối set, value = 20 p.Age = -5; // chạy khối set, value = -5, điều kiện sai nên bỏ qua Console.WriteLine(p.Age); // chạy khối get: 20 } } ``` Cách đọc: - `private int age` là **trường nền** (backing field), nơi lưu dữ liệu thật. - `get` chạy khi **đọc** `p.Age`, trả về giá trị của `age`. - `set` chạy khi **gán** `p.Age = ...`. Từ khóa `value` là giá trị ở vế phải dấu `=`. - Khi gán `-5`, điều kiện `value >= 0` sai nên `age` giữ nguyên 20. Nhìn từ bên ngoài, `p.Age = 20` giống hệt gán trường. Nhưng thực chất nó chạy khối `set`. ## Lợi ích của thuộc tính ### Kiểm soát dữ liệu đầu vào Đây là lợi ích quan trọng nhất. Trong `set`, bạn có thể: - **Xác thực:** giá trị có nằm trong phạm vi cho phép không (tuổi không âm, điểm từ 0 đến 100). - **Biến đổi:** tự chuyển dữ liệu về dạng mong muốn (ví dụ chuyển chuỗi thành chữ hoa). ### Thêm logic xử lý Khối `get` và `set` không chỉ để gán và lấy. Bạn có thể tính giá trị từ các trường khác, ghi nhật ký, hoặc phát sự kiện khi dữ liệu đổi. Ví dụ, thuộc tính `GiaBanSi` có thể tính từ giá bán lẻ mà không cần lưu riêng. ### Tương thích data binding Với các framework giao diện như WPF, WinForms hay ASP.NET Core MVC, cơ chế data binding của .NET được thiết kế để làm việc với **thuộc tính**. Nếu chỉ dùng trường `public`, việc liên kết dữ liệu với điều khiển giao diện sẽ khó hơn hoặc không làm được. ## Hoạt động: Theo dõi get và set của Person.Age Mô phỏng dưới đây dùng lớp `Person` ở trên. Bạn có thể đổi giá trị gán lần hai (mặc định là -5, hãy thử số dương hay số 0). Hãy thao tác theo thứ tự sau, bấm **Bước tiếp** để chạy từng dòng: - Mở tab **Person.Age**. Dòng `var p = new Person();` tạo `Person#1`, trường private `age` mặc định là 0. - Dòng `p.Age = 20;` trông như gán trường, nhưng dòng tô sáng nhảy vào khối `set` và hiện ô `value = 20`. Vì `20 >= 0` đúng nên `age` được gán 20. - Dòng `p.Age = -5;` (giá trị mặc định) lại chạy `set` với `value = -5`. Bước tiếp theo chỉ rõ điều kiện `value >= 0` sai, nên dòng gán bị bỏ qua và `age` vẫn là 20. Nếu bạn đổi thành số không âm, `age` sẽ nhận giá trị mới. - Dòng `Console.WriteLine(p.Age);` chạy khối `get`, trả về `age` và in 20 (với giá trị gán lần hai là -5). ``` <iframe src="https://codegym-vn.github.io/programming-course-demos/oop_ooad/doi-tuong-lop-va-dong-goi-encapsulation/thuoc-tinh-properties-trong-c-sharp/gioi-thieu-ve-thuoc-tinh-properties/" title="Giới thiệu Property" style="border:0;" allowfullscreen></iframe> ``` Điều rút ra: property trông như trường nhưng chạy qua `get` và `set`, nên `set` có thể kiểm tra dữ liệu trước khi gán vào trường private. ## Tóm tắt - **Thuộc tính** cho phép đọc và ghi dữ liệu nội bộ bằng cú pháp giống trường, nhưng chạy qua khối `get` và `set`. - Dữ liệu thật nằm trong trường private (backing field), thuộc tính là cửa công khai có kiểm soát. - Trong `set`, từ khóa `value` là giá trị đang được gán. Có thể kiểm tra và từ chối giá trị sai. - So với trường `public`: có kiểm soát. So với Get/Set truyền thống: ngắn gọn và tự nhiên hơn. - Thuộc tính là chuẩn của .NET, phù hợp với data binding.
A10: 13 | B10: 2. Đối tượng, Lớp và Đóng gói (Encapsulation) | C10: Thuộc tính (Properties) trong C# | D10: Cú pháp và Các loại Thuộc tính | E10: Bài đọc | F10: Làm thêm nếu muốn | G10: Done | H10: Các dạng property hay gặp. | I10: 4 tab: Auto-property { get; set; }; Chỉ đọc { get; } gán ngoài lớp báo lỗi biên dịch; private set chỉ lớp tự đổi; Tính toán (FullName => First + " " + Last) đổi First thì FullName đổi theo. Mỗi tab 3-4 bước. | J10: 1 cột, nhiều tab | K10: oop_ooad/doi-tuong-lop-va-dong-goi-encapsulation/thuoc-tinh-properties-trong-c-sharp/cu-phap-va-cac-loai-thuoc-tinh/index.html | L10: https://codegym-vn.github.io/programming-course-demos/oop_ooad/doi-tuong-lop-va-dong-goi-encapsulation/thuoc-tinh-properties-trong-c-sharp/cu-phap-va-cac-loai-thuoc-tinh/ | P10: Cú pháp cơ bản của Thuộc tính với get và set Như chúng ta đã tìm hiểu trong bài "Giới thiệu về Thuộc tính", thuộc tính (Properties) là một thành phần quan trọng trong C# giúp hiện thực hóa nguyên lý đóng gói (encapsulation). Chúng cung cấp một giao diện công khai để truy cập dữ liệu nội bộ của một đối tượng, trong khi vẫn cho phép kiểm soát cách dữ liệu đó được đọc hoặc ghi. Cú pháp cơ bản của một thuộc tính bao gồm một kiểu dữ liệu, tên thuộc tính, và hai bộ truy cập (accessors) chính: get và set. get accessor: Được gọi khi giá trị của thuộc tính được đọc. Nó chịu trách nhiệm trả về giá trị của dữ liệu nội bộ. set accessor: Được gọi khi giá trị của thuộc tính được gán. Nó chịu trách nhiệm nhận giá trị mới và lưu trữ nó vào dữ liệu nội bộ. Từ khóa value được sử dụng bên trong set để tham chiếu đến giá trị mà thuộc tính đang được gán. Dưới đây là cú pháp tổng quát: public KieuDuLieu TenThuocTinh { get { // Logic đọc giá trị return giaTriNoiBo; } set { // Logic ghi giá trị giaTriNoiBo = value; } } Hãy xem xét một ví dụ đơn giản với lớp SinhVien: public class SinhVien { private string _ten; // Trường dữ liệu (backing field) public string Ten { get { // Có thể thêm logic ở đây, ví dụ: ghi log khi đọc tên return _ten; } set { // Có thể thêm logic ở đây, ví dụ: kiểm tra tính hợp lệ của tên if (string.IsNullOrWhiteSpace(value)) { Console.WriteLine("Tên không được để trống."); } else { _ten = value; } } } public void HienThiThongTin() { Console.WriteLine($"Tên sinh viên: {Ten}"); } } // Cách sử dụng: // SinhVien sv = new SinhVien(); // sv.Ten = "Nguyễn Văn A"; // Gọi set accessor // Console.WriteLine(sv.Ten); // Gọi get accessor Trong ví dụ này, _ten là một trường (field) riêng tư dùng để lưu trữ dữ liệu thực tế. Thuộc tính Ten cung cấp một giao diện công khai để tương tác với trường _ten, cho phép chúng ta kiểm soát việc đọc và ghi giá trị. Thuộc tính tự động (Auto-implemented Properties) Trong nhiều trường hợp, logic bên trong get và set accessor rất đơn giản: chỉ là đọc và ghi giá trị trực tiếp vào một trường dữ liệu riêng tư mà không có bất kỳ xử lý phức tạp nào. C# cung cấp một cú pháp rút gọn được gọi là thuộc tính tự động (auto-implemented properties) cho những tình huống này. Khi bạn khai báo một thuộc tính tự động, trình biên dịch C# sẽ tự động tạo ra một trường dữ liệu backing field riêng tư ẩn danh (private, anonymous backing field) để lưu trữ giá trị của thuộc tính. Bạn không cần phải khai báo trường backing field đó một cách tường minh. Cú pháp của thuộc tính tự động rất gọn gàng: public KieuDuLieu TenThuocTinh { get; set; } Ví dụ với lớp SanPham: public class SanPham { // Thuộc tính tự động cho Mã sản phẩm public string MaSanPham { get; set; } // Thuộc tính tự động cho Tên sản phẩm public string TenSanPham { get; set; } // Thuộc tính tự động cho Giá public decimal Gia { get; set; } public void HienThiChiTiet() { Console.WriteLine($"Mã: {MaSanPham}, Tên: {TenSanPham}, Giá: {Gia:C}"); } } // Cách sử dụng: // SanPham sp = new SanPham(); // sp.MaSanPham = "SP001"; // sp.TenSanPham = "Laptop XYZ"; // sp.Gia = 15000000m; // sp.HienThiChiTiet(); Thuộc tính tự động giúp mã nguồn ngắn gọn và dễ đọc hơn, đặc biệt khi bạn không cần thêm logic phức tạp vào bộ truy cập. Chúng là lựa chọn lý tưởng cho các thuộc tính đơn giản. Thuộc tính với Backing Fields để thêm Logic xử lý phức tạp Mặc dù thuộc tính tự động rất tiện lợi, nhưng chúng không phù hợp khi bạn cần thêm logic xử lý đặc biệt trong quá trình đọc hoặc ghi giá trị. Đây là lúc chúng ta quay lại việc sử dụng các trường dữ liệu riêng tư (backing fields) một cách tường minh. Khi bạn cần: Xác thực dữ liệu trong set (ví dụ: đảm bảo tuổi không âm, điểm số trong một khoảng nhất định). Chuyển đổi dữ liệu trước khi lưu hoặc sau khi đọc. Kích hoạt các sự kiện hoặc thực hiện các hành động phụ khi giá trị thay đổi. Tính toán giá trị trong get thay vì lưu trữ trực tiếp. Bạn sẽ khai báo một trường riêng tư để lưu trữ dữ liệu thực tế, sau đó sử dụng các bộ truy cập get và set của thuộc tính để tương tác với trường đó, thêm vào bất kỳ logic cần thiết nào. Ví dụ về xác thực dữ liệu cho thuộc tính Tuoi (Tuổi): public class Nguoi { private string _hoTen; // Backing field private int _tuoi; // Backing field public string HoTen { get { return _hoTen; } set { if (string.IsNullOrWhiteSpace(value)) { throw new ArgumentException("Họ tên không được để trống."); } _hoTen = value; } } public int Tuoi { get { return _tuoi; } set { if (value < 0 || value > 120) // Logic xác thực: tuổi phải hợp lệ { throw new ArgumentOutOfRangeException(nameof(Tuoi), "Tuổi phải nằm trong khoảng từ 0 đến 120."); } _tuoi = value; } } public Nguoi(string hoTen, int tuoi) { HoTen = hoTen; // Gọi set accessor của HoTen Tuoi = tuoi; // Gọi set accessor của Tuoi } public void HienThiThongTin() { Console.WriteLine($"Họ tên: {HoTen}, Tuổi: {Tuoi}"); } } // Cách sử dụng: // Nguoi nguoi1 = new Nguoi("Trần Thị B", 30); // nguoi1.HienThiThongTin(); // Họ tên: Trần Thị B, Tuổi: 30 // Nguoi nguoi2 = new Nguoi("Lê Văn C", -5); // Sẽ ném ra ArgumentOutOfRangeException Trong ví dụ trên, thuộc tính Tuoi sử dụng trường _tuoi làm backing field. Bộ truy cập set kiểm tra xem giá trị được gán có hợp lệ (từ 0 đến 120) trước khi lưu vào _tuoi. Nếu không hợp lệ, nó sẽ ném ra một ngoại lệ, đảm bảo tính toàn vẹn của dữ liệu. Thuộc tính chỉ đọc (Read-only) và chỉ ghi (Write-only) Đôi khi, bạn chỉ muốn cho phép đọc hoặc chỉ cho phép ghi giá trị của một thuộc tính, nhưng không phải cả hai. C# cho phép bạn tạo các thuộc tính chỉ với một trong hai bộ truy cập get hoặc set. Thuộc tính chỉ đọc (Read-only Properties) Một thuộc tính chỉ đọc chỉ có get accessor và không có set accessor. Điều này có nghĩa là giá trị của thuộc tính chỉ có thể được đọc từ bên ngoài đối tượng, nhưng không thể được thay đổi trực tiếp. Giá trị của thuộc tính chỉ đọc thường được khởi tạo trong: Hàm tạo (constructor) của lớp. Trình khởi tạo thuộc tính (property initializer) nếu đó là thuộc tính tự động. Hoặc được tính toán động dựa trên các trường dữ liệu khác. Ví dụ về thuộc tính chỉ đọc MaSo (Mã số) và TenDayDu (Tên đầy đủ): public class TaiKhoan { public readonly string MaSo; // Trường chỉ đọc, có thể gán trong constructor public string Ho { get; set; } public string Ten { get; set; } // Thuộc tính chỉ đọc được tính toán dựa trên các thuộc tính khác public string TenDayDu { get { return $"{Ho} {Ten}"; } } public TaiKhoan(string maSo, string ho, string ten) { MaSo = maSo; // Gán giá trị cho trường chỉ đọc trong constructor Ho = ho; Ten = ten; } // Một thuộc tính tự động chỉ đọc (chỉ có get) public DateTime NgayTao { get; } = DateTime.Now; // Khởi tạo khi tạo đối tượng public void HienThiThongTin() { Console.WriteLine($"Mã số: {MaSo}, Tên đầy đủ: {TenDayDu}, Ngày tạo: {NgayTao.ToShortDateString()}"); } } // Cách sử dụng: // TaiKhoan tk = new TaiKhoan("TK123", "Nguyễn", "Văn B"); // Console.WriteLine(tk.MaSo); // Hợp lệ // Console.WriteLine(tk.TenDayDu); // Hợp lệ // tk.MaSo = "TK456"; // Lỗi biên dịch: Không thể gán cho thuộc tính chỉ đọc Thuộc tính chỉ ghi (Write-only Properties) Một thuộc tính chỉ ghi chỉ có set accessor và không có get accessor. Điều này có nghĩa là bạn có thể gán giá trị cho thuộc tính từ bên ngoài, nhưng không thể đọc lại giá trị đó. Thuộc tính chỉ ghi ít phổ biến hơn nhiều so với thuộc tính chỉ đọc. Chúng thường được sử dụng trong các tình huống đặc biệt, ví dụ như khi bạn muốn cho phép người dùng đặt một giá trị nhạy cảm (như mật khẩu) mà không bao giờ cho phép đọc lại nó trực tiếp. Ví dụ về thuộc tính chỉ ghi MatKhau: public class TaiKhoanNguoiDung { private string _hashedPassword; // Backing field lưu trữ mật khẩu đã hash public string TenDangNhap { get; set; } // Thuộc tính chỉ ghi cho mật khẩu public string MatKhau { set { // Trong thực tế, bạn sẽ hash mật khẩu ở đây _hashedPassword = HashPassword(value); Console.WriteLine("Mật khẩu đã được thiết lập và mã hóa."); } } private string HashPassword(string password) { // Đây chỉ là ví dụ đơn giản, không an toàn cho thực tế return $"[HASH]{password.GetHashCode()}"; } public TaiKhoanNguoiDung(string tenDangNhap) { TenDangNhap = tenDangNhap; } // Phương thức kiểm tra mật khẩu (không phải là thuộc tính get) public bool KiemTraMatKhau(string password) { return _hashedPassword == HashPassword(password); } } // Cách sử dụng: // TaiKhoanNguoiDung user = new TaiKhoanNguoiDung("admin"); // user.MatKhau = "password123"; // Hợp lệ, gọi set accessor // // string p = user.MatKhau; // Lỗi biên dịch: Không thể truy cập get accessor // Console.WriteLine(user.KiemTraMatKhau("password123")); // True // Console.WriteLine(user.KiemTraMatKhau("wrongpassword")); // False Trong ví dụ này, MatKhau là một thuộc tính chỉ ghi. Khi bạn gán một giá trị cho nó, giá trị đó được xử lý (trong trường hợp này là "hash") và lưu vào trường _hashedPassword. Bạn không thể đọc lại mật khẩu gốc qua thuộc tính MatKhau, tăng cường bảo mật. | Q10: # Cú pháp và Các loại Thuộc tính ## Mục tiêu học tập Sau bài học này, bạn có thể: - Viết thuộc tính đầy đủ với `get`, `set` và trường nền (backing field). - Viết thuộc tính tự động (auto-property) bằng `{ get; set; }`. - Phân biệt thuộc tính chỉ đọc `{ get; }`, thuộc tính `private set` và thuộc tính tính toán. - Nhận ra lỗi biên dịch CS0200 và CS0272 khi gán vào thuộc tính không cho phép. - Quan sát bốn loại thuộc tính chạy từng bước bằng hoạt động mô phỏng. ## Cú pháp cơ bản của thuộc tính Một thuộc tính gồm kiểu dữ liệu, tên và các bộ truy cập (accessor): - `get`: chạy khi **đọc** thuộc tính, trả về giá trị. - `set`: chạy khi **gán** thuộc tính. Từ khóa `value` là giá trị đang được gán. ```csharp public KieuDuLieu TenThuocTinh { get { return giaTriNoiBo; } set { giaTriNoiBo = value; } } ``` Khi cần kiểm tra dữ liệu, ta dùng **trường nền** (backing field) `private` để lưu giá trị thật, rồi đặt logic trong `get` hoặc `set`: ```csharp using System; public class Person { private int _age; // trường nền public int Age { get { return _age; } set { if (value < 0 || value > 120) { throw new ArgumentOutOfRangeException(nameof(Age), "Tuổi phải từ 0 đến 120."); } _age = value; } } } ``` Gán `Age = -5` sẽ ném ngoại lệ thay vì lưu giá trị sai. Dạng đầy đủ này dùng khi bạn cần xác thực, biến đổi dữ liệu hoặc thêm hành động phụ. ## Bốn dạng thuộc tính hay gặp ### Thuộc tính tự động (auto-property) Khi `get` và `set` chỉ đọc và ghi thẳng giá trị, ta viết gọn: ```csharp public int Age { get; set; } ``` Trình biên dịch tự tạo một **trường ẩn** để chứa giá trị. Bạn không cần khai báo trường nền. Đây là lựa chọn lý tưởng cho thuộc tính đơn giản. ### Thuộc tính chỉ đọc `{ get; }` Thuộc tính chỉ có `get` thì bên ngoài chỉ **đọc** được. Giá trị chỉ được gán trong **hàm tạo** của lớp (hoặc bằng trình khởi tạo ngay tại khai báo). ```csharp public class Book { public string Title { get; } public Book(string t) { Title = t; // được phép: nằm trong lớp, trong hàm tạo } } ``` Gán `Title` từ bên ngoài sẽ gây lỗi biên dịch **CS0200**: thuộc tính chỉ đọc không thể gán. ### Thuộc tính `private set` Muốn ai cũng đọc được nhưng **chỉ lớp tự đổi được**, ta giữ `get` là `public` và đặt `set` là `private`: ```csharp public class Counter { public int Count { get; private set; } public void Add() { Count++; // được phép: set private dùng được bên trong lớp } } ``` Gán `Count = 10` từ bên ngoài lớp gây lỗi biên dịch **CS0272**, vì bộ truy cập `set` không truy cập được. ### Thuộc tính tính toán Thuộc tính chỉ có `get` và **không lưu dữ liệu riêng**: giá trị được tính lại từ các trường khác mỗi lần đọc. ```csharp public class Person { public string First; public string Last; public string FullName => First + " " + Last; } ``` Dấu `=>` là cách viết gọn của `get { return ...; }`. Đổi `First` hoặc `Last` thì lần đọc `FullName` kế tiếp tự đổi theo. ## Một vài lưu ý thêm - Thuộc tính **chỉ ghi** (chỉ có `set`, không có `get`) là có thể nhưng hiếm dùng. Nó phù hợp khi cho đặt một giá trị nhạy cảm như mật khẩu mà không cho đọc lại. - Với dữ liệu cần kiểm tra, hãy dùng dạng đầy đủ với trường nền, không dùng auto-property. - Quy ước: tên thuộc tính viết PascalCase (`FullName`), còn trường nền `private` thường bắt đầu bằng gạch dưới (`_age`). ## Hoạt động: Bốn loại thuộc tính Mô phỏng dưới đây có bốn tab, mỗi tab là một dạng thuộc tính. Hãy thao tác theo thứ tự sau, bấm **Bước tiếp** để chạy từng dòng: - Mở tab **Auto-property**. Lớp `Student` có `public int Age { get; set; }`. Ngay khi `new Student()` chạy, C# tự tạo trường ẩn `Age (trường ẩn)` bằng 0. Dòng `s.Age = 18;` chạy `set` tự sinh, ghi 18 vào trường ẩn. Dòng `Console.WriteLine(s.Age);` chạy `get` tự sinh và in 18. - Chuyển sang tab **Chỉ đọc**. Lớp `Book` có `Title { get; }`. Constructor `new Book("C#")` gán `Title = "C#"`, được phép vì nằm trong lớp. Đọc `b.Title` in `C#`. Dòng cuối `b.Title = "Java";` báo lỗi biên dịch CS0200. - Mở tab **private set**. Lớp `Counter` có `Count { get; private set; }`. Dòng `c.Add();` làm `Count` tăng lên 1 vì `Add` nằm trong lớp. Đọc `c.Count` in 1. Dòng cuối `c.Count = 10;` ở ngoài lớp báo lỗi biên dịch CS0272. - Mở tab **Tính toán**. Lớp `Person` có `FullName => First + " " + Last`. Bộ nhớ chỉ có `First` và `Last`, `FullName` không có ô lưu trữ. Sau khi gán `First = "An"` và `Last = "Lê"`, đọc `FullName` in `An Lê`. Đổi `First = "Bình"` mà không đụng tới `FullName`, đọc lại thì được `Bình Lê`. ``` <iframe src="https://codegym-vn.github.io/programming-course-demos/oop_ooad/doi-tuong-lop-va-dong-goi-encapsulation/thuoc-tinh-properties-trong-c-sharp/cu-phap-va-cac-loai-thuoc-tinh/" title="Các loại Property" style="border:0;" allowfullscreen></iframe> ``` Điều rút ra: cùng là thuộc tính nhưng mỗi dạng có một vai trò. `{ get; set; }` đọc và ghi, `{ get; }` chỉ đọc, `private set` chỉ lớp tự đổi, còn thuộc tính tính toán không lưu dữ liệu mà tính lại mỗi lần đọc. ## Tóm tắt - Thuộc tính có `get` (đọc) và `set` (ghi, dùng `value`). - **Auto-property** `{ get; set; }`: ngắn gọn, trình biên dịch tự tạo trường ẩn. - **Chỉ đọc** `{ get; }`: chỉ gán trong hàm tạo, gán ngoài lớp gây lỗi CS0200. - **`private set`**: đọc từ ngoài được, chỉ lớp tự đổi được, gán ngoài lớp gây lỗi CS0272. - **Tính toán**: chỉ có `get`, tính từ các trường khác mỗi lần đọc. - Cần kiểm tra dữ liệu thì dùng dạng đầy đủ với trường nền `private`.
A11: 15 | B11: 2. Đối tượng, Lớp và Đóng gói (Encapsulation) | C11: Hàm tạo (Constructors) và Khởi tạo Đối tượng | D11: Mục đích của Hàm tạo (Constructors) | E11: Bài đọc | F11: Nên làm | G11: Done | H11: Constructor chạy ngay khi new, đảm bảo đối tượng có dữ liệu hợp lệ từ đầu. | I11: 2 cột. Cột trái: không constructor, new Book() rồi quên gán Title → Title = null, in ra rỗng. Cột phải: Book(string title, decimal price), new Book("C#", 99) → bước 1 cấp vùng nhớ (trường mặc định), bước 2 chạy thân constructor gán giá trị, bước 3 trả tham chiếu về biến. | J11: 2 cột song song | K11: oop_ooad/doi-tuong-lop-va-dong-goi-encapsulation/ham-tao-constructors-va-khoi-tao-doi-tuong/muc-dich-cua-ham-tao-constructors/index.html | L11: https://codegym-vn.github.io/programming-course-demos/oop_ooad/doi-tuong-lop-va-dong-goi-encapsulation/ham-tao-constructors-va-khoi-tao-doi-tuong/muc-dich-cua-ham-tao-constructors/ | P11: Hàm tạo là gì? Trong lập trình hướng đối tượng (OOP) với C#, đối tượng là một thể hiện của một lớp, đại diện cho một thực thể cụ thể. Để một đối tượng có thể hoạt động đúng đắn ngay từ khi được tạo ra, nó cần được thiết lập một trạng thái ban đầu hợp lệ. Đây chính là lúc hàm tạo (constructor) phát huy vai trò của mình. Hàm tạo là một phương thức đặc biệt trong một lớp, được tự động gọi khi một đối tượng mới của lớp đó được tạo ra. Khác với các phương thức thông thường, hàm tạo không có kiểu trả về (kể cả void) và tên của nó phải trùng hoàn toàn với tên của lớp. Vai trò chính của hàm tạo: Khởi tạo trạng thái ban đầu của đối tượng: Hàm tạo chịu trách nhiệm gán giá trị ban đầu cho các trường (fields) của đối tượng, đảm bảo rằng đối tượng được tạo ra luôn ở trạng thái sẵn sàng để sử dụng. Thực hiện logic khởi tạo: Ngoài việc gán giá trị, hàm tạo cũng có thể chứa các logic phức tạp hơn như kiểm tra dữ liệu đầu vào, cấp phát tài nguyên, hoặc gọi các phương thức khởi tạo khác. Hãy tưởng tượng bạn đang xây dựng một ngôi nhà. Hàm tạo giống như quá trình xây dựng móng, khung nhà và các hệ thống cơ bản (điện, nước). Bạn không thể dọn vào ở một ngôi nhà chưa có móng hoặc chưa có cửa. Tương tự, một đối tượng cần được "xây dựng" đúng cách trước khi các phương thức khác có thể "sử dụng" nó. Tại sao cần Hàm tạo? Đảm bảo trạng thái hợp lệ Mục đích cốt lõi của hàm tạo là đảm bảo rằng mọi đối tượng được tạo ra từ một lớp đều ở một trạng thái hợp lệ và có thể sử dụng được ngay lập tức. Nếu không có hàm tạo, hoặc nếu hàm tạo không được sử dụng đúng cách, bạn có thể gặp phải các vấn đề như: Dữ liệu không xác định hoặc không hợp lệ: Các trường của đối tượng có thể mang giá trị mặc định (như null cho các kiểu tham chiếu, 0 cho số nguyên, false cho boolean) mà có thể không phù hợp với ngữ cảnh nghiệp vụ. Ví dụ, một đối tượng TaiKhoanNganHang với số dư ban đầu là null hoặc không được định nghĩa sẽ gây lỗi khi thực hiện giao dịch. Lỗi thời gian chạy (runtime errors): Truy cập vào các trường chưa được khởi tạo có thể dẫn đến NullReferenceException hoặc các lỗi logic khác, làm chương trình bị treo hoặc hoạt động sai. Mã nguồn khó bảo trì: Nếu logic khởi tạo phân tán khắp nơi trong mã nguồn (ví dụ: gán giá trị sau khi tạo đối tượng), việc theo dõi và sửa lỗi sẽ trở nên phức tạp. Hàm tạo tập trung tất cả logic khởi tạo vào một nơi duy nhất, giúp mã nguồn rõ ràng và dễ quản lý hơn. Ví dụ minh họa: Xét một lớp SanPham (Product): public class SanPham { public string MaSanPham { get; set; } public string TenSanPham { get; set; } public decimal Gia { get; set; } public int SoLuongTonKho { get; set; } // Nếu không có hàm tạo, các thuộc tính này sẽ có giá trị mặc định: // MaSanPham = null, TenSanPham = null, Gia = 0.0m, SoLuongTonKho = 0 // Điều này có thể không phải là trạng thái hợp lệ mong muốn. } Nếu bạn tạo một SanPham mà không gán giá trị cho MaSanPham hoặc TenSanPham, chúng sẽ là null. Mọi thao tác sau đó dựa vào các giá trị này (như hiển thị tên sản phẩm trên giao diện) sẽ gặp lỗi. Hàm tạo giúp chúng ta thiết lập các giá trị cần thiết ngay từ đầu. Hàm tạo mặc định (Default Constructor) Khi bạn định nghĩa một lớp trong C# mà không khai báo bất kỳ hàm tạo nào một cách rõ ràng, trình biên dịch C# sẽ tự động cung cấp một hàm tạo mặc định (default constructor) công khai, không tham số cho lớp đó. Đặc điểm của hàm tạo mặc định: Tự động tạo: Nó được thêm vào bởi trình biên dịch C# nếu không có hàm tạo nào khác được định nghĩa. Không tham số: Nó không nhận bất kỳ tham số nào. Khởi tạo giá trị mặc định: Hàm tạo mặc định chỉ thực hiện một nhiệm vụ duy nhất: gán các giá trị mặc định cho tất cả các trường và thuộc tính của đối tượng. Đối với các kiểu số (int, double, decimal, v.v.), giá trị mặc định là 0. Đối với kiểu bool, giá trị mặc định là false. Đối với các kiểu tham chiếu (string, object, các lớp do người dùng định nghĩa), giá trị mặc định là null. Đối với các kiểu giá trị tùy chỉnh (struct), các trường của struct sẽ được khởi tạo theo mặc định. Ví dụ: public class SinhVien { public string MaSinhVien { get; set; } // Mặc định là null public string Ten { get; set; } // Mặc định là null public int Tuoi { get; set; } // Mặc định là 0 public bool DaTotNghiep { get; set; } // Mặc định là false // Trình biên dịch sẽ tự động tạo một hàm tạo mặc định như sau (nếu bạn không định nghĩa): // public SinhVien() // { // // Tất cả các thuộc tính sẽ được gán giá trị mặc định // } } // Khi bạn tạo đối tượng: SinhVien sv = new SinhVien(); // sv.MaSinhVien là null, sv.Ten là null, sv.Tuoi là 0, sv.DaTotNghiep là false Hàm tạo mặc định hữu ích khi bạn không có yêu cầu đặc biệt nào về việc khởi tạo đối tượng hoặc khi bạn muốn các trường của đối tượng bắt đầu với giá trị mặc định của chúng. Hàm tạo do người dùng định nghĩa (User-Defined Constructor) Ngược lại với hàm tạo mặc định, hàm tạo do người dùng định nghĩa là hàm tạo mà bạn (người lập trình) tự viết và khai báo trong lớp. Khi bạn định nghĩa ít nhất một hàm tạo rõ ràng cho một lớp, trình biên dịch C# sẽ không còn tự động cung cấp hàm tạo mặc định nữa. Mục đích chính của hàm tạo do người dùng định nghĩa: Cung cấp giá trị khởi tạo cụ thể: Cho phép bạn gán các giá trị ban đầu cho các trường của đối tượng dựa trên các tham số được truyền vào khi tạo đối tượng. Điều này đảm bảo rằng đối tượng được tạo ra với dữ liệu có ý nghĩa ngay lập tức. Thực thi logic khởi tạo phức tạp: Bạn có thể thêm các kiểm tra hợp lệ cho dữ liệu đầu vào, thực hiện các tính toán phức tạp hoặc khởi tạo các đối tượng phụ thuộc khác ngay trong quá trình tạo đối tượng chính. Buộc đối tượng ở trạng thái hợp lệ: Bằng cách yêu cầu các tham số cần thiết trong hàm tạo, bạn có thể đảm bảo rằng không thể tạo ra một đối tượng mà thiếu các thông tin quan trọng. Ví dụ: public class SanPham { public string MaSanPham { get; set; } public string TenSanPham { get; set; } public decimal Gia { get; set; } public int SoLuongTonKho { get; set; } // Hàm tạo do người dùng định nghĩa (có tham số) public SanPham(string maSp, string tenSp, decimal giaBan, int tonKho) { // Gán giá trị từ tham số cho các thuộc tính của đối tượng MaSanPham = maSp; TenSanPham = tenSp; Gia = giaBan; SoLuongTonKho = tonKho; // Có thể thêm logic kiểm tra: if (Gia < 0) { throw new ArgumentException("Giá sản phẩm không thể âm."); } } } // Khi bạn tạo đối tượng: SanPham sp1 = new SanPham("SP001", "Laptop ABC", 1500.00m, 10); // sp1.MaSanPham là "SP001", sp1.TenSanPham là "Laptop ABC", v.v. // Nếu không có hàm tạo này, bạn sẽ phải gán từng thuộc tính một cách thủ công: // SanPham sp2 = new SanPham(); // sp2.MaSanPham = "SP002"; // sp2.TenSanPham = "Chuột không dây"; // ... điều này dễ gây lỗi và không đảm bảo tính nhất quán. Trong ví dụ trên, hàm tạo đảm bảo rằng một đối tượng SanPham không thể tồn tại mà không có MaSanPham, TenSanPham, Gia và SoLuongTonKho hợp lệ. Điểm khác biệt chính và tầm quan trọng Sự khác biệt cơ bản nhất giữa hàm tạo mặc định và hàm tạo do người dùng định nghĩa nằm ở ai tạo ra nó và mức độ kiểm soát mà nó mang lại: Hàm tạo mặc định: Được cung cấp tự động bởi trình biên dịch khi không có hàm tạo nào khác. Nó chỉ thực hiện việc khởi tạo các trường về giá trị mặc định của kiểu dữ liệu. Bạn không có quyền kiểm soát logic bên trong nó. Hàm tạo do người dùng định nghĩa: Được tạo ra bởi chính bạn (người lập trình). Nó cho phép bạn hoàn toàn kiểm soát quá trình khởi tạo đối tượng, bao gồm việc gán giá trị cụ thể, thực hiện kiểm tra hợp lệ, và các logic phức tạp khác. Tầm quan trọng: Việc hiểu và sử dụng hàm tạo một cách hiệu quả là nền tảng của lập trình hướng đối tượng. Nó giúp bạn: Tăng cường tính toàn vẹn dữ liệu: Đảm bảo rằng đối tượng luôn ở trạng thái nhất quán và hợp lệ từ khi được sinh ra. Cải thiện khả năng đọc và bảo trì mã: Tập trung logic khởi tạo vào một nơi, làm cho mã nguồn dễ hiểu và dễ quản lý hơn. Giảm thiểu lỗi thời gian chạy: Tránh các lỗi liên quan đến việc sử dụng đối tượng chưa được khởi tạo đúng cách. Thiết kế API rõ ràng: Hàm tạo giúp định nghĩa rõ ràng cách thức để tạo ra một đối tượng hợp lệ, hướng dẫn người dùng lớp của bạn sử dụng nó đúng cách. Trong bài học tiếp theo, chúng ta sẽ đi sâu hơn vào cú pháp của các loại hàm tạo khác nhau và cách sử dụng kỹ thuật nạp chồng hàm tạo (constructor overloading) để cung cấp nhiều cách khởi tạo đối tượng khác nhau. | Q11: # Mục đích của Hàm tạo (Constructors) ## Mục tiêu học tập Sau bài học này, bạn có thể: - Giải thích hàm tạo (constructor) là gì và khi nào nó chạy. - Nêu được vì sao đối tượng cần có trạng thái hợp lệ ngay từ lúc được tạo. - Phân biệt hàm tạo mặc định do trình biên dịch cấp với hàm tạo do bạn tự viết. - Viết một hàm tạo có tham số để bắt buộc đối tượng có dữ liệu cần thiết. - Quan sát từng bước `new` chạy bằng hoạt động mô phỏng. ## Hàm tạo là gì? **Hàm tạo** (constructor) là một phương thức đặc biệt của lớp. Nó được gọi **tự động** ngay khi một đối tượng mới được tạo bằng `new`. Hàm tạo khác phương thức thường ở hai điểm: - Tên của nó **trùng hoàn toàn với tên lớp**. - Nó **không có kiểu trả về**, kể cả `void`. Hãy tưởng tượng bạn xây một ngôi nhà. Hàm tạo giống bước xây móng, dựng khung và lắp điện nước. Bạn không thể dọn vào một ngôi nhà chưa có móng. Tương tự, đối tượng cần được "dựng" xong trước khi các phương thức khác dùng đến nó. Vai trò chính của hàm tạo: - **Gán giá trị ban đầu** cho các trường (field) của đối tượng. - **Kiểm tra dữ liệu đầu vào** và thực hiện các bước chuẩn bị cần thiết. ## Vì sao cần hàm tạo? Mục đích cốt lõi của hàm tạo là bảo đảm mọi đối tượng sinh ra đều ở **trạng thái hợp lệ**, dùng được ngay. Nếu không có hàm tạo, các trường chỉ nhận **giá trị mặc định** của kiểu: | Kiểu | Giá trị mặc định | |---|---| | Số (`int`, `double`, `decimal`...) | `0` | | `bool` | `false` | | Kiểu tham chiếu (`string`, lớp tự định nghĩa...) | `null` | Những giá trị này thường không có ý nghĩa với bài toán thật. Một cuốn sách có `Title` là `null` thì khi hiển thị tên sách ta sẽ nhận được chuỗi rỗng, hoặc nặng hơn là lỗi `NullReferenceException` khi gọi phương thức trên `Title`. Nếu việc gán giá trị nằm rải rác ở nhiều nơi sau khi tạo đối tượng, ta cũng rất dễ quên và khó tìm lỗi. Hàm tạo gom việc khởi tạo vào **một chỗ duy nhất**. ## Hàm tạo mặc định Nếu bạn **không viết hàm tạo nào**, trình biên dịch C# tự thêm một **hàm tạo mặc định** (default constructor): công khai, không tham số, chỉ để các trường nhận giá trị mặc định. ```csharp using System; public class Book { public string Title; public decimal Price; } public class Program { public static void Main() { Book b = new Book(); Console.WriteLine("Tên: " + b.Title); // Tên: (rỗng, vì Title là null) Console.WriteLine(b.Price); // 0 } } ``` Chương trình vẫn chạy mà không báo lỗi gì, dù cuốn sách chưa có tên. Đây chính là điểm yếu của việc không có hàm tạo. ## Hàm tạo do bạn tự viết Khi bạn viết **ít nhất một** hàm tạo trong lớp, trình biên dịch **không còn cấp hàm tạo mặc định** nữa. Nhờ đó bạn có thể **bắt buộc** người dùng lớp đưa đủ dữ liệu: ```csharp using System; public class Book { public string Title; public decimal Price; public Book(string title, decimal price) { Title = title; Price = price; } } public class Program { public static void Main() { Book b = new Book("C#", 99); Console.WriteLine("Tên: " + b.Title); // Tên: C# // Book empty = new Book(); // Lỗi biên dịch CS7036: thiếu đối số } } ``` Lúc này không thể tạo `Book` mà thiếu `title` và `price`. Hàm tạo còn có thể kiểm tra dữ liệu (ví dụ ném `ArgumentException` khi giá âm) trước khi cho đối tượng tồn tại. ## Hoạt động: Book có và không có constructor Mô phỏng dưới đây có hai cột, cùng tạo một `Book` rồi in tên sách. Hãy thao tác theo thứ tự sau, bấm **Bước tiếp** để chạy từng dòng: - Mở tab **Book có và không có constructor**. Hai cột chạy cùng lúc mỗi lần bấm. - Nhìn cột trái **Không constructor**. `new Book()` tạo ngay `Book#1` với `Title = null` và `Price = 0`. Ta quên gán `Title`, nên chương trình in `Tên: ` rồi để trống, và không ai báo lỗi. - Nhìn cột phải **Có constructor**. Lớp có `Book(string title, decimal price)`, nên `new Book("C#", 99)` chạy qua ba bước: bước 1 cấp vùng nhớ cho `Book#1` với các trường mặc định (`null` và `0`), biến `b` chưa nhận gì; bước 2 chạy thân constructor, gán `Title = title` rồi `Price = price`; bước 3 trả tham chiếu tới `Book#1` về cho biến `b`. - Cột phải kết thúc bằng `Tên: C#`. Đối tượng có đủ dữ liệu ngay lúc tạo xong. ``` <iframe src="https://codegym-vn.github.io/programming-course-demos/oop_ooad/doi-tuong-lop-va-dong-goi-encapsulation/ham-tao-constructors-va-khoi-tao-doi-tuong/muc-dich-cua-ham-tao-constructors/" title="Mục đích của Constructor" style="border:0;" allowfullscreen></iframe> ``` Điều rút ra: constructor chạy ngay khi `new`, nên đối tượng có dữ liệu hợp lệ từ đầu mà không sợ quên gán. Không có constructor, đối tượng thiếu dữ liệu vẫn được tạo ra trong im lặng. ## Lợi ích - **Toàn vẹn dữ liệu:** đối tượng luôn nhất quán từ khi được sinh ra. - **Dễ đọc, dễ bảo trì:** logic khởi tạo nằm ở một nơi. - **Ít lỗi lúc chạy:** tránh dùng đối tượng chưa được khởi tạo đúng. - **Cách dùng lớp rõ ràng:** danh sách tham số cho biết cần đưa gì vào để tạo một đối tượng hợp lệ. ## Tóm tắt - **Hàm tạo** có tên trùng tên lớp, không có kiểu trả về, và chạy tự động khi `new`. - Mục đích chính là đưa đối tượng về **trạng thái hợp lệ** ngay từ đầu. - Không viết hàm tạo nào thì trình biên dịch cấp **hàm tạo mặc định**, chỉ gán giá trị mặc định (`0`, `false`, `null`). - Viết ít nhất một hàm tạo thì hàm tạo mặc định **không còn được cấp**. - `new` gồm ba bước: cấp vùng nhớ, chạy thân constructor, trả tham chiếu về biến.
A12: 16 | B12: 2. Đối tượng, Lớp và Đóng gói (Encapsulation) | C12: Hàm tạo (Constructors) và Khởi tạo Đối tượng | D12: Các loại Hàm tạo và Nạp chồng Hàm tạo | E12: Bài đọc | F12: Nên làm | G12: Done | H12: Nhiều constructor khác tham số; C# chọn theo đối số; : this(...) gọi lẫn nhau. | I12: 3 tab theo lời gọi: new Point(), new Point(5), new Point(5, 7). Mỗi tab tô sáng constructor được chọn, rồi theo : this(x, 0) nhảy sang constructor đầy đủ. Bộ nhớ hiện X, Y sau cùng. | J12: 1 cột, nhiều tab | K12: oop_ooad/doi-tuong-lop-va-dong-goi-encapsulation/ham-tao-constructors-va-khoi-tao-doi-tuong/cac-loai-ham-tao-va-nap-chong-ham-tao/index.html | L12: https://codegym-vn.github.io/programming-course-demos/oop_ooad/doi-tuong-lop-va-dong-goi-encapsulation/ham-tao-constructors-va-khoi-tao-doi-tuong/cac-loai-ham-tao-va-nap-chong-ham-tao/ | P12: Hàm tạo không tham số (Parameterless Constructor) Như bạn đã biết từ bài học trước, hàm tạo là một phương thức đặc biệt được gọi tự động khi một đối tượng mới của một lớp được tạo ra, với mục đích thiết lập trạng thái ban đầu hợp lệ cho đối tượng đó. Loại hàm tạo cơ bản nhất là hàm tạo không tham số, hay còn gọi là default constructor (mặc dù thuật ngữ này đôi khi gây nhầm lẫn với hàm tạo mặc định do C# cung cấp). Hàm tạo không tham số không nhận bất kỳ đối số nào khi được gọi. Nó thường được sử dụng để khởi tạo các trường dữ liệu về giá trị mặc định của chúng (ví dụ: số về 0, chuỗi về null hoặc chuỗi rỗng, đối tượng về null), hoặc để thực hiện các thiết lập cơ bản khác mà không cần thông tin đầu vào cụ thể từ bên ngoài. Cú pháp và Ví dụ Hàm tạo không tham số được khai báo tương tự như một phương thức, nhưng tên của nó phải trùng với tên của lớp và không có kiểu trả về (kể cả void). public class SinhVien { public string MaSoSinhVien { get; set; } public string HoTen { get; set; } public int Tuoi { get; set; } // Hàm tạo không tham số public SinhVien() { MaSoSinhVien = "SV000"; // Gán giá trị mặc định HoTen = "Chưa xác định"; Tuoi = 18; // Tuổi mặc định Console.WriteLine("Đối tượng SinhVien được tạo với hàm tạo không tham số."); } public void HienThiThongTin() { Console.WriteLine($"Mã số: {MaSoSinhVien}, Họ tên: {HoTen}, Tuổi: {Tuoi}"); } } Khi bạn tạo một đối tượng SinhVien mà không truyền bất kỳ tham số nào, hàm tạo không tham số sẽ được gọi: SinhVien sv1 = new SinhVien(); sv1.HienThiThongTin(); // Output: // Đối tượng SinhVien được tạo với hàm tạo không tham số. // Mã số: SV000, Họ tên: Chưa xác định, Tuổi: 18 Lưu ý quan trọng: Nếu bạn không định nghĩa bất kỳ hàm tạo nào trong lớp của mình, C# sẽ tự động cung cấp một hàm tạo không tham số ngầm định (implicit parameterless constructor). Hàm tạo ngầm định này sẽ khởi tạo tất cả các trường dữ liệu về giá trị mặc định của kiểu dữ liệu đó (ví dụ: int về 0, string về null). Tuy nhiên, nếu bạn tự định nghĩa bất kỳ hàm tạo nào (dù là có tham số hay không tham số), C# sẽ không cung cấp hàm tạo ngầm định nữa. Điều này có nghĩa là bạn phải tự định nghĩa hàm tạo không tham số nếu muốn có nó khi đã có các hàm tạo khác. Hàm tạo có tham số (Parameterized Constructor) Trong nhiều trường hợp, bạn muốn khởi tạo đối tượng với các giá trị cụ thể ngay từ thời điểm tạo ra, thay vì các giá trị mặc định. Đây là lúc hàm tạo có tham số phát huy tác dụng. Hàm tạo có tham số cho phép bạn truyền các giá trị đầu vào (dưới dạng tham số) để khởi tạo các trường dữ liệu của đối tượng. Cú pháp và Ví dụ Cú pháp của hàm tạo có tham số tương tự như hàm tạo không tham số, nhưng nó bao gồm một danh sách các tham số trong dấu ngoặc đơn. Các tham số này sau đó được sử dụng để gán giá trị cho các trường (fields) hoặc thuộc tính (properties) của đối tượng. public class SinhVien { public string MaSoSinhVien { get; set; } public string HoTen { get; set; } public int Tuoi { get; set; } // Hàm tạo không tham số (như đã định nghĩa ở trên) public SinhVien() { MaSoSinhVien = "SV000"; HoTen = "Chưa xác định"; Tuoi = 18; Console.WriteLine("Đối tượng SinhVien được tạo với hàm tạo không tham số."); } // Hàm tạo có tham số public SinhVien(string maSo, string hoTen, int tuoi) { MaSoSinhVien = maSo; // Gán giá trị từ tham số cho thuộc tính HoTen = hoTen; Tuoi = tuoi; Console.WriteLine("Đối tượng SinhVien được tạo với hàm tạo có tham số."); } public void HienThiThongTin() { Console.WriteLine($"Mã số: {MaSoSinhVien}, Họ tên: {HoTen}, Tuổi: {Tuoi}"); } } Khi bạn tạo một đối tượng SinhVien và truyền các giá trị tương ứng với tham số của hàm tạo: SinhVien sv2 = new SinhVien("SV123", "Nguyễn Văn A", 20); sv2.HienThiThongTin(); // Output: // Đối tượng SinhVien được tạo với hàm tạo có tham số. // Mã số: SV123, Họ tên: Nguyễn Văn A, Tuổi: 20 Trong ví dụ trên, các tham số maSo, hoTen, tuoi được sử dụng để khởi tạo các thuộc tính MaSoSinhVien, HoTen, Tuoi của đối tượng sv2. Điều này đảm bảo rằng đối tượng sv2 có một trạng thái hợp lệ và đầy đủ thông tin ngay lập tức. Sử dụng từ khóa this: Đôi khi, tên của tham số có thể trùng với tên của thuộc tính/trường. Để phân biệt rõ ràng, bạn có thể sử dụng từ khóa this để chỉ ra rằng bạn đang tham chiếu đến thuộc tính/trường của đối tượng hiện tại: public SinhVien(string maSoSinhVien, string hoTen, int tuoi) { this.MaSoSinhVien = maSoSinhVien; // 'this.MaSoSinhVien' là thuộc tính của đối tượng this.HoTen = hoTen; // 'hoTen' là tham số this.Tuoi = tuoi; } Nạp chồng Hàm tạo (Constructor Overloading) Nạp chồng hàm tạo là khả năng một lớp có nhiều hàm tạo khác nhau, miễn là mỗi hàm tạo có một chữ ký (signature) riêng biệt. Chữ ký của một hàm tạo được xác định bởi số lượng, kiểu dữ liệu và thứ tự của các tham số của nó. Tên của hàm tạo luôn giống nhau (tên lớp), nên sự khác biệt phải nằm ở danh sách tham số. Mục đích của nạp chồng hàm tạo là để cung cấp nhiều cách linh hoạt khác nhau để tạo và khởi tạo đối tượng của một lớp, phù hợp với các kịch bản sử dụng khác nhau. Ví dụ về Nạp chồng Hàm tạo Tiếp tục với lớp SinhVien, chúng ta có thể định nghĩa thêm các hàm tạo để cho phép tạo đối tượng với các mức độ thông tin khác nhau: public class SinhVien { public string MaSoSinhVien { get; set; } public string HoTen { get; set; } public int Tuoi { get; set; } public string Khoa { get; set; } // 1. Hàm tạo không tham số (Parameterless Constructor) public SinhVien() { MaSoSinhVien = "SV000"; HoTen = "Chưa xác định"; Tuoi = 18; Khoa = "Tổng hợp"; Console.WriteLine("Hàm tạo 1: Không tham số."); } // 2. Hàm tạo có tham số (Parameterized Constructor) - Khởi tạo 3 thuộc tính chính public SinhVien(string maSo, string hoTen, int tuoi) { MaSoSinhVien = maSo; HoTen = hoTen; Tuoi = tuoi; Khoa = "Tổng hợp"; // Gán giá trị mặc định cho Khoa Console.WriteLine("Hàm tạo 2: 3 tham số (mã, tên, tuổi)."); } // 3. Hàm tạo có tham số (Parameterized Constructor) - Khởi tạo đầy đủ 4 thuộc tính public SinhVien(string maSo, string hoTen, int tuoi, string khoa) { MaSoSinhVien = maSo; HoTen = hoTen; Tuoi = tuoi; Khoa = khoa; Console.WriteLine("Hàm tạo 3: 4 tham số (mã, tên, tuổi, khoa)."); } public void HienThiThongTin() { Console.WriteLine($"Mã số: {MaSoSinhVien}, Họ tên: {HoTen}, Tuổi: {Tuoi}, Khoa: {Khoa}"); } } Giờ đây, bạn có thể tạo đối tượng SinhVien theo ba cách khác nhau: // Sử dụng hàm tạo 1 SinhVien svA = new SinhVien(); svA.HienThiThongTin(); // Output: // Hàm tạo 1: Không tham số. // Mã số: SV000, Họ tên: Chưa xác định, Tuổi: 18, Khoa: Tổng hợp // Sử dụng hàm tạo 2 SinhVien svB = new SinhVien("SV001", "Trần Thị B", 19); svB.HienThiThongTin(); // Output: // Hàm tạo 2: 3 tham số (mã, tên, tuổi). // Mã số: SV001, Họ tên: Trần Thị B, Tuổi: 19, Khoa: Tổng hợp // Sử dụng hàm tạo 3 SinhVien svC = new SinhVien("SV002", "Lê Văn C", 21, "Công nghệ thông tin"); svC.HienThiThongTin(); // Output: // Hàm tạo 3: 4 tham số (mã, tên, tuổi, khoa). // Mã số: SV002, Họ tên: Lê Văn C, Tuổi: 21, Khoa: Công nghệ thông tin Lợi ích của Nạp chồng Hàm tạo Tính linh hoạt: Cung cấp cho người dùng lớp nhiều tùy chọn để tạo đối tượng, phù hợp với các tình huống khác nhau. Đảm bảo trạng thái hợp lệ: Mỗi hàm tạo có thể được thiết kế để đảm bảo đối tượng luôn ở trạng thái hợp lệ, ngay cả khi chỉ có một phần thông tin được cung cấp. Dễ sử dụng: Người dùng không cần phải nhớ các bước khởi tạo riêng lẻ sau khi tạo đối tượng; mọi thứ được thực hiện trong một lệnh gọi hàm tạo duy nhất. Nạp chồng hàm tạo là một kỹ thuật mạnh mẽ trong lập trình hướng đối tượng, giúp tăng cường tính linh hoạt và khả năng sử dụng của các lớp. Tổng kết Trong bài học này, chúng ta đã khám phá các loại hàm tạo phổ biến trong C# và cách sử dụng chúng để khởi tạo đối tượng một cách hiệu quả: Hàm tạo không tham số: Dùng để khởi tạo đối tượng với các giá trị mặc định hoặc thiết lập cơ bản khi không có thông tin cụ thể được cung cấp. Hàm tạo có tham số: Cho phép bạn truyền các giá trị cụ thể để khởi tạo các trường/thuộc tính của đối tượng ngay khi nó được tạo ra. Nạp chồng hàm tạo: Là khả năng một lớp có nhiều hàm tạo với các chữ ký khác nhau, cung cấp sự linh hoạt trong việc tạo và khởi tạo đối tượng theo nhiều cách khác nhau. Việc nắm vững cách sử dụng và nạp chồng hàm tạo là rất quan trọng để xây dựng các lớp mạnh mẽ, dễ sử dụng và đảm bảo tính toàn vẹn dữ liệu của đối tượng trong ứng dụng C# của bạn. | Q12: # Các loại Hàm tạo và Nạp chồng Hàm tạo ## Mục tiêu học tập Sau bài học này, bạn có thể: - Phân biệt hàm tạo không tham số và hàm tạo có tham số. - Giải thích **nạp chồng hàm tạo** (constructor overloading) và chữ ký (signature) của hàm tạo. - Viết nhiều hàm tạo cho một lớp và dùng `: this(...)` để tránh viết lặp. - Dự đoán C# chọn hàm tạo nào dựa trên số lượng và kiểu đối số. - Quan sát từng bước `new Point(...)` chọn và chạy hàm tạo bằng hoạt động mô phỏng. ## Hàm tạo không tham số **Hàm tạo không tham số** (parameterless constructor) không nhận đối số nào. Nó dùng để đặt giá trị ban đầu cố định cho đối tượng. ```csharp using System; public class Student { public string Id; public string Name; public int Age; public Student() { Id = "SV000"; Name = "Chưa xác định"; Age = 18; } } public class Program { public static void Main() { Student s = new Student(); Console.WriteLine($"{s.Id}, {s.Name}, {s.Age}"); // SV000, Chưa xác định, 18 } } ``` Lưu ý: nếu lớp **không có hàm tạo nào**, C# tự cấp một hàm tạo không tham số ngầm định. Nhưng chỉ cần bạn viết **bất kỳ** hàm tạo nào, C# sẽ ngừng cấp. Muốn vẫn có hàm tạo không tham số thì phải tự viết. ## Hàm tạo có tham số **Hàm tạo có tham số** (parameterized constructor) nhận giá trị từ bên ngoài để khởi tạo đối tượng ngay lúc tạo: ```csharp public Student(string id, string name, int age) { Id = id; Name = name; Age = age; } ``` Khi tên tham số trùng tên trường, dùng `this` để chỉ trường của đối tượng hiện tại: `this.Name = name;`. ## Nạp chồng hàm tạo **Nạp chồng hàm tạo** là việc một lớp có nhiều hàm tạo, miễn là mỗi hàm tạo có **chữ ký** khác nhau. Chữ ký được xác định bởi **số lượng, kiểu và thứ tự** của các tham số. Tên hàm tạo luôn là tên lớp nên sự khác biệt chỉ nằm ở danh sách tham số. Khi gặp `new`, C# chọn hàm tạo khớp nhất với các đối số bạn đưa vào. Việc chọn này diễn ra **lúc biên dịch**. ### Gọi hàm tạo khác bằng `: this(...)` Các hàm tạo thường có phần việc giống nhau. Thay vì viết lặp, ta cho hàm tạo "ngắn" gọi hàm tạo "đầy đủ" bằng `: this(...)`. Phần này chạy **trước** thân của hàm tạo đang viết. ```csharp using System; public class Point { public int X, Y; public Point() : this(0, 0) { } public Point(int x) : this(x, 0) { } public Point(int x, int y) { X = x; Y = y; } } public class Program { public static void Main() { Point a = new Point(); // X = 0, Y = 0 Point b = new Point(5); // X = 5, Y = 0 Point c = new Point(5, 7); // X = 5, Y = 7 Console.WriteLine($"{a.X},{a.Y} {b.X},{b.Y} {c.X},{c.Y}"); // 0,0 5,0 5,7 } } ``` Chỉ có **một** hàm tạo thực sự gán `X` và `Y`. Hai hàm tạo còn lại chuyển tiếp về đó, nên muốn sửa cách khởi tạo ta chỉ sửa một chỗ. Lợi ích của nạp chồng: - **Linh hoạt:** người dùng chọn cách tạo đối tượng phù hợp với thông tin đang có. - **Hợp lệ:** mỗi hàm tạo đều đưa đối tượng về trạng thái đầy đủ, dù chỉ nhận một phần thông tin. - **Dễ dùng:** mọi việc xong trong một lệnh `new`. ### Khi lời gọi không khớp hàm tạo nào C# chỉ chọn trong các hàm tạo mà lớp **thật sự có**. Với lớp `Point` ở trên, `new Point("a")` không khớp hàm tạo nào, nên trình biên dịch báo lỗi. Và nếu lớp chỉ có hàm tạo có tham số, `new Point()` cũng lỗi, vì khi đã tự viết hàm tạo thì C# không cấp hàm tạo không tham số ngầm định. ### Ví dụ có nhiều mức thông tin Lớp `Student` có thể cho phép tạo với 0, 3 hoặc 4 thông tin, tùy người dùng có bao nhiêu dữ liệu. Hàm tạo thiếu thông tin tự điền giá trị mặc định hợp lý, ví dụ `Faculty = "Tổng hợp"`: ```csharp public Student() : this("SV000", "Chưa xác định", 18, "Tổng hợp") { } public Student(string id, string name, int age) : this(id, name, age, "Tổng hợp") { } public Student(string id, string name, int age, string faculty) { Id = id; Name = name; Age = age; Faculty = faculty; } ``` Chỉ hàm tạo cuối cùng gán dữ liệu thật. Hai hàm tạo kia chuyển tiếp về đó nên không lặp mã. ## Hoạt động: C# chọn hàm tạo nào? Mô phỏng dưới đây có lớp `Point` với ba hàm tạo (ở dòng 4, 6 và 8 của khung code), và ba tab ứng với ba lời gọi `new`. Hãy thao tác theo thứ tự sau, bấm **Bước tiếp** để chạy từng dòng: - Mở tab **new Point()**. Bước đầu, `new` cấp bộ nhớ cho `Point#1` với `X = 0`, `Y = 0`. Lời gọi không có đối số nên C# chọn hàm tạo ở dòng 4. Phần `: this(0, 0)` nhảy sang hàm tạo đầy đủ với `x = 0`, `y = 0`. Sau đó `X = x` rồi `Y = y` chạy. Thân rỗng `{ }` của hàm tạo ban đầu chạy sau cùng, không đổi gì. - Chuyển sang tab **new Point(5)**. Lời gọi có một đối số `int` nên C# chọn hàm tạo ở dòng 6. Phần `: this(5, 0)` chuyển sang hàm tạo đầy đủ với `x = 5`, `y = 0`. Kết quả `X = 5`, `Y = 0`. - Mở tab **new Point(5, 7)**. Lời gọi có hai đối số `int` nên C# chọn thẳng hàm tạo đầy đủ ở dòng 8, không cần `: this(...)`. Thân gán `X = 5` rồi `Y = 7`. ``` <iframe src="https://codegym-vn.github.io/programming-course-demos/oop_ooad/doi-tuong-lop-va-dong-goi-encapsulation/ham-tao-constructors-va-khoi-tao-doi-tuong/cac-loai-ham-tao-va-nap-chong-ham-tao/" title="Nạp chồng Constructor" style="border:0;" allowfullscreen></iframe> ``` Điều rút ra: nhiều hàm tạo khác tham số thì C# chọn theo đối số của lời gọi `new`. Dùng `: this(...)` để hàm tạo ngắn gọi hàm tạo đầy đủ, khỏi viết lặp. ## Tóm tắt - **Hàm tạo không tham số** không nhận đối số. Nếu lớp có hàm tạo khác, bạn phải tự viết nó khi cần. - **Hàm tạo có tham số** gán giá trị từ bên ngoài ngay lúc tạo đối tượng. - **Nạp chồng hàm tạo:** nhiều hàm tạo trong một lớp, khác nhau về số lượng, kiểu hoặc thứ tự tham số. - C# chọn hàm tạo theo đối số của `new`, việc chọn diễn ra lúc biên dịch. - `: this(...)` gọi hàm tạo khác của cùng lớp và chạy trước thân hàm tạo hiện tại.
A13: 19 | B13: 3. Kế thừa (Inheritance) và Tái sử dụng Mã | C13: Giới thiệu về Kế thừa | D13: Kế thừa là gì? | E13: Bài đọc | F13: Nên làm | G13: Done | H13: Lớp con có sẵn trường và phương thức của lớp cha. | I13: Animal { Name; Eat() } và Dog : Animal { Bark() }. new Dog() → hộp đối tượng chia 2 phần: phần của Animal (Name) và phần của Dog. Gọi dog.Eat(): mô phỏng tìm Eat trong Dog, không thấy, lên Animal, tìm thấy (tô sáng đường đi). Gọi dog.Bark() tìm thấy ngay trong Dog. | J13: 1 cột | K13: oop_ooad/ke-thua-inheritance-va-tai-su-dung-ma/gioi-thieu-ve-ke-thua/ke-thua-la-gi/index.html | L13: https://codegym-vn.github.io/programming-course-demos/oop_ooad/ke-thua-inheritance-va-tai-su-dung-ma/gioi-thieu-ve-ke-thua/ke-thua-la-gi/ | P13: Kế thừa là gì? Một cái nhìn tổng quan Trong thế giới lập trình hướng đối tượng (OOP), Kế thừa (Inheritance) là một trong bốn trụ cột chính (cùng với Đóng gói, Trừu tượng và Đa hình). Nó là một cơ chế mạnh mẽ cho phép bạn tạo ra một lớp mới dựa trên một lớp đã tồn tại. Lớp mới này, thường được gọi là lớp con (hoặc lớp dẫn xuất), sẽ tự động "thừa hưởng" các thuộc tính (dữ liệu) và phương thức (hành vi) của lớp gốc, được gọi là lớp cha (hoặc lớp cơ sở). Hãy hình dung trong đời sống thực, một đứa trẻ thừa hưởng một số đặc điểm từ cha mẹ mình, như màu mắt, màu tóc, hoặc một số thói quen. Tương tự, trong lập trình, lớp con sẽ có sẵn những gì lớp cha đã định nghĩa, và sau đó có thể bổ sung thêm các thuộc tính, phương thức riêng, hoặc thay đổi (tùy chỉnh) hành vi của những gì được thừa hưởng. Mục tiêu chính của kế thừa là thiết lập một mối quan hệ phân cấp giữa các lớp, nơi một lớp là một loại của lớp khác. Ví dụ, một chiếc "Xe hơi" là một loại "Phương tiện giao thông". Mối quan hệ "is-a" (là một) này là trọng tâm của kế thừa và sẽ được phân tích kỹ hơn trong bài học tiếp theo. Mục đích và Lợi ích cốt lõi của Kế thừa Kế thừa không chỉ là một khái niệm trừu tượng mà còn mang lại những lợi ích thiết thực, giúp code của bạn trở nên hiệu quả và dễ quản lý hơn. Tái sử dụng mã (Code Reusability) Đây là lợi ích nổi bật và dễ nhận thấy nhất của kế thừa. Thay vì phải viết lại cùng một đoạn code (các thuộc tính và phương thức chung) cho nhiều lớp khác nhau, bạn có thể định nghĩa chúng một lần duy nhất trong lớp cha. Sau đó, tất cả các lớp con chỉ cần kế thừa từ lớp cha đó và tự động có được các chức năng này. Ví dụ, nếu bạn có một lớp ĐộngVật với các thuộc tính như Tên, Tuổi và phương thức Ăn(), Ngủ(). Khi tạo các lớp Chó, Mèo, Chim, bạn không cần phải định nghĩa lại Tên, Tuổi, Ăn(), Ngủ() cho từng lớp. Thay vào đó, Chó, Mèo, Chim có thể kế thừa từ ĐộngVật và sử dụng lại những chức năng cơ bản đó, rồi chỉ cần tập trung vào các đặc điểm riêng của chúng (ví dụ: GauGau() cho Chó, MeoMeo() cho Mèo, Bay() cho Chim). Lợi ích này giúp giảm đáng kể lượng mã nguồn, tiết kiệm thời gian phát triển và giảm thiểu lỗi có thể phát sinh do trùng lặp code. Tổ chức cấu trúc lớp một cách có hệ thống Kế thừa giúp bạn xây dựng một cấu trúc lớp rõ ràng và có tổ chức, phản ánh mối quan hệ phân cấp tự nhiên giữa các đối tượng trong hệ thống. Khi nhìn vào sơ đồ lớp, bạn có thể dễ dàng hiểu được các lớp liên quan đến nhau như thế nào, lớp nào là tổng quát và lớp nào là đặc thù. Một hệ thống được tổ chức tốt sẽ dễ đọc, dễ hiểu và dễ bảo trì hơn. Khi cần tìm một chức năng, bạn biết nên tìm ở lớp cha chung hay ở một lớp con cụ thể. Điều này đặc biệt quan trọng đối với các dự án lớn với nhiều lớp và nhiều nhà phát triển. Mở rộng và Tùy chỉnh (Extensibility and Customization) Kế thừa cung cấp một cơ chế mạnh mẽ để mở rộng chức năng của một lớp mà không cần sửa đổi mã nguồn của lớp đó. Khi bạn muốn thêm một tính năng mới hoặc thay đổi cách một hành vi hoạt động, bạn có thể tạo một lớp con mới và thực hiện các thay đổi đó trong lớp con. Lớp cha vẫn giữ nguyên, đảm bảo tính ổn định cho các phần khác của hệ thống đang sử dụng lớp cha. Điều này rất hữu ích khi bạn làm việc với các thư viện hoặc framework mà bạn không có quyền chỉnh sửa mã nguồn gốc. Bạn có thể kế thừa từ các lớp có sẵn và mở rộng chúng theo nhu cầu riêng của mình. Kế thừa trong đời sống thực: Một ví dụ minh họa Để giúp bạn hình dung rõ hơn về kế thừa trước khi đi sâu vào mã nguồn, hãy xem xét một ví dụ quen thuộc trong đời sống: Phương tiện giao thông. Chúng ta có thể định nghĩa một khái niệm chung là Phương tiệnGiaoThông. Bất kỳ phương tiện nào cũng có những đặc điểm chung như: Thuộc tính:TốcĐộTốiĐa, SốBánhXe, MàuSắc, NămSảnXuất. Hành vi:KhởiĐộng(), DiChuyển(), DừngLại(). Bây giờ, hãy nghĩ đến các loại phương tiện cụ thể hơn: XeHơi: Kế thừa từ PhươngTiệnGiaoThông. Có tất cả các thuộc tính và hành vi của PhươngTiệnGiaoThông. Thêm thuộc tính riêng:SốCửa, LoạiNhiênLiệu. Tùy chỉnh hành vi: Hành vi DiChuyển() của XeHơi sẽ khác với TàuThủy (di chuyển trên đường bộ). XeĐạp: Kế thừa từ PhươngTiệnGiaoThông. Có tất cả các thuộc tính và hành vi của PhươngTiệnGiaoThông. Thêm thuộc tính riêng:LoạiPhanh, SốTốcĐộ. Tùy chỉnh hành vi: Hành vi DiChuyển() của XeĐạp là bằng sức người. TàuThủy: Kế thừa từ PhươngTiệnGiaoThông. Có tất cả các thuộc tính và hành vi của PhươngTiệnGiaoThông. Thêm thuộc tính riêng:TrọngTải, SốThủyThủ. Tùy chỉnh hành vi: Hành vi DiChuyển() của TàuThủy là trên mặt nước. Qua ví dụ này, bạn có thể thấy rằng: PhươngTiệnGiaoThông là lớp tổng quát, định nghĩa những gì chung nhất. XeHơi, XeĐạp, TàuThủy là các lớp cụ thể hơn, chúng kế thừa những đặc điểm chung và sau đó thêm vào hoặc tùy chỉnh những đặc điểm riêng của mình. Mối quan hệ "is-a" được thể hiện rõ: "Xe hơi là một Phương tiện giao thông", "Xe đạp là một Phương tiện giao thông", v.v. Kế thừa giúp chúng ta mô hình hóa thế giới thực một cách tự nhiên và logic trong code của mình, đặt nền móng cho việc xây dựng các hệ thống phức tạp một cách có tổ chức và hiệu quả. | Q13: # Kế thừa là gì? ## Mục tiêu học tập Sau bài học này, bạn có thể: - Giải thích **kế thừa** (inheritance) là gì và vì sao nó là một trụ cột của OOP. - Phân biệt **lớp cha** (base class) và **lớp con** (derived class). - Nêu ba lợi ích chính của kế thừa: tái sử dụng mã, tổ chức lớp có hệ thống, mở rộng mà không sửa mã cũ. - Nhận ra rằng lớp con dùng được thành viên của lớp cha dù không tự viết lại. - Quan sát cách C# tìm một phương thức từ lớp con lên lớp cha bằng hoạt động mô phỏng. ## Kế thừa là gì? **Kế thừa** (Inheritance) là cơ chế cho phép tạo một lớp mới dựa trên một lớp đã có. Lớp mới gọi là **lớp con** (còn gọi là lớp dẫn xuất). Nó tự động "thừa hưởng" **dữ liệu** và **phương thức** của **lớp cha** (còn gọi là lớp cơ sở). Sau đó lớp con có thể thêm thành viên riêng hoặc thay đổi hành vi đã thừa hưởng. Hãy nghĩ đến một đứa trẻ thừa hưởng màu mắt, màu tóc từ cha mẹ, rồi có thêm những nét riêng của mình. Lớp con cũng vậy: có sẵn những gì lớp cha định nghĩa, rồi bổ sung điều riêng. Kế thừa tạo ra quan hệ phân cấp, trong đó một lớp **là một loại** của lớp khác. Ví dụ: "Xe hơi là một loại phương tiện giao thông". Quan hệ "is-a" này sẽ được học kỹ ở bài sau. ## Ví dụ đời thực: phương tiện giao thông Lớp tổng quát `Vehicle` (phương tiện) có những thứ chung cho mọi phương tiện: màu sắc, năm sản xuất, khởi động, di chuyển, dừng lại. Các lớp cụ thể hơn kế thừa lại và thêm phần riêng: | Lớp con | Thừa hưởng | Thêm riêng | |---|---|---| | `Car` (xe hơi) | Mọi thứ của `Vehicle` | Số cửa, loại nhiên liệu | | `Bicycle` (xe đạp) | Mọi thứ của `Vehicle` | Loại phanh, số tốc độ | | `Ship` (tàu thủy) | Mọi thứ của `Vehicle` | Trọng tải, số thủy thủ | `Vehicle` định nghĩa phần chung nhất. Mỗi lớp con chỉ cần tập trung vào điểm khác biệt của mình. ## Lợi ích của kế thừa - **Tái sử dụng mã:** viết phần chung một lần ở lớp cha, mọi lớp con dùng được. Ít mã hơn nghĩa là ít lỗi do trùng lặp. - **Tổ chức có hệ thống:** nhìn sơ đồ lớp, ta biết lớp nào tổng quát, lớp nào cụ thể. Dự án lớn nhờ vậy dễ đọc và dễ bảo trì. - **Mở rộng mà không sửa mã cũ:** muốn thêm tính năng, ta tạo lớp con. Lớp cha giữ nguyên nên các phần khác đang dùng nó vẫn ổn định. ## Lớp con làm được gì thêm? Kế thừa không chỉ là "nhận về". Lớp con còn có thể: - **Thêm** trường, thuộc tính và phương thức riêng (như `Bark()` của `Dog`). - **Thay đổi** hành vi đã thừa hưởng, bằng cách ghi đè phương thức. Phần này học ở bài về `virtual` và `override`. Chiều ngược lại thì không đúng: lớp cha **không** có những gì lớp con tự thêm. Một biến kiểu `Animal` không gọi được `Bark()`. ## Kế thừa trong C# Trong C#, ta khai báo kế thừa bằng dấu hai chấm `:`. Ví dụ `Dog` kế thừa `Animal`: ```csharp using System; public class Animal { public string Name; public void Eat() { Console.WriteLine($"{Name} ăn"); } } public class Dog : Animal { public void Bark() { Console.WriteLine("Gâu!"); } } public class Program { public static void Main() { Dog dog = new Dog(); dog.Name = "Lu"; // Name khai báo trong Animal dog.Eat(); // Lu ăn dog.Bark(); // Gâu! } } ``` `Dog` không tự viết `Name` hay `Eat()`, nhưng vẫn dùng được cả hai. ## Hoạt động: Dog kế thừa Animal Mô phỏng dưới đây chạy đoạn mã trên và có thêm sơ đồ lớp. Hãy thao tác theo thứ tự sau, bấm **Bước tiếp** để chạy từng dòng: - Mở tab **Dog kế thừa Animal**. Dòng `new Dog()` tạo `Dog#1`. Đối tượng gồm hai phần: phần thừa hưởng từ `Animal` (là `Name`, đang là `null`) và phần của riêng `Dog`. - Ở dòng `dog.Name = "Lu"`, `Name` dùng được dù khai báo trong `Animal`, vì `Dog` kế thừa `Animal`. - Ở dòng `dog.Eat()`, C# tìm `Eat()` trong lớp `Dog` trước và không thấy. Nó đi lên lớp cha `Animal` và tìm thấy `Eat()` ở đó. Sơ đồ lớp sáng đường nối từ `Dog` lên `Animal`. `Eat()` đọc `Name` của chính đối tượng này và in `Lu ăn`. - Ở dòng `dog.Bark()`, `Bark()` nằm ngay trong `Dog` nên C# không cần đi lên lớp cha. Chương trình in `Gâu!`. ``` <iframe src="https://codegym-vn.github.io/programming-course-demos/oop_ooad/ke-thua-inheritance-va-tai-su-dung-ma/gioi-thieu-ve-ke-thua/ke-thua-la-gi/" title="Kế thừa là gì?" style="border:0;" allowfullscreen></iframe> ``` Điều rút ra: lớp con có sẵn mọi thứ của lớp cha. C# tìm phương thức ở lớp con trước, không thấy thì đi lên lớp cha. ## Tóm tắt - **Kế thừa** cho phép lớp con thừa hưởng dữ liệu và phương thức của lớp cha. - Cú pháp C#: `class Dog : Animal`. - Lợi ích: tái sử dụng mã, tổ chức lớp rõ ràng, mở rộng mà không sửa lớp cha. - Lớp con có thể thêm thành viên riêng, như `Bark()` của `Dog`. - Khi gọi phương thức, C# tìm ở lớp con trước rồi mới lên lớp cha.
A14: 20 | B14: 3. Kế thừa (Inheritance) và Tái sử dụng Mã | C14: Giới thiệu về Kế thừa | D14: Mối quan hệ 'is-a' và lớp cha, lớp con | E14: Bài đọc | F14: Làm thêm nếu muốn | G14: Done | H14: Dog là một Animal, nhưng Animal chưa chắc là Dog. | I14: Từng bước chạy các phép kiểm tra is: dog is Animal → true, dog is Dog → true, animal is Dog → false, cat is Dog → false. Sơ đồ cây lớp bên cạnh tô sáng đường từ lớp con lên lớp cha khi true. | J14: 1 cột | K14: oop_ooad/ke-thua-inheritance-va-tai-su-dung-ma/gioi-thieu-ve-ke-thua/moi-quan-he-is-a-va-lop-cha-lop-con/index.html | L14: https://codegym-vn.github.io/programming-course-demos/oop_ooad/ke-thua-inheritance-va-tai-su-dung-ma/gioi-thieu-ve-ke-thua/moi-quan-he-is-a-va-lop-cha-lop-con/ | P14: Phân biệt Lớp cha (Base Class) và Lớp con (Derived Class) Trong lập trình hướng đối tượng (OOP), khi nói đến kế thừa, chúng ta thường đề cập đến hai loại lớp chính: lớp cha và lớp con. Mặc dù bạn đã được giới thiệu về khái niệm kế thừa và vai trò của lớp con trong bài học trước, việc hiểu rõ sự phân biệt và vai trò cụ thể của từng loại lớp là rất quan trọng để thiết kế hệ thống hiệu quả. Lớp cha (Base Class / Superclass) Lớp cha, còn được gọi là lớp cơ sở (Base Class) hoặc lớp siêu cấp (Superclass), là lớp mà các lớp khác có thể kế thừa từ nó. Nó đóng vai trò là một khuôn mẫu hoặc một bản thiết kế tổng quát, định nghĩa các thuộc tính (dữ liệu) và hành vi (phương thức) chung nhất mà tất cả các lớp con của nó sẽ chia sẻ. Đặc điểm: Cung cấp nền tảng chung. Chứa các thành viên (thuộc tính, phương thức) mà các lớp con sẽ "kế thừa" và có thể sử dụng trực tiếp hoặc tùy chỉnh. Có thể là một lớp cụ thể hoặc một lớp trừu tượng (chúng ta sẽ tìm hiểu về lớp trừu tượng sau). Lớp con (Derived Class / Subclass) Lớp con, còn được gọi là lớp dẫn xuất (Derived Class) hoặc lớp thứ cấp (Subclass), là lớp được tạo ra bằng cách kế thừa từ một lớp cha. Lớp con mở rộng hoặc chuyên biệt hóa hành vi của lớp cha. Nó tự động có quyền truy cập vào các thành viên công khai và được bảo vệ của lớp cha và có thể thêm các thành viên mới hoặc ghi đè (override) các phương thức hiện có để cung cấp hành vi cụ thể hơn. Đặc điểm: Kế thừa tất cả các thành viên (trừ private) từ lớp cha. Mở rộng hoặc chuyên biệt hóa chức năng của lớp cha. Có thể thêm các thuộc tính và phương thức riêng. Có thể ghi đè các phương thức ảo (virtual) của lớp cha để cung cấp hành vi riêng. Ví dụ trực quan: Hãy tưởng tượng một loài động vật. Animal có thể là lớp cha, định nghĩa các hành vi chung như Eat() (ăn) hoặc Sleep() (ngủ). Dog và Cat sẽ là các lớp con. Dog và Cat đều ăn và ngủ, nhưng chúng có thể có các hành vi đặc trưng riêng như Bark() (sủa) đối với Dog hoặc Meow() (kêu meo meo) đối với Cat. Mối quan hệ 'is-a' trong thiết kế lớp Mối quan hệ 'is-a' (là một loại) là nguyên tắc cốt lõi để xác định khi nào nên sử dụng kế thừa. Nó là một cách để kiểm tra tính hợp lệ của một mối quan hệ kế thừa giữa hai lớp. Nếu bạn có thể nói "Lớp B là một loại Lớp A" một cách logic và ngữ nghĩa, thì mối quan hệ kế thừa có thể phù hợp. Ý nghĩa của 'is-a' Tính chuyên biệt hóa: Lớp con là một phiên bản cụ thể hơn của lớp cha. Ví dụ: "Một chiếc Ô tô là một loại Phương tiện giao thông." Tính thay thế: Một đối tượng của lớp con có thể được sử dụng ở bất cứ đâu mà một đối tượng của lớp cha được mong đợi. Đây là Nguyên tắc Thay thế Liskov (Liskov Substitution Principle), một khái niệm quan trọng trong OOP mà chúng ta sẽ tìm hiểu sâu hơn. Nếu Car kế thừa từ Vehicle, thì một đối tượng Car có thể được coi là một Vehicle. Tính kế thừa hành vi và thuộc tính: Khi Lớp B là một loại Lớp A, điều đó ngụ ý rằng Lớp B sẽ có tất cả các thuộc tính và hành vi cơ bản của Lớp A, cùng với các thuộc tính và hành vi riêng của nó. Cách 'is-a' được thể hiện trong thiết kế lớp Trong thiết kế lớp, mối quan hệ 'is-a' giúp chúng ta xây dựng một hệ thống phân cấp rõ ràng và có tổ chức. Xác định các thực thể chung: Tìm kiếm các đặc điểm và hành vi chung giữa nhiều đối tượng. Các đặc điểm chung này sẽ hình thành lớp cha. Chuyên biệt hóa: Tạo các lớp con để đại diện cho các phiên bản cụ thể hơn của lớp cha, thêm các thuộc tính và phương thức độc đáo của chúng. Kiểm tra 'is-a': Luôn tự hỏi: "Lớp con này có phải là một loại của lớp cha đó không?" Nếu câu trả lời là "có", thì kế thừa là một lựa chọn hợp lý. Nếu câu trả lời là "không" hoặc "có thể", bạn có thể cần xem xét một mối quan hệ khác, chẳng hạn như mối quan hệ 'has-a' (có một), tức là thành phần (composition), mà chúng ta sẽ khám phá sau. Ví dụ cụ thể về mối quan hệ 'is-a' trong C# Hãy xem xét một ví dụ thực tế trong C# để minh họa mối quan hệ 'is-a' giữa lớp cha và lớp con. Chúng ta sẽ xây dựng một hệ thống phân cấp đơn giản cho các loại phương tiện. Giả sử chúng ta có một lớp cơ sở Vehicle (Phương tiện) với các thuộc tính và phương thức chung cho mọi phương tiện. public class Vehicle { public string Brand { get; set; } public int Year { get; set; } public Vehicle(string brand, int year) { Brand = brand; Year = year; } public void StartEngine() { Console.WriteLine($"{Brand} khởi động động cơ."); } public void StopEngine() { Console.WriteLine($"{Brand} tắt động cơ."); } } Bây giờ, chúng ta muốn tạo một lớp Car (Ô tô) và một lớp Motorcycle (Xe máy). Cả ô tô và xe máy đều là một loại phương tiện giao thông. Do đó, chúng ta có thể làm cho Car và Motorcycle kế thừa từ Vehicle. public class Car : Vehicle // Car là lớp con, Vehicle là lớp cha { public int NumberOfDoors { get; set; } public Car(string brand, int year, int numberOfDoors) : base(brand, year) // Gọi constructor của lớp cha { NumberOfDoors = numberOfDoors; } public void Drive() { Console.WriteLine($"Xe {Brand} đang di chuyển với {NumberOfDoors} cửa."); } } public class Motorcycle : Vehicle // Motorcycle là lớp con, Vehicle là lớp cha { public bool HasSideCar { get; set; } public Motorcycle(string brand, int year, bool hasSideCar) : base(brand, year) // Gọi constructor của lớp cha { HasSideCar = hasSideCar; } public void Ride() { Console.WriteLine($"Xe máy {Brand} đang được lái. Có thùng xe phụ: {HasSideCar}."); } } Trong ví dụ trên: Vehicle là lớp cha. Car và Motorcycle là các lớp con. Cả Car và Motorcycle đều kế thừa các thuộc tính Brand, Year và các phương thức StartEngine(), StopEngine() từ lớp Vehicle. Car có thêm thuộc tính NumberOfDoors và phương thức Drive(). Motorcycle có thêm thuộc tính HasSideCar và phương thức Ride(). Để chứng minh mối quan hệ 'is-a' trong mã nguồn: public class Program { public static void Main(string[] args) { // Tạo đối tượng từ các lớp con Car myCar = new Car("Toyota", 2023, 4); Motorcycle myMotorcycle = new Motorcycle("Honda", 2022, false); // Gọi các phương thức kế thừa từ lớp cha myCar.StartEngine(); // Output: Toyota khởi động động cơ. myMotorcycle.StartEngine(); // Output: Honda khởi động động cơ. // Gọi các phương thức riêng của lớp con myCar.Drive(); // Output: Xe Toyota đang di chuyển với 4 cửa. myMotorcycle.Ride(); // Output: Xe máy Honda đang được lái. Có thùng xe phụ: False. // Minh họa mối quan hệ 'is-a': Một Car LÀ MỘT Vehicle Vehicle genericVehicle1 = myCar; // Có thể gán đối tượng Car cho biến kiểu Vehicle genericVehicle1.StopEngine(); // Output: Toyota tắt động cơ. // Minh họa mối quan hệ 'is-a': Một Motorcycle LÀ MỘT Vehicle Vehicle genericVehicle2 = myMotorcycle; // Có thể gán đối tượng Motorcycle cho biến kiểu Vehicle genericVehicle2.StopEngine(); // Output: Honda tắt động cơ. // Không thể gọi phương thức riêng của lớp con qua biến kiểu lớp cha // genericVehicle1.Drive(); // Lỗi biên dịch: 'Vehicle' does not contain a definition for 'Drive' } } Như bạn thấy trong phần Main, chúng ta có thể gán một đối tượng Car hoặc Motorcycle cho một biến kiểu Vehicle. Điều này là bởi vì một Carlà một loạiVehicle, và một Motorcyclelà một loạiVehicle. Đây chính là bản chất của mối quan hệ 'is-a' và là lý do tại sao kế thừa là một công cụ mạnh mẽ để tái sử dụng mã và xây dựng các hệ thống linh hoạt trong OOP. | Q14: # Mối quan hệ 'is-a' và lớp cha, lớp con ## Mục tiêu học tập Sau bài học này, bạn có thể: - Phân biệt lớp cha (base class) và lớp con (derived class) và vai trò của từng lớp. - Giải thích quan hệ **is-a** ("là một loại") và dùng nó để kiểm tra khi nào nên kế thừa. - Gán đối tượng lớp con cho biến kiểu lớp cha. - Dự đoán kết quả của toán tử `is` giữa các lớp trong cùng cây kế thừa. - Quan sát từng phép kiểm tra `is` bằng hoạt động mô phỏng. ## Lớp cha và lớp con **Lớp cha** (base class, còn gọi là lớp cơ sở hay superclass) là lớp để các lớp khác kế thừa. Nó định nghĩa những thuộc tính và hành vi **chung nhất**. **Lớp con** (derived class, còn gọi là lớp dẫn xuất hay subclass) là lớp kế thừa từ lớp cha. Lớp con: - Có sẵn các thành viên của lớp cha (trừ thành viên `private` mà nó không truy cập được). - Có thể thêm thuộc tính và phương thức riêng. - Có thể ghi đè (override) phương thức `virtual` của lớp cha để có hành vi riêng. Ví dụ: `Animal` là lớp cha với `Eat()` và `Sleep()`. `Dog` và `Cat` là lớp con. Cả hai đều ăn và ngủ, nhưng `Dog` có thêm `Bark()` (sủa), còn `Cat` có thêm `Meow()` (kêu meo). ## Quan hệ 'is-a' Quan hệ **is-a** ("là một loại") là phép thử để biết có nên dùng kế thừa hay không. Nếu bạn nói được một cách hợp lý "B là một loại A" thì B có thể kế thừa A. - **Chuyên biệt hóa:** lớp con là phiên bản cụ thể hơn của lớp cha. "Ô tô là một loại phương tiện giao thông." - **Thay thế được:** đối tượng lớp con dùng được ở bất cứ chỗ nào cần đối tượng lớp cha. Nguyên tắc này sau này có tên là Nguyên tắc thay thế Liskov. - **Thừa hưởng:** B là một loại A nghĩa là B có mọi thành viên cơ bản của A, cộng thêm phần riêng của B. Khi thiết kế, hãy tự hỏi: "Lớp con này có thật sự là một loại của lớp cha không?" Nếu câu trả lời là "không" hoặc "có thể", có lẽ nên dùng quan hệ khác như **has-a** ("có một", tức thành phần), sẽ học ở bài sau. ### Ví dụ trong C# ```csharp using System; public class Vehicle { public string Brand { get; set; } public int Year { get; set; } public Vehicle(string brand, int year) { Brand = brand; Year = year; } public void StartEngine() { Console.WriteLine($"{Brand} khởi động động cơ."); } public void StopEngine() { Console.WriteLine($"{Brand} tắt động cơ."); } } public class Car : Vehicle { public int NumberOfDoors { get; set; } public Car(string brand, int year, int numberOfDoors) : base(brand, year) { NumberOfDoors = numberOfDoors; } public void Drive() { Console.WriteLine($"Xe {Brand} đang di chuyển với {NumberOfDoors} cửa."); } } public class Program { public static void Main() { Car myCar = new Car("Toyota", 2023, 4); myCar.StartEngine(); // Toyota khởi động động cơ. myCar.Drive(); // Xe Toyota đang di chuyển với 4 cửa. Vehicle vehicle = myCar; // Một Car là một Vehicle vehicle.StopEngine(); // Toyota tắt động cơ. // vehicle.Drive(); // Lỗi biên dịch CS1061: Vehicle không có Drive } } ``` Gán `Car` cho biến `Vehicle` được, vì `Car` là một loại `Vehicle`. Nhưng qua biến kiểu `Vehicle`, ta chỉ gọi được những gì `Vehicle` có. `Drive()` là của riêng `Car` nên bị báo lỗi. ### Toán tử `is` Toán tử `is` kiểm tra đối tượng thật có thuộc một kiểu hay không (kể cả kiểu cha của nó). Kết quả là `true` hoặc `false`. Quy tắc: từ kiểu thật của đối tượng, đi **lên** theo cây kế thừa, nếu gặp kiểu cần kiểm tra thì kết quả là `true`. ## Hoạt động: Các phép kiểm tra is Mô phỏng có ba lớp: `Animal` là cha, `Dog` và `Cat` là hai con. Sơ đồ lớp bên dưới thể hiện cây này. Hãy thao tác theo thứ tự sau, bấm **Bước tiếp** để chạy từng dòng: - Mở tab **Các phép kiểm tra is**. Ba dòng đầu tạo `Dog#1`, `Animal#2` và `Cat#3`. - Bốn dòng `Console.WriteLine(... is ...)` chạy lần lượt. `dog is Animal` cho `true`, vì `Dog` kế thừa `Animal`. `dog is Dog` cho `true`, vì đối tượng `Dog` tất nhiên là một `Dog`. - `animal is Dog` cho `false`. `Animal` là lớp cha, một `Animal` chưa chắc là `Dog`, và đi từ `Animal` lên không gặp `Dog`. - `cat is Dog` cho `false`. `Cat` và `Dog` là hai nhánh khác nhau của `Animal`. - Kết quả cuối cùng là `true`, `true`, `false`, `false`. Sơ đồ chỉ sáng đường đi lên ở những phép kiểm tra cho `true`. ``` <iframe src="https://codegym-vn.github.io/programming-course-demos/oop_ooad/ke-thua-inheritance-va-tai-su-dung-ma/gioi-thieu-ve-ke-thua/moi-quan-he-is-a-va-lop-cha-lop-con/" title="Quan hệ is-a" style="border:0;" allowfullscreen></iframe> ``` Điều rút ra: lớp con "là một" lớp cha (`Dog is Animal`), nhưng chiều ngược lại không đúng. Hai lớp con anh em cũng không phải là một của nhau. ## Tóm tắt - **Lớp cha** chứa phần chung. **Lớp con** thừa hưởng, thêm phần riêng và có thể ghi đè hành vi. - Quan hệ **is-a**: nếu nói được "B là một loại A" thì có thể cho B kế thừa A. - Đối tượng lớp con gán được cho biến kiểu lớp cha, nhưng qua biến đó chỉ gọi được thành viên của lớp cha. - `is` đi từ kiểu thật lên cây kế thừa: `dog is Animal` là `true`, `animal is Dog` và `cat is Dog` là `false`. - Nếu không thật sự "là một loại", hãy cân nhắc quan hệ **has-a** thay vì kế thừa.
