Workbook

Sheet Tong quan
A1: Phân tích hoạt động mô phỏng – Khóa C# Ứng dụng
A2: Danh sách 61 học liệu cần có hoạt động mô phỏng (đã loại các học liệu không cần: lý thuyết, tóm tắt, trùng ý, bài tập nộp, thảo luận, trắc nghiệm).
A4: Chương | B4: Nên làm | C4: Làm thêm nếu muốn | D4: Tổng học liệu | E4: Đã duyệt OK | F4: Done | G4: Chưa done
A5: 1. Cấu trúc dữ liệu nâng cao: Collections | B5: =COUNTIFS('Phan tich'!$B$2:$B$61,$A5,'Phan tich'!$F$2:$F$61,"Nên làm") | C5: =COUNTIFS('Phan tich'!$B$2:$B$61,$A5,'Phan tich'!$F$2:$F$61,"Làm thêm nếu muốn") | D5: =COUNTIF('Phan tich'!$B$2:$B$61,$A5) | E5: =COUNTIFS('Phan tich'!$B$2:$B$61,$A5,'Phan tich'!$T$2:$T$61,"OK") | F5: =COUNTIFS('Phan tich'!$B$2:$B$61,$A5,'Phan tich'!$G$2:$G$61,"Done") | G5: =COUNTIFS('Phan tich'!$B$2:$B$61,$A5,'Phan tich'!$G$2:$G$61,"Chưa done")
A6: 2. Xử lý lỗi và Ngoại lệ (Exception Handling) Cơ bản | B6: =COUNTIFS('Phan tich'!$B$2:$B$61,$A6,'Phan tich'!$F$2:$F$61,"Nên làm") | C6: =COUNTIFS('Phan tich'!$B$2:$B$61,$A6,'Phan tich'!$F$2:$F$61,"Làm thêm nếu muốn") | D6: =COUNTIF('Phan tich'!$B$2:$B$61,$A6) | E6: =COUNTIFS('Phan tich'!$B$2:$B$61,$A6,'Phan tich'!$T$2:$T$61,"OK") | F6: =COUNTIFS('Phan tich'!$B$2:$B$61,$A6,'Phan tich'!$G$2:$G$61,"Done") | G6: =COUNTIFS('Phan tich'!$B$2:$B$61,$A6,'Phan tich'!$G$2:$G$61,"Chưa done")
A7: 3. Xử lý lỗi và Ngoại lệ (Exception Handling) Nâng cao | B7: =COUNTIFS('Phan tich'!$B$2:$B$61,$A7,'Phan tich'!$F$2:$F$61,"Nên làm") | C7: =COUNTIFS('Phan tich'!$B$2:$B$61,$A7,'Phan tich'!$F$2:$F$61,"Làm thêm nếu muốn") | D7: =COUNTIF('Phan tich'!$B$2:$B$61,$A7) | E7: =COUNTIFS('Phan tich'!$B$2:$B$61,$A7,'Phan tich'!$T$2:$T$61,"OK") | F7: =COUNTIFS('Phan tich'!$B$2:$B$61,$A7,'Phan tich'!$G$2:$G$61,"Done") | G7: =COUNTIFS('Phan tich'!$B$2:$B$61,$A7,'Phan tich'!$G$2:$G$61,"Chưa done")
A8: 4. Đọc và Ghi File Văn bản | B8: =COUNTIFS('Phan tich'!$B$2:$B$61,$A8,'Phan tich'!$F$2:$F$61,"Nên làm") | C8: =COUNTIFS('Phan tich'!$B$2:$B$61,$A8,'Phan tich'!$F$2:$F$61,"Làm thêm nếu muốn") | D8: =COUNTIF('Phan tich'!$B$2:$B$61,$A8) | E8: =COUNTIFS('Phan tich'!$B$2:$B$61,$A8,'Phan tich'!$T$2:$T$61,"OK") | F8: =COUNTIFS('Phan tich'!$B$2:$B$61,$A8,'Phan tich'!$G$2:$G$61,"Done") | G8: =COUNTIFS('Phan tich'!$B$2:$B$61,$A8,'Phan tich'!$G$2:$G$61,"Chưa done")
A9: 5. Làm việc với Dữ liệu có Cấu trúc (CSV) | B9: =COUNTIFS('Phan tich'!$B$2:$B$61,$A9,'Phan tich'!$F$2:$F$61,"Nên làm") | C9: =COUNTIFS('Phan tich'!$B$2:$B$61,$A9,'Phan tich'!$F$2:$F$61,"Làm thêm nếu muốn") | D9: =COUNTIF('Phan tich'!$B$2:$B$61,$A9) | E9: =COUNTIFS('Phan tich'!$B$2:$B$61,$A9,'Phan tich'!$T$2:$T$61,"OK") | F9: =COUNTIFS('Phan tich'!$B$2:$B$61,$A9,'Phan tich'!$G$2:$G$61,"Done") | G9: =COUNTIFS('Phan tich'!$B$2:$B$61,$A9,'Phan tich'!$G$2:$G$61,"Chưa done")
A10: 6. Lưu trữ Đối tượng với Serialization | B10: =COUNTIFS('Phan tich'!$B$2:$B$61,$A10,'Phan tich'!$F$2:$F$61,"Nên làm") | C10: =COUNTIFS('Phan tich'!$B$2:$B$61,$A10,'Phan tich'!$F$2:$F$61,"Làm thêm nếu muốn") | D10: =COUNTIF('Phan tich'!$B$2:$B$61,$A10) | E10: =COUNTIFS('Phan tich'!$B$2:$B$61,$A10,'Phan tich'!$T$2:$T$61,"OK") | F10: =COUNTIFS('Phan tich'!$B$2:$B$61,$A10,'Phan tich'!$G$2:$G$61,"Done") | G10: =COUNTIFS('Phan tich'!$B$2:$B$61,$A10,'Phan tich'!$G$2:$G$61,"Chưa done")
A11: Tổng | B11: =SUM(B5:B10) | C11: =SUM(C5:C10) | D11: =SUM(D5:D10) | E11: =SUM(E5:E10) | F11: =SUM(F5:F10) | G11: =SUM(G5:G10)
A13: Cách đọc file
A14: Nên làm | B14: Bài đọc có quá trình chạy hoặc hiện tượng khó hình dung bằng chữ (dịch chuyển phần tử, luồng exception, bộ đệm tệp, phân tích CSV...).
A15: Làm thêm nếu muốn | B15: Có ích nhưng ý chính đã được bài khác hoặc bài đọc truyền tải khá tốt.
A16: Sheet 'Phan tich' | B16: Mỗi dòng một học liệu. Các cột từ 'Mục tiêu' tới 'Lưu ý kiến thức C#' là bản mô tả chi tiết để viết mô phỏng. Ô vàng cuối dòng để bạn chọn OK / Sửa / Bỏ và ghi ý kiến.
A17: Sheet 'Thu vien hinh' | B17: 22 thành phần hình minh họa dùng chung (mã H01–H22). Mỗi mô phỏng kết hợp khung code quen thuộc với 1–3 thành phần hình để đa dạng và trực quan hơn khóa trước.
A19: Nguyên tắc thiết kế
A20: Đơn giản trước | B20: Mỗi mô phỏng một ý chính, 4–9 bước mỗi tab, chỉ bấm Bước tiếp / Chạy hết / Làm lại. Không quiz, không thử thách. Tab chỉ để đổi tình huống.
A21: Hình minh họa | B21: Ngoài khung Mã nguồn – Console – Bộ nhớ, thêm khung 'Hình minh họa' vẽ bằng HTML/SVG thuần (không thư viện ngoài). Chuyển động nhẹ 200–300 ms; tắt chuyển động khi người dùng bật prefers-reduced-motion.
A22: Màu sắc thống nhất | B22: Vàng = đang xét; Xanh lá = thành công/đã xong; Đỏ = lỗi/mất dữ liệu; Xám = bị bỏ qua/không chạy. Có chế độ tối.
A23: Điện thoại | B23: Hiển thị tốt ở bề rộng 390px: hai cột xếp chồng, hình tự co, không tràn ngang.
A24: Sự thật kỹ thuật | B24: Thông điệp lỗi, mã lỗi biên dịch, số byte, kết quả tính toán phải đúng theo .NET hiện đại; tính bằng code thật trong mô phỏng, không bịa.
A25: Lưu ý nội dung lỗi thời | B25: Chương 6 dùng BinaryFormatter/ISerializable: đã bị loại bỏ trong .NET 9. Mô phỏng không minh họa BinaryFormatter; đề xuất cập nhật học liệu.
A26: Thư mục | B26: c-sharp-ung-dung/<chuong>/<bai-hoc>/<hoc-lieu>/index.html, đẩy lên GitHub Pages như các khóa trước.

Sheet Phan tich
A1: STT | B1: Chương (Module) | C1: Bài học (Lesson) | D1: Học liệu (Activity) | E1: Loại học liệu | F1: Mức đề xuất | G1: Trạng thái | H1: Mục tiêu của mô phỏng | I1: Dạng giao diện | J1: Hình minh họa | K1: Thành phần hình (mã) | L1: Tab / tình huống | M1: Kịch bản từng bước | N1: Dữ liệu mẫu | O1: Điểm chốt (bước cuối) | P1: Lưu ý kiến thức C# | Q1: Đường dẫn file (đề xuất) | R1: Link GitHub Pages (sau khi đẩy) | S1: Ghi chú / lý do | T1: Duyệt (OK / Sửa / Bỏ) | U1: Ý kiến của bạn | V1: Nội dung cũ | W1: Nội dung mới
A2: 1 | B2: 1. Cấu trúc dữ liệu nâng cao: Collections | C2: Giới thiệu về Collections và List<T> cơ bản | D2: Giới thiệu Collections trong C# | E2: Bài đọc | F2: Nên làm | G2: Done | H2: Thấy vì sao cần List<T>: mảng có kích thước cố định, còn List<T> tự mở rộng khi thêm phần tử. | I2: 2 cột song song: Mảng int[] | List<int> | J2: Mỗi cột một dãy ô có chỉ số. Ô dự phòng của List vẽ nét đứt. Khi mảng bị ghi quá giới hạn, ô 'không tồn tại' nháy đỏ. Khi List hết chỗ, hiện hiệu ứng cấp dãy ô mới gấp đôi và chép phần tử sang. | K2: H01, H03, H22 | L2: 1 tab: Thêm phần tử thứ 4 và thứ 5 | M2: Hai cột cùng cần lưu điểm 8, 6, 9. Trái: int[] a = new int[3]. Phải: List<int> l = new List<int>() (Count 0, Capacity 0). Trái gán a[0..2]. Phải gọi Add 3 lần: Count 1→3, lần Add đầu cấp sẵn 4 chỗ (Capacity 4, ô thứ 4 nét đứt). Cả hai muốn thêm điểm 7. Trái: a[3] = 7 → không có ô chỉ số 3, console hiện IndexOutOfRangeException, chương trình dừng. Phải: l.Add(7) → lấp ô dự phòng, Count 4, Capacity 4. Phải: l.Add(10) → hết chỗ, List cấp dãy mới 8 ô, chép 4 phần tử sang rồi thêm 10 (Count 5, Capacity 8). Xong: so sánh hai cột. | N2: Điểm: 8, 6, 9, 7, 10 | O2: Mảng cố định kích thước khi tạo. List<T> tự lo việc mở rộng, người dùng chỉ cần gọi Add. | P2: new List<int>() có Capacity 0; lần Add đầu cấp 4, sau đó nhân đôi (chi tiết cài đặt của .NET, chỉ nêu để minh họa). Ghi ngoài mảng ném IndexOutOfRangeException. | Q2: c-sharp-ung-dung/cau-truc-du-lieu-nang-cao-collections/gioi-thieu-ve-collections-va-list-t-co-ban/gioi-thieu-collections-trong-c-sharp/index.html | R2: https://codegym-vn.github.io/programming-course-demos/c-sharp-ung-dung/cau-truc-du-lieu-nang-cao-collections/gioi-thieu-ve-collections-va-list-t-co-ban/gioi-thieu-collections-trong-c-sharp/ | V2: Trong lập trình C#, việc quản lý và thao tác với các nhóm dữ liệu là một nhiệm vụ cơ bản và thường xuyên. Để làm được điều này một cách hiệu quả, .NET Framework cung cấp một tập hợp các cấu trúc dữ liệu mạnh mẽ được gọi là Collections. Collections không chỉ giúp chúng ta lưu trữ dữ liệu mà còn cung cấp các cơ chế linh hoạt để thêm, xóa, truy cập và sắp xếp chúng. Collections là gì và Tại sao cần sử dụng chúng? Một Collection (tập hợp) là một cấu trúc dữ liệu được thiết kế để lưu trữ và quản lý một nhóm các đối tượng. Tưởng tượng bạn có một danh sách các món đồ cần mua, một tập hợp các sinh viên trong lớp, hoặc một bộ sưu tập các bài hát yêu thích. Thay vì khai báo từng biến riêng lẻ cho mỗi món đồ, sinh viên hay bài hát, Collections cho phép bạn nhóm chúng lại thành một đơn vị duy nhất, dễ dàng quản lý hơn. Chúng ta cần sử dụng Collections vì những lý do sau: Quản lý nhóm dữ liệu: Collections cung cấp một cách có tổ chức để lưu trữ và truy cập nhiều phần tử cùng một lúc. Thao tác dữ liệu hiệu quả: Chúng đi kèm với nhiều phương thức tích hợp sẵn để thực hiện các thao tác phổ biến như thêm, xóa, tìm kiếm, sắp xếp các phần tử một cách dễ dàng và hiệu quả. Linh hoạt và tái sử dụng: Collections được thiết kế để hoạt động với nhiều kiểu dữ liệu khác nhau và có thể được tái sử dụng trong nhiều ngữ cảnh lập trình. Ưu điểm của Collections so với Mảng truyền thống Trước khi có Collections, lập trình viên thường sử dụng mảng (Array) để lưu trữ các nhóm dữ liệu. Tuy nhiên, mảng truyền thống trong C# có một số hạn chế đáng kể mà Collections khắc phục được: Kích thước cố định: Khi bạn khai báo một mảng, bạn phải chỉ định kích thước của nó ngay từ đầu. Sau đó, bạn không thể thay đổi kích thước này. Nếu bạn cần thêm phần tử vượt quá giới hạn hoặc xóa nhiều phần tử khiến mảng bị trống, bạn sẽ phải tạo một mảng mới và sao chép tất cả các phần tử, điều này rất tốn kém và không hiệu quả. int[] mangSoNguyen = new int[5]; // Kích thước cố định là 5 // Không thể thêm phần tử thứ 6 mà không tạo mảng mới Ngược lại, hầu hết các Collections đều có kích thước động. Chúng tự động điều chỉnh khả năng lưu trữ khi bạn thêm hoặc xóa phần tử, giúp bạn không cần lo lắng về việc quản lý kích thước thủ công. Thiếu các phương thức tiện ích: Mảng chỉ cung cấp các chức năng cơ bản như truy cập phần tử theo chỉ mục. Để thực hiện các thao tác phức tạp hơn như tìm kiếm một phần tử cụ thể, sắp xếp danh sách, hoặc kiểm tra sự tồn tại của một phần tử, bạn phải tự viết các vòng lặp và thuật toán. Collections cung cấp hàng loạt các phương thức được xây dựng sẵn để thực hiện các tác vụ này, giúp mã của bạn ngắn gọn hơn, dễ đọc hơn và ít lỗi hơn. Ví dụ, bạn có thể gọi một phương thức Sort() để sắp xếp toàn bộ Collection chỉ trong một dòng lệnh. An toàn kiểu (Type Safety): Mặc dù mảng cũng có thể được định kiểu (int[], string[]), nhưng việc sử dụng các mảng kiểu object[] để lưu trữ nhiều kiểu dữ liệu khác nhau có thể dẫn đến các lỗi thời gian chạy (runtime errors) và yêu cầu ép kiểu (casting), gây giảm hiệu suất do boxing/unboxing. Các Collections hiện đại trong .NET Framework (đặc biệt là các generic collections) được thiết kế để đảm bảo an toàn kiểu mà không cần ép kiểu thủ công, giúp phát hiện lỗi ngay tại thời điểm biên dịch và cải thiện hiệu suất. Tóm lại, Collections cung cấp một giải pháp mạnh mẽ và linh hoạt hơn nhiều so với mảng truyền thống, đặc biệt là khi bạn cần quản lý các tập hợp dữ liệu có kích thước thay đổi hoặc cần thực hiện nhiều thao tác phức tạp. Các loại Collection phổ biến trong .NET Framework .NET Framework cung cấp một thư viện phong phú các Collection, mỗi loại được thiết kế để giải quyết các bài toán cụ thể. Dưới đây là một số loại phổ biến nhất mà bạn sẽ thường xuyên gặp trong lập trình C#: List<T>: Đây là một trong những Collection được sử dụng rộng rãi nhất. List<T> đại diện cho một danh sách các đối tượng có thể truy cập theo chỉ mục. Nó có kích thước động, cho phép bạn thêm, xóa và truy cập các phần tử một cách dễ dàng. List<T> lý tưởng cho các tình huống cần lưu trữ một chuỗi các phần tử có thứ tự. Bạn sẽ tìm hiểu sâu hơn về List<T> trong các bài học tiếp theo, bao gồm khái niệm, cách khởi tạo, thêm, truy cập và xóa các phần tử. Dictionary<TKey, TValue>: Collection này lưu trữ dữ liệu dưới dạng các cặp khóa-giá trị (key-value pairs). Mỗi khóa là duy nhất và được sử dụng để truy xuất giá trị tương ứng một cách nhanh chóng. Dictionary<TKey, TValue> rất hữu ích khi bạn cần tìm kiếm dữ liệu dựa trên một định danh duy nhất, giống như một cuốn từ điển nơi mỗi từ (khóa) có một định nghĩa (giá trị). HashSet<T>: HashSet<T> là một tập hợp các phần tử không có thứ tự và không chứa các phần tử trùng lặp. Nó tối ưu cho các thao tác kiểm tra sự tồn tại của một phần tử, hợp nhất (union), giao (intersection) và hiệu (difference) giữa các tập hợp. Queue<T>: Queue<T> (hàng đợi) là một Collection hoạt động theo nguyên tắc "Vào trước, Ra trước" (FIFO - First-In, First-Out). Các phần tử được thêm vào cuối hàng đợi và được lấy ra từ đầu hàng đợi. Tương tự như một hàng người xếp hàng chờ mua vé. Stack<T>: Stack<T> (ngăn xếp) là một Collection hoạt động theo nguyên tắc "Vào sau, Ra trước" (LIFO - Last-In, First-Out). Các phần tử được thêm vào (push) và lấy ra (pop) từ cùng một đầu của ngăn xếp. Tương tự như một chồng đĩa, bạn chỉ có thể thêm hoặc lấy đĩa từ trên cùng. Việc lựa chọn đúng Collection cho bài toán của bạn là một kỹ năng quan trọng, giúp tối ưu hóa hiệu suất và làm cho mã của bạn dễ quản lý hơn. Namespace System.Collections.Generic Hầu hết các Collection phổ biến và mạnh mẽ mà chúng ta vừa thảo luận (như List<T>, Dictionary<TKey, TValue>, HashSet<T>, Queue<T>, Stack<T>) đều thuộc về namespace System.Collections.Generic. Namespace này chứa các generic collections. Từ "generic" (tổng quát) ở đây có nghĩa là các Collection này được thiết kế để hoạt động với bất kỳ kiểu dữ liệu nào mà bạn chỉ định, mà vẫn đảm bảo an toàn kiểu. Ví dụ, khi bạn khai báo List<string>, bạn đang tạo một danh sách chỉ có thể chứa các đối tượng kiểu string. Điều này giúp trình biên dịch kiểm tra lỗi ngay lập tức nếu bạn cố gắng thêm một kiểu dữ liệu khác vào danh sách này, đồng thời tránh được chi phí hiệu suất của việc boxing/unboxing khi làm việc với các kiểu giá trị. Để sử dụng các Collection từ namespace này, bạn cần thêm câu lệnh using vào đầu file mã nguồn của mình: using System; using System.Collections.Generic; // Cần thiết để sử dụng List<T>, Dictionary<TKey, TValue>, v.v. public class ChuongTrinh { public static void Main(string[] args) { List<string> tenSinhVien = new List<string>(); tenSinhVien.Add("Nguyễn Văn A"); tenSinhVien.Add("Trần Thị B"); foreach (string ten in tenSinhVien) { Console.WriteLine(ten); } } } Trong các bài học tiếp theo, chúng ta sẽ đi sâu vào cách làm việc với List<T>, khám phá các phương thức và thuộc tính của nó để bạn có thể tự tin quản lý các tập hợp dữ liệu trong ứng dụng C# của mình. | W2: # Giới thiệu Collections trong C# ## Mục tiêu học tập Sau bài học này, bạn có thể: - Giải thích Collection (tập hợp) là gì và vì sao cần dùng nó. - Nêu hai hạn chế chính của mảng: kích thước cố định và thiếu phương thức tiện ích. - Kể tên các collection phổ biến: `List<T>`, `Dictionary<TKey, TValue>`, `HashSet<T>`, `Queue<T>`, `Stack<T>`. - Nhận ra namespace `System.Collections.Generic` và ý nghĩa của "generic". - Quan sát mảng báo lỗi khi hết chỗ, còn `List<T>` tự mở rộng, bằng hoạt động mô phỏng. ## Collection là gì? Một **Collection** (tập hợp) là một cấu trúc dữ liệu dùng để lưu và quản lý một nhóm đối tượng. Hãy nghĩ đến danh sách đồ cần mua, danh sách sinh viên trong lớp hay danh sách bài hát yêu thích. Thay vì khai báo từng biến riêng lẻ, bạn gom chúng vào một đơn vị duy nhất. Collection giúp bạn: - **Quản lý nhóm dữ liệu** một cách có tổ chức, truy cập nhiều phần tử cùng lúc. - **Thao tác nhanh**: có sẵn các phương thức để thêm, xóa, tìm kiếm, sắp xếp. - **Tái sử dụng**: cùng một collection dùng được cho nhiều kiểu dữ liệu khác nhau. ## Vì sao không chỉ dùng mảng? Bạn đã biết **mảng** (array). Mảng rất tiện, nhưng có hai hạn chế khi dữ liệu thay đổi thường xuyên. **1. Kích thước cố định.** Số ô được quyết định lúc tạo và không đổi được nữa. Muốn thêm phần tử vượt giới hạn, bạn phải tạo mảng mới rồi chép dữ liệu sang. ```csharp int[] a = new int[3]; // đúng 3 ô: chỉ số 0, 1, 2 a[3] = 7; // lỗi lúc chạy: IndexOutOfRangeException ``` **2. Thiếu phương thức tiện ích.** Mảng chủ yếu cho phép đọc và ghi theo chỉ số. Muốn tìm, xóa hay sắp xếp, bạn thường phải tự viết vòng lặp. Collection khắc phục cả hai: hầu hết có **kích thước động** (tự co giãn khi thêm hoặc xóa) và đi kèm nhiều phương thức dựng sẵn. | Tiêu chí | Mảng `int[]` | `List<int>` | |---|---|---| | Kích thước | Cố định lúc tạo | Tự mở rộng khi `Add` | | Số phần tử hiện có | `Length` | `Count` | | Thêm, xóa, tìm, sắp xếp | Tự viết vòng lặp | Có sẵn phương thức | ## Các collection phổ biến | Collection | Ý chính | Hình dung | |---|---|---| | `List<T>` | Danh sách có thứ tự, truy cập theo chỉ số, tự co giãn | Danh sách mua sắm | | `Dictionary<TKey, TValue>` | Lưu cặp khóa - giá trị, tra theo khóa rất nhanh | Từ điển | | `HashSet<T>` | Tập hợp không trùng lặp, không quan tâm thứ tự | Tập hợp trong toán học | | `Queue<T>` | Vào trước, ra trước (FIFO) | Hàng người xếp mua vé | | `Stack<T>` | Vào sau, ra trước (LIFO) | Chồng đĩa | Chọn đúng collection cho bài toán giúp mã gọn hơn và chạy hiệu quả hơn. Các bài sau sẽ đi sâu vào `List<T>` trước, rồi đến `Dictionary<TKey, TValue>`. ## Namespace System.Collections.Generic Các collection trên nằm trong namespace `System.Collections.Generic`. Từ **generic** (tổng quát) nghĩa là collection hoạt động với kiểu dữ liệu do bạn chỉ định trong cặp `< >`, và vẫn **an toàn kiểu** (type safety). Ví dụ `List<string>` chỉ chứa `string`. Nếu bạn thêm một số vào, trình biên dịch báo lỗi ngay, không phải đợi đến lúc chạy. Để dùng, hãy thêm `using` ở đầu file: ```csharp using System; using System.Collections.Generic; public class Program { public static void Main() { List<string> names = new List<string>(); names.Add("Lan"); names.Add("Minh"); foreach (string name in names) { Console.WriteLine(name); } // Lan // Minh } } ``` ## Hoạt động: Mảng cố định và List tự mở rộng Mô phỏng dưới đây có hai cột cùng lưu năm điểm 8, 6, 9, 7, 10. Hãy thao tác theo thứ tự sau, bấm **Bước tiếp** để chạy từng dòng: - Mở tab **Thêm phần tử thứ 4 và thứ 5**. Quan sát **cột trái** (mảng `int[]`). `new int[3]` tạo đúng 3 ô, mỗi ô mang giá trị 0, `Length` là 3. Ba dòng `a[0] = 8`, `a[1] = 6`, `a[2] = 9` lấp đầy 3 ô. Đến `a[3] = 7`, không còn ô số 3, nên thẻ lỗi đỏ **IndexOutOfRangeException** hiện ra với thông báo "Index was outside the bounds of the array." và chương trình dừng. - Nhìn sang **cột phải** (`List<int>`). List mới tạo còn rỗng, `Count` 0 và `Capacity` 0. Lần `Add(8)` đầu tiên, List cấp sẵn 4 chỗ (các ô nét đứt là chỗ còn trống). `Add(6)` và `Add(9)` chỉ đặt vào ô kế tiếp, `Count` lên 3. `Add(7)` lấp ô dự phòng cuối: `Count` 4, `Capacity` 4, List đã đầy. - Với `Add(10)`, List hết chỗ. Hãy xem hình: List cấp một dãy mới gấp đôi (8 ô), chép 4 phần tử sang, dãy cũ mờ đi vì bị bỏ. Sau đó 10 vào ô số 4. Kết quả cuối: `Count` 5, `Capacity` 8, không có lỗi nào. ``` <iframe src="https://codegym-vn.github.io/programming-course-demos/c-sharp-ung-dung/cau-truc-du-lieu-nang-cao-collections/gioi-thieu-ve-collections-va-list-t-co-ban/gioi-thieu-collections-trong-c-sharp/" title="Giới thiệu Collections trong C#" style="border:0;" allowfullscreen></iframe> ``` Điều rút ra: mảng có kích thước cố định nên thêm phần tử thứ 4 vào mảng 3 ô là lỗi. `List<T>` tự cấp thêm chỗ khi cần, bạn chỉ việc gọi `Add`. Việc nhân đôi `Capacity` (4 rồi 8) là chi tiết cài đặt của .NET, chỉ nêu để bạn hình dung. ## Tóm tắt - **Collection** là cấu trúc dữ liệu để lưu và quản lý một nhóm đối tượng. - Mảng có kích thước cố định và ít phương thức tiện ích. Collection thường có kích thước động và nhiều phương thức dựng sẵn. - Các collection phổ biến: `List<T>`, `Dictionary<TKey, TValue>`, `HashSet<T>`, `Queue<T>`, `Stack<T>`. - Chúng nằm trong `System.Collections.Generic`. "Generic" nghĩa là chỉ định kiểu dữ liệu và được kiểm tra kiểu ngay lúc biên dịch. - `List<T>` tự mở rộng khi `Add`, còn mảng thì báo `IndexOutOfRangeException` khi vượt kích thước.
A3: 2 | B3: 1. Cấu trúc dữ liệu nâng cao: Collections | C3: Giới thiệu về Collections và List<T> cơ bản | D3: Khái niệm và Khởi tạo List<T> | E3: Bài đọc | F3: Nên làm | G3: Done | H3: Phân biệt 4 cách khởi tạo List<T> và hiểu Count (số phần tử thật) khác Capacity (chỗ đã chuẩn bị). | I3: 1 cột, 4 tab | J3: Dãy ô List với ô dự phòng nét đứt; hai ô biến lớn Count và Capacity. Tab 'Từ mảng' đặt dãy ô mảng và dãy ô List cạnh nhau để thấy là hai bản riêng. | K3: H01 | L3: Rỗng | Có sức chứa ban đầu | Khởi tạo kèm giá trị | Từ mảng có sẵn | M3: Tab Rỗng: new List<string>() → Count 0, Capacity 0; Add("An") → Count 1, Capacity 4. Tab Sức chứa: new List<string>(10) → 10 ô nét đứt, Count vẫn 0. Thử names[0] khi chưa Add → ArgumentOutOfRangeException: Capacity không phải số phần tử. Tab Kèm giá trị: new List<string> { "An", "Bình", "Chi" } → mô phỏng cho thấy trình biên dịch gọi Add 3 lần. Tab Từ mảng: int[] arr = {1, 2, 3}; var list = new List<int>(arr) → dữ liệu được chép. Đổi arr[0] = 99, list[0] vẫn là 1. Bước cuối mỗi tab: ghi chú Count và Capacity. | N3: Tên: An, Bình, Chi; mảng {1, 2, 3} | O3: Count là số phần tử đang có; Capacity là chỗ đã cấp sẵn. Chỉ truy cập được chỉ số 0 đến Count − 1. | P3: list[i] với i ≥ Count ném ArgumentOutOfRangeException (khác mảng: IndexOutOfRangeException). Collection initializer thực chất gọi Add. | Q3: c-sharp-ung-dung/cau-truc-du-lieu-nang-cao-collections/gioi-thieu-ve-collections-va-list-t-co-ban/khai-niem-va-khoi-tao-list-t/index.html | R3: https://codegym-vn.github.io/programming-course-demos/c-sharp-ung-dung/cau-truc-du-lieu-nang-cao-collections/gioi-thieu-ve-collections-va-list-t-co-ban/khai-niem-va-khoi-tao-list-t/ | V3: List<T> là gì? Trong lập trình C#, khi bạn cần quản lý một tập hợp các đối tượng cùng kiểu, List<T> là một trong những cấu trúc dữ liệu mạnh mẽ và được sử dụng phổ biến nhất. List<T> là một lớp thuộc không gian tên System.Collections.Generic, đại diện cho một danh sách các đối tượng được nhập mạnh (strongly typed) có thể được truy cập bằng chỉ mục. Chữ T trong List<T> là một tham số kiểu (type parameter), cho phép bạn chỉ định kiểu dữ liệu mà danh sách sẽ chứa. Các đặc điểm nổi bật của List<T>: Kích thước động: Không giống như mảng (Array) có kích thước cố định, List<T> có thể tự động co giãn khi bạn thêm hoặc xóa phần tử. Điều này giúp bạn linh hoạt hơn rất nhiều trong việc quản lý dữ liệu mà không cần phải lo lắng về việc cấp phát lại bộ nhớ thủ công. Được nhập mạnh (Strongly Typed): Khi bạn khai báo một List<T> (ví dụ: List<int>, List<string>), danh sách đó chỉ có thể chứa các phần tử thuộc kiểu T đã được chỉ định. Điều này giúp phát hiện lỗi kiểu dữ liệu ngay tại thời điểm biên dịch, tăng cường tính an toàn và dễ bảo trì của mã nguồn. Có thứ tự: Các phần tử trong List<T> được duy trì theo thứ tự chúng được thêm vào và có thể được truy cập thông qua chỉ mục (index) bắt đầu từ 0. Cung cấp nhiều phương thức tiện ích:List<T> đi kèm với rất nhiều phương thức dựng sẵn để thêm, xóa, tìm kiếm, sắp xếp và thao tác với các phần tử một cách dễ dàng. So sánh List<T> với Mảng (Array) Mặc dù cả List<T> và mảng đều có thể lưu trữ một tập hợp các phần tử cùng kiểu và truy cập bằng chỉ mục, chúng có những khác biệt cơ bản: Trong hầu hết các trường hợp ứng dụng thực tế, List<T> là lựa chọn ưu tiên khi bạn cần một danh sách linh hoạt và dễ thao tác. Khai báo và Khởi tạo List<T> rỗng Để sử dụng List<T>, trước tiên bạn cần khai báo một biến kiểu List<T> và sau đó khởi tạo một đối tượng List<T> mới. Cú pháp cơ bản để khai báo và khởi tạo một List<T> rỗng là: List<T> tenBienDanhSach = new List<T>(); Trong đó: T là kiểu dữ liệu của các phần tử mà danh sách sẽ chứa (ví dụ: int, string, double, hoặc một kiểu đối tượng tùy chỉnh). tenBienDanhSach là tên mà bạn đặt cho biến danh sách của mình. Ví dụ: // Khai báo và khởi tạo một List rỗng chứa các số nguyên List<int> danhSachSoNguyen = new List<int>(); // Khai báo và khởi tạo một List rỗng chứa các chuỗi List<string> danhSachTen = new List<string>(); // Khai báo và khởi tạo một List rỗng chứa các số thập phân List<double> danhSachDiem = new List<double>(); // Bạn có thể kiểm tra số lượng phần tử hiện có bằng thuộc tính Count Console.WriteLine($"Số lượng số nguyên: {danhSachSoNguyen.Count}"); // Kết quả: 0 Console.WriteLine($"Số lượng tên: {danhSachTen.Count}"); // Kết quả: 0 Khi bạn khởi tạo một List<T> rỗng bằng new List<T>(), nó sẽ tạo ra một danh sách trống. Bạn có thể bắt đầu thêm các phần tử vào danh sách này sau đó (các phương thức thêm phần tử sẽ được tìm hiểu chi tiết trong bài học tiếp theo). Khởi tạo với dung lượng ban đầu (Capacity) Mặc dù List<T> có kích thước động, bạn có thể tùy chọn cung cấp một dung lượng ban đầu (initial capacity) cho danh sách khi khởi tạo. Điều này hữu ích khi bạn biết trước (hoặc ước tính) số lượng phần tử mà danh sách sẽ chứa, giúp tối ưu hiệu suất bằng cách tránh các hoạt động cấp phát lại bộ nhớ không cần thiết khi danh sách mở rộng. // Khởi tạo một List<string> rỗng với dung lượng ban đầu là 10 phần tử List<string> danhSachMonHoc = new List<string>(10); Console.WriteLine($"Dung lượng ban đầu của danh sách môn học: {danhSachMonHoc.Capacity}"); // Kết quả: 10 Console.WriteLine($"Số lượng phần tử trong danh sách môn học: {danhSachMonHoc.Count}"); // Kết quả: 0 (vẫn rỗng) Lưu ý rằng Capacity (dung lượng) khác với Count (số lượng phần tử). Capacity là số lượng phần tử mà List<T> có thể chứa trước khi cần phải cấp phát lại bộ nhớ bên trong, trong khi Count là số lượng phần tử thực tế đang có trong danh sách. Khởi tạo List<T> với các phần tử ban đầu (Collection Initializer) C# cung cấp một cú pháp tiện lợi gọi là Collection Initializer (bộ khởi tạo tập hợp) để khởi tạo một List<T> và điền các phần tử vào nó ngay lập tức. Điều này giúp mã nguồn của bạn trở nên gọn gàng và dễ đọc hơn. Cú pháp sử dụng dấu ngoặc nhọn {} ngay sau lệnh khởi tạo new List<T>(), với các phần tử được phân tách bằng dấu phẩy: List<T> tenBienDanhSach = new List<T> { phanTu1, phanTu2, // ... phanTuN }; Ví dụ: // Khởi tạo List<string> với các tên học sinh ban đầu List<string> hocSinhs = new List<string> { "Nguyễn Văn A", "Trần Thị B", "Lê Hoàng C", "Phạm Minh D" }; Console.WriteLine($"Số lượng học sinh: {hocSinhs.Count}"); // Kết quả: 4 // Khởi tạo List<int> với các số chẵn ban đầu List<int> soChan = new List<int> { 2, 4, 6, 8, 10 }; Console.WriteLine($"Số lượng số chẵn: {soChan.Count}"); // Kết quả: 5 Collection Initializer là một cách rất hiệu quả để tạo ra một danh sách với dữ liệu ban đầu, đặc biệt khi bạn có một tập hợp các phần tử cố định hoặc đã biết trước. Các loại dữ liệu có thể lưu trữ trong List<T> Vì List<T> là một cấu trúc dữ liệu generic và được nhập mạnh, bạn có thể tạo danh sách chứa hầu hết mọi kiểu dữ liệu trong C#. 1. Kiểu dữ liệu nguyên thủy (Primitive Types) và Kiểu cấu trúc (Structs) Bạn có thể lưu trữ các kiểu dữ liệu cơ bản như số nguyên, số thực, ký tự, boolean, hoặc các kiểu cấu trúc (struct) tùy chỉnh. // List chứa số nguyên (int) List<int> danhSachTuoi = new List<int> { 25, 30, 22, 45 }; // List chứa số thực (double) List<double> danhSachGia = new List<double> { 19.99, 5.50, 120.00 }; // List chứa ký tự (char) List<char> danhSachKyTu = new List<char> { 'a', 'b', 'c', 'd' }; // List chứa boolean List<bool> danhSachTrangThai = new List<bool> { true, false, true }; 2. Kiểu dữ liệu tham chiếu (Reference Types) List<T> cũng rất mạnh mẽ khi làm việc với các kiểu dữ liệu tham chiếu, bao gồm string và các đối tượng của lớp (class) do bạn tự định nghĩa. // List chứa chuỗi (string) List<string> danhSachTenQuocGia = new List<string> { "Việt Nam", "Mỹ", "Nhật Bản", "Hàn Quốc" }; // Ví dụ với một lớp tùy chỉnh (giả định có lớp SinhVien) public class SinhVien { public int MaSV { get; set; } public string TenSV { get; set; } public SinhVien(int maSV, string tenSV) { MaSV = maSV; TenSV = tenSV; } } // List chứa các đối tượng SinhVien List<SinhVien> danhSachSinhVien = new List<SinhVien> { new SinhVien(101, "Nguyễn Văn An"), new SinhVien(102, "Trần Thị Bình"), new SinhVien(103, "Lê Văn Cường") }; Console.WriteLine($"Sinh viên đầu tiên: {danhSachSinhVien[0].TenSV}"); // Kết quả: Nguyễn Văn An 3. List (Lưu trữ các kiểu hỗn hợp) Mặc dù List<T> được thiết kế để nhập mạnh, bạn có thể sử dụng List<object> nếu bạn thực sự cần lưu trữ các phần tử thuộc nhiều kiểu dữ liệu khác nhau trong cùng một danh sách. Tuy nhiên, việc này thường không được khuyến khích vì: Mất an toàn kiểu dữ liệu: Trình biên dịch sẽ không thể kiểm tra kiểu dữ liệu tại thời điểm biên dịch, dẫn đến khả năng xảy ra lỗi InvalidCastException khi bạn cố gắng ép kiểu một đối tượng sai kiểu. Hiệu suất: Đối với các kiểu giá trị (như int, double), việc lưu trữ chúng trong List<object> sẽ gây ra hiện tượng boxing (đóng gói kiểu giá trị vào một đối tượng), và khi truy cập, bạn sẽ phải thực hiện unboxing (giải phóng khỏi đối tượng). Các hoạt động boxing/unboxing có thể làm giảm hiệu suất. Ví dụ về List (Sử dụng cẩn trọng): List<object> danhSachHonHop = new List<object> { 123, // int "Hello World", // string 3.14, // double true, // bool new SinhVien(201, "Dương Thị E") // Đối tượng tùy chỉnh }; // Cần ép kiểu rõ ràng và kiểm tra kiểu trước khi sử dụng if (danhSachHonHop[0] is int soNguyen) { Console.WriteLine($"Phần tử đầu tiên là số nguyên: {soNguyen}"); } // Nếu không kiểm tra, có thể gặp lỗi ép kiểu // string ten = (string)danhSachHonHop[0]; // Sẽ gây lỗi InvalidCastException Trong hầu hết các trường hợp, việc thiết kế mã nguồn của bạn sao cho List<T> chứa các đối tượng cùng một kiểu cụ thể là phương pháp tốt nhất, đảm bảo tính an toàn, dễ bảo trì và hiệu suất cao. Nếu bạn cần lưu trữ dữ liệu hỗn hợp một cách có cấu trúc, hãy cân nhắc sử dụng các kỹ thuật khác như tạo một lớp cơ sở chung, interface, hoặc sử dụng các cấu trúc dữ liệu khác như Dictionary<string, object>. | W3: # Khái niệm và Khởi tạo List<T> ## Mục tiêu học tập Sau bài học này, bạn có thể: - Giải thích `List<T>` là gì và ý nghĩa của tham số kiểu `T`. - Phân biệt `Count` (số phần tử thật) với `Capacity` (chỗ đã cấp sẵn). - Khởi tạo `List<T>` theo bốn cách: rỗng, có sức chứa ban đầu, kèm giá trị, từ mảng có sẵn. - Giải thích vì sao đổi mảng gốc không làm đổi `List<T>` đã tạo từ mảng đó. - Quan sát `Count` và `Capacity` thay đổi ở từng cách khởi tạo bằng hoạt động mô phỏng. ## List<T> là gì? `List<T>` là lớp trong namespace `System.Collections.Generic`, đại diện cho một **danh sách có thứ tự** các phần tử cùng kiểu, truy cập được bằng **chỉ số** (index) bắt đầu từ 0. Chữ `T` là **tham số kiểu** (type parameter): bạn thay nó bằng kiểu dữ liệu muốn lưu, như `List<int>` hay `List<string>`. Đặc điểm nổi bật: - **Kích thước động:** tự co giãn khi thêm hoặc xóa phần tử, khác với mảng. - **Gõ mạnh (strongly typed):** `List<string>` chỉ chứa `string`, lỗi kiểu được báo ngay lúc biên dịch. - **Có thứ tự:** phần tử nằm theo thứ tự được thêm vào. - **Nhiều phương thức sẵn có:** thêm, xóa, tìm, sắp xếp. | Tiêu chí | Mảng | `List<T>` | |---|---|---| | Kích thước | Cố định | Tự thay đổi | | Số phần tử | `Length` | `Count` | | Thêm, xóa | Không có sẵn | `Add`, `Insert`, `Remove`... | Khi cần một danh sách linh hoạt, `List<T>` thường là lựa chọn đầu tiên. ## Count và Capacity Bên trong, `List<T>` giữ một dãy ô. Hai con số cần phân biệt: - **`Count`**: số phần tử đang có thật trong danh sách. - **`Capacity`**: số ô List đã cấp sẵn. Luôn lớn hơn hoặc bằng `Count`. Capacity là chỗ dự phòng để lần `Add` sau không phải cấp thêm bộ nhớ. Bạn chỉ **đọc được các chỉ số từ 0 đến `Count - 1`**, không phải đến `Capacity - 1`. ## Bốn cách khởi tạo ### Cách 1: List rỗng ```csharp using System; using System.Collections.Generic; public class Program { public static void Main() { var names = new List<string>(); Console.WriteLine(names.Count); // 0 Console.WriteLine(names.Capacity); // 0 names.Add("An"); Console.WriteLine(names.Capacity); // 4 (lần Add đầu cấp sẵn 4 chỗ) names.Add("Bình"); Console.WriteLine(names.Count); // 2 Console.WriteLine(names.Capacity); // 4 } } ``` List rỗng có `Count` 0 và `Capacity` 0. Lần `Add` đầu tiên cấp sẵn 4 chỗ. ### Cách 2: Có sức chứa ban đầu Nếu biết trước khoảng bao nhiêu phần tử, bạn truyền số đó vào hàm khởi tạo để tránh phải cấp thêm chỗ về sau: ```csharp var names = new List<string>(10); Console.WriteLine(names.Count); // 0 Console.WriteLine(names.Capacity); // 10 // var x = names[0]; // lỗi: ArgumentOutOfRangeException ``` Mười ô dự phòng **chưa phải phần tử**. List vẫn rỗng, nên đọc `names[0]` sẽ ném `ArgumentOutOfRangeException`. ### Cách 3: Khởi tạo kèm giá trị **Collection initializer** (bộ khởi tạo tập hợp) cho phép liệt kê giá trị trong cặp ngoặc nhọn: ```csharp var names = new List<string> { "An", "Bình", "Chi" }; Console.WriteLine(names.Count); // 3 ``` Trình biên dịch thực chất tạo List rỗng, rồi gọi `Add` cho từng giá trị. Viết gọn hay gọi `Add` từng lần đều cho kết quả giống nhau: `Count` 3, `Capacity` 4. ### Cách 4: Từ mảng có sẵn ```csharp int[] arr = { 1, 2, 3 }; var list = new List<int>(arr); arr[0] = 99; Console.WriteLine(list[0]); // 1 ``` `new List<int>(arr)` **chép** từng phần tử sang một nơi riêng, nên mảng và List là hai bản độc lập. Đổi `arr` sau đó không ảnh hưởng `list`. Lúc này `Count` và `Capacity` đều là 3. ## Hoạt động: Bốn cách tạo List Mô phỏng dưới đây có bốn tab, mỗi tab là một cách khởi tạo. Hãy để ý hai ô **Count** và **Capacity**. Bấm **Bước tiếp** để chạy từng dòng: - Mở tab **Rỗng**. `new List<string>()` cho Count 0 và Capacity 0 (chưa có ô nào). `Add("An")` làm List cấp sẵn 4 chỗ (nét đứt) và đặt "An" vào ô 0: Count 1, Capacity 4. `Add("Bình")` chỉ đặt vào ô kế tiếp: Count 2, Capacity vẫn 4. - Mở tab **Có sức chứa ban đầu**. `new List<string>(10)` hiện 10 ô nét đứt nhưng Count vẫn 0. Dòng `names[0]` làm thẻ lỗi đỏ **ArgumentOutOfRangeException** xuất hiện, vì chưa có phần tử nào. - Mở tab **Khởi tạo kèm giá trị**. List rỗng được tạo trước, rồi "An", "Bình", "Chi" lần lượt vào bằng ba lần `Add` (ô mới màu xanh). Kết quả cuối: Count 3, Capacity 4. - Mở tab **Từ mảng có sẵn**. Hình chia hai bên: mảng `arr` và List `list`. Sau `new List<int>(arr)`, cả hai đều chứa 1, 2, 3. Khi `arr[0] = 99`, chỉ mảng đổi, còn `list[0]` vẫn in ra 1. ``` <iframe src="https://codegym-vn.github.io/programming-course-demos/c-sharp-ung-dung/cau-truc-du-lieu-nang-cao-collections/gioi-thieu-ve-collections-va-list-t-co-ban/khai-niem-va-khoi-tao-list-t/" title="Khởi tạo List<T>" style="border:0;" allowfullscreen></iframe> ``` Điều rút ra: `Count` là số phần tử thật, `Capacity` chỉ là chỗ đã chuẩn bị sẵn, và chỉ truy cập được chỉ số từ 0 đến `Count - 1`. Dù khởi tạo bằng cách nào, List cũng là một đối tượng riêng. List tạo từ mảng là bản chép, không liên kết với mảng. ## Lưu ý về List<object> Bạn có thể tạo `List<object>` để chứa nhiều kiểu khác nhau, nhưng nên tránh. Trình biên dịch không còn kiểm tra kiểu giúp bạn, ép kiểu sai sẽ gây `InvalidCastException`, và các kiểu giá trị như `int` bị đóng hộp (boxing) làm chậm chương trình. Hãy ưu tiên `List<T>` với một kiểu cụ thể. ## Tóm tắt - `List<T>` là danh sách có thứ tự, kích thước động, chứa các phần tử cùng kiểu `T`. - `Count` là số phần tử thật. `Capacity` là chỗ đã cấp sẵn, luôn lớn hơn hoặc bằng `Count`. - `new List<T>()` bắt đầu với Capacity 0. Lần `Add` đầu cấp sẵn 4 chỗ. - `new List<T>(n)` dành sẵn n chỗ nhưng List vẫn rỗng, chưa đọc được phần tử nào. - Collection initializer thực chất gọi `Add` cho từng giá trị. - `new List<T>(mảng)` chép dữ liệu sang List mới, đổi mảng sau đó không ảnh hưởng List.
A4: 3 | B4: 1. Cấu trúc dữ liệu nâng cao: Collections | C4: Giới thiệu về Collections và List<T> cơ bản | D4: Thêm, Truy cập và Xóa phần tử trong List<T> | E4: Bài đọc | F4: Nên làm | G4: Done | H4: Thấy các phần tử dịch chuyển thế nào khi Insert/Remove, và lỗi khi dùng chỉ số ngoài phạm vi. | I4: 1 cột, 4 tab | J4: Dãy ô có chỉ số. Ô mới trượt vào (vàng); khi chèn ở giữa, các ô phía sau trượt phải và chỉ số đổi (mũi tên 1→2, 2→3). Ô bị xóa mờ dần rồi các ô sau trượt trái. | K4: H01, H03 | L4: Add và Insert | Truy cập và sửa | Remove và RemoveAt | Lỗi chỉ số | M4: Add/Insert: fruits = {"Táo", "Cam"}. Add("Xoài") vào cuối (chỉ số 2). Insert(1, "Lê") → "Cam", "Xoài" dịch phải. Truy cập: fruits[0] đọc "Táo"; fruits[2] = "Nho" sửa tại chỗ, Count không đổi. Remove: Remove("Cam") xóa lần xuất hiện đầu tiên, các ô sau dịch trái, trả true. Remove("Dứa") không có → trả false, không lỗi. RemoveAt(0) xóa theo vị trí. Lỗi chỉ số: danh sách 3 phần tử, đọc fruits[3] → ArgumentOutOfRangeException; nhắc chỉ số hợp lệ 0..Count − 1. Bước cuối mỗi tab: tóm tắt trạng thái danh sách. | N4: Táo, Cam, Xoài, Lê, Nho, Dứa | O4: Thêm/xóa ở giữa làm dịch chỉ số các phần tử phía sau. Remove theo giá trị trả về bool, không ném lỗi khi không tìm thấy. | P4: RemoveAt/indexer với chỉ số sai ném ArgumentOutOfRangeException. Remove chỉ xóa lần xuất hiện đầu tiên. | Q4: c-sharp-ung-dung/cau-truc-du-lieu-nang-cao-collections/gioi-thieu-ve-collections-va-list-t-co-ban/them-truy-cap-va-xoa-phan-tu-trong-list-t/index.html | R4: https://codegym-vn.github.io/programming-course-demos/c-sharp-ung-dung/cau-truc-du-lieu-nang-cao-collections/gioi-thieu-ve-collections-va-list-t-co-ban/them-truy-cap-va-xoa-phan-tu-trong-list-t/ | V4: Sau khi đã nắm vững khái niệm về List<T> và cách khởi tạo một danh sách, bước tiếp theo là tìm hiểu cách tương tác với các phần tử bên trong nó. List<T> cung cấp các phương thức mạnh mẽ và trực quan để thêm, truy cập và xóa các phần tử, giúp bạn quản lý dữ liệu một cách linh hoạt. Thêm Phần tử vào List<T> Việc thêm phần tử là thao tác cơ bản đầu tiên khi làm việc với bất kỳ danh sách nào. List<T> hỗ trợ hai cách chính để thêm phần tử: vào cuối danh sách hoặc vào một vị trí cụ thể. Phương thức Add() Phương thức Add() được dùng để thêm một phần tử mới vào cuối danh sách. Đây là cách phổ biến nhất để bổ sung dữ liệu vào List<T>. List<string> danhSachMonHoc = new List<string>(); // Thêm các môn học vào cuối danh sách danhSachMonHoc.Add("Toán"); danhSachMonHoc.Add("Lý"); danhSachMonHoc.Add("Hóa"); Console.WriteLine("Danh sách môn học sau khi Add:"); foreach (string monHoc in danhSachMonHoc) { Console.WriteLine($"- {monHoc}"); } // Kết quả: // - Toán // - Lý // - Hóa Phương thức Insert() Khi bạn muốn thêm một phần tử vào một vị trí cụ thể trong danh sách, Insert() là phương thức phù hợp. Phương thức này nhận hai đối số: chỉ mục (index) nơi bạn muốn chèn và phần tử cần chèn. Các phần tử từ vị trí chèn trở đi sẽ được dịch chuyển sang phải. Lưu ý rằng chỉ mục phải nằm trong phạm vi từ 0 đến Count của danh sách. Nếu chỉ mục vượt quá phạm vi này, một ArgumentOutOfRangeException sẽ được ném ra. List<string> danhSachMonHoc = new List<string> { "Toán", "Lý", "Hóa" }; // Thêm "Văn" vào vị trí chỉ mục 1 (giữa Toán và Lý) danhSachMonHoc.Insert(1, "Văn"); Console.WriteLine("\nDanh sách môn học sau khi Insert:"); foreach (string monHoc in danhSachMonHoc) { Console.WriteLine($"- {monHoc}"); } // Kết quả: // - Toán // - Văn // - Lý // - Hóa Truy Cập Phần tử trong List<T> Để đọc hoặc thay đổi giá trị của một phần tử tại một vị trí cụ thể trong List<T>, bạn sử dụng indexer (chỉ mục) với cú pháp dấu ngoặc vuông []. Giống như mảng, List<T> sử dụng chỉ mục dựa trên 0, nghĩa là phần tử đầu tiên có chỉ mục 0, phần tử thứ hai có chỉ mục 1, v.v. List<int> danhSachSo = new List<int> { 10, 20, 30, 40, 50 }; // Truy cập phần tử tại chỉ mục 0 Console.WriteLine($"\nPhần tử đầu tiên: {danhSachSo[0]}"); // Kết quả: 10 // Truy cập phần tử tại chỉ mục 2 Console.WriteLine($"Phần tử thứ ba: {danhSachSo[2]}"); // Kết quả: 30 // Thay đổi giá trị của phần tử tại chỉ mục 1 danhSachSo[1] = 25; Console.WriteLine($"Phần tử thứ hai sau khi thay đổi: {danhSachSo[1]}"); // Kết quả: 25 // Lấy số lượng phần tử hiện có Console.WriteLine($"Số lượng phần tử trong danh sách: {danhSachSo.Count}"); // Kết quả: 5 // Thử truy cập một chỉ mục không hợp lệ sẽ gây ra lỗi // Console.WriteLine(danhSachSo[5]); // Sẽ ném ra System.ArgumentOutOfRangeException Việc truy cập phần tử bằng chỉ mục rất nhanh chóng và hiệu quả. Tuy nhiên, bạn cần đảm bảo chỉ mục nằm trong phạm vi từ 0 đến Count - 1. Nếu không, chương trình sẽ gặp lỗi ArgumentOutOfRangeException. Xóa Phần tử khỏi List<T> List<T> cung cấp nhiều phương thức để xóa phần tử, tùy thuộc vào việc bạn muốn xóa theo giá trị, theo vị trí hay xóa toàn bộ danh sách. Phương thức Remove() Phương thức Remove() được dùng để xóa lần xuất hiện đầu tiên của một phần tử có giá trị cụ thể trong danh sách. Nếu phần tử đó tồn tại và được xóa thành công, phương thức sẽ trả về true; ngược lại, nếu phần tử không tìm thấy, nó sẽ trả về false. List<string> danhSachTraiCay = new List<string> { "Táo", "Cam", "Chuối", "Táo", "Xoài" }; Console.WriteLine("\nDanh sách trái cây ban đầu:"); foreach (string traiCay in danhSachTraiCay) { Console.Write($"{traiCay} "); } Console.WriteLine(); // Xóa lần xuất hiện đầu tiên của "Táo" bool daXoaTao = danhSachTraiCay.Remove("Táo"); Console.WriteLine($"Đã xóa 'Táo'? {daXoaTao}"); // Kết quả: True Console.WriteLine("Danh sách trái cây sau khi xóa 'Táo':"); foreach (string traiCay in danhSachTraiCay) { Console.Write($"{traiCay} "); } Console.WriteLine(); // Kết quả: Cam Chuối Táo Xoài // Thử xóa một phần tử không tồn tại bool daXoaLe = danhSachTraiCay.Remove("Lê"); Console.WriteLine($"Đã xóa 'Lê'? {daXoaLe}"); // Kết quả: False Phương thức RemoveAt() Phương thức RemoveAt() xóa phần tử tại một chỉ mục cụ thể. Tương tự như Insert(), chỉ mục phải hợp lệ (từ 0 đến Count - 1). Các phần tử sau vị trí bị xóa sẽ tự động dịch chuyển sang trái. List<string> danhSachTraiCay = new List<string> { "Táo", "Cam", "Chuối", "Xoài" }; Console.WriteLine("\nDanh sách trái cây ban đầu:"); foreach (string traiCay in danhSachTraiCay) { Console.Write($"{traiCay} "); } Console.WriteLine(); // Xóa phần tử tại chỉ mục 1 (Cam) danhSachTraiCay.RemoveAt(1); Console.WriteLine("Danh sách trái cây sau khi xóa phần tử tại chỉ mục 1:"); foreach (string traiCay in danhSachTraiCay) { Console.Write($"{traiCay} "); } Console.WriteLine(); // Kết quả: Táo Chuối Xoài // Thử xóa tại một chỉ mục không hợp lệ sẽ gây ra lỗi // danhSachTraiCay.RemoveAt(10); // Sẽ ném ra System.ArgumentOutOfRangeException Phương thức Clear() Khi bạn muốn xóa tất cả các phần tử khỏi danh sách và làm cho nó trở thành một danh sách trống rỗng, phương thức Clear() là lựa chọn phù hợp nhất. List<string> danhSachTraiCay = new List<string> { "Táo", "Cam", "Chuối" }; Console.WriteLine($"\nSố lượng phần tử ban đầu: {danhSachTraiCay.Count}"); // Kết quả: 3 // Xóa tất cả các phần tử danhSachTraiCay.Clear(); Console.WriteLine($"Số lượng phần tử sau khi Clear: {danhSachTraiCay.Count}"); // Kết quả: 0 if (danhSachTraiCay.Count == 0) { Console.WriteLine("Danh sách trái cây hiện đang trống."); } Nắm vững các phương thức cơ bản này sẽ giúp bạn thao tác với dữ liệu trong List<T> một cách hiệu quả và linh hoạt, đặt nền tảng vững chắc cho việc sử dụng các cấu trúc dữ liệu phức tạp hơn trong C#. | W4: # Thêm, Truy cập và Xóa phần tử trong List<T> ## Mục tiêu học tập Sau bài học này, bạn có thể: - Phân biệt `Add` (thêm vào cuối) với `Insert` (chèn vào vị trí bất kỳ). - Đọc và sửa phần tử bằng chỉ số `list[i]`. - Phân biệt `Remove` (xóa theo giá trị) với `RemoveAt` (xóa theo vị trí), và dùng `Clear` để xóa hết. - Giải thích vì sao chỉ số ngoài khoảng 0 đến `Count - 1` gây `ArgumentOutOfRangeException`. - Quan sát các ô dịch chuyển và chỉ số thay đổi khi thêm, xóa bằng hoạt động mô phỏng. ## Thêm phần tử ### Add: thêm vào cuối `Add` đặt phần tử mới vào **cuối** danh sách. Các phần tử cũ giữ nguyên chỉ số. ### Insert: chèn vào vị trí bất kỳ `Insert(index, item)` chèn `item` tại chỉ số `index`. Các phần tử từ vị trí đó trở đi **dịch sang phải** một ô, nên chỉ số của chúng tăng thêm 1. Chỉ số hợp lệ cho `Insert` là từ 0 đến `Count` (chèn đúng bằng `Count` cũng được, tương đương `Add`). ```csharp using System; using System.Collections.Generic; public class Program { public static void Main() { var fruits = new List<string> { "Táo", "Cam" }; fruits.Add("Xoài"); // Táo, Cam, Xoài fruits.Insert(1, "Lê"); // Táo, Lê, Cam, Xoài Console.WriteLine(string.Join(", ", fruits)); // Táo, Lê, Cam, Xoài } } ``` ## Truy cập và sửa phần tử Dùng **indexer** `list[chỉ số]` để đọc hoặc ghi tại chỗ. Chỉ số bắt đầu từ 0. ```csharp var fruits = new List<string> { "Táo", "Cam", "Xoài" }; string s = fruits[0]; // "Táo", đọc không làm danh sách thay đổi fruits[2] = "Nho"; // thay "Xoài" bằng "Nho" ngay tại chỗ // Táo, Cam, Nho. Count vẫn là 3 ``` Sửa bằng chỉ số **không làm đổi `Count`**. ### Chỉ số hợp lệ Chỉ số hợp lệ là từ **0 đến `Count - 1`**. Ngoài khoảng đó, List ném `ArgumentOutOfRangeException`: ```csharp var fruits = new List<string> { "Táo", "Cam", "Xoài" }; string a = fruits[2]; // "Xoài", phần tử cuối string b = fruits[3]; // lỗi: ArgumentOutOfRangeException // Index was out of range. Must be non-negative and less than the size of the collection. (Parameter 'index') ``` ## Xóa phần tử | Phương thức | Xóa gì | Trả về | |---|---|---| | `Remove(item)` | Lần xuất hiện **đầu tiên** của giá trị | `bool`: `true` nếu xóa được, `false` nếu không thấy | | `RemoveAt(index)` | Phần tử tại chỉ số | Không trả về | | `Clear()` | Toàn bộ phần tử | Không trả về | Sau khi xóa, các phần tử phía sau **dịch sang trái** để lấp chỗ trống. ```csharp var fruits = new List<string> { "Táo", "Cam", "Xoài", "Lê" }; bool a = fruits.Remove("Cam"); // true, còn: Táo, Xoài, Lê bool b = fruits.Remove("Dứa"); // false, không có "Dứa", không ném lỗi fruits.RemoveAt(0); // xóa "Táo", còn: Xoài, Lê fruits.Clear(); // xóa hết, Count = 0 ``` `Remove` với giá trị không có chỉ trả về `false`. Còn `RemoveAt` với chỉ số ngoài khoảng 0 đến `Count - 1` thì ném `ArgumentOutOfRangeException`. ## Hoạt động: Các ô dịch chuyển Mô phỏng dưới đây có bốn tab, mỗi tab là một tình huống với danh sách `fruits`. Hãy thao tác theo thứ tự sau, bấm **Bước tiếp** để chạy từng dòng: - Mở tab **Add và Insert**. Danh sách ban đầu là "Táo" (chỉ số 0) và "Cam" (chỉ số 1). `Add("Xoài")` thêm ô mới màu xanh ở chỉ số 2. `Insert(1, "Lê")` chèn "Lê" vào chỉ số 1, còn "Cam" và "Xoài" dịch sang phải (nhãn nhỏ dưới ô ghi `1→2` và `2→3`). Danh sách cuối: Táo, Lê, Cam, Xoài. - Mở tab **Truy cập và sửa**. Danh sách có "Táo", "Cam", "Xoài". `fruits[0]` đọc ra "Táo" và danh sách không đổi. `fruits[2] = "Nho"` thay "Xoài" bằng "Nho" ngay tại chỗ, `Count` vẫn là 3. - Mở tab **Remove và RemoveAt**. Danh sách có Táo, Cam, Xoài, Lê. `Remove("Cam")` tìm thấy "Cam" ở chỉ số 1 và ô đó bị đánh dấu xóa. Sau đó "Xoài" và "Lê" dịch trái (nhãn `2→1` và `3→2`), `a` là `true`. `Remove("Dứa")` không thấy gì: các ô được tô mờ, `b` là `false`, danh sách giữ nguyên. `RemoveAt(0)` xóa "Táo", còn Xoài, Lê. - Mở tab **Lỗi chỉ số**. Danh sách có 3 phần tử nên chỉ số hợp lệ là 0 đến 2. `fruits[2]` đọc được "Xoài". `fruits[3]` làm hiện ô "?" đỏ và thẻ lỗi **ArgumentOutOfRangeException**, vì chỉ số 3 bằng `Count`. ``` <iframe src="https://codegym-vn.github.io/programming-course-demos/c-sharp-ung-dung/cau-truc-du-lieu-nang-cao-collections/gioi-thieu-ve-collections-va-list-t-co-ban/them-truy-cap-va-xoa-phan-tu-trong-list-t/" title="Thêm, truy cập và xóa phần tử trong List<T>" style="border:0;" allowfullscreen></iframe> ``` Điều rút ra: `Add` thêm vào cuối, còn `Insert` và các phép xóa làm các phần tử phía sau dịch chuyển, nên chỉ số của chúng thay đổi. Đọc hoặc ghi bằng chỉ số chỉ hợp lệ trong khoảng 0 đến `Count - 1`. ## Tóm tắt - `Add(x)` thêm vào cuối. `Insert(i, x)` chèn tại chỉ số `i` và đẩy các phần tử sau sang phải. - `list[i]` đọc hoặc sửa tại chỗ, không đổi `Count`. - Chỉ số hợp lệ là 0 đến `Count - 1`. Ngoài khoảng này ném `ArgumentOutOfRangeException`. - `Remove(x)` xóa lần xuất hiện đầu tiên và trả về `bool`. `RemoveAt(i)` xóa theo vị trí. `Clear()` xóa hết. - Sau mỗi lần xóa, các phần tử phía sau dịch sang trái.
A5: 4 | B5: 1. Cấu trúc dữ liệu nâng cao: Collections | C5: Thao tác nâng cao với List<T> | D5: Tìm kiếm phần tử trong List<T> | E5: Bài đọc | F5: Nên làm | G5: Done | H5: Thấy mọi phép tìm trên List đều quét từ đầu, và phân biệt kết quả của IndexOf, Find, FindAll, Exists. | I5: 1 cột, 4 tab | J5: Dãy ô với 'kính lúp' (ô đang xét nền vàng) di chuyển từng ô; dưới mỗi ô hiện kết quả điều kiện true/false; ô khớp viền xanh; kết quả trả về hiện trong thẻ riêng (một số, một phần tử, hay một List mới). | K5: H01, H22 | L5: IndexOf / Contains | Find | FindAll | Exists | M5: IndexOf(9): xét 7, 4, 9 → trả 2 và dừng ở lần xuất hiện đầu. IndexOf(5) quét hết → −1. Contains(x) tương đương IndexOf(x) ≥ 0. Find(x => x > 8): xét từng ô, hiện kết quả điều kiện; trả 9 (phần tử đầu tiên khớp). Find(x => x > 100) → trả 0 (default của int). FindAll(x => x >= 6): duyệt hết, thả các ô khớp vào một List mới {7, 9, 6, 9}; danh sách gốc giữ nguyên. Exists(x => x < 4): dừng ngay khi gặp 3 → true. Bước cuối: ô đếm 'số ô đã xét' cho từng phép tìm. | N5: scores = {7, 4, 9, 6, 9, 3} | O5: IndexOf trả vị trí, Find trả phần tử, FindAll trả danh sách mới, Exists trả true/false. Tất cả đều duyệt tuần tự. | P5: Find không thấy trả default(T) (0 với int, null với đối tượng) nên dễ nhầm với giá trị hợp lệ; khi cần phân biệt dùng FindIndex hoặc Exists. | Q5: c-sharp-ung-dung/cau-truc-du-lieu-nang-cao-collections/thao-tac-nang-cao-voi-list-t/tim-kiem-phan-tu-trong-list-t/index.html | R5: https://codegym-vn.github.io/programming-course-demos/c-sharp-ung-dung/cau-truc-du-lieu-nang-cao-collections/thao-tac-nang-cao-voi-list-t/tim-kiem-phan-tu-trong-list-t/ | V5: Giới thiệu về Tìm kiếm Phần tử trong List<T> Trong quá trình phát triển ứng dụng, việc lưu trữ dữ liệu trong các cấu trúc như List<T> là rất phổ biến. Tuy nhiên, chỉ lưu trữ thôi là chưa đủ; chúng ta cần các phương pháp hiệu quả để tìm kiếm các phần tử cụ thể hoặc các phần tử thỏa mãn một điều kiện nào đó. C# cung cấp một bộ sưu tập phong phú các phương thức tích hợp sẵn cho List<T> giúp chúng ta thực hiện các tác vụ tìm kiếm này một cách dễ dàng và hiệu quả. Việc nắm vững các phương thức tìm kiếm này không chỉ giúp bạn truy xuất dữ liệu nhanh chóng mà còn là nền tảng để xử lý dữ liệu phức tạp hơn, chẳng hạn như lọc, sắp xếp hoặc cập nhật các phần tử trong danh sách. Phương thức Contains(): Kiểm tra sự tồn tại của phần tử Phương thức Contains() là cách đơn giản nhất để kiểm tra xem một phần tử cụ thể có tồn tại trong List<T> hay không. Nó trả về một giá trị bool: true nếu phần tử được tìm thấy, và false nếu không. Đây là phương thức lý tưởng khi bạn chỉ cần biết "có hay không" một phần tử tồn tại, mà không cần biết vị trí của nó. List<string> danhSachMonHoc = new List<string> { "Toán", "Vật Lý", "Hóa Học", "Sinh Học" }; // Kiểm tra xem "Toán" có tồn tại không bool coMonToan = danhSachMonHoc.Contains("Toán"); Console.WriteLine($"Có môn Toán trong danh sách không? {coMonToan}"); // Output: True // Kiểm tra xem "Lịch Sử" có tồn tại không bool coMonLichSu = danhSachMonHoc.Contains("Lịch Sử"); Console.WriteLine($"Có môn Lịch Sử trong danh sách không? {coMonLichSu}"); // Output: False // Lưu ý: Contains() sử dụng phương thức Equals() để so sánh các đối tượng. // Với các kiểu dữ liệu phức tạp (custom objects), bạn cần đảm bảo // rằng phương thức Equals() được ghi đè đúng cách nếu muốn so sánh dựa trên giá trị. Tìm chỉ mục với IndexOf() và LastIndexOf() Khi bạn cần biết vị trí (chỉ mục) của một phần tử trong danh sách, IndexOf() và LastIndexOf() là các phương thức bạn cần sử dụng. IndexOf(T item): Tìm chỉ mục của lần xuất hiện đầu tiên của một phần tử trong danh sách. Nếu phần tử không được tìm thấy, nó sẽ trả về -1. LastIndexOf(T item): Tìm chỉ mục của lần xuất hiện cuối cùng của một phần tử trong danh sách. Tương tự, nếu không tìm thấy, nó sẽ trả về -1. List<int> danhSachSo = new List<int> { 10, 20, 30, 20, 40, 50, 20 }; // Tìm chỉ mục của lần xuất hiện đầu tiên của số 20 int chiMucDauTien = danhSachSo.IndexOf(20); Console.WriteLine($"Chỉ mục đầu tiên của số 20 là: {chiMucDauTien}"); // Output: 1 // Tìm chỉ mục của lần xuất hiện cuối cùng của số 20 int chiMucCuoiCung = danhSachSo.LastIndexOf(20); Console.WriteLine($"Chỉ mục cuối cùng của số 20 là: {chiMucCuoiCung}"); // Output: 6 // Tìm chỉ mục của số không tồn tại (ví dụ: 99) int chiMucKhongTonTai = danhSachSo.IndexOf(99); Console.WriteLine($"Chỉ mục của số 99 là: {chiMucKhongTonTai}"); // Output: -1 Các phiên bản quá tải (overload) của IndexOf() và LastIndexOf() cũng cho phép bạn chỉ định phạm vi tìm kiếm (bắt đầu từ chỉ mục nào, tìm kiếm bao nhiêu phần tử). Tìm kiếm theo điều kiện với Find() và FindAll() (Predicate) Trong nhiều trường hợp, bạn không tìm kiếm một phần tử cụ thể mà là một phần tử (hoặc nhiều phần tử) thỏa mãn một điều kiện nhất định. Các phương thức Find() và FindAll() sử dụng Predicate<T> (thường được viết dưới dạng biểu thức lambda) để thực hiện tác vụ này. Find(Predicate<T> match): Tìm và trả về phần tử đầu tiên trong danh sách thỏa mãn điều kiện được chỉ định bởi Predicate<T>. Nếu không tìm thấy phần tử nào, nó sẽ trả về giá trị mặc định của kiểu dữ liệu T (ví dụ: null cho kiểu tham chiếu, 0 cho int). FindAll(Predicate<T> match): Tìm và trả về tất cả các phần tử trong danh sách thỏa mãn điều kiện được chỉ định. Kết quả trả về là một List<T> mới chứa các phần tử tìm được. Nếu không có phần tử nào thỏa mãn, nó trả về một List<T> rỗng. Predicate<T> là một delegate nhận vào một tham số kiểu T và trả về một bool. Biểu thức lambda là cách viết ngắn gọn và tiện lợi để định nghĩa Predicate<T> ngay tại chỗ. public class SinhVien { public int MaSo { get; set; } public string Ten { get; set; } public double DiemTrungBinh { get; set; } } List<SinhVien> danhSachSinhVien = new List<SinhVien> { new SinhVien { MaSo = 101, Ten = "An", DiemTrungBinh = 8.5 }, new SinhVien { MaSo = 102, Ten = "Bình", DiemTrungBinh = 7.0 }, new SinhVien { MaSo = 103, Ten = "Cường", DiemTrungBinh = 9.2 }, new SinhVien { MaSo = 104, Ten = "Dung", DiemTrungBinh = 8.5 } }; // Sử dụng Find() để tìm sinh viên đầu tiên có điểm trung bình lớn hơn 8.0 SinhVien svDiemCao = danhSachSinhVien.Find(sv => sv.DiemTrungBinh > 8.0); if (svDiemCao != null) { Console.WriteLine($"Sinh viên đầu tiên có điểm > 8.0: {svDiemCao.Ten} ({svDiemCao.DiemTrungBinh})"); // Output: An (8.5) } // Sử dụng FindAll() để tìm tất cả sinh viên có điểm trung bình bằng 8.5 List<SinhVien> svCoDiem8_5 = danhSachSinhVien.FindAll(sv => sv.DiemTrungBinh == 8.5); Console.WriteLine("Các sinh viên có điểm trung bình 8.5:"); foreach (var sv in svCoDiem8_5) { Console.WriteLine($"- {sv.Ten} ({sv.DiemTrungBinh})"); } // Output: // - An (8.5) // - Dung (8.5) // Tìm sinh viên không tồn tại SinhVien svKhongCo = danhSachSinhVien.Find(sv => sv.MaSo == 999); Console.WriteLine($"Sinh viên mã số 999: {(svKhongCo == null ? "Không tìm thấy" : svKhongCo.Ten)}"); // Output: Không tìm thấy Kiểm tra sự tồn tại có điều kiện với Any() và All() Các phương thức mở rộng LINQ (Language Integrated Query) Any() và All() cung cấp một cách mạnh mẽ và biểu cảm để kiểm tra các điều kiện trên toàn bộ danh sách. Mặc dù chúng không trực tiếp trả về các phần tử, nhưng chúng rất hữu ích cho việc kiểm tra sự tồn tại có điều kiện. Any(Func<T, bool> predicate): Trả về true nếu ít nhất một phần tử trong danh sách thỏa mãn điều kiện được chỉ định. Nếu danh sách rỗng hoặc không có phần tử nào thỏa mãn, nó trả về false. All(Func<T, bool> predicate): Trả về true nếu tất cả các phần tử trong danh sách thỏa mãn điều kiện được chỉ định. Nếu danh sách rỗng, nó trả về true (một tập hợp rỗng luôn thỏa mãn mọi điều kiện). Nếu có bất kỳ phần tử nào không thỏa mãn, nó trả về false. List<int> danhSachDiem = new List<int> { 60, 75, 80, 90, 55 }; // Kiểm tra xem có bất kỳ điểm nào lớn hơn 85 không bool coDiemCao = danhSachDiem.Any(diem => diem > 85); Console.WriteLine($"Có điểm nào lớn hơn 85 không? {coDiemCao}"); // Output: True // Kiểm tra xem tất cả các điểm đều lớn hơn hoặc bằng 50 không bool tatCaDat = danhSachDiem.All(diem => diem >= 50); Console.WriteLine($"Tất cả các điểm đều đạt (>=50) không? {tatCaDat}"); // Output: True // Kiểm tra xem tất cả các điểm đều lớn hơn 70 không bool tatCaTren70 = danhSachDiem.All(diem => diem > 70); Console.WriteLine($"Tất cả các điểm đều trên 70 không? {tatCaTren70}"); // Output: False (vì có 60, 55) List<string> danhSachTen = new List<string> { "Alice", "Bob", "Charlie" }; // Kiểm tra xem có tên nào bắt đầu bằng 'A' không bool coTenBatDauBangA = danhSachTen.Any(ten => ten.StartsWith("A")); Console.WriteLine($"Có tên nào bắt đầu bằng 'A' không? {coTenBatDauBangA}"); // Output: True // Kiểm tra xem tất cả các tên đều có độ dài lớn hơn 3 không bool tatCaDaiHon3 = danhSachTen.All(ten => ten.Length > 3); Console.WriteLine($"Tất cả các tên đều dài hơn 3 ký tự không? {tatCaDaiHon3}"); // Output: True Any() và All() rất mạnh mẽ để kiểm tra các quy tắc nghiệp vụ hoặc điều kiện tổng quát trên một tập hợp dữ liệu mà không cần phải duyệt qua toàn bộ danh sách một cách thủ công. Chúng giúp mã nguồn trở nên ngắn gọn và dễ đọc hơn. | W5: # Tìm kiếm phần tử trong List<T> ## Mục tiêu học tập Sau bài học này, bạn có thể: - Dùng `IndexOf` để lấy vị trí đầu tiên của một giá trị (hoặc -1 nếu không có) và `Contains` để biết có hay không. - Viết điều kiện tìm kiếm bằng biểu thức lambda (`Predicate<T>`). - Phân biệt `Find` (một phần tử đầu tiên), `FindAll` (mọi phần tử khớp) và `Exists` (chỉ có hay không). - Nhận ra `Find` trả về giá trị mặc định (`default`) khi không tìm thấy. - Quan sát cách phép tìm quét từng ô từ đầu danh sách bằng hoạt động mô phỏng. ## Tìm theo giá trị: IndexOf và Contains - `IndexOf(x)` trả về **chỉ số của lần xuất hiện đầu tiên** của `x`, hoặc **-1** nếu không có. - `LastIndexOf(x)` tương tự nhưng tìm lần xuất hiện cuối cùng. - `Contains(x)` trả về `true` hoặc `false`. Kết quả giống `IndexOf(x) >= 0`. ```csharp using System; using System.Collections.Generic; public class Program { public static void Main() { var scores = new List<int> { 7, 4, 9, 6, 9, 3 }; int a = scores.IndexOf(9); // 2 (9 xuất hiện ở ô 2 và ô 4, lấy ô đầu) int b = scores.IndexOf(5); // -1 (không có) bool c = scores.Contains(9); // true int d = scores.LastIndexOf(9); // 4 Console.WriteLine($"{a} {b} {c} {d}"); // 2 -1 True 4 } } ``` Với kiểu đối tượng do bạn tự viết, `IndexOf` và `Contains` so sánh bằng `Equals`. Nếu không ghi đè `Equals`, hai đối tượng chỉ "bằng nhau" khi là cùng một đối tượng. ## Tìm theo điều kiện: Find, FindAll, Exists Đôi khi bạn không biết giá trị cụ thể, chỉ biết điều kiện, ví dụ "điểm lớn hơn 8". Khi đó bạn đưa vào một **điều kiện** (predicate): hàm nhận một phần tử và trả về `bool`. Cách viết gọn nhất là **biểu thức lambda** `x => x > 8`, đọc là "với mỗi x, kiểm tra x > 8". | Phương thức | Trả về | Khi không có phần tử khớp | |---|---|---| | `Find(điều kiện)` | Phần tử khớp **đầu tiên** | `default(T)`: 0 với `int`, `null` với đối tượng | | `FindAll(điều kiện)` | **List mới** chứa mọi phần tử khớp | List rỗng | | `Exists(điều kiện)` | `bool` | `false` | ```csharp var scores = new List<int> { 7, 4, 9, 6, 9, 3 }; int a = scores.Find(x => x > 8); // 9 int b = scores.Find(x => x > 100); // 0 (default(int)) List<int> r = scores.FindAll(x => x >= 6); // { 7, 9, 6, 9 } bool e = scores.Exists(x => x < 4); // true ``` **Lưu ý:** `Find` trả `0` khi không thấy, nhưng `0` cũng có thể là một điểm hợp lệ, nên khó phân biệt "không thấy" với "tìm được 0". Khi cần phân biệt, hãy dùng `FindIndex` (trả -1 nếu không thấy) hoặc `Exists`. Nếu bạn đã học LINQ, `Any(điều kiện)` và `All(điều kiện)` (cần `using System.Linq;`) làm việc tương tự cho các câu hỏi "có phần tử nào..." và "mọi phần tử đều...". ## Mọi phép tìm đều quét từ đầu Cả `IndexOf`, `Find`, `FindAll` và `Exists` đều **duyệt tuần tự từ đầu danh sách**. Chúng khác nhau ở chỗ dừng: - `IndexOf`, `Find`, `Exists` **dừng ngay** khi gặp phần tử khớp đầu tiên. - `FindAll` **không dừng sớm**, phải xét hết để gom đủ mọi phần tử khớp. - Nếu không có phần tử khớp, mọi phép tìm đều phải xét hết danh sách. ## Hoạt động: Quét từng ô Mô phỏng dưới đây dùng danh sách `scores` gồm 7, 4, 9, 6, 9, 3 (chỉ số 0 đến 5). Hãy thao tác theo thứ tự sau, bấm **Bước tiếp** để chạy từng dòng: - Mở tab **IndexOf / Contains**. Con trỏ "đang xét" đi qua từng ô, mỗi ô hiện `true` hoặc `false`. `IndexOf(9)` xét ô 0 (7) và ô 1 (4), rồi khớp ở ô 2 và dừng ngay, không xét ô 4 dù cũng là 9. Kết quả là 2. `IndexOf(5)` phải quét hết 6 ô rồi trả về -1. `Contains(9)` cho `true`. - Mở tab **Find**. `Find(x => x > 8)` thử 7 và 4 (đều `false`), đến 9 thì `true`, trả về chính phần tử 9 và dừng. `Find(x => x > 100)` xét hết 6 ô mà không có ô nào khớp nên trả về `default(int)`, tức là 0 (thẻ cảnh báo vàng). - Mở tab **FindAll**. Điều kiện `x >= 6` xét đủ sáu ô. Mỗi phần tử khớp (7, 9, 6, 9) được thả vào danh sách kết quả `r` (ô mới màu xanh). Kết quả cuối là {7, 9, 6, 9}, còn `scores` vẫn đủ 6 phần tử. - Mở tab **Exists**. Điều kiện `x < 4` lần lượt xét 7, 4, 9, 6, 9 (đều `false`), đến 3 thì `true`. `Exists` trả về `true` sau khi xét 6 ô. ``` <iframe src="https://codegym-vn.github.io/programming-course-demos/c-sharp-ung-dung/cau-truc-du-lieu-nang-cao-collections/thao-tac-nang-cao-voi-list-t/tim-kiem-phan-tu-trong-list-t/" title="Tìm kiếm phần tử trong List<T>" style="border:0;" allowfullscreen></iframe> ``` Điều rút ra: mọi phép tìm trong `List<T>` đều quét tuần tự từ đầu. Mỗi phương thức trả về một thứ khác nhau: vị trí (`IndexOf`), một phần tử (`Find`), một List mới (`FindAll`) hoặc đúng/sai (`Exists`, `Contains`). Chọn phương thức theo điều bạn cần biết. ## Tóm tắt - `IndexOf(x)` trả về chỉ số lần xuất hiện đầu tiên, hoặc -1 nếu không có. `Contains(x)` chỉ cho biết có hay không. - Điều kiện tìm kiếm viết bằng lambda, ví dụ `x => x > 8`. - `Find` trả về phần tử khớp đầu tiên, hoặc `default(T)` (0 với `int`, `null` với đối tượng) nếu không có. - `FindAll` trả về List mới chứa mọi phần tử khớp, danh sách gốc không đổi. - `Exists` chỉ trả về `true` hoặc `false` và dừng ngay khi gặp phần tử khớp.
A6: 5 | B6: 1. Cấu trúc dữ liệu nâng cao: Collections | C6: Thao tác nâng cao với List<T> | D6: Sắp xếp và Đảo ngược List<T> | E6: Bài đọc | F6: Nên làm | G6: Done | H6: Thấy kết quả Sort() với số, chuỗi, đối tượng theo tiêu chí riêng, và Reverse() chỉ lật thứ tự. | I6: 1 cột, 4 tab | J6: Hai hàng ô 'trước' và 'sau', đường nối từ vị trí cũ tới vị trí mới. Tab đối tượng dùng thẻ sản phẩm (tên + giá); hiện vài phép so sánh mẫu với kết quả âm/0/dương. | K6: H01, H17 | L6: Sort số | Sort chuỗi | Sort theo thuộc tính | Reverse | M6: Sort số: {5, 2, 8, 1} → {1, 2, 5, 8}. Nhấn mạnh Sort sửa chính danh sách, không tạo danh sách mới. Sort chuỗi: {"Minh", "An", "Lan", "Bao"} → {"An", "Bao", "Lan", "Minh"}. Sort theo thuộc tính: products.Sort((a, b) => a.Price.CompareTo(b.Price)); hiện 2-3 phép so sánh mẫu (5000 vs 12000 → âm: a đứng trước). Đổi thành b.Price.CompareTo(a.Price) → giảm dần. Reverse: {1, 2, 5, 8} → {8, 5, 2, 1}. Thử Reverse trên {5, 2, 8, 1} → {1, 8, 2, 5} để thấy Reverse không sắp xếp. Bước cuối mỗi tab: hai hàng trước/sau. | N6: Số {5, 2, 8, 1}; tên không dấu; sản phẩm: Bút 5000, Vở 12000, Thước 8000 | O6: Sort() và Reverse() thay đổi trực tiếp danh sách; sắp theo tiêu chí riêng bằng cách truyền hàm so sánh. | P6: Sort chuỗi mặc định theo quy tắc văn hóa (culture) nên ví dụ dùng tên không dấu cho dễ đoán. List.Sort không ổn định (các phần tử bằng nhau có thể đổi thứ tự); cần ổn định thì dùng OrderBy. | Q6: c-sharp-ung-dung/cau-truc-du-lieu-nang-cao-collections/thao-tac-nang-cao-voi-list-t/sap-xep-va-dao-nguoc-list-t/index.html | R6: https://codegym-vn.github.io/programming-course-demos/c-sharp-ung-dung/cau-truc-du-lieu-nang-cao-collections/thao-tac-nang-cao-voi-list-t/sap-xep-va-dao-nguoc-list-t/ | V6: Sắp xếp đơn giản với Sort() Một trong những thao tác phổ biến nhất với danh sách dữ liệu là sắp xếp chúng theo một thứ tự nhất định. C# cung cấp phương thức Sort() cho List<T> để thực hiện việc này một cách dễ dàng. Khi bạn gọi Sort() mà không truyền bất kỳ tham số nào, List<T> sẽ cố gắng sắp xếp các phần tử theo thứ tự tăng dần (mặc định). Điều này hoạt động tốt với các kiểu dữ liệu cơ bản như số nguyên (int), số thực (double), chuỗi (string) vì chúng đã có cơ chế so sánh mặc định. Ví dụ sắp xếp một danh sách số nguyên: using System; using System.Collections.Generic; public class Program { public static void Main(string[] args) { List<int> soNguyen = new List<int> { 5, 2, 8, 1, 9, 3 }; Console.WriteLine("Danh sách gốc: " + string.Join(", ", soNguyen)); soNguyen.Sort(); // Sắp xếp theo thứ tự tăng dần mặc định Console.WriteLine("Danh sách sau khi sắp xếp: " + string.Join(", ", soNguyen)); List<string> tenSinhVien = new List<string> { "An", "Binh", "Huy", "Dat", "Chi" }; Console.WriteLine("Danh sách tên gốc: " + string.Join(", ", tenSinhVien)); tenSinhVien.Sort(); // Sắp xếp theo thứ tự bảng chữ cái mặc định Console.WriteLine("Danh sách tên sau khi sắp xếp: " + string.Join(", ", tenSinhVien)); } } Kết quả: Danh sách gốc: 5, 2, 8, 1, 9, 3 Danh sách sau khi sắp xếp: 1, 2, 3, 5, 8, 9 Danh sách tên gốc: An, Binh, Huy, Dat, Chi Danh sách tên sau khi sắp xếp: An, Binh, Chi, Dat, Huy Đối với các kiểu dữ liệu tùy chỉnh (ví dụ: một class hoặc struct mà bạn tự định nghĩa), để Sort() hoạt động mặc định, kiểu dữ liệu đó cần phải triển khai giao diện IComparable<T>. Nếu không, bạn sẽ nhận được một lỗi khi cố gắng sắp xếp. Sắp xếp các kiểu dữ liệu phức tạp: IComparable<T>, IComparer<T> và Comparer<T> Khi làm việc với các đối tượng phức tạp, bạn thường cần sắp xếp chúng dựa trên một hoặc nhiều thuộc tính cụ thể. C# cung cấp các cơ chế linh hoạt để tùy chỉnh logic sắp xếp: IComparable<T>, IComparer<T> và Comparer<T>. Sắp xếp bằng cách triển khai IComparable<T> Khi một lớp triển khai giao diện IComparable<T>, nó tự định nghĩa cách các thể hiện của chính nó được so sánh với nhau. Điều này hữu ích khi có một cách sắp xếp "tự nhiên" hoặc mặc định cho đối tượng đó. Ví dụ, một lớp SanPham có thể được sắp xếp mặc định theo MaSanPham. using System; using System.Collections.Generic; public class SanPham : IComparable<SanPham> { public int MaSanPham { get; set; } public string TenSanPham { get; set; } public decimal Gia { get; set; } public SanPham(int ma, string ten, decimal gia) { MaSanPham = ma; TenSanPham = ten; Gia = gia; } public int CompareTo(SanPham other) { if (other == null) return 1; // Null is always "less" return this.MaSanPham.CompareTo(other.MaSanPham); // Sắp xếp theo MaSanPham } public override string ToString() { return $"[{MaSanPham}] {TenSanPham} - {Gia:C}"; } } public class Program { public static void Main(string[] args) { List<SanPham> danhSachSanPham = new List<SanPham> { new SanPham(103, "Bánh mì", 15000), new SanPham(101, "Sữa tươi", 25000), new SanPham(102, "Nước ngọt", 12000) }; Console.WriteLine("Danh sách sản phẩm gốc:"); danhSachSanPham.ForEach(Console.WriteLine); danhSachSanPham.Sort(); // Sắp xếp theo MaSanPham (do IComparable<SanPham>) Console.WriteLine("\nDanh sách sản phẩm sau khi sắp xếp theo mã:"); danhSachSanPham.ForEach(Console.WriteLine); } } Sắp xếp với IComparer<T> hoặc Comparer<T> Đôi khi, bạn muốn sắp xếp một đối tượng theo nhiều cách khác nhau hoặc không muốn sửa đổi lớp đối tượng gốc. Trong trường hợp này, bạn có thể tạo một lớp riêng triển khai giao diện IComparer<T>. Comparer<T> là một lớp trừu tượng cung cấp cách tạo các bộ so sánh tùy chỉnh dễ dàng hơn, thường được dùng thông qua Comparer<T>.Default (nếu kiểu T triển khai IComparable<T>) hoặc bằng cách kế thừa và ghi đè phương thức Compare. Ví dụ sắp xếp SanPham theo Gia bằng IComparer<T>: using System; using System.Collections.Generic; // ... (Lớp SanPham như trên, không cần IComparable<T> nếu bạn chỉ dùng IComparer<T>) public class SanPhamTheoGiaComparer : IComparer<SanPham> { public int Compare(SanPham x, SanPham y) { if (x == null && y == null) return 0; if (x == null) return -1; // null is "less" than a valid object if (y == null) return 1; return x.Gia.CompareTo(y.Gia); // Sắp xếp theo Gia tăng dần } } public class Program { public static void Main(string[] args) { List<SanPham> danhSachSanPham = new List<SanPham> { new SanPham(103, "Bánh mì", 15000), new SanPham(101, "Sữa tươi", 25000), new SanPham(102, "Nước ngọt", 12000) }; Console.WriteLine("Danh sách sản phẩm gốc:"); danhSachSanPham.ForEach(Console.WriteLine); // Sắp xếp theo giá sử dụng IComparer<SanPham> danhSachSanPham.Sort(new SanPhamTheoGiaComparer()); Console.WriteLine("\nDanh sách sản phẩm sau khi sắp xếp theo giá:"); danhSachSanPham.ForEach(Console.WriteLine); } } Sắp xếp tùy chỉnh với biểu thức Lambda Để đơn giản hóa việc sắp xếp tùy chỉnh mà không cần tạo một lớp IComparer<T> riêng biệt, bạn có thể sử dụng biểu thức lambda trực tiếp với phương thức Sort() của List<T>. Đây là cách rất phổ biến và linh hoạt trong C#. Phương thức Sort() có một overload chấp nhận một Comparison<T> delegate, và biểu thức lambda là cách tuyệt vời để triển khai delegate này. Ví dụ sắp xếp SanPham theo TenSanPham (tăng dần) và sau đó theo Gia (giảm dần) sử dụng lambda: using System; using System.Collections.Generic; // ... (Lớp SanPham như trên) public class Program { public static void Main(string[] args) { List<SanPham> danhSachSanPham = new List<SanPham> { new SanPham(103, "Bánh mì", 15000), new SanPham(101, "Sữa tươi", 25000), new SanPham(102, "Nước ngọt", 12000), new SanPham(104, "Sữa chua", 20000) }; Console.WriteLine("Danh sách sản phẩm gốc:"); danhSachSanPham.ForEach(Console.WriteLine); // Sắp xếp theo TenSanPham tăng dần danhSachSanPham.Sort((sp1, sp2) => sp1.TenSanPham.CompareTo(sp2.TenSanPham)); Console.WriteLine("\nDanh sách sản phẩm sau khi sắp xếp theo Tên sản phẩm:"); danhSachSanPham.ForEach(Console.WriteLine); // Sắp xếp theo Giá giảm dần danhSachSanPham.Sort((sp1, sp2) => sp2.Gia.CompareTo(sp1.Gia)); // Đảo ngược sp1 và sp2 để sắp xếp giảm dần Console.WriteLine("\nDanh sách sản phẩm sau khi sắp xếp theo Giá giảm dần:"); danhSachSanPham.ForEach(Console.WriteLine); // Sắp xếp theo TenSanPham tăng dần, nếu tên giống nhau thì sắp xếp theo Giá giảm dần danhSachSanPham.Sort((sp1, sp2) => { int result = sp1.TenSanPham.CompareTo(sp2.TenSanPham); if (result == 0) // Nếu tên giống nhau { result = sp2.Gia.CompareTo(sp1.Gia); // Sắp xếp theo giá giảm dần } return result; }); Console.WriteLine("\nDanh sách sản phẩm sau khi sắp xếp theo Tên tăng dần, Giá giảm dần:"); danhSachSanPham.ForEach(Console.WriteLine); } } Biểu thức lambda giúp code gọn gàng và dễ đọc hơn rất nhiều cho các trường hợp sắp xếp tùy chỉnh "một lần dùng". Đảo ngược thứ tự với Reverse() Bên cạnh việc sắp xếp, đôi khi bạn chỉ muốn đảo ngược thứ tự hiện tại của các phần tử trong List<T>. Phương thức Reverse() thực hiện chính xác điều này. Nó thay đổi vị trí của các phần tử trong danh sách, đưa phần tử cuối cùng lên đầu, phần tử đầu tiên xuống cuối, v.v. Ví dụ: using System; using System.Collections.Generic; public class Program { public static void Main(string[] args) { List<string> chuCai = new List<string> { "A", "B", "C", "D", "E" }; Console.WriteLine("Danh sách gốc: " + string.Join(", ", chuCai)); chuCai.Reverse(); // Đảo ngược thứ tự Console.WriteLine("Danh sách sau khi đảo ngược: " + string.Join(", ", chuCai)); List<int> soNguyen = new List<int> { 1, 2, 3, 4, 5 }; Console.WriteLine("Danh sách số nguyên gốc: " + string.Join(", ", soNguyen)); soNguyen.Reverse(); Console.WriteLine("Danh sách số nguyên sau khi đảo ngược: " + string.Join(", ", soNguyen)); } } Kết quả: Danh sách gốc: A, B, C, D, E Danh sách sau khi đảo ngược: E, D, C, B, A Danh sách số nguyên gốc: 1, 2, 3, 4, 5 Danh sách số nguyên sau khi đảo ngược: 5, 4, 3, 2, 1 Phương thức Reverse() cũng có một overload cho phép bạn đảo ngược một phần của danh sách bằng cách chỉ định index bắt đầu và count số phần tử cần đảo ngược. Tổng kết Trong bài học này, chúng ta đã khám phá các phương pháp mạnh mẽ để quản lý thứ tự các phần tử trong List<T>: Sort() mặc định: Để sắp xếp các kiểu dữ liệu cơ bản hoặc các đối tượng triển khai IComparable<T> theo thứ tự tăng dần. IComparer<T> / Comparer<T>: Để định nghĩa logic sắp xếp tùy chỉnh bên ngoài lớp đối tượng, hữu ích khi bạn cần nhiều cách sắp xếp khác nhau hoặc không thể sửa đổi lớp gốc. Biểu thức Lambda: Cung cấp một cách gọn gàng và linh hoạt để định nghĩa logic sắp xếp tùy chỉnh trực tiếp tại chỗ, rất phổ biến cho các trường hợp sắp xếp cụ thể. Reverse(): Đơn giản đảo ngược thứ tự hiện có của các phần tử trong danh sách. Việc nắm vững các kỹ thuật này sẽ giúp bạn thao tác dữ liệu trong List<T> một cách hiệu quả và linh hoạt hơn rất nhiều trong các ứng dụng C#. | W6: # Sắp xếp và Đảo ngược List<T> ## Mục tiêu học tập Sau bài học này, bạn có thể: - Dùng `Sort()` để sắp xếp tăng dần danh sách số hoặc chuỗi. - Giải thích `Sort()` và `Reverse()` đều sửa trực tiếp danh sách gốc. - Chọn giữa ba cách sắp xếp đối tượng: `IComparable<T>`, `IComparer<T>` và lambda. - Viết hàm so sánh bằng lambda để sắp xếp theo một hoặc nhiều thuộc tính, tăng dần hoặc giảm dần. - Phân biệt `Reverse()` (lật thứ tự) với `Sort()` (sắp xếp). - Quan sát từng cặp so sánh và các ô đổi chỗ bằng hoạt động mô phỏng. ## Sort(): sắp xếp tăng dần `Sort()` xếp các phần tử của `List<T>` theo thứ tự tăng dần, **ngay trên danh sách gốc**. Không có danh sách mới nào được tạo, và thứ tự cũ không còn nữa. Nếu muốn giữ bản cũ, hãy chép ra một List khác trước khi sắp xếp. Cách này hoạt động tốt với `int`, `double`, `string`... vì các kiểu này đã có sẵn cách so sánh mặc định. ```csharp using System; using System.Collections.Generic; public class Program { public static void Main() { var a = new List<int> { 5, 2, 8, 1 }; a.Sort(); Console.WriteLine(string.Join(", ", a)); // 1, 2, 5, 8 var names = new List<string> { "Minh", "An", "Lan", "Bao" }; names.Sort(); Console.WriteLine(string.Join(", ", names)); // An, Bao, Lan, Minh } } ``` Với chuỗi, `Sort()` so sánh theo **thứ tự chữ cái**, bắt đầu từ ký tự đầu tiên. Ví dụ trên dùng tên không dấu cho dễ đoán. Chuỗi có dấu tiếng Việt được so sánh theo quy tắc ngôn ngữ (culture) của máy, nên thứ tự có thể khác với bảng chữ cái tiếng Việt. ## Sắp xếp đối tượng tự định nghĩa `Sort()` không tự biết cách so sánh hai đối tượng do bạn viết, ví dụ hai `Product`. Có ba cách để chỉ cho nó. Cả ba đều dựa trên cùng một quy ước: hàm so sánh trả về số **âm** nếu `a` đứng trước `b`, số **dương** nếu `a` phải đứng sau `b` (hai bên đổi chỗ), và **0** nếu coi như bằng nhau. Kiểu số và chuỗi đều có sẵn `CompareTo` để tạo ra kết quả này. Các ví dụ dưới đây dùng chung lớp `Product`: ```csharp public class Product { public string Name { get; set; } public int Price { get; set; } public override string ToString() => $"{Name} {Price}"; } ``` ### Cách 1: IComparable<T> (thứ tự "tự nhiên") Nếu lớp có một cách sắp xếp mặc định, hãy cho lớp cài đặt `IComparable<T>`. Khi đó gọi `Sort()` không tham số là đủ. ```csharp public class Product : IComparable<Product> { public string Name { get; set; } public int Price { get; set; } public int CompareTo(Product other) { if (other == null) return 1; // mọi đối tượng đều "lớn hơn" null return Price.CompareTo(other.Price); } } // products.Sort(); // sắp theo giá tăng dần ``` Nếu lớp không cài đặt `IComparable<T>` mà bạn vẫn gọi `Sort()` không tham số, chương trình sẽ báo lỗi lúc chạy. ### Cách 2: IComparer<T> (bộ so sánh riêng) Khi cần nhiều cách sắp xếp khác nhau, hoặc không sửa được lớp gốc, hãy viết một lớp riêng cài đặt `IComparer<T>` rồi truyền vào `Sort`: ```csharp using System.Collections.Generic; public class ProductByNameComparer : IComparer<Product> { public int Compare(Product x, Product y) { return string.Compare(x.Name, y.Name); } } // products.Sort(new ProductByNameComparer()); ``` ### Cách 3: Lambda (gọn nhất) `Sort` còn nhận một hàm so sánh dạng lambda `(a, b) => ...`. Đây là cách phổ biến nhất cho kiểu sắp xếp "dùng một lần": ```csharp using System; using System.Collections.Generic; public class Program { public static void Main() { var products = new List<Product> { new Product { Name = "Bút", Price = 5000 }, new Product { Name = "Vở", Price = 12000 }, new Product { Name = "Thước", Price = 8000 } }; // Giá tăng dần products.Sort((a, b) => a.Price.CompareTo(b.Price)); Console.WriteLine(string.Join(", ", products)); // Bút 5000, Thước 8000, Vở 12000 // Giá giảm dần: đảo vế a và b products.Sort((a, b) => b.Price.CompareTo(a.Price)); Console.WriteLine(string.Join(", ", products)); // Vở 12000, Thước 8000, Bút 5000 } } ``` Muốn đổi chiều sắp xếp, chỉ cần **đảo vai trò hai vế** `a` và `b`. Nếu muốn sắp theo nhiều tiêu chí (ví dụ tên tăng dần, tên trùng thì giá giảm dần), hãy so sánh tiêu chí đầu trước, chỉ khi bằng nhau (kết quả 0) mới xét tiêu chí sau: ```csharp products.Sort((a, b) => { int result = a.Name.CompareTo(b.Name); if (result == 0) { result = b.Price.CompareTo(a.Price); } return result; }); ``` Nếu không muốn thay đổi danh sách gốc, LINQ có `OrderBy` (cần `using System.Linq;`). Nó trả về một dãy mới đã sắp xếp. ## Reverse(): lật ngược thứ tự `Reverse()` chỉ **đảo vị trí**: phần tử đầu thành cuối và ngược lại. Nó không so sánh giá trị nào, nên không phải là sắp xếp. Giống `Sort()`, nó sửa trực tiếp danh sách gốc. ```csharp var a = new List<int> { 1, 2, 5, 8 }; a.Reverse(); // 8, 5, 2, 1 var b = new List<int> { 5, 2, 8, 1 }; b.Reverse(); // 1, 8, 2, 5 (chỉ là bản lật ngược, chưa được sắp xếp) ``` `Reverse(index, count)` có thể lật ngược chỉ một đoạn của danh sách. Muốn danh sách giảm dần, hãy `Sort()` rồi mới `Reverse()`, hoặc dùng hàm so sánh đảo vế như trên. | Phương thức | Làm gì | Thay đổi danh sách gốc | |---|---|---| | `Sort()` | Sắp xếp tăng dần theo thứ tự mặc định | Có | | `Sort((a, b) => ...)` | Sắp xếp theo tiêu chí tự chọn | Có | | `Reverse()` | Lật ngược thứ tự hiện có | Có | ## Hoạt động: Sắp xếp và lật ngược Mô phỏng dưới đây có bốn tab. Ở mỗi tab, hãy bấm **Bước tiếp** để chạy từng dòng: - Mở tab **Sort số**. Danh sách `a` ban đầu là {5, 2, 8, 1}. Sau `a.Sort()`, hình chia hai hàng "trước" và "sau": các ô mới màu xanh, dưới mỗi ô ghi số đó đến từ ô nào của danh sách cũ. Kết quả {1, 2, 5, 8}, và thứ tự cũ không còn nữa. - Mở tab **Sort chuỗi**. Danh sách `names` là Minh, An, Lan, Bao, và dưới mỗi ô hiện chữ cái đầu. `names.Sort()` xếp thành An, Bao, Lan, Minh theo chữ cái đầu. - Mở tab **Sort theo thuộc tính**. Có ba sản phẩm: Bút 5000, Vở 12000, Thước 8000. Hình dòng chảy cho thấy một cặp so sánh. Bút so với Vở cho kết quả âm nên giữ nguyên. Vở so với Thước cho kết quả dương nên hai ô đổi chỗ. Sau lần Sort đầu: Bút 5000, Thước 8000, Vở 12000. Khi đảo vế thành `b.Price.CompareTo(a.Price)`, kết quả thành giá giảm dần: Vở 12000, Thước 8000, Bút 5000. - Mở tab **Reverse**. Danh sách `a` = {1, 2, 5, 8} sau `Reverse()` thành {8, 5, 2, 1}. Danh sách `b` = {5, 2, 8, 1} sau `Reverse()` chỉ thành {1, 8, 2, 5}, vẫn lộn xộn vì `Reverse` không sắp xếp. ``` <iframe src="https://codegym-vn.github.io/programming-course-demos/c-sharp-ung-dung/cau-truc-du-lieu-nang-cao-collections/thao-tac-nang-cao-voi-list-t/sap-xep-va-dao-nguoc-list-t/" title="Sắp xếp và đảo ngược List<T>" style="border:0;" allowfullscreen></iframe> ``` Điều rút ra: `Sort` và `Reverse` đều thay đổi chính danh sách gốc. `Sort` dựa trên so sánh giá trị (kể cả theo tiêu chí bạn tự đưa vào), còn `Reverse` chỉ lật ngược vị trí và không hề so sánh. ## Tóm tắt - `Sort()` sắp xếp tăng dần ngay trên danh sách gốc, dùng được cho số và chuỗi. - Với đối tượng, có ba cách: cài `IComparable<T>`, viết lớp `IComparer<T>`, hoặc truyền lambda `(a, b) => a.Price.CompareTo(b.Price)`. - Kết quả so sánh âm nghĩa là `a` đứng trước `b`. Đảo vế `a` và `b` để đổi sang giảm dần. - Sắp theo nhiều tiêu chí: xét tiêu chí sau khi tiêu chí trước cho kết quả 0. - `Reverse()` chỉ lật thứ tự hiện có, không sắp xếp. Muốn giữ danh sách cũ, hãy chép ra trước.
A7: 6 | B7: 1. Cấu trúc dữ liệu nâng cao: Collections | C7: Thao tác nâng cao với List<T> | D7: Duyệt và Chuyển đổi List<T> | E7: Bài đọc | F7: Nên làm | G7: Done | H7: Phân biệt for và foreach, hiểu vì sao không được thêm/xóa phần tử trong foreach, và chuyển đổi List sang dạng khác. | I7: 1 cột, 3 tab | J7: Dãy ô với con trỏ duyệt. Tab lỗi có thẻ 'phiên bản danh sách' (version 1 → 2) để giải thích vì sao vòng lặp phát hiện danh sách bị sửa. Tab chuyển đổi hiện danh sách mới xuất hiện bên dưới, danh sách gốc giữ nguyên. | K7: H01, H03 | L7: for và foreach | Xóa trong foreach | Chuyển đổi | M7: for: i chạy 0..Count − 1, prices[i] = prices[i] * 2 sửa trực tiếp từng phần tử. foreach: biến p lần lượt nhận từng giá trị để đọc (tính tổng). Ghi chú: gán p = ... là lỗi biên dịch CS1656. Xóa trong foreach: nums = {1, 2, 3, 4}; khi gặp 2 gọi nums.Remove(2) → phiên bản danh sách đổi → lần lặp kế tiếp ném InvalidOperationException "Collection was modified; enumeration operation may not execute." Cách đúng: nums.RemoveAll(n => n % 2 == 0) → {1, 3}. Chuyển đổi: prices.ConvertAll(p => p * 1.1) tạo List<double> mới; ToArray() tạo mảng; danh sách gốc không đổi. | N7: prices = {100, 200, 300}; nums = {1, 2, 3, 4} | O7: Dùng for khi cần chỉ số hoặc sửa phần tử, foreach để đọc. Không thêm/xóa phần tử trong foreach; dùng RemoveAll hoặc for duyệt ngược. | P7: InvalidOperationException ném ở lần MoveNext sau khi danh sách bị thay đổi. CS1656: không gán được cho biến lặp foreach. | Q7: c-sharp-ung-dung/cau-truc-du-lieu-nang-cao-collections/thao-tac-nang-cao-voi-list-t/duyet-va-chuyen-doi-list-t/index.html | R7: https://codegym-vn.github.io/programming-course-demos/c-sharp-ung-dung/cau-truc-du-lieu-nang-cao-collections/thao-tac-nang-cao-voi-list-t/duyet-va-chuyen-doi-list-t/ | V7: Duyệt và Chuyển đổi List<T> Trong quá trình phát triển ứng dụng C#, List<T> là một trong những cấu trúc dữ liệu linh hoạt và được sử dụng rộng rãi nhất. Tuy nhiên, việc lưu trữ dữ liệu chỉ là bước khởi đầu. Để thực sự làm việc hiệu quả với List<T>, chúng ta cần nắm vững các kỹ thuật duyệt qua các phần tử của nó và biết cách chuyển đổi nó sang các cấu trúc dữ liệu khác khi cần thiết. Bài đọc này sẽ hướng dẫn bạn các phương pháp phổ biến để thực hiện những thao tác này. Duyệt List<T> với Vòng lặp foreach Vòng lặp foreach là cách đơn giản và phổ biến nhất để duyệt qua tất cả các phần tử trong một List<T> hoặc bất kỳ tập hợp nào triển khai giao diện IEnumerable<T>. Nó được thiết kế để đọc từng phần tử một cách tuần tự mà không cần quan tâm đến chỉ mục của chúng. Khi nào nên dùng foreach: Khi bạn chỉ cần đọc hoặc truy cập giá trị của từng phần tử. Khi bạn không cần chỉnh sửa các phần tử bên trong danh sách (trừ khi phần tử đó là kiểu tham chiếu và bạn chỉnh sửa các thuộc tính bên trong nó, nhưng không thể gán lại toàn bộ phần tử). Khi bạn muốn một cú pháp ngắn gọn và dễ đọc. Ví dụ: using System; using System.Collections.Generic; public class Program { public static void Main(string[] args) { List<string> monHoc = new List<string> { "Toán", "Lý", "Hóa", "Sinh" }; Console.WriteLine("Danh sách các môn học:"); foreach (string mon in monHoc) { Console.WriteLine($"- {mon}"); } // Ví dụ truy cập thuộc tính của đối tượng trong List List<SinhVien> danhSachSinhVien = new List<SinhVien> { new SinhVien { MaSV = "SV001", Ten = "Nguyễn Văn A" }, new SinhVien { MaSV = "SV002", Ten = "Trần Thị B" } }; Console.WriteLine("\nThông tin sinh viên:"); foreach (SinhVien sv in danhSachSinhVien) { Console.WriteLine($"Mã SV: {sv.MaSV}, Tên: {sv.Ten}"); // Có thể sửa đổi thuộc tính của đối tượng, ví dụ: // sv.Ten = sv.Ten.ToUpper(); // Chỉ sửa đổi thuộc tính, không gán lại sv } } } public class SinhVien { public string MaSV { get; set; } public string Ten { get; set; } } Duyệt và Chỉnh sửa List<T> với Vòng lặp for (dùng chỉ mục) Vòng lặp for truyền thống cung cấp quyền kiểm soát chi tiết hơn bằng cách sử dụng chỉ mục (index) của các phần tử. Điều này đặc biệt hữu ích khi bạn cần truy cập hoặc chỉnh sửa một phần tử dựa trên vị trí của nó trong danh sách. Khi nào nên dùng for: Khi bạn cần chỉnh sửa giá trị của các phần tử trong danh sách tại một vị trí cụ thể. Khi bạn cần duyệt qua danh sách theo một thứ tự không tuần tự (ví dụ: duyệt ngược, duyệt cách quãng). Khi bạn cần biết vị trí (chỉ mục) của phần tử đang được xử lý. Khi bạn cần xóa phần tử trong quá trình duyệt (lưu ý phải duyệt ngược để tránh lỗi chỉ mục). Ví dụ chỉnh sửa phần tử: using System; using System.Collections.Generic; public class Program { public static void Main(string[] args) { List<int> diemSo = new List<int> { 7, 8, 5, 9, 6 }; Console.WriteLine("Điểm số ban đầu:"); foreach (int diem in diemSo) { Console.Write($"{diem} "); } Console.WriteLine(); // Cộng thêm 1 điểm cho tất cả các điểm số for (int i = 0; i < diemSo.Count; i++) { diemSo[i] += 1; // Chỉnh sửa phần tử tại chỉ mục i } Console.WriteLine("Điểm số sau khi cập nhật:"); for (int i = 0; i < diemSo.Count; i++) { Console.Write($"{diemSo[i]} "); } Console.WriteLine(); // Ví dụ xóa phần tử khi duyệt ngược List<string> sanPham = new List<string> { "Áo", "Quần", "Giày", "Mũ", "Tất" }; Console.WriteLine("\nDanh sách sản phẩm ban đầu:"); foreach (string sp in sanPham) Console.Write($"{sp} "); Console.WriteLine(); // Xóa các sản phẩm có độ dài tên nhỏ hơn 3 ký tự (ví dụ: "Áo", "Mũ") for (int i = sanPham.Count - 1; i >= 0; i--) // Duyệt ngược { if (sanPham[i].Length < 3) { sanPham.RemoveAt(i); } } Console.WriteLine("Danh sách sản phẩm sau khi xóa:"); foreach (string sp in sanPham) Console.Write($"{sp} "); Console.WriteLine(); } } Lưu ý quan trọng: Khi bạn cần xóa phần tử khỏi List<T> trong quá trình duyệt, luôn luôn duyệt từ cuối danh sách về đầu danh sách (sử dụng vòng lặp for với chỉ mục giảm dần). Nếu bạn duyệt từ đầu về cuối và xóa phần tử, các chỉ mục của các phần tử còn lại sẽ thay đổi, dẫn đến việc bỏ sót phần tử hoặc gây ra lỗi IndexOutOfRangeException. Chuyển đổi List<T> sang Mảng (Array) với ToArray() Đôi khi, bạn cần một cấu trúc dữ liệu có kích thước cố định hoặc cần tương tác với các API cũ hơn chỉ chấp nhận mảng. List<T> cung cấp phương thức ToArray() để chuyển đổi nội dung của nó thành một mảng T[] mới. Khi nào nên dùng ToArray(): Khi bạn cần một bản sao dữ liệu có kích thước cố định. Khi bạn muốn truyền dữ liệu tới một phương thức yêu cầu tham số là mảng. Khi bạn muốn "đóng băng" trạng thái hiện tại của danh sách để tránh các thay đổi không mong muốn sau này. Ví dụ: using System; using System.Collections.Generic; public class Program { public static void Main(string[] args) { List<double> nhietDo = new List<double> { 25.5, 26.1, 24.9, 27.0 }; // Chuyển đổi List<double> sang mảng double[] double[] mangNhietDo = nhietDo.ToArray(); Console.WriteLine("Các giá trị nhiệt độ trong mảng:"); foreach (double temp in mangNhietDo) { Console.WriteLine(temp); } // Sau khi chuyển đổi, thay đổi List sẽ không ảnh hưởng đến mảng nhietDo.Add(28.5); Console.WriteLine($"\nSố lượng phần tử trong List: {nhietDo.Count}"); // 5 Console.WriteLine($"Số lượng phần tử trong mảng: {mangNhietDo.Length}"); // 4 } } Chuyển đổi sang List<T> với ToList() Ngược lại với ToArray(), phương thức mở rộng ToList() (thuộc không gian tên System.Linq) cho phép bạn chuyển đổi bất kỳ tập hợp nào triển khai IEnumerable<T> thành một List<T> mới. Điều này rất hữu ích khi bạn nhận được dữ liệu từ một nguồn khác (ví dụ: một mảng, kết quả truy vấn LINQ, hoặc một loại collection khác) và muốn sử dụng sự linh hoạt của List<T>. Khi nào nên dùng ToList(): Khi bạn cần chuyển đổi một tập hợp có kích thước cố định (như mảng) sang một tập hợp có kích thước động để dễ dàng thêm/bớt phần tử. Khi bạn muốn tạo một bản sao độc lập của một tập hợp hiện có. Khi bạn muốn sử dụng các phương thức tiện ích của List<T> sau khi thực hiện một truy vấn LINQ. Ví dụ: using System; using System.Collections.Generic; using System.Linq; // Cần include namespace này để sử dụng ToList() public class Program { public static void Main(string[] args) { // Chuyển đổi từ một mảng sang List<string> string[] tenThanhPho = { "Hà Nội", "Đà Nẵng", "TP.HCM" }; List<string> danhSachThanhPho = tenThanhPho.ToList(); Console.WriteLine("Danh sách thành phố:"); danhSachThanhPho.Add("Cần Thơ"); // Có thể thêm phần tử sau khi chuyển đổi foreach (string tp in danhSachThanhPho) { Console.WriteLine($"- {tp}"); } // Chuyển đổi từ một tập hợp khác (ví dụ: kết quả truy vấn LINQ) sang List<int> IEnumerable<int> soNguyenChan = Enumerable.Range(1, 10).Where(n => n % 2 == 0); List<int> danhSachSoChan = soNguyenChan.ToList(); Console.WriteLine("\nDanh sách số chẵn từ 1 đến 10:"); foreach (int so in danhSachSoChan) { Console.Write($"{so} "); } Console.WriteLine(); } } Tổng kết và Lựa chọn Phương pháp Việc lựa chọn phương pháp duyệt và chuyển đổi List<T> phụ thuộc vào nhu cầu cụ thể của bạn: Sử dụng foreach khi bạn chỉ cần đọc dữ liệu, không quan tâm đến chỉ mục và muốn một cú pháp đơn giản, an toàn. Sử dụng for khi bạn cần truy cập hoặc chỉnh sửa phần tử dựa trên chỉ mục của nó, hoặc khi bạn cần xóa phần tử trong quá trình duyệt (hãy nhớ duyệt ngược!). Sử dụng ToArray() khi bạn cần một mảng có kích thước cố định, cần truyền dữ liệu tới API yêu cầu mảng, hoặc muốn tạo một bản sao "đóng băng" của danh sách. Sử dụng ToList() khi bạn cần chuyển đổi một tập hợp bất kỳ (mảng, kết quả LINQ, v.v.) sang một List<T> để tận dụng sự linh hoạt và các phương thức tiện ích của nó. Nắm vững các kỹ thuật này sẽ giúp bạn quản lý và thao tác dữ liệu trong List<T> một cách hiệu quả và linh hoạt hơn trong các ứng dụng C#. | W7: # Duyệt và Chuyển đổi List<T> ## Mục tiêu học tập Sau bài học này, bạn có thể: - Duyệt `List<T>` bằng `for` và `foreach`, và biết khi nào dùng cái nào. - Giải thích vì sao không gán được biến lặp của `foreach`. - Nhận ra vì sao thêm hoặc xóa phần tử trong `foreach` gây `InvalidOperationException`, và dùng `RemoveAll` hoặc `for` duyệt ngược thay thế. - Chuyển List sang dạng khác bằng `ConvertAll`, `ToArray`, `ToList` mà không đụng tới danh sách gốc. - Quan sát con trỏ duyệt đi qua danh sách bằng hoạt động mô phỏng. ## Duyệt bằng foreach `foreach` là cách đơn giản và phổ biến nhất để đi qua mọi phần tử. Nó lấy lần lượt từng phần tử vào một biến lặp, không cần chỉ số. Dùng khi: - Bạn chỉ cần **đọc** từng phần tử. - Bạn muốn cú pháp ngắn gọn, dễ đọc. Biến lặp là **chỉ đọc**: bạn không thể gán lại nó (lỗi biên dịch CS1656). Tuy nhiên, nếu phần tử là đối tượng (kiểu tham chiếu), bạn vẫn sửa được **thuộc tính bên trong** đối tượng đó, chỉ không gán lại cả biến lặp. ```csharp using System; using System.Collections.Generic; public class Student { public string Id { get; set; } public string Name { get; set; } } public class Program { public static void Main() { var list = new List<Student> { new Student { Id = "SV01", Name = "An" }, new Student { Id = "SV02", Name = "Bình" } }; foreach (Student s in list) { s.Name = s.Name.ToUpper(); // được: sửa thuộc tính // s = null; // lỗi biên dịch CS1656: không gán lại biến lặp Console.WriteLine($"{s.Id}: {s.Name}"); } // SV01: AN // SV02: BÌNH } } ``` ## Duyệt bằng for `for` dùng chỉ số `i` chạy từ 0 đến `Count - 1`. Vì có chỉ số, bạn vừa đọc được vừa **sửa được** phần tử. Dùng khi: - Cần sửa giá trị phần tử tại một vị trí. - Cần biết vị trí của phần tử đang xử lý. - Cần duyệt ngược hoặc cách quãng. ```csharp var prices = new List<int> { 100, 200, 300 }; for (int i = 0; i < prices.Count; i++) { prices[i] = prices[i] * 2; } // prices: 200, 400, 600 int sum = 0; foreach (int p in prices) { sum += p; } Console.WriteLine(sum); // 1200 ``` | | `for` | `foreach` | |---|---|---| | Có chỉ số `i` | Có | Không | | Sửa phần tử số, chuỗi | Được (`list[i] = ...`) | Không (biến lặp chỉ đọc) | | Phù hợp khi | Cần chỉ số hoặc sửa phần tử | Chỉ đọc từng phần tử | ## Xóa phần tử khi đang duyệt ### Không xóa trong foreach Mỗi `List<T>` ghi nhớ một "phiên bản" (version), tăng lên mỗi khi danh sách bị thêm hoặc xóa. Vòng `foreach` nhớ phiên bản lúc bắt đầu. Nếu giữa chừng danh sách bị sửa cấu trúc, ở lần lặp kế tiếp `foreach` thấy phiên bản khác nhau và ném lỗi: ```csharp var nums = new List<int> { 1, 2, 3, 4 }; foreach (int n in nums) { if (n == 2) { nums.Remove(2); // sửa danh sách khi đang duyệt } } // Lỗi: System.InvalidOperationException // Collection was modified; enumeration operation may not execute. ``` ### Cách đúng 1: RemoveAll Muốn xóa theo điều kiện, hãy để List tự lo: ```csharp var nums = new List<int> { 1, 2, 3, 4 }; nums.RemoveAll(n => n % 2 == 0); // xóa mọi số chẵn // nums: 1, 3 ``` ### Cách đúng 2: for duyệt ngược Nếu cần xóa bằng `for`, hãy duyệt từ **cuối về đầu**. Xóa một ô làm các ô phía sau dịch trái, nhưng với duyệt ngược, các ô còn phải xét đều nằm phía trước nên chỉ số của chúng không bị lệch. Nếu duyệt xuôi rồi xóa, chỉ số bị lệch, dễ bỏ sót phần tử hoặc truy cập sai vị trí. ```csharp var products = new List<string> { "Áo", "Quần", "Giày", "Mũ", "Tất" }; for (int i = products.Count - 1; i >= 0; i--) { if (products[i].Length < 3) { products.RemoveAt(i); // xóa "Mũ", "Áo" } } Console.WriteLine(string.Join(", ", products)); // Quần, Giày, Tất ``` ## Chuyển đổi List Bạn có thể tạo bản mới ở dạng khác, danh sách gốc giữ nguyên: - **`ConvertAll`**: biến mỗi phần tử thành một giá trị khác, trả về `List` mới (có thể khác kiểu). - **`ToArray`**: chép các phần tử sang một mảng mới. Hữu ích khi một API chỉ nhận mảng, hoặc khi bạn muốn "chụp lại" trạng thái hiện tại của danh sách. - **`ToList`** (cần `using System.Linq;`): làm điều ngược lại, biến mảng hoặc kết quả LINQ thành `List<T>` mới để có thể thêm bớt phần tử. ```csharp using System.Linq; var prices = new List<int> { 100, 200, 300 }; List<double> big = prices.ConvertAll(p => p * 1.5); // 150, 300, 450 int[] arr = prices.ToArray(); // 100, 200, 300 prices.Add(400); Console.WriteLine(arr.Length); // 3 (mảng là bản chép riêng) string[] cities = { "Hà Nội", "Đà Nẵng" }; List<string> cityList = cities.ToList(); cityList.Add("Cần Thơ"); // thêm được, vì giờ là List ``` ## Hoạt động: Con trỏ duyệt đi qua danh sách Mô phỏng dưới đây có ba tab. Hãy thao tác theo thứ tự sau, bấm **Bước tiếp** để chạy từng dòng: - Mở tab **for và foreach**. Danh sách `prices` là 100, 200, 300. Vòng `for` có con trỏ `i` đi qua từng ô, nhân đôi ngay tại ô đó: 200, 400, 600. Tiếp theo vòng `foreach` có con trỏ `p` đi qua từng ô, và ô `sum` tăng dần 200, 600, 1200. Dòng cuối nhắc rằng `p = 5` bị lỗi biên dịch CS1656. - Mở tab **Xóa trong foreach**. Danh sách `nums` là 1, 2, 3, 4 và ô "phiên bản danh sách" là 1. Khi `n = 2`, lệnh `nums.Remove(2)` làm danh sách còn 1, 3, 4 và phiên bản thành 2 (ô báo đỏ). Ở lần lặp kế tiếp, thẻ lỗi đỏ **InvalidOperationException** xuất hiện vì phiên bản 1 khác 2. Bước cuối cho thấy cách đúng: `RemoveAll(n => n % 2 == 0)` trên danh sách mới {1, 2, 3, 4}, hai số chẵn bị đánh dấu xóa, còn lại 1 và 3. - Mở tab **Chuyển đổi**. `prices` là List<int> gồm 100, 200, 300. `ConvertAll(p => p * 1.5)` tạo List<double> mới 150.0, 300.0, 450.0 (ô mới màu xanh) và danh sách gốc mờ đi vì nằm yên. `ToArray()` tạo mảng `int[]` mới. Cuối cùng có ba nơi riêng biệt: `prices`, `big` và `arr`. ``` <iframe src="https://codegym-vn.github.io/programming-course-demos/c-sharp-ung-dung/cau-truc-du-lieu-nang-cao-collections/thao-tac-nang-cao-voi-list-t/duyet-va-chuyen-doi-list-t/" title="Duyệt và chuyển đổi List<T>" style="border:0;" allowfullscreen></iframe> ``` Điều rút ra: dùng `for` khi cần chỉ số hoặc sửa phần tử, dùng `foreach` để đọc. Không thêm hoặc xóa phần tử trong lúc `foreach` đang chạy, hãy dùng `RemoveAll` hoặc `for` duyệt ngược. `ConvertAll` và `ToArray` tạo bản mới, không đụng tới danh sách gốc. ## Tóm tắt - `for` có chỉ số và sửa được phần tử. `foreach` gọn hơn nhưng chỉ để đọc. - Biến lặp của `foreach` không gán được (lỗi biên dịch CS1656), nhưng vẫn sửa được thuộc tính của đối tượng bên trong. - Thêm hoặc xóa phần tử trong `foreach` gây `InvalidOperationException`. - Xóa theo điều kiện bằng `RemoveAll`, hoặc dùng `for` duyệt ngược từ cuối về đầu. - `ConvertAll`, `ToArray` và `ToList` tạo List hoặc mảng mới, danh sách gốc giữ nguyên.
A8: 7 | B8: 1. Cấu trúc dữ liệu nâng cao: Collections | C8: Giới thiệu về Dictionary<K,V> | D8: Giới thiệu Dictionary<K,V> và tầm quan trọng của Key-Value Pair | E8: Bài đọc | F8: Nên làm | G8: Done | H8: Hình dung Dictionary như tủ có ngăn dán nhãn: tra theo khóa đi thẳng tới giá trị, không phải quét từng phần tử. | I8: 2 cột song song: List<Student> | Dictionary<string, string> | J8: Trái: dãy thẻ sinh viên, kính lúp quét từng thẻ. Phải: tủ 6 ngăn, nhãn là mã SV; mũi tên đi thẳng tới ngăn cần tìm. Dưới mỗi cột là bảng đếm số lần so sánh. | K8: H01, H02, H22 | L8: Tìm SV05 | Tìm SV09 (không có) | M8: Cả hai chứa 6 sinh viên SV01..SV06. Trái: Find(s => s.Id == "SV05") xét SV01, SV02... mỗi bước tăng bộ đếm. Phải: dict["SV05"] → tính vị trí từ khóa và đi thẳng tới ngăn SV05 (1 lần tra). Kết quả: trái 5 lần so sánh, phải 1 lần tra. Tab SV09: trái quét hết 6 thẻ rồi trả null; phải TryGetValue trả false ngay. | N8: SV01 An, SV02 Bình, SV03 Chi, SV04 Dũng, SV05 Hà, SV06 Khoa | O8: Mỗi khóa là duy nhất và dẫn thẳng tới một giá trị. Tra theo khóa là thế mạnh của Dictionary. | P8: Tra theo khóa trung bình O(1) nhờ bảng băm; mô phỏng chỉ minh họa ý 'đi thẳng tới ngăn', không vẽ chi tiết bảng băm. | Q8: c-sharp-ung-dung/cau-truc-du-lieu-nang-cao-collections/gioi-thieu-ve-dictionary-k-v/gioi-thieu-dictionary-k-v-va-tam-quan-trong-cua-key-value-pair/index.html | R8: https://codegym-vn.github.io/programming-course-demos/c-sharp-ung-dung/cau-truc-du-lieu-nang-cao-collections/gioi-thieu-ve-dictionary-k-v/gioi-thieu-dictionary-k-v-va-tam-quan-trong-cua-key-value-pair/ | V8: Giới thiệu Dictionary<K,V> Trong thế giới lập trình, việc tổ chức và quản lý dữ liệu hiệu quả là chìa khóa để xây dựng các ứng dụng mạnh mẽ và có hiệu suất cao. Bạn đã làm quen với List<T> - một cấu trúc dữ liệu tuyệt vời cho việc lưu trữ các tập hợp có thứ tự. Tuy nhiên, khi nhu cầu của bạn là tìm kiếm hoặc truy cập dữ liệu dựa trên một định danh (identifier) cụ thể thay vì vị trí theo chỉ mục, List<T> có thể không phải là lựa chọn tối ưu nhất. Đây chính là lúc Dictionary<K,V> phát huy sức mạnh của mình. Dictionary<K,V> là một cấu trúc dữ liệu thuộc họ các collection trong C#, được thiết kế để lưu trữ dữ liệu dưới dạng các cặp khóa-giá trị (Key-Value Pair). Chữ K đại diện cho kiểu dữ liệu của khóa (Key), và V đại diện cho kiểu dữ liệu của giá trị (Value). Hãy tưởng tượng một cuốn từ điển: bạn không tìm một từ dựa trên việc nó nằm ở trang thứ bao nhiêu, mà bạn tìm nó dựa trên chính bản thân từ đó (khóa), và kết quả trả về là định nghĩa của từ đó (giá trị). Dictionary<K,V> hoạt động theo nguyên tắc tương tự, cho phép bạn truy cập giá trị cực kỳ nhanh chóng thông qua khóa tương ứng của nó. Khái niệm Key-Value Pair: Nền tảng của Dictionary Điểm cốt lõi làm nên Dictionary<K,V> chính là khái niệm Key-Value Pair. Mỗi phần tử trong Dictionary là một cặp dữ liệu, bao gồm: Key (Khóa): Là một giá trị duy nhất dùng để định danh và truy cập đến một phần tử. Trong một Dictionary, mỗi khóa phải là duy nhất (unique). Bạn không thể có hai phần tử với cùng một khóa. Khóa có thể là bất kỳ kiểu dữ liệu nào (chuỗi, số nguyên, đối tượng tùy chỉnh...), miễn là nó có thể được sử dụng để băm (hashing). Value (Giá trị): Là dữ liệu thực tế mà bạn muốn lưu trữ. Giá trị được liên kết với một khóa cụ thể. Không giống như khóa, các giá trị có thể trùng lặp. Ví dụ, nếu bạn muốn lưu trữ thông tin về mã sản phẩm và tên sản phẩm tương ứng, mã sản phẩm (ví dụ: "SP001") sẽ là khóa, và tên sản phẩm ("Bàn phím cơ") sẽ là giá trị. // Một Key-Value Pair ví dụ // Key: "SP001" (kiểu string) // Value: "Bàn phím cơ" (kiểu string) Sự kết hợp giữa khóa và giá trị tạo ra một mối quan hệ một-một: mỗi khóa duy nhất sẽ trỏ tới một giá trị duy nhất. Nguyên tắc hoạt động và tốc độ truy cập Dictionary<K,V> được triển khai dựa trên cấu trúc dữ liệu Hash Table (Bảng băm). Khi bạn thêm một cặp khóa-giá trị vào Dictionary: Hệ thống sẽ tính toán một giá trị băm (hash code) từ khóa. Giá trị băm này được sử dụng để xác định vị trí lưu trữ của cặp khóa-giá trị trong bộ nhớ. Nhờ cơ chế băm này, việc tìm kiếm, thêm hoặc xóa một phần tử trong Dictionary có thể được thực hiện với độ phức tạp thời gian trung bình là O(1) (hằng số). Điều này có nghĩa là, dù Dictionary của bạn có 10 phần tử hay 1 triệu phần tử, thời gian để tìm một phần tử theo khóa vẫn gần như không đổi. Đây là một ưu điểm vượt trội so với List<T> khi bạn cần truy cập dữ liệu nhanh chóng. Trong List<T>, để tìm một phần tử theo giá trị, bạn thường phải duyệt qua từng phần tử một (phép tìm kiếm tuần tự), dẫn đến độ phức tạp thời gian trung bình là O(N), với N là số lượng phần tử. Dictionary<K,V> và List<T>: Khi nào sử dụng loại nào? Để hiểu rõ hơn khi nào nên sử dụng Dictionary<K,V>, hãy cùng so sánh nó với List<T>: List<T> Cấu trúc: Một danh sách các phần tử có thứ tự, được truy cập thông qua chỉ mục số nguyên (0, 1, 2...). Truy cập: Nhanh chóng khi truy cập theo chỉ mục (list[index]) với độ phức tạp O(1). Tìm kiếm: Chậm khi tìm kiếm một phần tử theo giá trị của nó (cần duyệt qua danh sách), độ phức tạp O(N). Khi sử dụng: Khi thứ tự của các phần tử là quan trọng. Khi bạn cần truy cập các phần tử dựa trên vị trí của chúng. Khi bạn thường xuyên thêm/xóa phần tử ở cuối danh sách. Khi bạn cần lưu trữ một tập hợp các giá trị không có định danh duy nhất rõ ràng. Dictionary<K,V> Cấu trúc: Một tập hợp các cặp khóa-giá trị, không có thứ tự cố định. Truy cập: Cực kỳ nhanh chóng khi truy cập theo khóa (dictionary[key]) với độ phức tạp trung bình O(1). Tìm kiếm: Nhanh chóng khi kiểm tra sự tồn tại của một khóa hoặc truy xuất giá trị tương ứng. Khi sử dụng: Khi bạn cần lưu trữ dữ liệu mà mỗi phần tử có một định danh duy nhất (khóa). Khi bạn cần truy cập dữ liệu cực kỳ nhanh chóng dựa trên định danh đó. Khi bạn muốn ánh xạ (map) một giá trị này sang một giá trị khác (ví dụ: mã quốc gia sang tên quốc gia). Khi thứ tự của các phần tử không quan trọng. Tóm lại, nếu bạn có một định danh duy nhất cho mỗi mảnh dữ liệu và cần truy xuất nó một cách hiệu quả, Dictionary<K,V> là lựa chọn lý tưởng. Nếu bạn chỉ cần một danh sách các mục có thứ tự và thường xuyên truy cập theo vị trí, List<T> sẽ phù hợp hơn. Các trường hợp sử dụng lý tưởng cho Dictionary<K,V> Nhờ vào khả năng truy cập nhanh chóng bằng khóa, Dictionary<K,V> được ứng dụng rộng rãi trong nhiều tình huống thực tế: Lưu trữ cấu hình ứng dụng: Ví dụ, bạn có thể lưu trữ các cài đặt như {"DatabaseConnection": "...", "LogLevel": "Debug"}. Quản lý thông tin người dùng: Sử dụng ID người dùng làm khóa và đối tượng User làm giá trị. // Dictionary<int, User> usersById; // usersById.Add(101, new User { Id = 101, Name = "Alice" }); // User alice = usersById[101]; // Truy cập nhanh chóng Hệ thống tra cứu (Look-up tables): Ví dụ, ánh xạ mã sản phẩm sang giá tiền, mã quốc gia sang tên quốc gia đầy đủ. // Dictionary<string, decimal> productPrices; // productPrices.Add("IPHONE15", 999.99M); // decimal price = productPrices["IPHONE15"]; Bộ nhớ đệm (Caching): Lưu trữ tạm thời các kết quả tính toán hoặc truy vấn cơ sở dữ liệu để tăng tốc độ phản hồi cho các yêu cầu lặp lại. Đếm tần suất: Đếm số lần xuất hiện của các từ trong một đoạn văn bản, sử dụng từ làm khóa và số lần xuất hiện làm giá trị. Trong các bài học tiếp theo, bạn sẽ tìm hiểu chi tiết về cách khởi tạo, thêm, truy cập, cập nhật và xóa các phần tử trong Dictionary<K,V>, cùng với các phương thức hữu ích khác để làm việc với cấu trúc dữ liệu mạnh mẽ này. | W8: # Giới thiệu Dictionary<K,V> và tầm quan trọng của Key-Value Pair ## Mục tiêu học tập Sau bài học này, bạn có thể: - Giải thích **cặp khóa - giá trị** (key-value pair) và vì sao khóa phải duy nhất. - Khai báo và khởi tạo `Dictionary<TKey, TValue>` trong C#. - So sánh tra cứu bằng `List<T>` (quét từng phần tử) với tra cứu bằng `Dictionary` (đi thẳng theo khóa). - Chọn `List<T>` hay `Dictionary` tùy bài toán, và kể được vài tình huống dùng Dictionary. - Dùng `TryGetValue` để tra một khóa có thể không tồn tại mà không gặp lỗi. - Quan sát số lần so sánh của List và Dictionary khi tìm cùng một sinh viên bằng hoạt động mô phỏng. ## Bài toán: tìm theo mã Giả sử bạn có danh sách sinh viên, mỗi người có một mã (`SV01`, `SV02`...) và một tên. Bạn cần tìm tên của sinh viên có mã `SV05`. Nếu lưu trong `List<Student>`, bạn phải xét **từng thẻ từ đầu** cho tới khi gặp mã khớp. Danh sách càng dài, số lần so sánh càng nhiều. Khi nhu cầu là tìm theo một **định danh** (identifier) thay vì theo vị trí, `List<T>` không phải lựa chọn tối ưu. Đây là lúc `Dictionary` phát huy sức mạnh. ## Dictionary<TKey, TValue> là gì? `Dictionary<TKey, TValue>` (từ điển) lưu dữ liệu dưới dạng các **cặp khóa - giá trị**. Hãy nghĩ đến một cuốn từ điển: bạn không tìm từ theo số trang, mà theo chính từ đó (khóa), và nhận về định nghĩa (giá trị). - **Khóa** (key, kiểu `TKey`): nhãn dùng để tra cứu, ví dụ mã sinh viên `"SV05"`. Khóa phải **duy nhất**. Khóa có thể là chuỗi, số nguyên hoặc kiểu khác, miễn là tính được mã băm (hash code) của nó. - **Giá trị** (value, kiểu `TValue`): dữ liệu đi kèm khóa, ví dụ tên `"Hà"`. Giá trị có thể trùng nhau. Hãy hình dung một **tủ nhiều ngăn kéo**: mỗi ngăn dán một nhãn (khóa) và chứa một thứ bên trong (giá trị). Muốn lấy đồ, bạn nhìn nhãn rồi mở thẳng ngăn đó, không cần mở từng ngăn. Mỗi khóa trỏ tới đúng một giá trị. Dictionary nằm trong `System.Collections.Generic`. ```csharp using System; using System.Collections.Generic; public class Program { public static void Main() { var dict = new Dictionary<string, string> { ["SV01"] = "An", ["SV02"] = "Bình", ["SV05"] = "Hà" }; string name = dict["SV05"]; Console.WriteLine(name); // Hà } } ``` ## Vì sao tra theo khóa nhanh? Dictionary được xây dựng trên **bảng băm** (hash table). Khi bạn thêm một cặp: 1. Hệ thống tính một **mã băm** từ khóa. 2. Mã băm đó cho biết cặp được đặt ở ngăn nào. Nhờ vậy, khi tra cứu, .NET tính lại mã băm và đi thẳng tới ngăn cần tìm. Thời gian tra trung bình gần như **không đổi** (ký hiệu O(1)), dù có 10 hay 1 triệu phần tử. Ngược lại, `List` tìm theo giá trị phải quét tuần tự, thời gian tăng theo số phần tử N (ký hiệu O(N)). ## List hay Dictionary? | | `List<T>` | `Dictionary<TKey, TValue>` | |---|---|---| | Cấu trúc | Dãy phần tử có thứ tự, truy cập theo chỉ số 0, 1, 2... | Các cặp khóa - giá trị, không đảm bảo thứ tự | | Cách tìm theo giá trị hoặc khóa | Quét từng phần tử từ đầu | Đi thẳng tới ngăn theo khóa | | Phù hợp khi | Thứ tự quan trọng, truy cập theo vị trí, thêm xóa ở cuối | Mỗi phần tử có định danh duy nhất, cần tra nhanh, cần ánh xạ giá trị này sang giá trị khác | Một vài tình huống thường dùng `Dictionary`: - **Bảng tra cứu**: mã sản phẩm sang giá, mã quốc gia sang tên quốc gia. - **Quản lý người dùng**: ID người dùng làm khóa, đối tượng người dùng làm giá trị. - **Đếm tần suất**: mỗi từ là một khóa, số lần xuất hiện là giá trị. - **Lưu cấu hình** và **bộ nhớ đệm** (cache) các kết quả đã tính. ## Tra khóa có thể không tồn tại Đọc bằng `dict["SV09"]` khi khóa không có sẽ ném `KeyNotFoundException`. Cách an toàn là `TryGetValue`: trả về `bool` cho biết có tìm thấy không, và đưa giá trị ra qua tham số `out`. ```csharp string name; bool ok = dict.TryGetValue("SV09", out name); // ok là false, name là null (giá trị mặc định của string), không có lỗi ``` Bài sau sẽ nói kỹ hơn về thêm, đọc và cập nhật phần tử trong Dictionary. ## Hoạt động: Quét từng thẻ hay đi thẳng tới ngăn Mô phỏng dưới đây có hai cột cùng chứa sinh viên SV01 đến SV06 (An, Bình, Chi, Dũng, Hà, Khoa). Hãy thao tác theo thứ tự sau, bấm **Bước tiếp** để chạy từng dòng: - Mở tab **Tìm SV05**. **Cột trái** là `List<Student>` gồm 6 thẻ, dùng `Find`. Con trỏ "xét" đi qua SV01, SV02, SV03, SV04, mỗi lần báo "khác" và bộ đếm "số lần so sánh" tăng. Đến SV05 thì khớp, tìm thấy Hà sau **5 lần so sánh**. **Cột phải** là `Dictionary<string, string>` dạng tủ 6 ngăn. Dòng `dict["SV05"]` đi thẳng tới ngăn SV05 (sáng lên, các ngăn khác mờ đi), lấy được Hà sau **1 lần tra**. - Mở tab **Tìm SV09 (không có)**. Cột trái phải xét cả 6 thẻ, bộ đếm lên 6 (báo đỏ), rồi `Find` trả về `null` (thẻ cảnh báo vàng). Cột phải dùng `TryGetValue`: chỉ **1 lần tra**, thấy không có ngăn nào mang nhãn SV09, trả về `false` và `name` là `null`, không có lỗi. ``` <iframe src="https://codegym-vn.github.io/programming-course-demos/c-sharp-ung-dung/cau-truc-du-lieu-nang-cao-collections/gioi-thieu-ve-dictionary-k-v/gioi-thieu-dictionary-k-v-va-tam-quan-trong-cua-key-value-pair/" title="Dictionary và cặp Key-Value" style="border:0;" allowfullscreen></iframe> ``` Điều rút ra: mỗi khóa là duy nhất và dẫn thẳng tới một giá trị, nên tra theo khóa chỉ cần một lần. List phải quét từng thẻ, và danh sách càng dài thì khoảng cách giữa hai cách càng lớn. Với khóa có thể không tồn tại, `TryGetValue` cho biết ngay mà không gây lỗi. ## Tóm tắt - `Dictionary<TKey, TValue>` lưu các cặp **khóa - giá trị**. Khóa là nhãn tra cứu, giá trị là dữ liệu đi kèm. - Mỗi khóa chỉ xuất hiện một lần. Giá trị có thể trùng. - Dictionary dùng bảng băm nên tra theo khóa nhanh (trung bình O(1)), còn `List` phải quét từng phần tử (O(N)). - Dùng `Dictionary` khi có định danh duy nhất và cần tra nhanh. Dùng `List` khi thứ tự và vị trí quan trọng. - Đọc khóa không có bằng `[ ]` ném `KeyNotFoundException`. Dùng `TryGetValue` để tra an toàn.
A9: 8 | B9: 1. Cấu trúc dữ liệu nâng cao: Collections | C9: Giới thiệu về Dictionary<K,V> | D9: Thêm, Truy cập và Cập nhật phần tử trong Dictionary<K,V> | E9: Bài đọc | F9: Nên làm | G9: Done | H9: Phân biệt Add và gán bằng chỉ mục [key], và nhận ra hai lỗi hay gặp nhất. | I9: 1 cột, 4 tab | J9: Tủ ngăn kéo: ngăn mới trượt vào (xanh), ngăn cập nhật nháy vàng, thẻ lỗi đỏ khi Add trùng khóa hoặc đọc khóa không có. | K9: H02, H03 | L9: Add | Gán bằng [ ] | Add trùng khóa | Đọc khóa không có | M9: Add: stock.Add("thước", 3) → thêm ngăn mới, Count 3. Gán: stock["vở"] = 8 → cập nhật ngăn có sẵn; stock["tẩy"] = 2 → khóa chưa có nên thêm mới. Add trùng: stock.Add("bút", 7) → ArgumentException "An item with the same key has already been added. Key: bút". Đọc khóa không có: int n = stock["kéo"] → KeyNotFoundException "The given key 'kéo' was not present in the dictionary." Cách an toàn: stock.TryGetValue("kéo", out n) → false, n = 0, không lỗi. | N9: stock: bút = 10, vở = 5 | O9: Add chỉ để thêm (trùng khóa là lỗi); [key] = value vừa thêm vừa cập nhật; đọc an toàn bằng TryGetValue. | P9: Thông điệp lỗi theo .NET hiện đại (.NET Core/.NET 5+). | Q9: c-sharp-ung-dung/cau-truc-du-lieu-nang-cao-collections/gioi-thieu-ve-dictionary-k-v/them-truy-cap-va-cap-nhat-phan-tu-trong-dictionary-k-v/index.html | R9: https://codegym-vn.github.io/programming-course-demos/c-sharp-ung-dung/cau-truc-du-lieu-nang-cao-collections/gioi-thieu-ve-dictionary-k-v/them-truy-cap-va-cap-nhat-phan-tu-trong-dictionary-k-v/ | V9: Để tận dụng tối đa sức mạnh của Dictionary<K,V>, bạn cần nắm vững các thao tác cơ bản để thêm, truy cập và cập nhật các cặp khóa-giá trị. Trang này sẽ hướng dẫn bạn chi tiết về các phương thức và cú pháp phổ biến nhất cho những tác vụ này. Thêm cặp khóa-giá trị mới bằng phương thức Add() Phương thức Add() là cách trực tiếp nhất để thêm một cặp khóa-giá trị vào Dictionary<K,V>. Bạn cung cấp khóa và giá trị tương ứng làm đối số cho phương thức này. Cú pháp cơ bản: myDictionary.Add(key, value); Lưu ý quan trọng: Mỗi khóa trong Dictionary phải là duy nhất. Nếu bạn cố gắng thêm một cặp khóa-giá trị với một khóa đã tồn tại, phương thức Add() sẽ ném ra một ngoại lệ ArgumentException. Ví dụ: Giả sử chúng ta có một Dictionary lưu trữ tên các quốc gia và thủ đô của chúng. using System; using System.Collections.Generic; public class Program { public static void Main(string[] args) { // Khởi tạo một Dictionary với khóa là string (tên quốc gia) // và giá trị là string (tên thủ đô) Dictionary<string, string> capitals = new Dictionary<string, string>(); // Thêm các cặp khóa-giá trị mới capitals.Add("Vietnam", "Hanoi"); capitals.Add("USA", "Washington D.C."); capitals.Add("France", "Paris"); Console.WriteLine("Các thủ đô đã được thêm:"); foreach (var entry in capitals) { Console.WriteLine($"- {entry.Key}: {entry.Value}"); } // Thử thêm một khóa đã tồn tại (sẽ gây lỗi) try { capitals.Add("Vietnam", "Ho Chi Minh City"); // Lỗi: Khóa 'Vietnam' đã tồn tại } catch (ArgumentException ex) { Console.WriteLine($"\nLỗi khi thêm: {ex.Message}"); } } } Kết quả: Các thủ đô đã được thêm: - Vietnam: Hanoi - USA: Washington D.C. - France: Paris Lỗi khi thêm: An item with the same key has already been added. Key: Vietnam Truy cập giá trị bằng khóa (Indexer) Cách phổ biến và trực quan nhất để truy cập giá trị liên kết với một khóa cụ thể trong Dictionary là sử dụng cú pháp indexer (giống như truy cập phần tử trong mảng hoặc List bằng chỉ mục, nhưng ở đây là bằng khóa). Cú pháp cơ bản: ValueType myValue = myDictionary[key]; Lưu ý quan trọng: Nếu bạn cố gắng truy cập một khóa không tồn tại trong Dictionary, indexer sẽ ném ra một ngoại lệ KeyNotFoundException. Ví dụ: Tiếp tục với Dictionary về thủ đô: using System; using System.Collections.Generic; public class Program { public static void Main(string[] args) { Dictionary<string, string> capitals = new Dictionary<string, string> { {"Vietnam", "Hanoi"}, {"USA", "Washington D.C."}, {"France", "Paris"} }; // Truy cập giá trị bằng khóa string vietnamCapital = capitals["Vietnam"]; Console.WriteLine($"Thủ đô của Vietnam là: {vietnamCapital}"); string usaCapital = capitals["USA"]; Console.WriteLine($"Thủ đô của USA là: {usaCapital}"); // Thử truy cập một khóa không tồn tại (sẽ gây lỗi) try { string germanyCapital = capitals["Germany"]; // Lỗi: Khóa 'Germany' không tồn tại } catch (KeyNotFoundException ex) { Console.WriteLine($"\nLỗi khi truy cập: {ex.Message}"); } } } Kết quả: Thủ đô của Vietnam là: Hanoi Thủ đô của USA là: Washington D.C. Lỗi khi truy cập: The given key 'Germany' was not present in the dictionary. Để truy cập giá trị một cách an toàn hơn mà không lo lỗi khi khóa không tồn tại, bạn có thể sử dụng phương thức TryGetValue() hoặc ContainsKey() trước khi truy cập, như đã được đề cập trong bài học "Kiểm tra sự tồn tại và Xóa phần tử trong Dictionary<K,V>". Cập nhật giá trị của một khóa đã tồn tại Bạn cũng sử dụng cú pháp indexer để cập nhật giá trị liên kết với một khóa đã tồn tại. Khi bạn gán một giá trị mới cho myDictionary[key] và khóa đó đã có sẵn trong Dictionary, giá trị cũ sẽ được thay thế bằng giá trị mới. Lưu ý thú vị: Nếu khóa bạn dùng để gán giá trị mới chưa tồn tại, indexer sẽ tự động thêm khóa đó cùng với giá trị mới vào Dictionary. Điều này khác biệt với phương thức Add() (sẽ gây lỗi nếu khóa đã tồn tại). Ví dụ: using System; using System.Collections.Generic; public class Program { public static void Main(string[] args) { Dictionary<string, int> studentScores = new Dictionary<string, int> { {"Alice", 85}, {"Bob", 90}, {"Charlie", 78} }; Console.WriteLine("Điểm ban đầu:"); foreach (var entry in studentScores) { Console.WriteLine($"- {entry.Key}: {entry.Value}"); } // Cập nhật điểm cho Bob studentScores["Bob"] = 92; Console.WriteLine("\nĐiểm của Bob sau khi cập nhật: " + studentScores["Bob"]); // Thêm một sinh viên mới bằng indexer (nếu khóa chưa tồn tại) studentScores["David"] = 88; Console.WriteLine("Điểm của David (mới thêm): " + studentScores["David"]); Console.WriteLine("\nĐiểm sau khi cập nhật và thêm:"); foreach (var entry in studentScores) { Console.WriteLine($"- {entry.Key}: {entry.Value}"); } } } Kết quả: Điểm ban đầu: - Alice: 85 - Bob: 90 - Charlie: 78 Điểm của Bob sau khi cập nhật: 92 Điểm của David (mới thêm): 88 Điểm sau khi cập nhật và thêm: - Alice: 85 - Bob: 92 - Charlie: 78 - David: 88 Nếu bạn chỉ muốn cập nhật một khóa chắc chắn đã tồn tại và không muốn thêm mới nếu khóa không có, bạn có thể kiểm tra sự tồn tại của khóa trước khi gán, ví dụ: if (studentScores.ContainsKey("Eve")) { studentScores["Eve"] = 95; }. Thêm an toàn bằng phương thức TryAdd() Trong .NET Core 2.0 trở lên (và .NET 5+), phương thức TryAdd() được giới thiệu để cung cấp một cách an toàn hơn để thêm các cặp khóa-giá trị. Thay vì ném ngoại lệ khi khóa đã tồn tại, TryAdd() sẽ trả về false. Cú pháp cơ bản: bool wasAdded = myDictionary.TryAdd(key, value); Ưu điểm:TryAdd() giúp bạn tránh được khối try-catch khi bạn không chắc chắn về sự tồn tại của khóa và muốn thêm nó chỉ khi nó chưa có. Ví dụ: using System; using System.Collections.Generic; public class Program { public static void Main(string[] args) { Dictionary<string, string> users = new Dictionary<string, string>(); // Thêm người dùng mới thành công bool added1 = users.TryAdd("john.doe", "password123"); Console.WriteLine($"Đã thêm 'john.doe': {added1}"); // True // Thêm người dùng khác thành công bool added2 = users.TryAdd("jane.smith", "securepass"); Console.WriteLine($"Đã thêm 'jane.smith': {added2}"); // True // Thử thêm một người dùng với khóa đã tồn tại bool added3 = users.TryAdd("john.doe", "newpassword"); Console.WriteLine($"Đã thêm 'john.doe' lần nữa: {added3}"); // False (không thêm, không lỗi) Console.WriteLine("\nDanh sách người dùng hiện tại:"); foreach (var user in users) { Console.WriteLine($"- {user.Key}"); } } } Kết quả: Đã thêm 'john.doe': True Đã thêm 'jane.smith': True Đã thêm 'john.doe' lần nữa: False Danh sách người dùng hiện tại: - john.doe - jane.smith Như bạn thấy, TryAdd() trả về false khi khóa "john.doe" đã tồn tại, cho phép bạn xử lý logic mà không làm chương trình bị dừng bởi ngoại lệ. Đây là một phương thức rất hữu ích để kiểm soát luồng chương trình một cách linh hoạt hơn khi thao tác với Dictionary. | W9: # Thêm, Truy cập và Cập nhật phần tử trong Dictionary<K,V> ## Mục tiêu học tập Sau bài học này, bạn có thể: - Thêm cặp khóa - giá trị bằng `Add` và bằng chỉ mục `[khóa] = giá trị`. - Phân biệt `Add` (lỗi khi trùng khóa) với gán bằng `[ ]` (cập nhật nếu có, thêm mới nếu chưa có). - Đọc giá trị theo khóa và nhận ra `KeyNotFoundException` khi khóa không tồn tại. - Dùng `TryGetValue`, `ContainsKey` và `TryAdd` để làm việc an toàn, không cần `try-catch`. - Duyệt Dictionary bằng `foreach` qua `Key` và `Value`. - Quan sát các ngăn kéo thay đổi và các thẻ lỗi bằng hoạt động mô phỏng. ## Khởi tạo Dictionary Ví dụ trong bài là kho hàng `stock`: khóa là tên hàng (`string`), giá trị là số lượng (`int`). ```csharp using System; using System.Collections.Generic; public class Program { public static void Main() { var empty = new Dictionary<string, int>(); // rỗng Console.WriteLine(empty.Count); // 0 var stock = new Dictionary<string, int> { ["bút"] = 10, ["vở"] = 5 }; Console.WriteLine(stock.Count); // 2 } } ``` `Count` cho biết số cặp khóa - giá trị đang có. ## Thêm phần tử ### Add: chỉ để thêm khóa mới ```csharp var stock = new Dictionary<string, int>(); stock.Add("bút", 10); stock.Add("vở", 5); stock.Add("thước", 3); // Count = 3 ``` Mỗi khóa phải duy nhất. Nếu khóa **đã có**, `Add` ném `ArgumentException` (không tự ghi đè): ```csharp stock.Add("bút", 7); // Lỗi: System.ArgumentException // An item with the same key has already been added. Key: bút ``` ### Gán bằng [ ]: cập nhật hoặc thêm mới ```csharp stock["vở"] = 8; // "vở" đã có: cập nhật 5 thành 8, Count không đổi stock["tẩy"] = 2; // "tẩy" chưa có: thêm ngăn mới, Count tăng ``` Cùng một cú pháp: **có khóa thì cập nhật, chưa có thì thêm**, không báo lỗi. Vì thế muốn ghi đè một khóa đã có, hãy gán bằng `[ ]` thay cho `Add`. Nếu bạn chỉ muốn cập nhật khi khóa chắc chắn đã tồn tại, hãy kiểm tra `ContainsKey` trước khi gán. | Cách viết | Khóa đã có | Khóa chưa có | |---|---|---| | `Add(khóa, giá trị)` | Ném `ArgumentException` | Thêm mới | | `d[khóa] = giá trị` | Cập nhật giá trị | Thêm mới | | `TryAdd(khóa, giá trị)` | Trả về `false`, không đổi gì | Thêm mới, trả về `true` | ### TryAdd: thêm an toàn `TryAdd` (có từ .NET Core 2.0, dùng được trong .NET 8) chỉ thêm khi khóa chưa có và trả về `bool`. Nó giúp tránh `try-catch` khi bạn không chắc khóa đã tồn tại: ```csharp var stock = new Dictionary<string, int> { ["bút"] = 10 }; bool a = stock.TryAdd("vở", 5); // true: đã thêm bool b = stock.TryAdd("bút", 7); // false: "bút" đã có, giá trị vẫn là 10 Console.WriteLine($"{a} {b}"); // True False ``` ## Truy cập phần tử Đọc giá trị bằng `d[khóa]`: ```csharp int n = stock["bút"]; // 10 ``` Nếu khóa **không có**, Dictionary ném `KeyNotFoundException`: ```csharp int m = stock["kéo"]; // Lỗi: System.Collections.Generic.KeyNotFoundException // The given key 'kéo' was not present in the dictionary. ``` Với khóa có thể không tồn tại, hãy đọc an toàn bằng `TryGetValue`: ```csharp int count; bool ok = stock.TryGetValue("kéo", out count); // ok là false, count là 0 (giá trị mặc định của int), không có lỗi if (ok) { Console.WriteLine($"Còn {count} cái kéo"); } ``` Hãy kiểm tra `ok` trước khi dùng `count`. Cũng có thể gọi `stock.ContainsKey("kéo")` để biết khóa có tồn tại hay không. ## Duyệt Dictionary Mỗi phần tử khi duyệt là một cặp `KeyValuePair`, có thuộc tính `Key` và `Value`: ```csharp var stock = new Dictionary<string, int> { ["bút"] = 10, ["vở"] = 5 }; foreach (var entry in stock) { Console.WriteLine($"{entry.Key}: {entry.Value}"); } // bút: 10 // vở: 5 ``` Dictionary không cam kết thứ tự duyệt. Đừng dựa vào thứ tự các cặp khi viết chương trình. ## Hoạt động: Các ngăn kéo thay đổi Mô phỏng dưới đây có bốn tab, mỗi tab là một tình huống với `stock`. Hãy thao tác theo thứ tự sau, bấm **Bước tiếp** để chạy từng dòng: - Mở tab **Add**. Tủ bắt đầu rỗng. Ba lần `Add("bút", 10)`, `Add("vở", 5)`, `Add("thước", 3)` thêm lần lượt ba ngăn mới (màu xanh), và `Count` tăng từ 1 đến 3. - Mở tab **Gán bằng [ ]**. Tủ có hai ngăn: "bút" chứa 10 và "vở" chứa 5. `stock["vở"] = 8` cập nhật ngăn "vở" từ 5 thành 8, `Count` vẫn là 2. `stock["tẩy"] = 2` thêm ngăn mới "tẩy" nên `Count` lên 3. - Mở tab **Add trùng khóa**. Dòng `stock.Add("bút", 7)` tìm thấy ngăn "bút" đang chứa 10 và ngăn đó chuyển sang màu đỏ. Thẻ lỗi **ArgumentException** hiện ra với thông báo "An item with the same key has already been added. Key: bút". Ngăn "bút" vẫn chứa 10. Thẻ gợi ý cuối nhắc dùng `stock["bút"] = 7` nếu muốn ghi đè. - Mở tab **Đọc khóa không có**. Tủ có "bút" và "vở", không có ngăn "kéo". `stock["kéo"]` làm hiện thẻ lỗi **KeyNotFoundException** với thông báo "The given key 'kéo' was not present in the dictionary.". Bước tiếp theo, `TryGetValue("kéo", out m)` trả về `false` và `m` là 0, thẻ xanh cho biết không có lỗi. ``` <iframe src="https://codegym-vn.github.io/programming-course-demos/c-sharp-ung-dung/cau-truc-du-lieu-nang-cao-collections/gioi-thieu-ve-dictionary-k-v/them-truy-cap-va-cap-nhat-phan-tu-trong-dictionary-k-v/" title="Thêm, truy cập và cập nhật trong Dictionary" style="border:0;" allowfullscreen></iframe> ``` Điều rút ra: mỗi khóa chỉ có một ngăn. `Add` chỉ dùng để thêm khóa mới và báo lỗi khi trùng, còn gán bằng `[ ]` vừa cập nhật vừa thêm mới. Đọc bằng `[ ]` với khóa không có sẽ gây lỗi, nên dùng `TryGetValue` khi chưa chắc khóa tồn tại. ## Tóm tắt - `Add(khóa, giá trị)` thêm khóa mới. Trùng khóa thì ném `ArgumentException`. - `d[khóa] = giá trị` cập nhật nếu khóa có sẵn, thêm mới nếu chưa có, không báo lỗi. - `TryAdd` chỉ thêm khi khóa chưa có, trả về `false` thay vì ném lỗi. - `d[khóa]` đọc giá trị. Khóa không có thì ném `KeyNotFoundException`. - `TryGetValue(khóa, out giá_trị)` trả về `bool`, không ném lỗi, và gán giá trị mặc định khi không thấy. `ContainsKey` kiểm tra khóa có tồn tại. - `foreach` duyệt từng `KeyValuePair` qua `Key` và `Value`, thứ tự không được đảm bảo.
A10: 9 | B10: 1. Cấu trúc dữ liệu nâng cao: Collections | C10: Giới thiệu về Dictionary<K,V> | D10: Kiểm tra sự tồn tại và Xóa phần tử trong Dictionary<K,V> | E10: Bài đọc | F10: Làm thêm nếu muốn | G10: Done | H10: Dùng đúng ContainsKey, ContainsValue và Remove; thấy kiểm tra giá trị chậm hơn kiểm tra khóa. | I10: 1 cột, 3 tab | J10: Tủ ngăn kéo: ContainsKey đi thẳng tới ngăn; ContainsValue mở lần lượt từng ngăn; ngăn bị Remove mờ đỏ rồi biến mất. | K10: H02 | L10: ContainsKey | ContainsValue | Remove | M10: ContainsKey("vở") → true sau 1 lần tra; ContainsKey("kéo") → false. ContainsValue(5) → mở lần lượt từng ngăn đến khi gặp giá trị 5 (đếm số ngăn đã mở). Remove("bút") → true, Count giảm; Remove("kéo") → false, không lỗi. Remove("vở", out int old) → lấy luôn giá trị vừa xóa (old = 5). | N10: stock: bút = 10, vở = 5, thước = 3 | O10: Kiểm tra khóa nhanh, kiểm tra giá trị phải duyệt; Remove khóa không có chỉ trả false. | P10: Remove(key, out value) có từ .NET Core 2.0. | Q10: c-sharp-ung-dung/cau-truc-du-lieu-nang-cao-collections/gioi-thieu-ve-dictionary-k-v/kiem-tra-su-ton-tai-va-xoa-phan-tu-trong-dictionary-k-v/index.html | R10: https://codegym-vn.github.io/programming-course-demos/c-sharp-ung-dung/cau-truc-du-lieu-nang-cao-collections/gioi-thieu-ve-dictionary-k-v/kiem-tra-su-ton-tai-va-xoa-phan-tu-trong-dictionary-k-v/ | V10: Kiểm tra sự Tồn tại của Khóa và Giá trị Trong quá trình làm việc với Dictionary<K,V>, không phải lúc nào bạn cũng biết chắc chắn liệu một khóa hoặc một giá trị cụ thể có tồn tại trong bộ sưu tập hay không. Việc cố gắng truy cập một khóa không tồn tại bằng cách sử dụng toán tử [] sẽ gây ra lỗi KeyNotFoundException, làm gián đoạn chương trình của bạn. Để tránh những tình huống này và giúp bạn quản lý dữ liệu một cách linh hoạt, C# cung cấp các phương thức hiệu quả để kiểm tra sự tồn tại và xóa các phần tử. Phương thức ContainsKey() ContainsKey() là phương thức dùng để kiểm tra xem một khóa (key) cụ thể có tồn tại trong Dictionary hay không. Phương thức này trả về true nếu khóa tồn tại và false nếu không. Đây là cách an toàn và được khuyến nghị để kiểm tra trước khi cố gắng truy cập một phần tử, giúp bạn tránh được lỗi KeyNotFoundException. Ví dụ: using System; using System.Collections.Generic; public class Program { public static void Main(string[] args) { Dictionary<string, int> diemSinhVien = new Dictionary<string, int>() { { "Nguyen Van A", 85 }, { "Tran Thi B", 92 }, { "Le Van C", 78 } }; // Kiểm tra sự tồn tại của một sinh viên string tenSinhVienCanTim1 = "Nguyen Van A"; if (diemSinhVien.ContainsKey(tenSinhVienCanTim1)) { Console.WriteLine($"Sinh viên '{tenSinhVienCanTim1}' có trong danh sách với điểm số: {diemSinhVien[tenSinhVienCanTim1]}"); } else { Console.WriteLine($"Sinh viên '{tenSinhVienCanTim1}' không có trong danh sách."); } string tenSinhVienCanTim2 = "Pham Minh D"; if (diemSinhVien.ContainsKey(tenSinhVienCanTim2)) { Console.WriteLine($"Sinh viên '{tenSinhVienCanTim2}' có trong danh sách với điểm số: {diemSinhVien[tenSinhVienCanTim2]}"); } else { Console.WriteLine($"Sinh viên '{tenSinhVienCanTim2}' không có trong danh sách."); } } } Trong ví dụ trên, chúng ta sử dụng ContainsKey() để kiểm tra xem "Nguyen Van A" và "Pham Minh D" có trong diemSinhVien hay không trước khi cố gắng truy cập điểm số của họ. Phương thức ContainsValue() Tương tự như ContainsKey(), phương thức ContainsValue() được sử dụng để kiểm tra xem một giá trị (value) cụ thể có tồn tại trong bất kỳ cặp khóa-giá trị nào của Dictionary hay không. Phương thức này cũng trả về true hoặc false. Lưu ý: Vì Dictionary được tối ưu hóa cho việc tìm kiếm theo khóa, việc sử dụng ContainsValue() có thể kém hiệu quả hơn ContainsKey() đối với các Dictionary lớn, vì nó thường phải duyệt qua tất cả các giá trị để tìm kiếm. Ví dụ: using System; using System.Collections.Generic; public class Program { public static void Main(string[] args) { Dictionary<string, int> diemSinhVien = new Dictionary<string, int>() { { "Nguyen Van A", 85 }, { "Tran Thi B", 92 }, { "Le Van C", 78 } }; // Kiểm tra sự tồn tại của một điểm số int diemCanTim1 = 92; if (diemSinhVien.ContainsValue(diemCanTim1)) { Console.WriteLine($"Có sinh viên đạt điểm {diemCanTim1} trong danh sách."); } else { Console.WriteLine($"Không có sinh viên nào đạt điểm {diemCanTim1} trong danh sách."); } int diemCanTim2 = 100; if (diemSinhVien.ContainsValue(diemCanTim2)) { Console.WriteLine($"Có sinh viên đạt điểm {diemCanTim2} trong danh sách."); } else { Console.WriteLine($"Không có sinh viên nào đạt điểm {diemCanTim2} trong danh sách."); } } } Truy cập an toàn với TryGetValue() Phương thức TryGetValue() là một cách thay thế hiệu quả và an toàn để vừa kiểm tra sự tồn tại của khóa, vừa lấy giá trị tương ứng nếu khóa đó tồn tại. Nó trả về true nếu khóa được tìm thấy và gán giá trị của nó vào tham số out được cung cấp. Nếu khóa không tồn tại, nó trả về false và gán giá trị mặc định của kiểu giá trị (default(TValue)) vào tham số out. Ưu điểm của TryGetValue() là nó chỉ thực hiện một lần tìm kiếm để vừa kiểm tra, vừa lấy giá trị, hiệu quả hơn so với việc gọi ContainsKey() rồi sau đó truy cập bằng toán tử []. Ví dụ: using System; using System.Collections.Generic; public class Program { public static void Main(string[] args) { Dictionary<string, int> diemSinhVien = new Dictionary<string, int>() { { "Nguyen Van A", 85 }, { "Tran Thi B", 92 }, { "Le Van C", 78 } }; // Sử dụng TryGetValue để lấy điểm của sinh viên string tenSinhVien1 = "Tran Thi B"; if (diemSinhVien.TryGetValue(tenSinhVien1, out int diem1)) { Console.WriteLine($"Điểm của '{tenSinhVien1}' là: {diem1}"); } else { Console.WriteLine($"Sinh viên '{tenSinhVien1}' không tồn tại trong danh sách."); } string tenSinhVien2 = "Dang Van E"; if (diemSinhVien.TryGetValue(tenSinhVien2, out int diem2)) { Console.WriteLine($"Điểm của '{tenSinhVien2}' là: {diem2}"); } else { Console.WriteLine($"Sinh viên '{tenSinhVien2}' không tồn tại trong danh sách."); } } } Xóa phần tử khỏi Dictionary Khi bạn không còn cần một cặp khóa-giá trị cụ thể, bạn có thể xóa nó khỏi Dictionary bằng phương thức Remove(). Phương thức Remove() Phương thức Remove() nhận một khóa làm đối số và cố gắng xóa cặp khóa-giá trị tương ứng. Nó trả về true nếu phần tử được tìm thấy và xóa thành công, và false nếu khóa không tồn tại trong Dictionary (trong trường hợp này, không có gì được xóa). Ví dụ: using System; using System.Collections.Generic; public class Program { public static void Main(string[] args) { Dictionary<string, int> diemSinhVien = new Dictionary<string, int>() { { "Nguyen Van A", 85 }, { "Tran Thi B", 92 }, { "Le Van C", 78 } }; Console.WriteLine("Danh sách ban đầu:"); foreach (var sv in diemSinhVien) { Console.WriteLine($"- {sv.Key}: {sv.Value}"); } Console.WriteLine(); // Xóa một sinh viên đã có string svCanXoa1 = "Tran Thi B"; if (diemSinhVien.Remove(svCanXoa1)) { Console.WriteLine($"Đã xóa sinh viên '{svCanXoa1}' khỏi danh sách."); } else { Console.WriteLine($"Không tìm thấy sinh viên '{svCanXoa1}' để xóa."); } // Xóa một sinh viên không có string svCanXoa2 = "Pham Minh D"; if (diemSinhVien.Remove(svCanXoa2)) { Console.WriteLine($"Đã xóa sinh viên '{svCanXoa2}' khỏi danh sách."); } else { Console.WriteLine($"Không tìm thấy sinh viên '{svCanXoa2}' để xóa."); } Console.WriteLine("\nDanh sách sau khi xóa:"); foreach (var sv in diemSinhVien) { Console.WriteLine($"- {sv.Key}: {sv.Value}"); } } } Xóa toàn bộ nội dung với Clear() Đôi khi bạn muốn xóa tất cả các phần tử khỏi một Dictionary để bắt đầu lại với một bộ sưu tập trống. Phương thức Clear() thực hiện chính xác điều này. Nó không nhận đối số và không trả về giá trị. Ví dụ: using System; using System.Collections.Generic; public class Program { public static void Main(string[] args) { Dictionary<string, int> danhSachMonHoc = new Dictionary<string, int>() { { "Toan", 101 }, { "Ly", 102 }, { "Hoa", 103 } }; Console.WriteLine($"Số lượng môn học ban đầu: {danhSachMonHoc.Count}"); // Xóa tất cả các phần tử danhSachMonHoc.Clear(); Console.WriteLine($"Số lượng môn học sau khi xóa: {danhSachMonHoc.Count}"); if (danhSachMonHoc.Count == 0) { Console.WriteLine("Dictionary hiện đã trống."); } } } Tóm tắt và Lựa chọn Phương pháp Bạn đã học được các công cụ cần thiết để kiểm tra sự tồn tại và quản lý việc xóa phần tử trong Dictionary<K,V>: Sử dụng ContainsKey() để kiểm tra sự tồn tại của khóa trước khi truy cập bằng toán tử [], giúp tránh KeyNotFoundException. Sử dụng ContainsValue() khi bạn cần kiểm tra xem một giá trị cụ thể có trong Dictionary hay không, nhưng hãy lưu ý về hiệu suất đối với các tập dữ liệu lớn. Sử dụng TryGetValue() để truy cập giá trị an toàn và hiệu quả hơn, đặc biệt khi bạn cần cả việc kiểm tra và lấy giá trị nếu khóa tồn tại. Sử dụng Remove(key) để xóa một cặp khóa-giá trị cụ thể. Sử dụng Clear() để xóa tất cả các phần tử, làm trống Dictionary. Việc lựa chọn phương thức phù hợp sẽ giúp code của bạn an toàn hơn, dễ đọc hơn và hiệu quả hơn khi làm việc với Dictionary. | W10: # Kiểm tra sự tồn tại và Xóa phần tử trong Dictionary<K,V> ## Mục tiêu học tập Sau bài học này, bạn có thể: - Giải thích vì sao đọc một khóa không tồn tại bằng `[]` gây ra `KeyNotFoundException`. - Dùng `ContainsKey()` và `TryGetValue()` để kiểm tra khóa một cách an toàn. - Phân biệt `ContainsKey()` (theo khóa, nhanh) với `ContainsValue()` (theo giá trị, phải duyệt). - Xóa phần tử bằng `Remove()` và `Clear()`, hiểu giá trị `bool` mà `Remove()` trả về. - Quan sát từng bước chạy của `ContainsKey`, `ContainsValue` và `Remove` bằng hoạt động mô phỏng. ## Vì sao cần kiểm tra trước khi truy cập `Dictionary<TKey, TValue>` lưu dữ liệu theo cặp **khóa - giá trị**. Hãy hình dung một chiếc tủ có nhiều ngăn kéo: mỗi ngăn có một nhãn (khóa) và đồ bên trong (giá trị). Nếu bạn đọc một khóa không có bằng toán tử `[]`, chương trình ném `KeyNotFoundException` và dừng lại. Vì vậy, khi không chắc khóa có tồn tại, hãy kiểm tra trước. Các ví dụ trong bài dùng một kho văn phòng phẩm: bút 10 cái, vở 5 quyển, thước 3 cái. ```csharp using System; using System.Collections.Generic; public class Program { public static void Main() { var stock = new Dictionary<string, int> { ["bút"] = 10, ["vở"] = 5, ["thước"] = 3 }; // int n = stock["kéo"]; // ném KeyNotFoundException vì không có khóa "kéo" Console.WriteLine(stock.Count); // 3 } } ``` ## Kiểm tra khóa với ContainsKey() `ContainsKey(key)` trả về `true` nếu khóa có trong Dictionary, ngược lại trả về `false`. Khóa không có chỉ cho kết quả `false`, **không gây lỗi**. `ContainsKey()` rất nhanh: Dictionary đi thẳng tới ngăn có nhãn đó, không cần mở các ngăn khác. ```csharp bool a = stock.ContainsKey("vở"); // true bool b = stock.ContainsKey("kéo"); // false ``` ## Kiểm tra giá trị với ContainsValue() `ContainsValue(value)` cho biết có ít nhất một cặp nào mang giá trị đó hay không. ```csharp bool c = stock.ContainsValue(5); // true ``` Dictionary được tổ chức để tìm theo khóa, không theo giá trị. Vì vậy `ContainsValue()` phải **duyệt lần lượt từng phần tử**. Nếu giá trị không có, nó phải duyệt hết. Dictionary càng lớn thì càng chậm, nên chỉ dùng khi thật sự cần. ## Lấy giá trị an toàn với TryGetValue() Nếu bạn muốn vừa kiểm tra vừa lấy giá trị, dùng `TryGetValue(key, out value)`: ```csharp if (stock.TryGetValue("vở", out int soLuong)) { Console.WriteLine($"Còn {soLuong} quyển vở."); // Còn 5 quyển vở. } else { Console.WriteLine("Không có mặt hàng này."); } ``` Phương thức trả về `true` và gán giá trị vào `soLuong` khi tìm thấy khóa. Nếu không tìm thấy, nó trả về `false` và `soLuong` nhận giá trị mặc định (`0` với `int`). Cách này chỉ tra khóa **một lần**, gọn hơn việc gọi `ContainsKey()` rồi đọc bằng `[]`. ## Xóa phần tử ### Remove() `Remove(key)` xóa cặp có khóa tương ứng và trả về `bool`: - `true`: có cặp để xóa và đã xóa xong. - `false`: không có khóa đó, không xóa gì và **không báo lỗi**. ```csharp bool r1 = stock.Remove("bút"); // true, Count còn 2 bool r2 = stock.Remove("kéo"); // false, Count vẫn là 2 ``` Có thêm phiên bản `Remove(key, out value)` vừa xóa vừa trả lại giá trị của cặp vừa bị xóa: ```csharp bool r3 = stock.Remove("vở", out int old); // r3 = true, old = 5, Count còn 1 (chỉ còn "thước") ``` ### Clear() `Clear()` xóa tất cả phần tử, không nhận tham số và không trả về giá trị. Sau đó `Count` bằng 0. ```csharp stock.Clear(); Console.WriteLine(stock.Count); // 0 ``` ## Hoạt động: Kiểm tra và xóa trong tủ ngăn kéo Mô phỏng dưới đây là một chiếc tủ ba ngăn: bút 10, vở 5, thước 3. Hãy thao tác theo thứ tự sau, bấm **Bước tiếp** để chạy từng dòng: - Mở tab **ContainsKey**. Hỏi tủ có ngăn "vở" không: Dictionary đi thẳng tới ngăn "vở" chỉ sau 1 lần tra và trả về `a = true`. Sau đó hỏi ngăn "kéo": không ngăn nào mang nhãn này, nên `b = false` và không có lỗi nào xảy ra. - Chuyển sang tab **ContainsValue**. Lần này ta không biết nhãn, chỉ tìm giá trị 5. Các ngăn được mở lần lượt: "bút" chứa 10 (khác 5) nên mở tiếp, "vở" chứa 5 nên dừng. Bộ đếm cho thấy phải mở 2 trên 3 ngăn. Nếu giá trị không có, phải mở hết cả 3 ngăn. - Mở tab **Remove**. `Remove("bút")` đánh dấu ngăn "bút" rồi bỏ đi, trả về `r1 = true`, `Count` giảm còn 2. `Remove("kéo")` trả về `r2 = false`, `Count` vẫn là 2. Cuối cùng `Remove("vở", out int old)` bỏ ngăn "vở" và lưu giá trị `old = 5`, `Count` còn 1, chỉ còn ngăn "thước". ``` <iframe src="https://codegym-vn.github.io/programming-course-demos/c-sharp-ung-dung/cau-truc-du-lieu-nang-cao-collections/gioi-thieu-ve-dictionary-k-v/kiem-tra-su-ton-tai-va-xoa-phan-tu-trong-dictionary-k-v/" title="Kiểm tra tồn tại và xóa trong Dictionary" style="border:0;" allowfullscreen></iframe> ``` Điều rút ra: `ContainsKey()` đi thẳng tới ngăn nên nhanh, còn `ContainsValue()` phải mở từng ngăn nên chậm dần khi dữ liệu lớn. `Remove()` với khóa không có chỉ trả về `false`, không gây lỗi. > **Lưu ý:** Đừng dùng `ContainsKey()` rồi `[]` khi bạn cần giá trị. `TryGetValue()` làm cả hai việc trong một lần tra. ## Tóm tắt - Đọc khóa không có bằng `[]` ném `KeyNotFoundException`, nên hãy kiểm tra trước. - `ContainsKey()` kiểm tra theo khóa, nhanh. Khóa không có chỉ trả về `false`. - `ContainsValue()` phải duyệt từng phần tử nên chậm hơn khi Dictionary lớn. - `TryGetValue()` vừa kiểm tra vừa lấy giá trị, chỉ tra một lần. - `Remove(key)` trả về `true` nếu đã xóa, `false` nếu không có khóa. `Remove(key, out value)` lấy luôn giá trị vừa xóa. - `Clear()` xóa toàn bộ phần tử, sau đó `Count` bằng 0.
A11: 10 | B11: 1. Cấu trúc dữ liệu nâng cao: Collections | C11: Thao tác nâng cao với Dictionary<K,V> và lựa chọn Collections | D11: Duyệt qua Dictionary<K,V> | E11: Bài đọc | F11: Làm thêm nếu muốn | G11: Done | H11: Thấy mỗi lần lặp foreach nhận một cặp KeyValuePair, và cách duyệt riêng Keys hoặc Values. | I11: 1 cột, 3 tab | J11: Tủ ngăn kéo với con trỏ duyệt; thẻ 'kv' hiện Key và Value của lần lặp hiện tại; console in dần. | K11: H02 | L11: foreach KeyValuePair | Keys | Values | M11: foreach (var kv in scores): lần 1 kv.Key = "An", kv.Value = 8 ... in từng dòng. Keys: duyệt chỉ các khóa, in danh sách tên. Values: duyệt chỉ giá trị, tính tổng và điểm trung bình (tính từ dữ liệu). Bước cuối: ghi chú thứ tự duyệt. | N11: scores: An 8, Bình 6, Chi 9 | O11: foreach trên Dictionary trả về từng cặp khóa – giá trị. Thứ tự duyệt không được bảo đảm. | P11: Thứ tự duyệt thường trùng thứ tự thêm nhưng tài liệu không bảo đảm; cần thứ tự thì dùng SortedDictionary hoặc OrderBy. | Q11: c-sharp-ung-dung/cau-truc-du-lieu-nang-cao-collections/thao-tac-nang-cao-voi-dictionary-k-v-va-lua-chon-collections/duyet-qua-dictionary-k-v/index.html | R11: https://codegym-vn.github.io/programming-course-demos/c-sharp-ung-dung/cau-truc-du-lieu-nang-cao-collections/thao-tac-nang-cao-voi-dictionary-k-v-va-lua-chon-collections/duyet-qua-dictionary-k-v/ | V11: Trong C#, Dictionary<K,V> là một cấu trúc dữ liệu mạnh mẽ để lưu trữ các cặp khóa-giá trị, cho phép truy cập dữ liệu nhanh chóng dựa trên khóa. Tuy nhiên, để tận dụng tối đa Dictionary, bạn cần biết cách duyệt qua các phần tử của nó một cách hiệu quả. Trang này sẽ hướng dẫn bạn các phương pháp phổ biến và mạnh mẽ để thực hiện điều đó. Duyệt qua tất cả các Khóa (Keys) Đôi khi, bạn chỉ cần xử lý các khóa trong Dictionary mà không cần quan tâm đến giá trị tương ứng. Dictionary<K,V> cung cấp thuộc tính Keys, trả về một tập hợp các khóa (Dictionary<K,V>.KeyCollection) mà bạn có thể duyệt qua. Việc duyệt qua các khóa rất hữu ích khi bạn muốn: Kiểm tra sự tồn tại của một tập hợp các khóa cụ thể. Tạo một danh sách các khóa duy nhất. Thực hiện các thao tác chỉ dựa trên thông tin khóa. using System; using System.Collections.Generic; public class DuyetQuaKeys { public static void Main(string[] args) { Dictionary<string, int> diemMonHoc = new Dictionary<string, int>() { { "Toan", 90 }, { "Ly", 85 }, { "Hoa", 92 }, { "Van", 78 } }; Console.WriteLine("Danh sách các môn học (khóa):"); foreach (string monHoc in diemMonHoc.Keys) { Console.WriteLine($"- {monHoc}"); } } } Kết quả của đoạn code trên sẽ là: Danh sách các môn học (khóa): - Toan - Ly - Hoa - Van Duyệt qua tất cả các Giá trị (Values) Tương tự như việc duyệt qua các khóa, bạn cũng có thể chỉ muốn làm việc với các giá trị được lưu trữ trong Dictionary. Thuộc tính Values của Dictionary<K,V> trả về một tập hợp các giá trị (Dictionary<K,V>.ValueCollection), cho phép bạn truy cập tất cả các giá trị mà không cần khóa. Phương pháp này hữu ích khi bạn cần: Tính tổng, trung bình hoặc các thống kê khác từ các giá trị. Lọc hoặc biến đổi các giá trị. Kiểm tra sự tồn tại của một giá trị cụ thể. using System; using System.Collections.Generic; public class DuyetQuaValues { public static void Main(string[] args) { Dictionary<string, int> diemMonHoc = new Dictionary<string, int>() { { "Toan", 90 }, { "Ly", 85 }, { "Hoa", 92 }, { "Van", 78 } }; Console.WriteLine("\nDanh sách các điểm số (giá trị):"); foreach (int diem in diemMonHoc.Values) { Console.WriteLine($"- {diem}"); } // Ví dụ: Tính tổng điểm int tongDiem = 0; foreach (int diem in diemMonHoc.Values) { tongDiem += diem; } Console.WriteLine($"\nTổng điểm của các môn: {tongDiem}"); } } Kết quả của đoạn code trên sẽ là: Danh sách các điểm số (giá trị): - 90 - 85 - 92 - 78 Tổng điểm của các môn: 345 Duyệt qua cả Cặp Khóa-Giá trị (Key-Value Pairs) Trong nhiều trường hợp, bạn cần truy cập cả khóa và giá trị tương ứng của nó trong mỗi lần lặp. Dictionary<K,V> triển khai giao diện IEnumerable<KeyValuePair<K,V>>, cho phép bạn duyệt qua từng cặp khóa-giá trị bằng vòng lặp foreach. Mỗi phần tử trong vòng lặp sẽ là một đối tượng KeyValuePair<K,V>, có hai thuộc tính: Key và Value. Đây là phương pháp phổ biến nhất khi bạn cần xử lý mối quan hệ giữa khóa và giá trị. using System; using System.Collections.Generic; public class DuyetQuaKeyValuePair { public static void Main(string[] args) { Dictionary<string, int> diemMonHoc = new Dictionary<string, int>() { { "Toan", 90 }, { "Ly", 85 }, { "Hoa", 92 }, { "Van", 78 } }; Console.WriteLine("\nThông tin điểm các môn học:"); foreach (KeyValuePair<string, int> capDiem in diemMonHoc) { Console.WriteLine($"Môn: {capDiem.Key}, Điểm: {capDiem.Value}"); } // Ví dụ: Tìm môn học có điểm cao nhất string monDiemCaoNhat = ""; int diemCaoNhat = -1; // Giả sử điểm không âm foreach (KeyValuePair<string, int> capDiem in diemMonHoc) { if (capDiem.Value > diemCaoNhat) { diemCaoNhat = capDiem.Value; monDiemCaoNhat = capDiem.Key; } } Console.WriteLine($"\nMôn học có điểm cao nhất là: {monDiemCaoNhat} ({diemCaoNhat} điểm)"); } } Kết quả của đoạn code trên sẽ là: Thông tin điểm các môn học: Môn: Toan, Điểm: 90 Môn: Ly, Điểm: 85 Môn: Hoa, Điểm: 92 Môn: Van, Điểm: 78 Môn học có điểm cao nhất là: Hoa (92 điểm) Sử dụng LINQ để Truy vấn và Duyệt Dictionary Language Integrated Query (LINQ) cung cấp một cú pháp mạnh mẽ và linh hoạt để truy vấn các tập hợp dữ liệu, bao gồm cả Dictionary<K,V>. Với LINQ, bạn có thể lọc, sắp xếp, nhóm và biến đổi dữ liệu trong Dictionary một cách dễ dàng và biểu cảm hơn so với các vòng lặp truyền thống. Khi bạn sử dụng LINQ, các phương thức mở rộng (extension methods) như Where(), Select(), OrderBy() sẽ hoạt động trên các cặp KeyValuePair<K,V>. LINQ đặc biệt hữu ích khi bạn cần: Lọc các phần tử dựa trên điều kiện của khóa hoặc giá trị. Sắp xếp Dictionary theo khóa hoặc giá trị. Chuyển đổi Dictionary thành một cấu trúc dữ liệu khác (ví dụ: List<T>). Thực hiện các phép chiếu (projection) để chỉ lấy một phần của dữ liệu. using System; using System.Collections.Generic; using System.Linq; // Quan trọng: cần thêm using System.Linq public class DuyetQuaDictionaryVoiLINQ { public static void Main(string[] args) { Dictionary<string, int> diemMonHoc = new Dictionary<string, int>() { { "Toan", 90 }, { "Ly", 85 }, { "Hoa", 92 }, { "Van", 78 }, { "Anh", 90 } }; Console.WriteLine("--- Các môn có điểm từ 90 trở lên (sử dụng LINQ.Where) ---"); var monHocDiemCao = diemMonHoc.Where(cap => cap.Value >= 90); foreach (var cap in monHocDiemCao) { Console.WriteLine($"Môn: {cap.Key}, Điểm: {cap.Value}"); } Console.WriteLine("\n--- Các môn học được sắp xếp theo tên (sử dụng LINQ.OrderBy) ---"); var monHocSapXepTheoTen = diemMonHoc.OrderBy(cap => cap.Key); foreach (var cap in monHocSapXepTheoTen) { Console.WriteLine($"Môn: {cap.Key}, Điểm: {cap.Value}"); } Console.WriteLine("\n--- Chỉ lấy tên các môn học (sử dụng LINQ.Select) ---"); var tenMonHoc = diemMonHoc.Select(cap => cap.Key); foreach (var ten in tenMonHoc) { Console.WriteLine($"- {ten}"); } Console.WriteLine("\n--- Chuyển đổi sang List các object ẩn danh (sử dụng LINQ.Select) ---"); var danhSachMonHoc = diemMonHoc.Select(cap => new { TenMon = cap.Key, DiemSo = cap.Value }).ToList(); foreach (var mon in danhSachMonHoc) { Console.WriteLine($"Môn: {mon.TenMon}, Điểm: {mon.DiemSo}"); } } } Kết quả của đoạn code trên sẽ là: --- Các môn có điểm từ 90 trở lên (sử dụng LINQ.Where) --- Môn: Toan, Điểm: 90 Môn: Hoa, Điểm: 92 Môn: Anh, Điểm: 90 --- Các môn học được sắp xếp theo tên (sử dụng LINQ.OrderBy) --- Môn: Anh, Điểm: 90 Môn: Hoa, Điểm: 92 Môn: Ly, Điểm: 85 Môn: Toan, Điểm: 90 Môn: Van, Điểm: 78 --- Chỉ lấy tên các môn học (sử dụng LINQ.Select) --- - Toan - Ly - Hoa - Van - Anh --- Chuyển đổi sang List các object ẩn danh (sử dụng LINQ.Select) --- Môn: Toan, Điểm: 90 Môn: Ly, Điểm: 85 Môn: Hoa, Điểm: 92 Môn: Van, Điểm: 78 Môn: Anh, Điểm: 90 Tổng kết Việc lựa chọn phương pháp duyệt Dictionary<K,V> phụ thuộc vào nhu cầu cụ thể của bạn: Sử dụng Dictionary.Keys khi bạn chỉ cần xử lý các khóa. Sử dụng Dictionary.Values khi bạn chỉ cần xử lý các giá trị. Sử dụng vòng lặp foreach với KeyValuePair<K,V> khi bạn cần truy cập cả khóa và giá trị cùng lúc và thực hiện các thao tác đơn giản. Sử dụng LINQ khi bạn cần các truy vấn phức tạp hơn như lọc, sắp xếp, hoặc biến đổi dữ liệu, mang lại mã nguồn ngắn gọn và dễ đọc hơn. Việc nắm vững các kỹ thuật này sẽ giúp bạn thao tác với Dictionary một cách hiệu quả và linh hoạt trong các ứng dụng C#. | W11: # Duyệt qua Dictionary<K,V> ## Mục tiêu học tập Sau bài học này, bạn có thể: - Dùng `foreach` để duyệt từng cặp `KeyValuePair<TKey, TValue>` của Dictionary. - Duyệt riêng các khóa bằng `Keys` và riêng các giá trị bằng `Values`. - Chọn cách duyệt phù hợp với nhu cầu: cần cả khóa lẫn giá trị, chỉ khóa, hay chỉ giá trị. - Nhớ rằng thứ tự duyệt của Dictionary không được bảo đảm. - Quan sát từng lần lặp của ba cách duyệt bằng hoạt động mô phỏng. ## Ba cách duyệt Dictionary Dictionary lưu dữ liệu theo cặp khóa - giá trị, nên bạn có ba lựa chọn khi duyệt: | Cách duyệt | Mỗi lần lặp nhận | Dùng khi | |---|---|---| | `foreach (var kv in dict)` | một `KeyValuePair` | cần cả khóa và giá trị | | `foreach (var k in dict.Keys)` | một khóa | chỉ cần các khóa | | `foreach (var v in dict.Values)` | một giá trị | chỉ cần các giá trị | Các ví dụ dưới đây dùng một bảng điểm ba học sinh: ```csharp using System; using System.Collections.Generic; public class Program { public static void Main() { var scores = new Dictionary<string, int> { ["An"] = 8, ["Bình"] = 6, ["Chi"] = 9 }; } } ``` ## Duyệt từng cặp khóa - giá trị `Dictionary<TKey, TValue>` cài đặt `IEnumerable<KeyValuePair<TKey, TValue>>`, nên `foreach` trực tiếp trên Dictionary sẽ trả về từng **cặp**. Mỗi `KeyValuePair` có hai thuộc tính: `Key` và `Value`. ```csharp foreach (var kv in scores) { Console.WriteLine(kv.Key + ": " + kv.Value); } // An: 8 // Bình: 6 // Chi: 9 ``` Đây là cách duyệt phổ biến nhất vì bạn nhìn thấy cả hai phần của mỗi cặp. ## Duyệt các khóa với Keys Thuộc tính `Keys` là tập hợp chỉ gồm các khóa. Giá trị không xuất hiện. ```csharp foreach (string k in scores.Keys) { Console.WriteLine(k); } // An // Bình // Chi ``` Cách này hợp khi bạn chỉ cần danh sách tên, hoặc muốn xử lý theo khóa. ## Duyệt các giá trị với Values Thuộc tính `Values` là tập hợp chỉ gồm các giá trị. Cách này tiện để tính tổng hoặc trung bình: ```csharp int sum = 0; foreach (int v in scores.Values) { sum += v; } double avg = (double)sum / scores.Count; Console.WriteLine(avg.ToString("F2")); // 7.67 ``` Tổng là 8 + 6 + 9 = 23, chia cho 3 học sinh ra 7.67. ## Lưu ý về thứ tự và khi sửa trong lúc duyệt - Thứ tự duyệt thường trùng với thứ tự thêm vào, nhưng **không được bảo đảm**. Nếu cần thứ tự cố định, dùng `SortedDictionary` hoặc sắp xếp bằng LINQ `OrderBy`. - Không thêm hoặc xóa phần tử của Dictionary bên trong vòng `foreach` đang duyệt chính nó, vì sẽ gây `InvalidOperationException`. Hãy thu thập các khóa cần xóa vào một danh sách rồi xóa sau khi duyệt xong. ## Hoạt động: Ba cách duyệt bảng điểm Mô phỏng dưới đây dùng bảng điểm ba ngăn: An 8, Bình 6, Chi 9. Hãy thao tác theo thứ tự sau, bấm **Bước tiếp** để chạy từng dòng: - Mở tab **foreach KeyValuePair**. Qua ba lần lặp, mỗi lần `foreach` lấy ra một cặp: `kv.Key = "An"`, `kv.Value = 8`, rồi "Bình" với 6, rồi "Chi" với 9. Thẻ `kv (KeyValuePair)` hiện hai dòng Key và Value, ngăn đang xét được tô sáng và các ngăn đã duyệt chuyển sang màu xanh. Mỗi lần lặp in ra một dòng như `An: 8`. - Chuyển sang tab **Keys**. Chỉ các khóa được lấy ra: ở mỗi lần lặp `k` là "An", "Bình", "Chi" và được in ra. Ô "Các khóa đã lấy" tăng dần, cuối cùng có 3 khóa: An, Bình, Chi. Điểm số không xuất hiện. - Mở tab **Values**. Biến `sum` bắt đầu bằng 0, rồi lần lượt cộng 8 (sum = 8), cộng 6 (sum = 14), cộng 9 (sum = 23). Sau đó `avg = 23 / 3 = 7.67` và kết quả `7.67` được in ra. ``` <iframe src="https://codegym-vn.github.io/programming-course-demos/c-sharp-ung-dung/cau-truc-du-lieu-nang-cao-collections/thao-tac-nang-cao-voi-dictionary-k-v-va-lua-chon-collections/duyet-qua-dictionary-k-v/" title="Duyệt qua Dictionary" style="border:0;" allowfullscreen></iframe> ``` Điều rút ra: `foreach` trên Dictionary cho mỗi lần lặp một cặp `KeyValuePair`. Khi chỉ cần một nửa dữ liệu, dùng `Keys` hoặc `Values` cho gọn và rõ ý. ## Mở rộng: Duyệt bằng LINQ LINQ cho phép lọc và sắp xếp ngay khi duyệt. Mỗi phần tử mà LINQ xử lý vẫn là một `KeyValuePair`. ```csharp using System; using System.Collections.Generic; using System.Linq; public class Program { public static void Main() { var scores = new Dictionary<string, int> { ["An"] = 8, ["Bình"] = 6, ["Chi"] = 9 }; foreach (var kv in scores.Where(p => p.Value >= 8).OrderBy(p => p.Key)) { Console.WriteLine(kv.Key + ": " + kv.Value); } // An: 8 // Chi: 9 } } ``` ## Tóm tắt - `foreach (var kv in dict)` trả về từng `KeyValuePair` với `Key` và `Value`. - `dict.Keys` chỉ chứa các khóa, `dict.Values` chỉ chứa các giá trị. - Chọn cách duyệt theo nhu cầu: cần cả hai thì duyệt cặp, cần một nửa thì dùng `Keys` hoặc `Values`. - Thứ tự duyệt không được bảo đảm. Cần thứ tự cố định thì dùng `SortedDictionary` hoặc `OrderBy`. - Không thêm hoặc xóa phần tử của Dictionary trong lúc đang `foreach` chính nó. - LINQ giúp lọc và sắp xếp gọn khi duyệt.
A12: 11 | B12: 1. Cấu trúc dữ liệu nâng cao: Collections | C12: Thao tác nâng cao với Dictionary<K,V> và lựa chọn Collections | D12: So sánh List<T> và Dictionary<K,V>: Khi nào sử dụng cái nào? | E12: Bài đọc | F12: Nên làm | G12: Done | H12: Chọn đúng cấu trúc theo nhu cầu: tra theo khóa, lấy theo vị trí, hay cần giữ giá trị trùng. | I12: 2 cột song song, 3 tab | J12: Trái dãy ô List, phải tủ ngăn Dictionary. Dưới mỗi cột là bảng điểm số bước; bước cuối gắn cờ 'phù hợp hơn' cho cột thắng ở tình huống đó. | K12: H01, H02, H22 | L12: Tra theo mã | Lấy phần tử thứ 3 | Lưu giá trị trùng | M12: Tra theo mã (8 phần tử, tìm phần tử thứ 6): List quét 6 bước, Dictionary 1 bước → Dictionary phù hợp. Lấy phần tử thứ 3: List dùng list[2] trong 1 bước; Dictionary không có chỉ số vị trí, phải duyệt → List phù hợp. Lưu giá trị trùng: List chứa "An", "An" bình thường; Dictionary Add khóa "An" lần 2 → ArgumentException → khóa phải duy nhất. Bước cuối: bảng tổng hợp 3 tình huống. | N12: 8 sản phẩm SP01..SP08 | O12: List: thứ tự và vị trí. Dictionary: tra nhanh theo khóa duy nhất. Có thể kết hợp, ví dụ Dictionary<string, List<T>>. | P12: Số bước được đếm từ dữ liệu thật trong mô phỏng. | Q12: c-sharp-ung-dung/cau-truc-du-lieu-nang-cao-collections/thao-tac-nang-cao-voi-dictionary-k-v-va-lua-chon-collections/so-sanh-list-t-va-dictionary-k-v-khi-nao-su-dung-cai-nao/index.html | R12: https://codegym-vn.github.io/programming-course-demos/c-sharp-ung-dung/cau-truc-du-lieu-nang-cao-collections/thao-tac-nang-cao-voi-dictionary-k-v-va-lua-chon-collections/so-sanh-list-t-va-dictionary-k-v-khi-nao-su-dung-cai-nao/ | V12: So sánh List<T> và Dictionary<K,V>: Khi nào sử dụng cái nào? Trong quá trình phát triển ứng dụng C#, việc lựa chọn cấu trúc dữ liệu phù hợp là một trong những quyết định quan trọng nhất ảnh hưởng đến hiệu suất và khả năng bảo trì của mã nguồn. Hai trong số các collection được sử dụng phổ biến nhất là List<T> và Dictionary<K,V>. Mặc dù cả hai đều dùng để lưu trữ tập hợp các đối tượng, chúng lại có những đặc tính và ưu điểm riêng, phù hợp với các tình huống sử dụng khác nhau. Trang này sẽ giúp bạn hiểu rõ sự khác biệt giữa chúng và đưa ra lựa chọn tối ưu cho từng bài toán cụ thể. List<T>: Lưu trữ có thứ tự và truy cập theo chỉ mục List<T> là một collection linh hoạt, đại diện cho một danh sách các đối tượng có thể thay đổi kích thước. Nó được xây dựng dựa trên một mảng động, cho phép bạn thêm, xóa và truy cập các phần tử một cách dễ dàng. Ưu điểm của List<T> Duy trì thứ tự chèn (Insertion Order): Các phần tử trong List<T> được lưu trữ theo đúng thứ tự mà chúng được thêm vào. Điều này rất quan trọng khi bạn cần bảo toàn trình tự của dữ liệu. Truy cập nhanh chóng theo chỉ mục: Bạn có thể truy cập bất kỳ phần tử nào trong danh sách bằng chỉ mục số nguyên (bắt đầu từ 0) của nó. Thao tác này có độ phức tạp thời gian là O(1) (hằng số), nghĩa là thời gian truy cập không phụ thuộc vào kích thước của danh sách. Linh hoạt trong việc thêm/xóa ở cuối: Việc thêm một phần tử vào cuối List<T> hoặc xóa phần tử cuối cùng thường rất hiệu quả, với độ phức tạp thời gian trung bình là O(1). Mặc dù đôi khi cần tái cấp phát bộ nhớ khi danh sách đầy, nhưng cơ chế này được tối ưu để hiệu quả trong hầu hết các trường hợp. Dễ dàng duyệt qua:List<T> có thể được duyệt qua một cách tuần tự bằng vòng lặp for hoặc foreach, rất tiện lợi khi bạn cần xử lý từng phần tử theo thứ tự. Khi nào nên chọn List<T>? Bạn nên chọn List<T> khi: Bạn cần một danh sách đơn giản các đối tượng mà thứ tự của chúng là quan trọng. Bạn chủ yếu truy cập các phần tử theo vị trí (chỉ mục) hoặc duyệt qua toàn bộ danh sách. Bạn thường xuyên thêm hoặc xóa các phần tử ở cuối danh sách. Bạn không cần tìm kiếm các phần tử dựa trên một "khóa" duy nhất, mà chủ yếu là duyệt hoặc tìm kiếm tuần tự. Ví dụ: // Danh sách các tên học sinh, thứ tự có thể quan trọng (ví dụ: thứ tự đăng ký) List<string> tenHocSinh = new List<string>(); tenHocSinh.Add("Nguyễn Văn A"); tenHocSinh.Add("Trần Thị B"); tenHocSinh.Add("Lê Minh C"); // Truy cập theo chỉ mục Console.WriteLine($"Học sinh đầu tiên: {tenHocSinh[0]}"); // Nguyễn Văn A // Danh sách các bước trong một quy trình List<string> cacBuocQuyTrinh = new List<string> { "Khởi tạo", "Xử lý dữ liệu", "Ghi kết quả", "Hoàn thành" }; Dictionary<K,V>: Lưu trữ theo cặp khóa-giá trị và tìm kiếm nhanh Dictionary<K,V> là một collection lưu trữ dữ liệu dưới dạng các cặp khóa-giá trị (key-value pairs). Mỗi khóa phải là duy nhất và được sử dụng để truy xuất giá trị tương ứng. Dictionary<K,V> được triển khai bằng cách sử dụng bảng băm (hash table), mang lại hiệu suất tìm kiếm vượt trội. Ưu điểm của Dictionary<K,V> Truy cập nhanh chóng theo khóa: Đây là ưu điểm nổi bật nhất của Dictionary<K,V>. Việc tìm kiếm, thêm hoặc xóa một phần tử dựa trên khóa có độ phức tạp thời gian trung bình là O(1). Điều này làm cho Dictionary<K,V> cực kỳ hiệu quả khi bạn cần truy xuất dữ liệu nhanh chóng dựa trên một định danh duy nhất. Lưu trữ dữ liệu có quan hệ:Dictionary<K,V> lý tưởng để lưu trữ các tập dữ liệu mà mỗi "bản ghi" có thể được xác định bằng một khóa duy nhất, tạo ra một ánh xạ rõ ràng giữa khóa và giá trị. Đảm bảo tính duy nhất của khóa:Dictionary<K,V> tự động đảm bảo rằng mỗi khóa chỉ xuất hiện một lần. Nếu bạn cố gắng thêm một khóa đã tồn tại, nó sẽ gây ra lỗi hoặc bạn có thể cập nhật giá trị của khóa đó. Khi nào nên chọn Dictionary<K,V>? Bạn nên chọn Dictionary<K,V> khi: Bạn cần tìm kiếm, truy cập hoặc thao tác dữ liệu cực kỳ nhanh chóng dựa trên một giá trị định danh duy nhất (khóa). Bạn cần lưu trữ các đối tượng có cấu trúc bản ghi, nơi mỗi bản ghi có một "ID" hoặc "tên" duy nhất. Thứ tự của các phần tử không quan trọng hoặc không cần phải được duy trì. Bạn cần một ánh xạ (mapping) giữa một khóa và một giá trị. Ví dụ: // Danh sách người dùng, truy cập nhanh bằng ID Dictionary<int, string> danhSachNguoiDung = new Dictionary<int, string>(); danhSachNguoiDung.Add(101, "Alice"); danhSachNguoiDung.Add(102, "Bob"); danhSachNguoiDung.Add(103, "Charlie"); // Truy cập nhanh bằng khóa Console.WriteLine($"Tên người dùng có ID 102: {danhSachNguoiDung[102]}"); // Bob // Cấu hình ứng dụng Dictionary<string, string> cauHinhUngDung = new Dictionary<string, string> { { "Theme", "Dark" }, { "LogLevel", "Info" }, { "DatabaseConnection", "Server=localhost;..." } }; Console.WriteLine($"Chủ đề hiện tại: {cauHinhUngDung["Theme"]}"); // Dark Để tìm hiểu thêm về cách duyệt qua các phần tử của Dictionary<K,V>, bạn có thể tham khảo bài đọc "Duyệt qua Dictionary<K,V>" trong cùng bài học này. Các yếu tố cần cân nhắc khi lựa chọn Khi quyết định giữa List<T> và Dictionary<K,V>, hãy xem xét các yếu tố sau: Yêu cầu về thứ tự Nếu thứ tự chèn của các phần tử là quan trọng và cần được duy trì, hãy chọn List<T>. Nếu thứ tự không quan trọng hoặc có thể thay đổi, Dictionary<K,V> vẫn là một lựa chọn tốt nếu phù hợp với các yếu tố khác. Cách truy cập dữ liệu Nếu bạn chủ yếu truy cập dữ liệu bằng chỉ mục số nguyên (ví dụ: phần tử thứ 5, phần tử cuối cùng) hoặc duyệt tuần tự, List<T> là lựa chọn tối ưu. Nếu bạn cần truy cập dữ liệu nhanh chóng bằng một giá trị định danh duy nhất (khóa), Dictionary<K,V> là lựa chọn vượt trội. Hiệu suất Tìm kiếm:Dictionary<K,V> cung cấp hiệu suất tìm kiếm O(1) (trung bình) theo khóa, trong khi List<T> yêu cầu tìm kiếm tuần tự O(n) theo giá trị (trừ khi bạn biết chỉ mục). Thêm/Xóa: Thêm/xóa ở cuối List<T> là O(1) (trung bình). Thêm/xóa ở giữa List<T> là O(n). Thêm/xóa trong Dictionary<K,V> là O(1) (trung bình) cho một khóa đã biết. Bộ nhớ List<T> thường sử dụng ít bộ nhớ hơn một chút so với Dictionary<K,V> cho cùng một số lượng phần tử, vì Dictionary<K,V> cần lưu trữ cả khóa và giá trị, cùng với cấu trúc bảng băm để quản lý các cặp này. Tuy nhiên, đối với hầu hết các ứng dụng, sự khác biệt này không đáng kể trừ khi bạn làm việc với tập dữ liệu cực lớn. Tính duy nhất của phần tử/khóa List<T> cho phép các phần tử trùng lặp. Dictionary<K,V> yêu cầu các khóa phải là duy nhất. Nếu bạn cần đảm bảo tính duy nhất của một trường nào đó, Dictionary<K,V> có thể hỗ trợ điều này thông qua khóa. Kết luận Không có "cấu trúc dữ liệu tốt nhất" tuyệt đối; chỉ có cấu trúc dữ liệu phù hợp nhất cho từng tình huống cụ thể. List<T> xuất sắc trong việc quản lý các tập hợp có thứ tự và truy cập theo chỉ mục, trong khi Dictionary<K,V> không thể đánh bại về tốc độ truy xuất dữ liệu theo khóa. Bằng cách hiểu rõ đặc tính, ưu nhược điểm và yêu cầu của bài toán, bạn sẽ có thể đưa ra lựa chọn sáng suốt, xây dựng các ứng dụng C# hiệu quả và mạnh mẽ hơn. | W12: # So sánh List<T> và Dictionary<K,V>: Khi nào sử dụng cái nào? ## Mục tiêu học tập Sau bài học này, bạn có thể: - Mô tả đặc điểm chính của `List<T>` (có thứ tự, có chỉ số) và `Dictionary<TKey, TValue>` (tra theo khóa duy nhất). - Chọn đúng cấu trúc khi cần tra theo mã, lấy theo vị trí hoặc lưu giá trị trùng. - So sánh số bước cần để tìm một phần tử trong `List` và trong `Dictionary`. - Giải thích vì sao `Dictionary` báo lỗi khi thêm khóa trùng còn `List` thì không. - Quan sát hai cấu trúc cùng xử lý một nhu cầu bằng hoạt động mô phỏng. ## Hai cấu trúc, hai thế mạnh Cả `List<T>` và `Dictionary<TKey, TValue>` đều chứa nhiều phần tử, nhưng cách tổ chức khác nhau nên hợp với những việc khác nhau. Không có cấu trúc "tốt nhất" tuyệt đối, chỉ có cấu trúc **phù hợp nhất** với nhu cầu. ### List<T>: có thứ tự và có chỉ số `List<T>` là danh sách có thể đổi kích thước, các phần tử xếp theo thứ tự thêm vào và mỗi phần tử có một **chỉ số** bắt đầu từ 0. - Lấy phần tử theo chỉ số (`list[2]`) rất nhanh: nhảy thẳng tới ô đó. - Cho phép giá trị **trùng lặp**. - Muốn tìm một giá trị khi không biết vị trí, phải quét từ đầu, tức là duyệt từng phần tử. ```csharp var tenHocSinh = new List<string> { "An", "Bình", "Chi" }; Console.WriteLine(tenHocSinh[0]); // An ``` ### Dictionary<TKey, TValue>: tra nhanh theo khóa `Dictionary` lưu các cặp khóa - giá trị. Mỗi khóa phải **duy nhất** và dùng để tìm giá trị tương ứng. - Tra, thêm, xóa theo khóa rất nhanh (trung bình gần như không phụ thuộc số phần tử), vì đi thẳng tới "ngăn" có nhãn đó. - **Khóa không được trùng.** Thêm khóa đã có bằng `Add()` sẽ ném `ArgumentException`. - **Không có chỉ số vị trí.** Không có `dict[2]` để lấy "phần tử thứ 3", và thứ tự duyệt không được bảo đảm. ```csharp var tenNguoiDung = new Dictionary<int, string> { [101] = "Alice", [102] = "Bob" }; Console.WriteLine(tenNguoiDung[102]); // Bob ``` ## Bảng so sánh | Tiêu chí | `List<T>` | `Dictionary<TKey, TValue>` | |---|---|---| | Tra theo mã/khóa | Phải quét từng phần tử | Đi thẳng tới ngăn, rất nhanh | | Lấy theo vị trí | `list[i]`, nhanh | Không có chỉ số vị trí | | Giá trị trùng | Cho phép | Khóa phải duy nhất | | Thứ tự | Theo thứ tự thêm vào | Không bảo đảm | | Bộ nhớ | Ít hơn | Nhiều hơn một chút (lưu cả khóa và cấu trúc tra cứu) | ## Cách chọn nhanh - Cần tra thường xuyên theo một mã định danh (mã sản phẩm, ID, tên đăng nhập): chọn `Dictionary`. - Cần giữ thứ tự, lấy theo vị trí hoặc duyệt hết từ đầu đến cuối: chọn `List`. - Cần lưu cả giá trị trùng nhau: chọn `List`. - Cần vừa tra theo khóa vừa gom nhiều phần tử dưới mỗi khóa: kết hợp, ví dụ `Dictionary<string, List<T>>`. ## Hoạt động: Cùng một nhu cầu, hai cấu trúc Mô phỏng dưới đây chia hai cột: cột trái là `List<string>`, cột phải là `Dictionary<string, int>`. Hai cột cùng xử lý một nhu cầu. Hãy thao tác theo thứ tự sau, bấm **Bước tiếp** để hai cột cùng chạy: - Mở tab **Tra theo mã**. Cần tìm sản phẩm SP06 trong 8 sản phẩm (SP01 đến SP08). Cột trái (List) phải so sánh lần lượt SP01, SP02, ... cho đến SP06, mất 6 bước, các ô đã loại được đánh dấu mờ. Cột phải (Dictionary) đi thẳng tới ngăn SP06 qua `dict["SP06"]`, chỉ 1 bước. - Chuyển sang tab **Lấy phần tử thứ 3**. Cột trái dùng `list[2]` (chỉ số bắt đầu từ 0) nhảy thẳng tới ô số 2, lấy được "SP03" chỉ trong 1 bước. Cột phải không có `dict[2]`, nên phải duyệt và đếm tới ngăn thứ 3, mất 3 bước, và thứ tự duyệt cũng không được bảo đảm. - Mở tab **Lưu giá trị trùng**. Cả hai bên cùng lưu "An" hai lần. Cột trái: List nhận cả hai, có 2 phần tử. Cột phải: lần `Add("An", 2)` thứ hai bị lỗi, khung đỏ hiện `ArgumentException` với thông điệp `An item with the same key has already been added. Key: An`, và Dictionary chỉ giữ 1 ngăn "An". ``` <iframe src="https://codegym-vn.github.io/programming-course-demos/c-sharp-ung-dung/cau-truc-du-lieu-nang-cao-collections/thao-tac-nang-cao-voi-dictionary-k-v-va-lua-chon-collections/so-sanh-list-t-va-dictionary-k-v-khi-nao-su-dung-cai-nao/" title="List hay Dictionary?" style="border:0;" allowfullscreen></iframe> ``` Điều rút ra: mỗi cấu trúc thắng ở một việc. Dictionary thắng khi tra theo khóa (1 bước so với 6), List thắng khi lấy theo vị trí (1 bước so với 3) và khi cần lưu giá trị trùng (2 phần tử so với 1). ## Tóm tắt - `List<T>` có thứ tự, có chỉ số, cho phép giá trị trùng. Tìm theo giá trị phải quét từng phần tử. - `Dictionary<TKey, TValue>` tra nhanh theo khóa duy nhất nhưng không có chỉ số vị trí. - Thêm khóa trùng bằng `Add()` làm `Dictionary` ném `ArgumentException`. - Tra theo mã: chọn `Dictionary`. Lấy theo vị trí hoặc giữ giá trị trùng: chọn `List`. - Có thể kết hợp hai cấu trúc, ví dụ `Dictionary<string, List<T>>`, khi bài toán cần cả hai.
A13: 12 | B13: 2. Xử lý lỗi và Ngoại lệ (Exception Handling) Cơ bản | C13: Giới thiệu về Exception và Tầm quan trọng | D13: Exception là gì? | E13: Bài đọc | F13: Nên làm | G13: Done | H13: Thấy exception là một đối tượng được 'ném' ra khi có lỗi lúc chạy, và nếu không ai bắt thì chương trình dừng ngay tại đó. | I13: 1 cột, có ô nhập chuỗi (chips gợi ý) | J13: Mã nguồn tô dòng đang chạy. Khi lỗi, thẻ Exception đỏ bật lên cạnh dòng gây lỗi; các dòng phía sau mờ đi với nhãn 'không được chạy'; console in thông báo lỗi. | K13: H03 | L13: 1 tab, ô nhập 'input' (mặc định abc; gợi ý: 20, abc, rỗng, -5) | M13: Console.Write("Nhập tuổi: "); input = giá trị trong ô nhập. int age = int.Parse(input) → với "abc", .NET tạo một đối tượng FormatException và ném ra. Thẻ đỏ: FormatException, "The input string 'abc' was not in a correct format." Không có try-catch nên chương trình dừng; hai dòng in phía sau mờ đi. Với "20": chạy hết và in "Năm sau bạn 21 tuổi". Với "-5": không lỗi (chỉ là dữ liệu sai nghiệp vụ, không phải exception). | N13: Ô nhập: abc (mặc định), 20, rỗng, -5 | O13: Exception là sự cố lúc chạy, được biểu diễn bằng một đối tượng; không bắt thì chương trình dừng. Lỗi định dạng khác lỗi nghiệp vụ. | P13: Thông điệp theo .NET 8: "The input string 'abc' was not in a correct format." (bản cũ: "Input string was not in a correct format."). Ô nhập cần cho phép chuỗi rỗng và dấu '-'. | Q13: c-sharp-ung-dung/xu-ly-loi-va-ngoai-le-exception-handling-co-ban/gioi-thieu-ve-exception-va-tam-quan-trong/exception-la-gi/index.html | R13: https://codegym-vn.github.io/programming-course-demos/c-sharp-ung-dung/xu-ly-loi-va-ngoai-le-exception-handling-co-ban/gioi-thieu-ve-exception-va-tam-quan-trong/exception-la-gi/ | V13: Exception là gì? Trong lập trình, mọi thứ không phải lúc nào cũng diễn ra suôn sẻ theo kịch bản lý tưởng. Sẽ có những lúc chương trình của bạn gặp phải các tình huống bất ngờ, nằm ngoài luồng xử lý thông thường. Đây chính là lúc khái niệm "Exception" trở nên vô cùng quan trọng. Định nghĩa Exception Exception (ngoại lệ) là một sự kiện xảy ra trong quá trình thực thi chương trình (runtime) làm gián đoạn luồng bình thường của lệnh. Khi một exception xảy ra, chương trình sẽ ngừng thực hiện các lệnh tiếp theo trong khối mã hiện tại và tìm kiếm một cơ chế để xử lý sự kiện bất thường này. Hãy hình dung chương trình của bạn như một dây chuyền sản xuất. Bình thường, các sản phẩm sẽ tuần tự đi qua từng công đoạn. Nhưng đột nhiên, một máy móc bị hỏng, hoặc một nguyên liệu không đạt chuẩn được đưa vào. Sự kiện "máy hỏng" hay "nguyên liệu lỗi" chính là một exception. Nó làm gián đoạn dây chuyền, và nếu không được xử lý, toàn bộ dây chuyền có thể ngừng hoạt động hoặc tạo ra sản phẩm lỗi. Trong lập trình, một exception có thể phát sinh từ nhiều nguyên nhân khác nhau, chẳng hạn như: Dữ liệu đầu vào không hợp lệ (ví dụ: người dùng nhập chữ vào ô yêu cầu số). Cố gắng truy cập một tài nguyên không tồn tại (ví dụ: đọc một tập tin đã bị xóa). Lỗi logic toán học (ví dụ: chia một số cho 0). Vấn đề về bộ nhớ hoặc hệ thống. Mục tiêu của việc xử lý exception là để chương trình có thể "bắt" được các sự kiện bất thường này và thực hiện các hành động khắc phục, thay vì bị dừng đột ngột (crash). Phân biệt Lỗi Biên dịch và Lỗi Chạy Để hiểu rõ hơn về exception, chúng ta cần phân biệt hai loại lỗi cơ bản trong lập trình: Lỗi Biên dịch (Compile-time Errors) Lỗi biên dịch xảy ra trong giai đoạn biên dịch mã nguồn thành mã máy hoặc mã trung gian (như IL trong C#). Đây thường là các lỗi về cú pháp, ngữ pháp của ngôn ngữ lập trình hoặc lỗi kiểu dữ liệu. Ví dụ: Thiếu dấu chấm phẩy (;) ở cuối câu lệnh. Khai báo một biến nhưng chưa định nghĩa kiểu dữ liệu. Gọi một phương thức không tồn tại hoặc sai tên. // Ví dụ lỗi biên dịch: Thiếu dấu chấm phẩy public class MyProgram { public static void Main(string[] args) { Console.WriteLine("Hello World") // Lỗi: Thiếu ';' } } Trình biên dịch (compiler) sẽ phát hiện ra những lỗi này và không cho phép chương trình được xây dựng thành công. Bạn sẽ nhận được thông báo lỗi từ IDE (như Visual Studio) và không thể chạy ứng dụng cho đến khi các lỗi này được sửa. Lỗi biên dịch ngăn chặn chương trình khởi động hoàn toàn. Lỗi Chạy (Runtime Errors) Lỗi chạy, hay lỗi thời gian thực thi, xảy ra khi chương trình đã được biên dịch thành công và đang chạy. Những lỗi này không thể được phát hiện bởi trình biên dịch vì chúng thường phụ thuộc vào dữ liệu đầu vào, trạng thái của hệ thống hoặc các điều kiện phát sinh trong quá trình chương trình hoạt động. Ví dụ: Chia một số cho 0 (ví dụ: 10 / 0). Cố gắng truy cập một phần tử ngoài giới hạn của mảng. Cố gắng sử dụng một đối tượng chưa được khởi tạo (null reference). Định dạng dữ liệu không hợp lệ khi chuyển đổi kiểu (ví dụ: chuyển "abc" thành số nguyên). // Ví dụ lỗi chạy: Chia cho 0 public class MyProgram { public static void Main(string[] args) { int numerator = 10; int denominator = 0; int result = numerator / denominator; // Lỗi này sẽ xảy ra khi chương trình chạy Console.WriteLine(result); } } Khi một lỗi chạy xảy ra mà không được xử lý, nó sẽ tạo ra một Exception. Nếu exception này không được "bắt" và quản lý, chương trình sẽ dừng đột ngột và hiển thị thông báo lỗi cho người dùng (hoặc ghi vào log hệ thống). Các exception chính là cơ chế để lập trình viên có thể chủ động đối phó với những tình huống bất ngờ này. Vai trò của Exception trong việc Thông báo và Quản lý các Tình huống Bất thường Exception không chỉ là một sự kiện lỗi, mà còn là một công cụ mạnh mẽ để thông báo và quản lý các tình huống bất thường trong chương trình C#. 1. Thông báo lỗi một cách có cấu trúc Khi một tình huống bất thường xảy ra, thay vì chỉ trả về một mã lỗi hoặc giá trị null khó hiểu, hệ thống sẽ "ném" (throw) một đối tượng Exception. Đối tượng này chứa đựng rất nhiều thông tin hữu ích về lỗi, bao gồm: Loại Exception: Cho biết cụ thể lỗi gì đã xảy ra (ví dụ: DivideByZeroException, FormatException). Thông điệp lỗi (Message): Một chuỗi mô tả chi tiết về nguyên nhân lỗi. Stack Trace: Chuỗi các hàm đã được gọi cho đến khi exception xảy ra, giúp bạn xác định chính xác vị trí lỗi trong mã nguồn. Nhờ có cấu trúc này, việc xác định nguyên nhân và vị trí lỗi trở nên dễ dàng hơn rất nhiều so với các phương pháp xử lý lỗi truyền thống chỉ dựa vào mã trả về. 2. Quản lý và phục hồi chương trình Vai trò quan trọng nhất của exception là cho phép lập trình viên "bắt" (catch) các lỗi chạy và thực hiện các hành động quản lý phù hợp. Thay vì để chương trình bị crash, bạn có thể: Ghi nhật ký (Log) lỗi: Lưu trữ thông tin chi tiết về exception vào một tệp log để phân tích sau này, giúp cải thiện chất lượng ứng dụng. Thông báo cho người dùng: Hiển thị một thông báo thân thiện, dễ hiểu cho người dùng về sự cố đã xảy ra, thay vì một màn hình lỗi kỹ thuật. Phục hồi hoặc thay thế: Cố gắng khắc phục tình huống (ví dụ: thử lại thao tác, sử dụng giá trị mặc định) hoặc chuyển hướng chương trình sang một luồng xử lý an toàn khác. Đóng ứng dụng một cách an toàn: Trong trường hợp không thể phục hồi, đảm bảo rằng mọi tài nguyên đã được giải phóng và dữ liệu được lưu trữ trước khi chương trình kết thúc. Việc xử lý exception hiệu quả giúp tăng tính ổn định, độ bền và trải nghiệm người dùng của ứng dụng. Nó cho phép chương trình của bạn "sống sót" qua những tình huống không mong muốn và tiếp tục hoạt động hoặc kết thúc một cách có kiểm soát. Trong các bài học tiếp theo, chúng ta sẽ đi sâu vào các loại exception phổ biến trong C# và cách sử dụng cấu trúc try/catch để bắt và xử lý chúng một cách hiệu quả. | W13: # Exception là gì? ## Mục tiêu học tập Sau bài học này, bạn có thể: - Giải thích exception (ngoại lệ) là một sự cố lúc chạy, được biểu diễn bằng một đối tượng. - Phân biệt lỗi biên dịch (compile-time) với lỗi lúc chạy (runtime). - Nêu những thông tin một đối tượng exception mang theo: loại, thông điệp, dấu vết. - Nhận ra rằng exception không ai bắt thì chương trình dừng ngay tại dòng gây lỗi. - Quan sát đường đi của chương trình khi nhập tuổi hợp lệ và không hợp lệ bằng hoạt động mô phỏng. ## Exception là gì **Exception** (ngoại lệ) là một sự cố xảy ra **trong lúc chương trình đang chạy** và làm gián đoạn luồng thực thi bình thường. Khi sự cố xảy ra, .NET tạo ra một **đối tượng exception** mô tả lỗi rồi "ném" (throw) nó ra. Nếu không có đoạn mã nào "bắt" (catch) đối tượng này, chương trình dừng ngay tại dòng gây lỗi. Hãy hình dung một dây chuyền sản xuất. Bình thường sản phẩm đi qua từng công đoạn. Khi một máy hỏng, dây chuyền bị gián đoạn: sự kiện "máy hỏng" chính là exception. Nếu không ai xử lý, cả dây chuyền dừng. Một số nguyên nhân thường gặp: - Dữ liệu đầu vào sai (nhập chữ vào ô cần số). - Truy cập thứ không tồn tại (đọc tập tin đã bị xóa). - Phép tính không hợp lệ (chia số nguyên cho 0). - Dùng một biến `null` như thể nó là một đối tượng. ## Lỗi biên dịch và lỗi lúc chạy | | Lỗi biên dịch | Lỗi lúc chạy | |---|---|---| | Khi nào xảy ra | Lúc build, trước khi chạy | Khi chương trình đang chạy | | Nguyên nhân | Sai cú pháp, sai tên, sai kiểu | Phụ thuộc dữ liệu hoặc hoàn cảnh | | Ai phát hiện | Trình biên dịch | Chỉ biết khi chạy | | Hậu quả | Không chạy được chương trình | Sinh ra exception | ```csharp // Lỗi biên dịch: thiếu dấu chấm phẩy, không build được Console.WriteLine("Xin chào") ``` ```csharp using System; public class Program { public static void Main() { int a = 10; int b = 0; int r = a / b; // build được, nhưng khi chạy ném DivideByZeroException Console.WriteLine(r); } } ``` Exception thuộc nhóm lỗi lúc chạy: trình biên dịch không thể biết trước người dùng sẽ nhập gì hay hệ thống ở trạng thái nào. ## Exception mang theo thông tin gì Vì exception là một đối tượng, nó chứa nhiều thông tin hữu ích: - **Loại exception:** cho biết chuyện gì đã xảy ra, ví dụ `FormatException`, `DivideByZeroException`. - **Thông điệp (`Message`):** câu mô tả nguyên nhân. - **Dấu vết ngăn xếp (`StackTrace`):** các phương thức đã được gọi cho đến khi lỗi xảy ra, giúp tìm đúng vị trí lỗi. Nhờ đó, việc tìm lỗi dễ hơn nhiều so với cách chỉ trả về một mã lỗi khó hiểu. Bạn sẽ học cách bắt và đọc các thông tin này ở các bài sau. ## Hoạt động: Nhập tuổi và xem chuyện gì xảy ra Mô phỏng dưới đây chạy đoạn mã đọc một chuỗi nhập vào rồi đổi thành số bằng `int.Parse`. Bạn có thể chọn một giá trị gợi ý (`20`, `abc`, ô trống, `-5`) hoặc tự gõ vào ô `input`. Hãy thao tác theo thứ tự sau, bấm **Bước tiếp** để chạy từng dòng: - Mở tab **Nhập tuổi**. Trước hết thử `abc` (giá trị mặc định). Biến `input` nhận chuỗi "abc". Đến dòng `int.Parse(input)`, .NET không đổi được nên ném `FormatException`: thẻ lỗi đỏ hiện ra với thông điệp `The input string 'abc' was not in a correct format.` và bước "int.Parse" trên sơ đồ đường đi chuyển đỏ. - Bấm tiếp. Vì không có `try-catch` nên chương trình dừng ngay tại dòng lỗi. Bước "In kết quả" trên sơ đồ ghi "không được chạy" và khối `Console.WriteLine` phía sau bị làm mờ. - Đặt lại rồi thử `20`. `int.Parse` thành công, `age = 20`, chương trình in `Năm sau bạn 21 tuổi` và cả ba bước đều xanh. Nhập thử `-5`: chương trình vẫn chạy bình thường và in `Năm sau bạn -4 tuổi`. Tuổi âm là dữ liệu sai theo nghiệp vụ chứ không phải exception, nên ta phải tự kiểm tra. Ô trống thì giống `abc`: cũng là `FormatException`. ``` <iframe src="https://codegym-vn.github.io/programming-course-demos/c-sharp-ung-dung/xu-ly-loi-va-ngoai-le-exception-handling-co-ban/gioi-thieu-ve-exception-va-tam-quan-trong/exception-la-gi/" title="Exception là gì?" style="border:0;" allowfullscreen></iframe> ``` Điều rút ra: exception là một đối tượng được ném ra khi có sự cố lúc chạy, và nếu không ai bắt thì chương trình dừng ngay tại đó. Dữ liệu sai nghiệp vụ như tuổi âm không tự gây exception. ## Tóm tắt - Exception là sự cố lúc chạy, được biểu diễn bằng một đối tượng và được "ném" ra. - Lỗi biên dịch bị chặn trước khi chạy, còn exception chỉ xuất hiện khi chương trình đang chạy. - Đối tượng exception có loại, thông điệp (`Message`) và dấu vết (`StackTrace`). - Không ai bắt thì chương trình dừng ngay tại dòng gây lỗi, các dòng sau không chạy. - Dữ liệu sai nghiệp vụ (như tuổi âm) không tự ném exception, ta phải tự kiểm tra.
... A15: 14 | B15: 2. Xử lý lỗi và Ngoại lệ (Exception Handling) Cơ bản | C15: Giới thiệu về Exception và Tầm quan trọng | D15: Các loại Exception phổ biến trong C# | E15: Bài đọc | F15: Nên làm | G15: Done | H15: Nhận diện các exception hay gặp qua chính dòng code gây ra chúng. | I15: 1 cột, 6 tab (bộ sưu tập thẻ lỗi) | J15: Mỗi tab là một 'thẻ bài' exception: biểu tượng, tên loại, dòng code gây lỗi, thông điệp thật của .NET, một dòng 'Cách phòng tránh'. Khung bộ nhớ hiện giá trị biến dẫn tới lỗi. | K15: H03 | L15: FormatException | DivideByZeroException | IndexOutOfRangeException | NullReferenceException | InvalidCastException | OverflowException | M15: Mỗi tab 3 bước: (1) chuẩn bị dữ liệu, (2) chạy dòng gây lỗi, (3) thẻ lỗi + cách phòng tránh. Format: int.Parse("12a") → "The input string '12a' was not in a correct format." → dùng int.TryParse. DivideByZero: int a = 10, b = 0; a / b → "Attempted to divide by zero." → kiểm tra b != 0. Ghi chú: double chia 0 không lỗi mà ra ∞. IndexOutOfRange: int[] arr = new int[3]; arr[3] → "Index was outside the bounds of the array." → kiểm tra i < arr.Length. NullReference: string s = null; s.Length → "Object reference not set to an instance of an object." → kiểm tra null hoặc dùng s?.Length. InvalidCast: object o = "abc"; (int)o → "Unable to cast object of type 'System.String' to type 'System.Int32'." → dùng is/as. Overflow: checked { int x = int.MaxValue; x = x + 1; } → "Arithmetic operation resulted in an overflow." Ghi chú: không có checked thì không lỗi mà quay vòng thành số âm. | N15: Dữ liệu cố định từng tab | O15: Tên loại exception cho biết nguyên nhân; đọc tên loại là bước đầu tiên để sửa lỗi. | P15: Thông điệp theo .NET hiện đại. OverflowException chỉ xảy ra trong ngữ cảnh checked (hoặc khi Parse/Convert số quá lớn). | Q15: c-sharp-ung-dung/xu-ly-loi-va-ngoai-le-exception-handling-co-ban/gioi-thieu-ve-exception-va-tam-quan-trong/cac-loai-exception-pho-bien-trong-c-sharp/index.html | R15: https://codegym-vn.github.io/programming-course-demos/c-sharp-ung-dung/xu-ly-loi-va-ngoai-le-exception-handling-co-ban/gioi-thieu-ve-exception-va-tam-quan-trong/cac-loai-exception-pho-bien-trong-c-sharp/ | V15: Hệ thống phân cấp Exception trong C# Trong bài học trước, chúng ta đã tìm hiểu khái niệm cơ bản về Exception là gì. Để hiểu sâu hơn về cách các lỗi này được tổ chức và xử lý trong C#, chúng ta cần nắm rõ hệ thống phân cấp Exception. Trong C#, tất cả các loại ngoại lệ đều kế thừa từ một lớp cơ sở duy nhất là System.Exception. Điều này có nghĩa là bất kỳ đối tượng Exception nào bạn gặp phải hoặc tạo ra đều là một phiên bản của System.Exception hoặc một lớp con của nó. Hệ thống phân cấp này rất quan trọng vì nó cho phép chúng ta bắt và xử lý các loại ngoại lệ cụ thể hoặc tổng quát hơn khi cần thiết. System.Exception là "cha đẻ" của mọi Exception. Từ lớp này, có hai nhánh chính: System.SystemException: Đây là lớp cơ sở cho hầu hết các lỗi xảy ra trong quá trình thực thi ứng dụng do Common Language Runtime (CLR) phát hiện. Các lỗi này thường liên quan đến các vấn đề nội bộ của .NET Framework hoặc các lỗi lập trình phổ biến. System.ApplicationException: Lớp này được khuyến nghị sử dụng làm lớp cơ sở cho các Exception do lập trình viên định nghĩa (custom exceptions) để phân biệt rõ ràng với các lỗi của hệ thống. Trong phạm vi bài học này, chúng ta sẽ tập trung vào một số loại System.SystemException phổ biến nhất mà bạn sẽ thường xuyên gặp phải trong quá trình phát triển ứng dụng C#. Các Exception phổ biến và cách nhận diện Việc nhận diện các loại Exception phổ biến là kỹ năng then chốt để có thể xử lý chúng một cách hiệu quả. Dưới đây là một số Exception bạn sẽ thường xuyên gặp phải, cùng với nguyên nhân và biểu hiện của chúng. DivideByZeroException DivideByZeroException xảy ra khi bạn cố gắng thực hiện phép chia một số nguyên (integer) hoặc số thập phân (decimal) cho số không (0). Đây là một lỗi toán học cơ bản mà máy tính không thể thực hiện được. Nguyên nhân: Thực hiện phép toán chia cho 0. Biểu hiện: Chương trình sẽ dừng đột ngột (crash) tại dòng code thực hiện phép chia nếu không được xử lý. Ví dụ: int tuSo = 10; int mauSo = 0; int ketQua = tuSo / mauSo; // Dòng này sẽ gây ra DivideByZeroException Console.WriteLine(ketQua); Lưu ý: Với kiểu dữ liệu dấu phẩy động (như float hoặc double), chia cho 0 sẽ không gây ra Exception mà sẽ trả về các giá trị đặc biệt như Infinity (vô cùng) hoặc NaN (Not a Number), tùy thuộc vào ngữ cảnh. DivideByZeroException chỉ xảy ra với kiểu số nguyên và decimal. FormatException FormatException xảy ra khi một giá trị không nằm trong định dạng mong đợi được truyền cho một phương thức chuyển đổi kiểu dữ liệu. Điều này thường gặp khi cố gắng chuyển đổi một chuỗi (string) thành một kiểu dữ liệu số hoặc ngày tháng. Nguyên nhân: Dữ liệu đầu vào không đúng định dạng mà phương thức chuyển đổi mong đợi. Biểu hiện: Chương trình dừng đột ngột. Ví dụ: string chuoiSo = "abc"; int soNguyen = int.Parse(chuoiSo); // Dòng này sẽ gây ra FormatException Console.WriteLine(soNguyen); Trong ví dụ trên, phương thức int.Parse() mong đợi một chuỗi có thể biểu diễn thành số nguyên. Chuỗi "abc" rõ ràng không phải là một số hợp lệ, dẫn đến FormatException. NullReferenceException NullReferenceException có lẽ là một trong những Exception phổ biến và "khó chịu" nhất đối với lập trình viên C#. Nó xảy ra khi bạn cố gắng truy cập một thành viên (phương thức hoặc thuộc tính) của một đối tượng mà tham chiếu của nó đang có giá trị null (không trỏ đến bất kỳ đối tượng nào trong bộ nhớ). Nguyên nhân: Cố gắng sử dụng một biến tham chiếu có giá trị null như thể nó đang trỏ đến một đối tượng hợp lệ. Biểu hiện: Chương trình dừng đột ngột, thường đi kèm với thông báo "Object reference not set to an instance of an object." Ví dụ: string ten = null; int doDai = ten.Length; // Dòng này sẽ gây ra NullReferenceException Console.WriteLine(doDai); Trong ví dụ này, biến ten đang giữ giá trị null. Khi bạn cố gắng truy cập thuộc tính Length của nó, hệ thống không tìm thấy đối tượng nào để truy cập, dẫn đến lỗi. Để tránh lỗi này, bạn cần đảm bảo rằng biến tham chiếu đã được khởi tạo trước khi sử dụng. IndexOutOfRangeException IndexOutOfRangeException xảy ra khi bạn cố gắng truy cập một phần tử của một mảng (array) hoặc một bộ sưu tập (collection) bằng một chỉ số (index) nằm ngoài phạm vi hợp lệ của mảng/bộ sưu tập đó. Nguyên nhân: Chỉ số truy cập nhỏ hơn 0 hoặc lớn hơn hoặc bằng số lượng phần tử của mảng/bộ sưu tập. Biểu hiện: Chương trình dừng đột ngột. Ví dụ: int[] soNguyenArr = new int[5]; // Mảng có 5 phần tử, chỉ số hợp lệ từ 0 đến 4 soNguyenArr[0] = 10; soNguyenArr[4] = 20; int giaTri = soNguyenArr[5]; // Dòng này sẽ gây ra IndexOutOfRangeException Console.WriteLine(giaTri); Ở đây, mảng soNguyenArr có kích thước 5, nghĩa là các chỉ số hợp lệ là 0, 1, 2, 3, 4. Việc cố gắng truy cập soNguyenArr[5] là không hợp lệ vì chỉ số 5 nằm ngoài phạm vi này. Việc hiểu rõ các loại Exception phổ biến này là bước đầu tiên và quan trọng nhất trong việc học cách xử lý lỗi hiệu quả. Trong các bài học tiếp theo, chúng ta sẽ đi sâu vào cách sử dụng các cấu trúc try-catch để bắt và xử lý những ngoại lệ này một cách an toàn, giúp chương trình của bạn trở nên mạnh mẽ và đáng tin cậy hơn. | W15: # Các loại Exception phổ biến trong C# ## Mục tiêu học tập Sau bài học này, bạn có thể: - Nêu được rằng mọi exception trong .NET đều kế thừa từ lớp `System.Exception`. - Nhận ra sáu exception hay gặp qua dòng code gây ra chúng. - Giải thích nguyên nhân của `FormatException`, `DivideByZeroException`, `IndexOutOfRangeException`, `NullReferenceException`, `InvalidCastException` và `OverflowException`. - Nêu cách phòng tránh phù hợp cho từng loại. - Quan sát từng exception xuất hiện ở đúng dòng gây lỗi bằng hoạt động mô phỏng. ## Hệ thống phân cấp exception Trong C#, mọi exception đều là đối tượng của lớp `System.Exception` hoặc một lớp con của nó. Nhờ vậy, sau này bạn có thể bắt một loại cụ thể hoặc bắt chung bằng `Exception`. Các exception do môi trường chạy (runtime) hoặc thư viện .NET ném ra như những loại trong bài này thường là lớp con của `System.SystemException`. Với exception tự định nghĩa, .NET hiện đại khuyên kế thừa trực tiếp từ `Exception` (không dùng `ApplicationException`). **Tên loại exception là manh mối đầu tiên** để sửa lỗi: đọc tên là biết ngay vấn đề thuộc nhóm nào. ## Sáu exception hay gặp ### FormatException Xảy ra khi chuỗi **không đúng định dạng** mà phương thức chuyển đổi mong đợi. ```csharp string s = "12a"; int n = int.Parse(s); // FormatException: The input string '12a' was not in a correct format. ``` Phòng tránh: dùng `int.TryParse` để kiểm tra trước, nó không ném lỗi mà trả về `false`. ### DivideByZeroException Xảy ra khi **chia số nguyên cho 0**. ```csharp int a = 10; int b = 0; int r = a / b; // DivideByZeroException: Attempted to divide by zero. ``` Lưu ý: với `double`, phép `10.0 / 0` không ném lỗi mà cho kết quả vô cực (`Infinity`). Phòng tránh: kiểm tra `b != 0` trước khi chia. ### IndexOutOfRangeException Xảy ra khi truy cập mảng bằng **chỉ số ngoài phạm vi**. Chỉ số bắt đầu từ 0 nên mảng 3 phần tử chỉ có chỉ số 0, 1, 2. ```csharp int[] arr = new int[3]; int x = arr[3]; // IndexOutOfRangeException: Index was outside the bounds of the array. ``` Phòng tránh: kiểm tra `i < arr.Length` trước khi truy cập. ### NullReferenceException Xảy ra khi dùng dấu chấm trên một biến đang là `null`, tức là không trỏ tới đối tượng nào. ```csharp string s = null; int n = s.Length; // NullReferenceException: Object reference not set to an instance of an object. ``` Phòng tránh: kiểm tra `s != null` hoặc dùng toán tử `s?.Length`. ### InvalidCastException Xảy ra khi **ép kiểu không hợp lệ**: biến `object` đang chứa kiểu này nhưng bị ép về kiểu khác. ```csharp object o = "abc"; int n = (int)o; // InvalidCastException: Unable to cast object of type 'System.String' to type 'System.Int32'. ``` Phòng tránh: kiểm tra bằng `is` (ví dụ `if (o is int)`) hoặc dùng `as` trước khi ép. ### OverflowException Xảy ra khi phép tính **tràn số** trong ngữ cảnh kiểm tra tràn, ví dụ khối `checked`. ```csharp checked { int x = int.MaxValue; // 2147483647 x = x + 1; // OverflowException: Arithmetic operation resulted in an overflow. } ``` Nếu không có `checked`, mặc định C# không kiểm tra tràn số và kết quả quay vòng thành số âm (`-2147483648`). Phòng tránh: dùng kiểu lớn hơn như `long`, hoặc kiểm tra giới hạn trước khi cộng. ## Bảng tóm lược | Exception | Nguyên nhân | Cách phòng tránh | |---|---|---| | `FormatException` | Chuỗi sai định dạng khi đổi kiểu | `int.TryParse` | | `DivideByZeroException` | Chia số nguyên cho 0 | Kiểm tra `b != 0` | | `IndexOutOfRangeException` | Chỉ số ngoài mảng | Kiểm tra `i < arr.Length` | | `NullReferenceException` | Dùng biến `null` | Kiểm tra `null` hoặc `?.` | | `InvalidCastException` | Ép kiểu sai | `is` hoặc `as` | | `OverflowException` | Tràn số trong `checked` | Kiểu lớn hơn, kiểm tra giới hạn | ## Hoạt động: Sáu exception qua từng dòng code Mỗi tab của mô phỏng là một exception, với cùng ba bước: chuẩn bị dữ liệu, chạy dòng gây lỗi, rồi hiện kết quả. Hãy thao tác theo thứ tự sau, bấm **Bước tiếp** để chạy từng dòng: - Mở tab **FormatException**. Biến `s = "12a"` có cả chữ lẫn số. Dòng `int.Parse(s)` ném lỗi, thẻ đỏ hiện thông điệp `The input string '12a' was not in a correct format.` - Mở tab **DivideByZeroException**. Với `a = 10`, `b = 0`, dòng `a / b` ném lỗi với thông điệp `Attempted to divide by zero.` - Mở tab **IndexOutOfRangeException**. Mảng `arr` có 3 phần tử (`arr.Length = 3`), nhưng `arr[3]` vượt quá chỉ số lớn nhất là 2. Thông điệp: `Index was outside the bounds of the array.` - Mở tab **NullReferenceException**. Biến `s` là `null`, nên `s.Length` ném lỗi: `Object reference not set to an instance of an object.` - Mở tab **InvalidCastException**. Biến `o` kiểu `object` chứa chuỗi "abc", nhưng `(int)o` ép về `int`. Thông điệp: `Unable to cast object of type 'System.String' to type 'System.Int32'.` - Mở tab **OverflowException**. Trong khối `checked`, `x = int.MaxValue = 2147483647`, cộng thêm 1 thì tràn: `Arithmetic operation resulted in an overflow.` Thẻ cũng ghi chú rằng nếu không có `checked`, kết quả quay vòng thành số âm. Ở mỗi tab, thẻ lỗi cuối cùng còn gợi ý cách phòng tránh tương ứng. ``` <iframe src="https://codegym-vn.github.io/programming-course-demos/c-sharp-ung-dung/xu-ly-loi-va-ngoai-le-exception-handling-co-ban/gioi-thieu-ve-exception-va-tam-quan-trong/cac-loai-exception-pho-bien-trong-c-sharp/" title="Các loại Exception phổ biến" style="border:0;" allowfullscreen></iframe> ``` Điều rút ra: mỗi loại exception ứng với một kiểu sự cố cụ thể. Đọc tên loại và dòng gây lỗi là bước đầu tiên để biết cách sửa. ## Tóm tắt - Mọi exception đều kế thừa từ `System.Exception`. - `FormatException`: chuỗi sai định dạng. `DivideByZeroException`: chia số nguyên cho 0. - `IndexOutOfRangeException`: chỉ số ngoài mảng. `NullReferenceException`: dùng biến `null`. - `InvalidCastException`: ép kiểu sai. `OverflowException`: tràn số trong `checked`. - Chia `double` cho 0 không ném exception mà cho `Infinity`. - Phần lớn các lỗi này có thể phòng tránh bằng cách kiểm tra điều kiện trước.
A16: 15 | B16: 2. Xử lý lỗi và Ngoại lệ (Exception Handling) Cơ bản | C16: Cấu trúc try-catch cơ bản | D16: Giới thiệu về khối try-catch | E16: Bài đọc | F16: Nên làm | G16: Done | H16: Thấy đường đi của chương trình qua try-catch trong hai trường hợp: không lỗi và có lỗi. | I16: 1 cột, 2 tab | J16: Sơ đồ luồng nhỏ đặt cạnh mã: khối try, khối catch, khối 'sau try-catch'. Đường đi tô xanh khi bình thường, tô đỏ khi nhảy sang catch. Các dòng còn lại trong try bị bỏ qua hiện mờ. | K16: H04, H03 | L16: Không lỗi ("25") | Có lỗi ("abc") | M16: Không lỗi: vào try → Parse thành công → in "Bạn 25 tuổi" → hết try → catch bị bỏ qua → in "Kết thúc". Có lỗi: vào try → Parse ném FormatException. Dòng in tuổi còn lại trong try bị bỏ qua (mờ), chương trình nhảy thẳng vào catch. catch in "Vui lòng nhập số". Chương trình chạy tiếp sau khối, in "Kết thúc". | N16: "25" và "abc" | O16: Lỗi trong try làm phần còn lại của try bị bỏ qua; catch chỉ chạy khi có lỗi; chương trình tiếp tục sau khối try-catch. | Q16: c-sharp-ung-dung/xu-ly-loi-va-ngoai-le-exception-handling-co-ban/cau-truc-try-catch-co-ban/gioi-thieu-ve-khoi-try-catch/index.html | R16: https://codegym-vn.github.io/programming-course-demos/c-sharp-ung-dung/xu-ly-loi-va-ngoai-le-exception-handling-co-ban/cau-truc-try-catch-co-ban/gioi-thieu-ve-khoi-try-catch/ | V16: Trong lập trình, không phải lúc nào mọi thứ cũng diễn ra suôn sẻ. Có những lúc chương trình của bạn có thể gặp phải các tình huống bất ngờ, không mong muốn, dẫn đến lỗi hoặc thậm chí là dừng hoạt động đột ngột (crash). Những tình huống này được gọi là ngoại lệ (exceptions). Để đảm bảo ứng dụng của bạn luôn ổn định và cung cấp trải nghiệm tốt cho người dùng, việc xử lý các ngoại lệ này là vô cùng quan trọng. C# cung cấp một cơ chế mạnh mẽ để xử lý ngoại lệ có tên là khối try-catch. Đây là công cụ cơ bản giúp bạn "bắt" và xử lý các lỗi một cách có kiểm soát, ngăn chặn chương trình bị sập và cho phép bạn phục hồi hoặc thông báo lỗi một cách thân thiện. Cú pháp cơ bản của khối try-catch Cấu trúc try-catch trong C# được thiết kế để bao bọc các đoạn mã có khả năng gây ra ngoại lệ. Cú pháp cơ bản của nó như sau: try { // Đoạn mã có khả năng gây ra ngoại lệ // Ví dụ: chia cho 0, truy cập file không tồn tại, // chuyển đổi dữ liệu không hợp lệ. } catch (Exception ex) { // Đoạn mã xử lý ngoại lệ nếu nó xảy ra trong khối try // 'ex' là đối tượng ngoại lệ chứa thông tin chi tiết về lỗi } Trong cấu trúc này, có hai khối chính: try block: Chứa mã mà bạn muốn giám sát để phát hiện ngoại lệ. catch block: Chứa mã sẽ được thực thi khi một ngoại lệ xảy ra trong khối try. Chúng ta sẽ đi sâu vào chức năng của từng khối. Chức năng của khối try: Nơi mã tiềm ẩn lỗi Khối try là nơi bạn đặt tất cả các câu lệnh mà bạn nghi ngờ có thể gây ra một ngoại lệ. Mục đích của khối try là "thử" thực thi một đoạn mã và "theo dõi" xem có bất kỳ lỗi nào xảy ra trong quá trình đó hay không. Nếu tất cả các câu lệnh trong khối try được thực thi mà không có bất kỳ ngoại lệ nào, thì khối catch tương ứng sẽ bị bỏ qua và chương trình sẽ tiếp tục thực thi các câu lệnh sau khối try-catch. Tuy nhiên, nếu một ngoại lệ xảy ra trong khối try, ngay lập tức, việc thực thi khối try sẽ dừng lại. Hệ thống sẽ tìm kiếm một khối catch phù hợp để xử lý ngoại lệ đó. Ví dụ về mã có khả năng gây ra ngoại lệ: Hãy xem xét một ví dụ đơn giản về việc chia hai số nguyên. Nếu số chia là 0, một ngoại lệ DivideByZeroException sẽ xảy ra. Console.Write("Nhập tử số: "); int tuSo = Convert.ToInt32(Console.ReadLine()); Console.Write("Nhập mẫu số: "); int mauSo = Convert.ToInt32(Console.ReadLine()); // Đoạn mã này có thể gây lỗi nếu mauSo là 0 int ketQua = tuSo / mauSo; Console.WriteLine($"Kết quả: {ketQua}"); Nếu bạn chạy đoạn mã trên và nhập 0 cho mẫu số, chương trình sẽ dừng lại với một lỗi System.DivideByZeroException. Để ngăn chặn điều này, chúng ta sẽ đặt đoạn mã có khả năng gây lỗi vào khối try. Chức năng của khối catch: Nơi xử lý ngoại lệ Khối catch là nơi bạn định nghĩa cách ứng dụng của bạn sẽ phản ứng khi một ngoại lệ xảy ra trong khối try liên quan. Khi một ngoại lệ được "ném" (thrown) từ khối try, chương trình sẽ chuyển quyền kiểm soát sang khối catch phù hợp. Mục tiêu chính của khối catch là: Ngăn chặn chương trình bị crash: Thay vì dừng đột ngột, bạn có thể xử lý lỗi một cách có kiểm soát. Thông báo lỗi cho người dùng: Cung cấp thông báo thân thiện thay vì thông báo lỗi kỹ thuật khó hiểu. Ghi log lỗi: Lưu lại thông tin chi tiết về lỗi để nhà phát triển có thể điều tra và sửa chữa sau này. Phục hồi chương trình: Cố gắng đưa chương trình về trạng thái ổn định hoặc thực hiện một hành động thay thế. Mỗi khối catch có thể chỉ định loại ngoại lệ mà nó muốn bắt (ví dụ: DivideByZeroException, FormatException, FileNotFoundException). Nếu bạn chỉ định Exception (như trong cú pháp cơ bản), khối catch đó sẽ bắt mọi loại ngoại lệ. Đối tượng Exception (ex trong ví dụ cú pháp) được truyền vào khối catch chứa nhiều thông tin hữu ích về lỗi đã xảy ra. Các thuộc tính như Message, StackTrace sẽ cung cấp chi tiết về nguyên nhân và vị trí lỗi. Bạn sẽ tìm hiểu sâu hơn về đối tượng Exception và các thuộc tính của nó trong bài đọc "Đối tượng Exception và các thuộc tính". Ví dụ về cách sử dụng khối catch: Tiếp nối ví dụ chia số, chúng ta sẽ thêm khối catch để xử lý ngoại lệ DivideByZeroException: Console.Write("Nhập tử số: "); int tuSo = Convert.ToInt32(Console.ReadLine()); Console.Write("Nhập mẫu số: "); int mauSo = Convert.ToInt32(Console.ReadLine()); try { int ketQua = tuSo / mauSo; // Đây là mã có thể gây lỗi Console.WriteLine($"Kết quả: {ketQua}"); } catch (DivideByZeroException ex) // Bắt ngoại lệ chia cho 0 cụ thể { Console.WriteLine("Lỗi: Không thể chia cho số 0."); // Có thể ghi log lỗi ở đây: Console.WriteLine($"Chi tiết lỗi: {ex.Message}"); } catch (FormatException ex) // Bắt ngoại lệ nếu người dùng nhập không phải số { Console.WriteLine("Lỗi: Vui lòng nhập một số nguyên hợp lệ."); // Có thể ghi log lỗi ở đây } catch (Exception ex) // Bắt tất cả các ngoại lệ khác { Console.WriteLine("Đã xảy ra lỗi không xác định."); Console.WriteLine($"Chi tiết lỗi: {ex.Message}"); } Console.WriteLine("Chương trình tiếp tục sau khi xử lý lỗi."); Trong ví dụ này: Nếu mauSo là 0, DivideByZeroException sẽ được bắt bởi khối catch (DivideByZeroException ex). Nếu người dùng nhập văn bản thay vì số (ví dụ: "abc"), FormatException sẽ được bắt. Bất kỳ ngoại lệ nào khác (nếu có) sẽ được bắt bởi khối catch (Exception ex). Nhờ try-catch, chương trình không bị dừng đột ngột mà thay vào đó hiển thị một thông báo lỗi thân thiện và tiếp tục thực thi các câu lệnh sau khối try-catch. Đây là cốt lõi của việc xử lý ngoại lệ chuyên nghiệp, giúp ứng dụng của bạn trở nên mạnh mẽ và đáng tin cậy hơn. | W16: # Giới thiệu về khối try-catch ## Mục tiêu học tập Sau bài học này, bạn có thể: - Viết cú pháp cơ bản của khối `try-catch` trong C#. - Giải thích vai trò của khối `try` (đặt mã có thể lỗi) và khối `catch` (xử lý lỗi). - Mô tả đường đi của chương trình khi không có lỗi và khi có lỗi. - Biết rằng sau `try-catch`, chương trình vẫn chạy tiếp. - Quan sát hai đường đi qua `try-catch` với dữ liệu "25" và "abc" bằng hoạt động mô phỏng. ## Vì sao cần try-catch Ở các bài trước, bạn đã biết exception không ai bắt thì chương trình dừng đột ngột. Khối **`try-catch`** cho phép ta "bắt" lỗi và xử lý có kiểm soát: báo người dùng, ghi log, hoặc dùng giá trị thay thế, rồi để chương trình chạy tiếp. ## Cú pháp cơ bản ```csharp try { // mã có thể gây exception } catch (Exception ex) { // mã xử lý khi exception xảy ra trong try } ``` - **Khối `try`:** chứa các câu lệnh có thể gây exception. - **Khối `catch`:** chạy **chỉ khi** có exception xảy ra trong `try`. Biến `ex` là đối tượng exception mang thông tin về lỗi. ## Khối try: nơi đặt mã có thể lỗi Chương trình chạy các dòng trong `try` từ trên xuống. - Nếu **không có lỗi**, `try` chạy hết và khối `catch` bị bỏ qua. - Nếu **có lỗi** ở một dòng, phần còn lại của `try` bị bỏ qua và chương trình **nhảy ngay sang `catch`** phù hợp. ## Khối catch: nơi xử lý lỗi `catch` có thể chỉ rõ loại exception cần bắt, ví dụ `catch (FormatException)`. Chỉ khi exception có loại tương ứng thì khối này mới chạy. Nếu viết `catch (Exception ex)`, khối này bắt mọi loại exception. Đối tượng `ex` có các thuộc tính như `Message` và `StackTrace`, bạn sẽ học ở bài sau. Ví dụ hoàn chỉnh: ```csharp using System; public class Program { public static void Main() { string input = "abc"; try { int age = int.Parse(input); Console.WriteLine("Bạn " + age + " tuổi"); } catch (FormatException) { Console.WriteLine("Vui lòng nhập số"); } Console.WriteLine("Kết thúc"); } } // Với input = "abc": // Vui lòng nhập số // Kết thúc // // Với input = "25": // Bạn 25 tuổi // Kết thúc ``` Dù có lỗi hay không, dòng `Console.WriteLine("Kết thúc")` sau khối `try-catch` vẫn chạy. ## Hoạt động: Hai đường đi qua try-catch Mô phỏng dưới đây chạy cùng một đoạn `try-catch` với hai giá trị nhập. Sơ đồ "Đường đi của chương trình" có ba chặng: Khối try, Khối catch và Sau try-catch. Hãy thao tác theo thứ tự sau, bấm **Bước tiếp** để chạy từng dòng: - Mở tab **Không lỗi ("25")**. Chương trình vào `try` với `input = "25"`. `int.Parse("25")` thành công, `age = 25`, rồi in `Bạn 25 tuổi`. Hết `try`, khối catch được đánh dấu "bị bỏ qua", sau đó chương trình in `Kết thúc`. Cuối cùng khối try xanh, catch xám và phần sau try-catch xanh. - Chuyển sang tab **Có lỗi ("abc")**. `int.Parse("abc")` ném `FormatException`: khối try chuyển đỏ và thẻ lỗi hiện thông điệp `The input string 'abc' was not in a correct format.` Dòng in tuổi bị làm mờ vì không được chạy, chương trình nhảy thẳng vào catch. `catch (FormatException)` bắt đúng loại lỗi và in `Vui lòng nhập số`. Sau đó chương trình chạy tiếp và in `Kết thúc`. ``` <iframe src="https://codegym-vn.github.io/programming-course-demos/c-sharp-ung-dung/xu-ly-loi-va-ngoai-le-exception-handling-co-ban/cau-truc-try-catch-co-ban/gioi-thieu-ve-khoi-try-catch/" title="Giới thiệu về khối try-catch" style="border:0;" allowfullscreen></iframe> ``` Điều rút ra: `catch` chỉ chạy khi có lỗi trong `try`. Lỗi làm phần còn lại của `try` bị bỏ qua, nhưng chương trình không dừng mà tiếp tục sau khối `try-catch`. ## Nhiều khối catch Bạn có thể đặt nhiều `catch` để xử lý từng loại lỗi khác nhau. Hãy đặt loại **cụ thể** lên trước và `catch (Exception)` (bắt chung) ở cuối: ```csharp try { int ketQua = tuSo / mauSo; } catch (DivideByZeroException) { Console.WriteLine("Không thể chia cho 0."); } catch (Exception ex) { Console.WriteLine("Lỗi khác: " + ex.Message); } ``` Nếu đặt `catch (Exception)` trước, trình biên dịch sẽ báo lỗi vì các `catch` cụ thể phía sau không bao giờ được chạy. ## Tóm tắt - `try` chứa mã có thể gây exception, `catch` xử lý khi có exception. - Không có lỗi: `try` chạy hết, `catch` bị bỏ qua. - Có lỗi: phần còn lại của `try` bị bỏ qua, chương trình nhảy sang `catch` phù hợp. - Chương trình luôn chạy tiếp sau khối `try-catch`. - Đặt `catch` cụ thể trước, `catch (Exception)` chung ở cuối.
